Workbook

Sheet schedule_ARAS
C1: WORK SCHEDULE VERSUS RESOURCE CHART
C2: PROJECT NAME: | D2: FİLYOS LİMANI TAHKİMAT İŞİ
C3: PROJECT DURATION: | D3: 36 | E3: Months
E4: Verim = | I4: 42217 | M4: 42248 | Q4: =+M4+31 -> 42279 | U4: =+Q4+31 -> 42310 | Y4: =+U4+31 -> 42341 | AC4: =+Y4+31 -> 42372 | AG4: =+AC4+31 -> 42403 | AK4: =+AG4+31 -> 42434 | AO4: =+AK4+31 -> 42465 | AS4: =+AO4+31 -> 42496 | AW4: =+AS4+31 -> 42527 | BA4: =+AW4+31 -> 42558 | BE4: =+BA4+31 -> 42589 | BI4: =+BE4+31 -> 42620 | BM4: =+BI4+31 -> 42651 | BQ4: =+BM4+31 -> 42682 | BU4: =+BQ4+31 -> 42713 | BY4: =+BU4+31 -> 42744 | CC4: =+BY4+31 -> 42775 | CG4: =+CC4+31 -> 42806 | CK4: =+CG4+31 -> 42837 | CO4: =+CK4+31 -> 42868 | CS4: =+CO4+31 -> 42899 | CW4: =+CS4+31 -> 42930 | DA4: =+CW4+31 -> 42961 | DE4: =+DA4+31 -> 42992
B5: S.NO. | C5: WORK DESCRIPTION | D5: UNIT | E5: QTY. | F5: Günlük Kapasite | G5: Günlük Verimli Kapasite | H5: Süre (Makine / Adam.Ay) | I5: Month-1 | M5: Month-2 | Q5: Month-3 | U5: Month-4 | Y5: Month-5 | AC5: Month-6 | AG5: Month-7 | AK5: Month-8 | AO5: Month-9 | AS5: Month-10 | AW5: Month-11 | BA5: Month-12 | BE5: Month-13 | BI5: Month-14 | BM5: Month-15 | BQ5: Month-16 | BU5: Month-17 | BY5: Month-18 | CC5: Month-19 | CG5: Month-20 | CK5: Month-21 | CO5: Month-22 | CS5: Month-23 | CW5: Month-24 | DA5: Month-25 | DE5: Month-26 | DI5: Month-27 | DM5: Month-28 | DQ5: Month-29 | DU5: Month-30 | DY5: Month-31 | EC5: Month-32 | EG5: Month-33 | EK5: Month-34 | EO5: Month-35 | ES5: Month-36 | EW5: Makine / Adam.Ay | EX5: Working per Day | EY5: Stand-by per Day | EZ5: Total Working | FA5: Total Stand-by
C6: Sözleşme İmzalanması
C7: Mobilizasyon
C8: Demobilizasyon
C10: Makine&Ekipman
EW11: =SUM(I11:DD11)/4 -> 0 | EZ11: =+EW11*EX11*28 -> 0 | FA11: =+EW11*EY11*30 -> 0
C12: Kurtuluş Kara | D12: Adet | E12: 1 | AG12: =+E12 -> 1 | AH12: =+E12 -> 1 | AI12: =+E12 -> 1 | AJ12: =+E12 -> 1 | AK12: =+E12 -> 1 | AL12: =+E12 -> 1 | AM12: =+E12 -> 1 | AN12: =+E12 -> 1 | AO12: =+E12 -> 1 | AP12: =+E12 -> 1 | AQ12: =+E12 -> 1 | AR12: =+E12 -> 1 | AS12: =+E12 -> 1 | AT12: =+E12 -> 1 | AU12: =+E12 -> 1 | AV12: =+E12 -> 1 | AW12: =+E12 -> 1 | AX12: =+E12 -> 1 | AY12: =+E12 -> 1 | AZ12: =+E12 -> 1 | BA12: =+E12 -> 1 | BB12: =+E12 -> 1 | BC12: =+E12 -> 1 | BD12: =+E12 -> 1 | BE12: =+E12 -> 1 | BF12: =+E12 -> 1 | BG12: =+E12 -> 1 | BH12: =+E12 -> 1 | BI12: =+E12 -> 1 | BJ12: =+E12 -> 1 | BK12: =+E12 -> 1 | BL12: =+E12 -> 1 | BM12: =+E12 -> 1 | BN12: =+E12 -> 1 | BO12: =+E12 -> 1 | BP12: =+E12 -> 1 | BQ12: =+AK12 -> 1 | BR12: =+AK12 -> 1 | BS12: =+AK12 -> 1 | BT12: =+AK12 -> 1 | BU12: =+AO12 -> 1 | BV12: =+AO12 -> 1 | BW12: =+AO12 -> 1 | BX12: =+AO12 -> 1 | BY12: =+AS12 -> 1 | BZ12: =+AS12 -> 1 | CA12: =+AS12 -> 1 | CB12: =+AS12 -> 1 | CC12: =+AW12 -> 1 | CD12: =+AW12 -> 1 | CE12: =+AW12 -> 1 | CF12: =+AW12 -> 1 | CG12: =+BA12 -> 1 | CH12: =+BA12 -> 1 | CI12: =+BA12 -> 1 | CJ12: =+BA12 -> 1 | CK12: =+BE12 -> 1 | CL12: =+BE12 -> 1 | CM12: =+BE12 -> 1 | CN12: =+BE12 -> 1 | CO12: =+BI12 -> 1 | CP12: =+BI12 -> 1 | CQ12: =+BI12 -> 1 | CR12: =+BI12 -> 1 | CS12: =+BM12 -> 1 | CT12: =+BM12 -> 1 | CU12: =+BM12 -> 1 | CV12: =+BM12 -> 1 | CW12: =+BQ12 -> 1 | CX12: =+BQ12 -> 1 | CY12: =+BQ12 -> 1 | CZ12: =+BQ12 -> 1 | DA12: =+BU12 -> 1 | DB12: =+BU12 -> 1 | DC12: =+BU12 -> 1 | DD12: =+BU12 -> 1 | DE12: =+BY12 -> 1 | DF12: =+BY12 -> 1 | DG12: =+BY12 -> 1 | DH12: =+BY12 -> 1 | DI12: =+CC12 -> 1 | DJ12: =+CC12 -> 1 | DK12: =+CC12 -> 1 | DL12: =+CC12 -> 1 | DM12: =+CG12 -> 1 | DN12: =+CG12 -> 1 | DO12: =+CG12 -> 1 | DP12: =+CG12 -> 1 | DQ12: =+CK12 -> 1 | DR12: =+CK12 -> 1 | DS12: =+CK12 -> 1 | DT12: =+CK12 -> 1 | DU12: =+CO12 -> 1 | DV12: =+CO12 -> 1 | DW12: =+CO12 -> 1 | DX12: =+CO12 -> 1 | DY12: =+CS12 -> 1 | DZ12: =+CS12 -> 1 | EA12: =+CS12 -> 1 | EB12: =+CS12 -> 1 | EC12: =+CW12 -> 1 | ED12: =+CW12 -> 1 | EE12: =+CW12 -> 1 | EF12: =+CW12 -> 1 | EG12: =+DA12 -> 1 | EH12: =+DA12 -> 1 | EI12: =+DA12 -> 1 | EJ12: =+DA12 -> 1 | EK12: =+DE12 -> 1 | EL12: =+DE12 -> 1 | EM12: =+DE12 -> 1 | EN12: =+DE12 -> 1 | EO12: =+DI12 -> 1 | EP12: =+DI12 -> 1 | EQ12: =+DI12 -> 1 | ER12: =+DI12 -> 1 | ES12: =+DM12 -> 1 | ET12: =+DM12 -> 1 | EU12: =+DM12 -> 1 | EV12: =+DM12 -> 1 | EW12: =SUM(I12:EV12)/4 -> 30 | EX12: 16 | EY12: =24-EX12 -> 8 | EZ12: =+EW12*EX12*28 -> 13440 | FA12: =+EW12*EY12*30 -> 7200
C13: Koparan | D13: Adet | E13: 1 | AG13: =+E13 -> 1 | AH13: =+E13 -> 1 | AI13: =+E13 -> 1 | AJ13: =+E13 -> 1 | AK13: =+E13 -> 1 | AL13: =+E13 -> 1 | AM13: =+E13 -> 1 | AN13: =+E13 -> 1 | AO13: =+E13 -> 1 | AP13: =+E13 -> 1 | AQ13: =+E13 -> 1 | AR13: =+E13 -> 1 | AS13: =+E13 -> 1 | AT13: =+E13 -> 1 | AU13: =+E13 -> 1 | AV13: =+E13 -> 1 | AW13: =+E13 -> 1 | AX13: =+E13 -> 1 | AY13: =+E13 -> 1 | AZ13: =+E13 -> 1 | BA13: =+E13 -> 1 | BB13: =+E13 -> 1 | BC13: =+E13 -> 1 | BD13: =+E13 -> 1 | BE13: =+E13 -> 1 | BF13: =+E13 -> 1 | BG13: =+E13 -> 1 | BH13: =+E13 -> 1 | BI13: =+E13 -> 1 | BJ13: =+E13 -> 1 | BK13: =+E13 -> 1 | BL13: =+E13 -> 1 | BM13: =+E13 -> 1 | BN13: =+E13 -> 1 | BO13: =+E13 -> 1 | BP13: =+E13 -> 1 | BQ13: =+AK13 -> 1 | BR13: =+AK13 -> 1 | BS13: =+AK13 -> 1 | BT13: =+AK13 -> 1 | BU13: =+AO13 -> 1 | BV13: =+AO13 -> 1 | BW13: =+AO13 -> 1 | BX13: =+AO13 -> 1 | BY13: =+AS13 -> 1 | BZ13: =+AS13 -> 1 | CA13: =+AS13 -> 1 | CB13: =+AS13 -> 1 | CC13: =+AW13 -> 1 | CD13: =+AW13 -> 1 | CE13: =+AW13 -> 1 | CF13: =+AW13 -> 1 | CG13: =+BA13 -> 1 | CH13: =+BA13 -> 1 | CI13: =+BA13 -> 1 | CJ13: =+BA13 -> 1 | CK13: =+BE13 -> 1 | CL13: =+BE13 -> 1 | CM13: =+BE13 -> 1 | CN13: =+BE13 -> 1 | CO13: =+BI13 -> 1 | CP13: =+BI13 -> 1 | CQ13: =+BI13 -> 1 | CR13: =+BI13 -> 1 | CS13: =+BM13 -> 1 | CT13: =+BM13 -> 1 | CU13: =+BM13 -> 1 | CV13: =+BM13 -> 1 | CW13: =+BQ13 -> 1 | CX13: =+BQ13 -> 1 | CY13: =+BQ13 -> 1 | CZ13: =+BQ13 -> 1 | DA13: =+BU13 -> 1 | DB13: =+BU13 -> 1 | DC13: =+BU13 -> 1 | DD13: =+BU13 -> 1 | DE13: =+BY13 -> 1 | DF13: =+BY13 -> 1 | DG13: =+BY13 -> 1 | DH13: =+BY13 -> 1 | DI13: =+CC13 -> 1 | DJ13: =+CC13 -> 1 | DK13: =+CC13 -> 1 | DL13: =+CC13 -> 1 | DM13: =+CG13 -> 1 | DN13: =+CG13 -> 1 | DO13: =+CG13 -> 1 | DP13: =+CG13 -> 1 | DQ13: =+CK13 -> 1 | DR13: =+CK13 -> 1 | DS13: =+CK13 -> 1 | DT13: =+CK13 -> 1 | DU13: =+CO13 -> 1 | DV13: =+CO13 -> 1 | DW13: =+CO13 -> 1 | DX13: =+CO13 -> 1 | DY13: =+CS13 -> 1 | DZ13: =+CS13 -> 1 | EA13: =+CS13 -> 1 | EB13: =+CS13 -> 1 | EC13: =+CW13 -> 1 | ED13: =+CW13 -> 1 | EE13: =+CW13 -> 1 | EF13: =+CW13 -> 1 | EG13: =+DA13 -> 1 | EH13: =+DA13 -> 1 | EI13: =+DA13 -> 1 | EJ13: =+DA13 -> 1 | EK13: =+DE13 -> 1 | EL13: =+DE13 -> 1 | EM13: =+DE13 -> 1 | EN13: =+DE13 -> 1 | EO13: =+DI13 -> 1 | EP13: =+DI13 -> 1 | EQ13: =+DI13 -> 1 | ER13: =+DI13 -> 1 | ES13: =+DM13 -> 1 | ET13: =+DM13 -> 1 | EU13: =+DM13 -> 1 | EV13: =+DM13 -> 1 | EW13: =SUM(I13:EV13)/4 -> 30 | EX13: 16 | EY13: =24-EX13 -> 8 | EZ13: =+EW13*EX13*28 -> 13440 | FA13: =+EW13*EY13*30 -> 7200
C14: Necem D-18 | D14: Adet | E14: 1 | AG14: =+E14 -> 1 | AH14: =+E14 -> 1 | AI14: =+E14 -> 1 | AJ14: =+E14 -> 1 | AK14: =+E14 -> 1 | AL14: =+E14 -> 1 | AM14: =+E14 -> 1 | AN14: =+E14 -> 1 | AO14: =+E14 -> 1 | AP14: =+E14 -> 1 | AQ14: =+E14 -> 1 | AR14: =+E14 -> 1 | AS14: =+E14 -> 1 | AT14: =+E14 -> 1 | AU14: =+E14 -> 1 | AV14: =+E14 -> 1 | AW14: =+E14 -> 1 | AX14: =+E14 -> 1 | AY14: =+E14 -> 1 | AZ14: =+E14 -> 1 | BA14: =+E14 -> 1 | BB14: =+E14 -> 1 | BC14: =+E14 -> 1 | BD14: =+E14 -> 1 | BE14: =+E14 -> 1 | BF14: =+E14 -> 1 | BG14: =+E14 -> 1 | BH14: =+E14 -> 1 | BI14: =+E14 -> 1 | BJ14: =+E14 -> 1 | BK14: =+E14 -> 1 | BL14: =+E14 -> 1 | BM14: =+E14 -> 1 | BN14: =+E14 -> 1 | BO14: =+E14 -> 1 | BP14: =+E14 -> 1 | BQ14: =+AK14 -> 1 | BR14: =+AK14 -> 1 | BS14: =+AK14 -> 1 | BT14: =+AK14 -> 1 | BU14: =+AO14 -> 1 | BV14: =+AO14 -> 1 | BW14: =+AO14 -> 1 | BX14: =+AO14 -> 1 | BY14: =+AS14 -> 1 | BZ14: =+AS14 -> 1 | CA14: =+AS14 -> 1 | CB14: =+AS14 -> 1 | CC14: =+AW14 -> 1 | CD14: =+AW14 -> 1 | CE14: =+AW14 -> 1 | CF14: =+AW14 -> 1 | CG14: =+BA14 -> 1 | CH14: =+BA14 -> 1 | CI14: =+BA14 -> 1 | CJ14: =+BA14 -> 1 | CK14: =+BE14 -> 1 | CL14: =+BE14 -> 1 | CM14: =+BE14 -> 1 | CN14: =+BE14 -> 1 | CO14: =+BI14 -> 1 | CP14: =+BI14 -> 1 | CQ14: =+BI14 -> 1 | CR14: =+BI14 -> 1 | CS14: =+BM14 -> 1 | CT14: =+BM14 -> 1 | CU14: =+BM14 -> 1 | CV14: =+BM14 -> 1 | CW14: =+BQ14 -> 1 | CX14: =+BQ14 -> 1 | CY14: =+BQ14 -> 1 | CZ14: =+BQ14 -> 1 | DA14: =+BU14 -> 1 | DB14: =+BU14 -> 1 | DC14: =+BU14 -> 1 | DD14: =+BU14 -> 1 | DE14: =+BY14 -> 1 | DF14: =+BY14 -> 1 | DG14: =+BY14 -> 1 | DH14: =+BY14 -> 1 | DI14: =+CC14 -> 1 | DJ14: =+CC14 -> 1 | DK14: =+CC14 -> 1 | DL14: =+CC14 -> 1 | DM14: =+CG14 -> 1 | DN14: =+CG14 -> 1 | DO14: =+CG14 -> 1 | DP14: =+CG14 -> 1 | DQ14: =+CK14 -> 1 | DR14: =+CK14 -> 1 | DS14: =+CK14 -> 1 | DT14: =+CK14 -> 1 | DU14: =+CO14 -> 1 | DV14: =+CO14 -> 1 | DW14: =+CO14 -> 1 | DX14: =+CO14 -> 1 | DY14: =+CS14 -> 1 | DZ14: =+CS14 -> 1 | EA14: =+CS14 -> 1 | EB14: =+CS14 -> 1 | EC14: =+CW14 -> 1 | ED14: =+CW14 -> 1 | EE14: =+CW14 -> 1 | EF14: =+CW14 -> 1 | EG14: =+DA14 -> 1 | EH14: =+DA14 -> 1 | EI14: =+DA14 -> 1 | EJ14: =+DA14 -> 1 | EK14: =+DE14 -> 1 | EL14: =+DE14 -> 1 | EM14: =+DE14 -> 1 | EN14: =+DE14 -> 1 | EO14: =+DI14 -> 1 | EP14: =+DI14 -> 1 | EQ14: =+DI14 -> 1 | ER14: =+DI14 -> 1 | ES14: =+DM14 -> 1 | ET14: =+DM14 -> 1 | EU14: =+DM14 -> 1 | EV14: =+DM14 -> 1 | EW14: =SUM(I14:EV14)/4 -> 30 | EX14: 16 | EY14: =24-EX14 -> 8 | EZ14: =+EW14*EX14*28 -> 13440 | FA14: =+EW14*EY14*30 -> 7200
C15: Alpaslan - II | D15: Adet | E15: 1 | G15: =+F15*$G$4 -> 0 | AG15: =+E15 -> 1 | AH15: =+E15 -> 1 | AI15: =+E15 -> 1 | AJ15: =+E15 -> 1 | AK15: =+E15 -> 1 | AL15: =+E15 -> 1 | AM15: =+E15 -> 1 | AN15: =+E15 -> 1 | AO15: =+E15 -> 1 | AP15: =+E15 -> 1 | AQ15: =+E15 -> 1 | AR15: =+E15 -> 1 | AS15: =+E15 -> 1 | AT15: =+E15 -> 1 | AU15: =+E15 -> 1 | AV15: =+E15 -> 1 | AW15: =+E15 -> 1 | AX15: =+E15 -> 1 | AY15: =+E15 -> 1 | AZ15: =+E15 -> 1 | BA15: =+E15 -> 1 | BB15: =+E15 -> 1 | BC15: =+E15 -> 1 | BD15: =+E15 -> 1 | BE15: =+E15 -> 1 | BF15: =+E15 -> 1 | BG15: =+E15 -> 1 | BH15: =+E15 -> 1 | BI15: =+E15 -> 1 | BJ15: =+E15 -> 1 | BK15: =+E15 -> 1 | BL15: =+E15 -> 1 | BM15: =+E15 -> 1 | BN15: =+E15 -> 1 | BO15: =+E15 -> 1 | BP15: =+E15 -> 1 | BQ15: =+AK15 -> 1 | BR15: =+AK15 -> 1 | BS15: =+AK15 -> 1 | BT15: =+AK15 -> 1 | BU15: =+AO15 -> 1 | BV15: =+AO15 -> 1 | BW15: =+AO15 -> 1 | BX15: =+AO15 -> 1 | BY15: =+AS15 -> 1 | BZ15: =+AS15 -> 1 | CA15: =+AS15 -> 1 | CB15: =+AS15 -> 1 | CC15: =+AW15 -> 1 | CD15: =+AW15 -> 1 | CE15: =+AW15 -> 1 | CF15: =+AW15 -> 1 | CG15: =+BA15 -> 1 | CH15: =+BA15 -> 1 | CI15: =+BA15 -> 1 | CJ15: =+BA15 -> 1 | CK15: =+BE15 -> 1 | CL15: =+BE15 -> 1 | CM15: =+BE15 -> 1 | CN15: =+BE15 -> 1 | CO15: =+BI15 -> 1 | CP15: =+BI15 -> 1 | CQ15: =+BI15 -> 1 | CR15: =+BI15 -> 1 | CS15: =+BM15 -> 1 | CT15: =+BM15 -> 1 | CU15: =+BM15 -> 1 | CV15: =+BM15 -> 1 | CW15: =+BQ15 -> 1 | CX15: =+BQ15 -> 1 | CY15: =+BQ15 -> 1 | CZ15: =+BQ15 -> 1 | DA15: =+BU15 -> 1 | DB15: =+BU15 -> 1 | DC15: =+BU15 -> 1 | DD15: =+BU15 -> 1 | DE15: =+BY15 -> 1 | DF15: =+BY15 -> 1 | DG15: =+BY15 -> 1 | DH15: =+BY15 -> 1 | DI15: =+CC15 -> 1 | DJ15: =+CC15 -> 1 | DK15: =+CC15 -> 1 | DL15: =+CC15 -> 1 | DM15: =+CG15 -> 1 | DN15: =+CG15 -> 1 | DO15: =+CG15 -> 1 | DP15: =+CG15 -> 1 | DQ15: =+CK15 -> 1 | DR15: =+CK15 -> 1 | DS15: =+CK15 -> 1 | DT15: =+CK15 -> 1 | DU15: =+CO15 -> 1 | DV15: =+CO15 -> 1 | DW15: =+CO15 -> 1 | DX15: =+CO15 -> 1 | DY15: =+CS15 -> 1 | DZ15: =+CS15 -> 1 | EA15: =+CS15 -> 1 | EB15: =+CS15 -> 1 | EC15: =+CW15 -> 1 | ED15: =+CW15 -> 1 | EE15: =+CW15 -> 1 | EF15: =+CW15 -> 1 | EG15: =+DA15 -> 1 | EH15: =+DA15 -> 1 | EI15: =+DA15 -> 1 | EJ15: =+DA15 -> 1 | EK15: =+DE15 -> 1 | EL15: =+DE15 -> 1 | EM15: =+DE15 -> 1 | EN15: =+DE15 -> 1 | EO15: =+DI15 -> 1 | EP15: =+DI15 -> 1 | EQ15: =+DI15 -> 1 | ER15: =+DI15 -> 1 | ES15: =+DM15 -> 1 | ET15: =+DM15 -> 1 | EU15: =+DM15 -> 1 | EV15: =+DM15 -> 1 | EW15: =SUM(I15:EV15)/4 -> 30 | EX15: 16 | EY15: =24-EX15 -> 8 | EZ15: =+EW15*EX15*28 -> 13440 | FA15: =+EW15*EY15*30 -> 7200
C16: Koca Seyit | D16: Adet | E16: 1 | G16: =+F16*$G$4 -> 0 | AG16: =+E16 -> 1 | AH16: =+E16 -> 1 | AI16: =+E16 -> 1 | AJ16: =+E16 -> 1 | AK16: =+E16 -> 1 | AL16: =+E16 -> 1 | AM16: =+E16 -> 1 | AN16: =+E16 -> 1 | AO16: =+E16 -> 1 | AP16: =+E16 -> 1 | AQ16: =+E16 -> 1 | AR16: =+E16 -> 1 | AS16: =+E16 -> 1 | AT16: =+E16 -> 1 | AU16: =+E16 -> 1 | AV16: =+E16 -> 1 | AW16: =+E16 -> 1 | AX16: =+E16 -> 1 | AY16: =+E16 -> 1 | AZ16: =+E16 -> 1 | BA16: =+E16 -> 1 | BB16: =+E16 -> 1 | BC16: =+E16 -> 1 | BD16: =+E16 -> 1 | BE16: =+E16 -> 1 | BF16: =+E16 -> 1 | BG16: =+E16 -> 1 | BH16: =+E16 -> 1 | BI16: =+E16 -> 1 | BJ16: =+E16 -> 1 | BK16: =+E16 -> 1 | BL16: =+E16 -> 1 | BM16: =+E16 -> 1 | BN16: =+E16 -> 1 | BO16: =+E16 -> 1 | BP16: =+E16 -> 1 | BQ16: =+AK16 -> 1 | BR16: =+AK16 -> 1 | BS16: =+AK16 -> 1 | BT16: =+AK16 -> 1 | BU16: =+AO16 -> 1 | BV16: =+AO16 -> 1 | BW16: =+AO16 -> 1 | BX16: =+AO16 -> 1 | BY16: =+AS16 -> 1 | BZ16: =+AS16 -> 1 | CA16: =+AS16 -> 1 | CB16: =+AS16 -> 1 | CC16: =+AW16 -> 1 | CD16: =+AW16 -> 1 | CE16: =+AW16 -> 1 | CF16: =+AW16 -> 1 | CG16: =+BA16 -> 1 | CH16: =+BA16 -> 1 | CI16: =+BA16 -> 1 | CJ16: =+BA16 -> 1 | CK16: =+BE16 -> 1 | CL16: =+BE16 -> 1 | CM16: =+BE16 -> 1 | CN16: =+BE16 -> 1 | CO16: =+BI16 -> 1 | CP16: =+BI16 -> 1 | CQ16: =+BI16 -> 1 | CR16: =+BI16 -> 1 | CS16: =+BM16 -> 1 | CT16: =+BM16 -> 1 | CU16: =+BM16 -> 1 | CV16: =+BM16 -> 1 | CW16: =+BQ16 -> 1 | CX16: =+BQ16 -> 1 | CY16: =+BQ16 -> 1 | CZ16: =+BQ16 -> 1 | DA16: =+BU16 -> 1 | DB16: =+BU16 -> 1 | DC16: =+BU16 -> 1 | DD16: =+BU16 -> 1 | DE16: =+BY16 -> 1 | DF16: =+BY16 -> 1 | DG16: =+BY16 -> 1 | DH16: =+BY16 -> 1 | DI16: =+CC16 -> 1 | DJ16: =+CC16 -> 1 | DK16: =+CC16 -> 1 | DL16: =+CC16 -> 1 | DM16: =+CG16 -> 1 | DN16: =+CG16 -> 1 | DO16: =+CG16 -> 1 | DP16: =+CG16 -> 1 | DQ16: =+CK16 -> 1 | DR16: =+CK16 -> 1 | DS16: =+CK16 -> 1 | DT16: =+CK16 -> 1 | DU16: =+CO16 -> 1 | DV16: =+CO16 -> 1 | DW16: =+CO16 -> 1 | DX16: =+CO16 -> 1 | DY16: =+CS16 -> 1 | DZ16: =+CS16 -> 1 | EA16: =+CS16 -> 1 | EB16: =+CS16 -> 1 | EC16: =+CW16 -> 1 | ED16: =+CW16 -> 1 | EE16: =+CW16 -> 1 | EF16: =+CW16 -> 1 | EG16: =+DA16 -> 1 | EH16: =+DA16 -> 1 | EI16: =+DA16 -> 1 | EJ16: =+DA16 -> 1 | EK16: =+DE16 -> 1 | EL16: =+DE16 -> 1 | EM16: =+DE16 -> 1 | EN16: =+DE16 -> 1 | EO16: =+DI16 -> 1 | EP16: =+DI16 -> 1 | EQ16: =+DI16 -> 1 | ER16: =+DI16 -> 1 | ES16: =+DM16 -> 1 | ET16: =+DM16 -> 1 | EU16: =+DM16 -> 1 | EV16: =+DM16 -> 1 | EW16: =SUM(I16:EV16)/4 -> 30 | EX16: 16 | EY16: =24-EX16 -> 8 | EZ16: =+EW16*EX16*28 -> 13440 | FA16: =+EW16*EY16*30 -> 7200
C17: Floating Crane 3 | D17: Adet | E17: 1 | AG17: =+E17 -> 1 | AH17: =+E17 -> 1 | AI17: =+E17 -> 1 | AJ17: =+E17 -> 1 | AK17: =+E17 -> 1 | AL17: =+E17 -> 1 | AM17: =+E17 -> 1 | AN17: =+E17 -> 1 | AO17: =+E17 -> 1 | AP17: =+E17 -> 1 | AQ17: =+E17 -> 1 | AR17: =+E17 -> 1 | AS17: =+E17 -> 1 | AT17: =+E17 -> 1 | AU17: =+E17 -> 1 | AV17: =+E17 -> 1 | AW17: =+E17 -> 1 | AX17: =+E17 -> 1 | AY17: =+E17 -> 1 | AZ17: =+E17 -> 1 | BA17: =+E17 -> 1 | BB17: =+E17 -> 1 | BC17: =+E17 -> 1 | BD17: =+E17 -> 1 | BE17: =+E17 -> 1 | BF17: =+E17 -> 1 | BG17: =+E17 -> 1 | BH17: =+E17 -> 1 | BI17: =+E17 -> 1 | BJ17: =+E17 -> 1 | BK17: =+E17 -> 1 | BL17: =+E17 -> 1 | BM17: =+E17 -> 1 | BN17: =+E17 -> 1 | BO17: =+E17 -> 1 | BP17: =+E17 -> 1 | BQ17: =+AK17 -> 1 | BR17: =+AK17 -> 1 | BS17: =+AK17 -> 1 | BT17: =+AK17 -> 1 | BU17: =+AO17 -> 1 | BV17: =+AO17 -> 1 | BW17: =+AO17 -> 1 | BX17: =+AO17 -> 1 | BY17: =+AS17 -> 1 | BZ17: =+AS17 -> 1 | CA17: =+AS17 -> 1 | CB17: =+AS17 -> 1 | CC17: =+AW17 -> 1 | CD17: =+AW17 -> 1 | CE17: =+AW17 -> 1 | CF17: =+AW17 -> 1 | CG17: =+BA17 -> 1 | CH17: =+BA17 -> 1 | CI17: =+BA17 -> 1 | CJ17: =+BA17 -> 1 | CK17: =+BE17 -> 1 | CL17: =+BE17 -> 1 | CM17: =+BE17 -> 1 | CN17: =+BE17 -> 1 | CO17: =+BI17 -> 1 | CP17: =+BI17 -> 1 | CQ17: =+BI17 -> 1 | CR17: =+BI17 -> 1 | CS17: =+BM17 -> 1 | CT17: =+BM17 -> 1 | CU17: =+BM17 -> 1 | CV17: =+BM17 -> 1 | CW17: =+BQ17 -> 1 | CX17: =+BQ17 -> 1 | CY17: =+BQ17 -> 1 | CZ17: =+BQ17 -> 1 | DA17: =+BU17 -> 1 | DB17: =+BU17 -> 1 | DC17: =+BU17 -> 1 | DD17: =+BU17 -> 1 | DE17: =+BY17 -> 1 | DF17: =+BY17 -> 1 | DG17: =+BY17 -> 1 | DH17: =+BY17 -> 1 | DI17: =+CC17 -> 1 | DJ17: =+CC17 -> 1 | DK17: =+CC17 -> 1 | DL17: =+CC17 -> 1 | DM17: =+CG17 -> 1 | DN17: =+CG17 -> 1 | DO17: =+CG17 -> 1 | DP17: =+CG17 -> 1 | DQ17: =+CK17 -> 1 | DR17: =+CK17 -> 1 | DS17: =+CK17 -> 1 | DT17: =+CK17 -> 1 | DU17: =+CO17 -> 1 | DV17: =+CO17 -> 1 | DW17: =+CO17 -> 1 | DX17: =+CO17 -> 1 | DY17: =+CS17 -> 1 | DZ17: =+CS17 -> 1 | EA17: =+CS17 -> 1 | EB17: =+CS17 -> 1 | EC17: =+CW17 -> 1 | ED17: =+CW17 -> 1 | EE17: =+CW17 -> 1 | EF17: =+CW17 -> 1 | EG17: =+DA17 -> 1 | EH17: =+DA17 -> 1 | EI17: =+DA17 -> 1 | EJ17: =+DA17 -> 1 | EK17: =+DE17 -> 1 | EL17: =+DE17 -> 1 | EM17: =+DE17 -> 1 | EN17: =+DE17 -> 1 | EO17: =+DI17 -> 1 | EP17: =+DI17 -> 1 | EQ17: =+DI17 -> 1 | ER17: =+DI17 -> 1 | ES17: =+DM17 -> 1 | ET17: =+DM17 -> 1 | EU17: =+DM17 -> 1 | EV17: =+DM17 -> 1 | EW17: =SUM(I17:EV17)/4 -> 30 | EX17: 16 | EY17: =24-EX17 -> 8 | EZ17: =+EW17*EX17*28 -> 13440 | FA17: =+EW17*EY17*30 -> 7200
C18: Midia 5 | D18: Adet | E18: 1 | AG18: =+E18 -> 1 | AH18: =+E18 -> 1 | AI18: =+E18 -> 1 | AJ18: =+E18 -> 1 | AK18: =+E18 -> 1 | AL18: =+E18 -> 1 | AM18: =+E18 -> 1 | AN18: =+E18 -> 1 | AO18: =+E18 -> 1 | AP18: =+E18 -> 1 | AQ18: =+E18 -> 1 | AR18: =+E18 -> 1 | AS18: =+E18 -> 1 | AT18: =+E18 -> 1 | AU18: =+E18 -> 1 | AV18: =+E18 -> 1 | AW18: =+E18 -> 1 | AX18: =+E18 -> 1 | AY18: =+E18 -> 1 | AZ18: =+E18 -> 1 | BA18: =+E18 -> 1 | BB18: =+E18 -> 1 | BC18: =+E18 -> 1 | BD18: =+E18 -> 1 | BE18: =+E18 -> 1 | BF18: =+E18 -> 1 | BG18: =+E18 -> 1 | BH18: =+E18 -> 1 | BI18: =+E18 -> 1 | BJ18: =+E18 -> 1 | BK18: =+E18 -> 1 | BL18: =+E18 -> 1 | BM18: =+E18 -> 1 | BN18: =+E18 -> 1 | BO18: =+E18 -> 1 | BP18: =+E18 -> 1 | BQ18: =+AK18 -> 1 | BR18: =+AK18 -> 1 | BS18: =+AK18 -> 1 | BT18: =+AK18 -> 1 | BU18: =+AO18 -> 1 | BV18: =+AO18 -> 1 | BW18: =+AO18 -> 1 | BX18: =+AO18 -> 1 | BY18: =+AS18 -> 1 | BZ18: =+AS18 -> 1 | CA18: =+AS18 -> 1 | CB18: =+AS18 -> 1 | CC18: =+AW18 -> 1 | CD18: =+AW18 -> 1 | CE18: =+AW18 -> 1 | CF18: =+AW18 -> 1 | CG18: =+BA18 -> 1 | CH18: =+BA18 -> 1 | CI18: =+BA18 -> 1 | CJ18: =+BA18 -> 1 | CK18: =+BE18 -> 1 | CL18: =+BE18 -> 1 | CM18: =+BE18 -> 1 | CN18: =+BE18 -> 1 | CO18: =+BI18 -> 1 | CP18: =+BI18 -> 1 | CQ18: =+BI18 -> 1 | CR18: =+BI18 -> 1 | CS18: =+BM18 -> 1 | CT18: =+BM18 -> 1 | CU18: =+BM18 -> 1 | CV18: =+BM18 -> 1 | CW18: =+BQ18 -> 1 | CX18: =+BQ18 -> 1 | CY18: =+BQ18 -> 1 | CZ18: =+BQ18 -> 1 | DA18: =+BU18 -> 1 | DB18: =+BU18 -> 1 | DC18: =+BU18 -> 1 | DD18: =+BU18 -> 1 | DE18: =+BY18 -> 1 | DF18: =+BY18 -> 1 | DG18: =+BY18 -> 1 | DH18: =+BY18 -> 1 | DI18: =+CC18 -> 1 | DJ18: =+CC18 -> 1 | DK18: =+CC18 -> 1 | DL18: =+CC18 -> 1 | DM18: =+CG18 -> 1 | DN18: =+CG18 -> 1 | DO18: =+CG18 -> 1 | DP18: =+CG18 -> 1 | DQ18: =+CK18 -> 1 | DR18: =+CK18 -> 1 | DS18: =+CK18 -> 1 | DT18: =+CK18 -> 1 | DU18: =+CO18 -> 1 | DV18: =+CO18 -> 1 | DW18: =+CO18 -> 1 | DX18: =+CO18 -> 1 | DY18: =+CS18 -> 1 | DZ18: =+CS18 -> 1 | EA18: =+CS18 -> 1 | EB18: =+CS18 -> 1 | EC18: =+CW18 -> 1 | ED18: =+CW18 -> 1 | EE18: =+CW18 -> 1 | EF18: =+CW18 -> 1 | EG18: =+DA18 -> 1 | EH18: =+DA18 -> 1 | EI18: =+DA18 -> 1 | EJ18: =+DA18 -> 1 | EK18: =+DE18 -> 1 | EL18: =+DE18 -> 1 | EM18: =+DE18 -> 1 | EN18: =+DE18 -> 1 | EO18: =+DI18 -> 1 | EP18: =+DI18 -> 1 | EQ18: =+DI18 -> 1 | ER18: =+DI18 -> 1 | ES18: =+DM18 -> 1 | ET18: =+DM18 -> 1 | EU18: =+DM18 -> 1 | EV18: =+DM18 -> 1 | EW18: =SUM(I18:EV18)/4 -> 30 | EX18: 16 | EY18: =24-EX18 -> 8 | EZ18: =+EW18*EX18*28 -> 13440 | FA18: =+EW18*EY18*30 -> 7200
C19: Midia 8 | D19: Adet | E19: 1 | AG19: =+E19 -> 1 | AH19: =+E19 -> 1 | AI19: =+E19 -> 1 | AJ19: =+E19 -> 1 | AK19: =+E19 -> 1 | AL19: =+E19 -> 1 | AM19: =+E19 -> 1 | AN19: =+E19 -> 1 | AO19: =+E19 -> 1 | AP19: =+E19 -> 1 | AQ19: =+E19 -> 1 | AR19: =+E19 -> 1 | AS19: =+E19 -> 1 | AT19: =+E19 -> 1 | AU19: =+E19 -> 1 | AV19: =+E19 -> 1 | AW19: =+E19 -> 1 | AX19: =+E19 -> 1 | AY19: =+E19 -> 1 | AZ19: =+E19 -> 1 | BA19: =+E19 -> 1 | BB19: =+E19 -> 1 | BC19: =+E19 -> 1 | BD19: =+E19 -> 1 | BE19: =+E19 -> 1 | BF19: =+E19 -> 1 | BG19: =+E19 -> 1 | BH19: =+E19 -> 1 | BI19: =+E19 -> 1 | BJ19: =+E19 -> 1 | BK19: =+E19 -> 1 | BL19: =+E19 -> 1 | BM19: =+E19 -> 1 | BN19: =+E19 -> 1 | BO19: =+E19 -> 1 | BP19: =+E19 -> 1 | BQ19: =+AK19 -> 1 | BR19: =+AK19 -> 1 | BS19: =+AK19 -> 1 | BT19: =+AK19 -> 1 | BU19: =+AO19 -> 1 | BV19: =+AO19 -> 1 | BW19: =+AO19 -> 1 | BX19: =+AO19 -> 1 | BY19: =+AS19 -> 1 | BZ19: =+AS19 -> 1 | CA19: =+AS19 -> 1 | CB19: =+AS19 -> 1 | CC19: =+AW19 -> 1 | CD19: =+AW19 -> 1 | CE19: =+AW19 -> 1 | CF19: =+AW19 -> 1 | CG19: =+BA19 -> 1 | CH19: =+BA19 -> 1 | CI19: =+BA19 -> 1 | CJ19: =+BA19 -> 1 | CK19: =+BE19 -> 1 | CL19: =+BE19 -> 1 | CM19: =+BE19 -> 1 | CN19: =+BE19 -> 1 | CO19: =+BI19 -> 1 | CP19: =+BI19 -> 1 | CQ19: =+BI19 -> 1 | CR19: =+BI19 -> 1 | CS19: =+BM19 -> 1 | CT19: =+BM19 -> 1 | CU19: =+BM19 -> 1 | CV19: =+BM19 -> 1 | CW19: =+BQ19 -> 1 | CX19: =+BQ19 -> 1 | CY19: =+BQ19 -> 1 | CZ19: =+BQ19 -> 1 | DA19: =+BU19 -> 1 | DB19: =+BU19 -> 1 | DC19: =+BU19 -> 1 | DD19: =+BU19 -> 1 | DE19: =+BY19 -> 1 | DF19: =+BY19 -> 1 | DG19: =+BY19 -> 1 | DH19: =+BY19 -> 1 | DI19: =+CC19 -> 1 | DJ19: =+CC19 -> 1 | DK19: =+CC19 -> 1 | DL19: =+CC19 -> 1 | DM19: =+CG19 -> 1 | DN19: =+CG19 -> 1 | DO19: =+CG19 -> 1 | DP19: =+CG19 -> 1 | DQ19: =+CK19 -> 1 | DR19: =+CK19 -> 1 | DS19: =+CK19 -> 1 | DT19: =+CK19 -> 1 | DU19: =+CO19 -> 1 | DV19: =+CO19 -> 1 | DW19: =+CO19 -> 1 | DX19: =+CO19 -> 1 | DY19: =+CS19 -> 1 | DZ19: =+CS19 -> 1 | EA19: =+CS19 -> 1 | EB19: =+CS19 -> 1 | EC19: =+CW19 -> 1 | ED19: =+CW19 -> 1 | EE19: =+CW19 -> 1 | EF19: =+CW19 -> 1 | EG19: =+DA19 -> 1 | EH19: =+DA19 -> 1 | EI19: =+DA19 -> 1 | EJ19: =+DA19 -> 1 | EK19: =+DE19 -> 1 | EL19: =+DE19 -> 1 | EM19: =+DE19 -> 1 | EN19: =+DE19 -> 1 | EO19: =+DI19 -> 1 | EP19: =+DI19 -> 1 | EQ19: =+DI19 -> 1 | ER19: =+DI19 -> 1 | ES19: =+DM19 -> 1 | ET19: =+DM19 -> 1 | EU19: =+DM19 -> 1 | EV19: =+DM19 -> 1 | EW19: =SUM(I19:EV19)/4 -> 30 | EX19: 16 | EY19: =24-EX19 -> 8 | EZ19: =+EW19*EX19*28 -> 13440 | FA19: =+EW19*EY19*30 -> 7200
C20: Midia 13 | D20: Adet | E20: 1 | AG20: =+E20 -> 1 | AH20: =+E20 -> 1 | AI20: =+E20 -> 1 | AJ20: =+E20 -> 1 | AK20: =+E20 -> 1 | AL20: =+E20 -> 1 | AM20: =+E20 -> 1 | AN20: =+E20 -> 1 | AO20: =+E20 -> 1 | AP20: =+E20 -> 1 | AQ20: =+E20 -> 1 | AR20: =+E20 -> 1 | AS20: =+E20 -> 1 | AT20: =+E20 -> 1 | AU20: =+E20 -> 1 | AV20: =+E20 -> 1 | AW20: =+E20 -> 1 | AX20: =+E20 -> 1 | AY20: =+E20 -> 1 | AZ20: =+E20 -> 1 | BA20: =+E20 -> 1 | BB20: =+E20 -> 1 | BC20: =+E20 -> 1 | BD20: =+E20 -> 1 | BE20: =+E20 -> 1 | BF20: =+E20 -> 1 | BG20: =+E20 -> 1 | BH20: =+E20 -> 1 | BI20: =+E20 -> 1 | BJ20: =+E20 -> 1 | BK20: =+E20 -> 1 | BL20: =+E20 -> 1 | BM20: =+E20 -> 1 | BN20: =+E20 -> 1 | BO20: =+E20 -> 1 | BP20: =+E20 -> 1 | BQ20: =+AK20 -> 1 | BR20: =+AK20 -> 1 | BS20: =+AK20 -> 1 | BT20: =+AK20 -> 1 | BU20: =+AO20 -> 1 | BV20: =+AO20 -> 1 | BW20: =+AO20 -> 1 | BX20: =+AO20 -> 1 | BY20: =+AS20 -> 1 | BZ20: =+AS20 -> 1 | CA20: =+AS20 -> 1 | CB20: =+AS20 -> 1 | CC20: =+AW20 -> 1 | CD20: =+AW20 -> 1 | CE20: =+AW20 -> 1 | CF20: =+AW20 -> 1 | CG20: =+BA20 -> 1 | CH20: =+BA20 -> 1 | CI20: =+BA20 -> 1 | CJ20: =+BA20 -> 1 | CK20: =+BE20 -> 1 | CL20: =+BE20 -> 1 | CM20: =+BE20 -> 1 | CN20: =+BE20 -> 1 | CO20: =+BI20 -> 1 | CP20: =+BI20 -> 1 | CQ20: =+BI20 -> 1 | CR20: =+BI20 -> 1 | CS20: =+BM20 -> 1 | CT20: =+BM20 -> 1 | CU20: =+BM20 -> 1 | CV20: =+BM20 -> 1 | CW20: =+BQ20 -> 1 | CX20: =+BQ20 -> 1 | CY20: =+BQ20 -> 1 | CZ20: =+BQ20 -> 1 | DA20: =+BU20 -> 1 | DB20: =+BU20 -> 1 | DC20: =+BU20 -> 1 | DD20: =+BU20 -> 1 | DE20: =+BY20 -> 1 | DF20: =+BY20 -> 1 | DG20: =+BY20 -> 1 | DH20: =+BY20 -> 1 | DI20: =+CC20 -> 1 | DJ20: =+CC20 -> 1 | DK20: =+CC20 -> 1 | DL20: =+CC20 -> 1 | DM20: =+CG20 -> 1 | DN20: =+CG20 -> 1 | DO20: =+CG20 -> 1 | DP20: =+CG20 -> 1 | DQ20: =+CK20 -> 1 | DR20: =+CK20 -> 1 | DS20: =+CK20 -> 1 | DT20: =+CK20 -> 1 | DU20: =+CO20 -> 1 | DV20: =+CO20 -> 1 | DW20: =+CO20 -> 1 | DX20: =+CO20 -> 1 | DY20: =+CS20 -> 1 | DZ20: =+CS20 -> 1 | EA20: =+CS20 -> 1 | EB20: =+CS20 -> 1 | EC20: =+CW20 -> 1 | ED20: =+CW20 -> 1 | EE20: =+CW20 -> 1 | EF20: =+CW20 -> 1 | EG20: =+DA20 -> 1 | EH20: =+DA20 -> 1 | EI20: =+DA20 -> 1 | EJ20: =+DA20 -> 1 | EK20: =+DE20 -> 1 | EL20: =+DE20 -> 1 | EM20: =+DE20 -> 1 | EN20: =+DE20 -> 1 | EO20: =+DI20 -> 1 | EP20: =+DI20 -> 1 | EQ20: =+DI20 -> 1 | ER20: =+DI20 -> 1 | ES20: =+DM20 -> 1 | ET20: =+DM20 -> 1 | EU20: =+DM20 -> 1 | EV20: =+DM20 -> 1 | EW20: =SUM(I20:EV20)/4 -> 30 | EX20: 16 | EY20: =24-EX20 -> 8 | EZ20: =+EW20*EX20*28 -> 13440 | FA20: =+EW20*EY20*30 -> 7200
C21: Paşa | D21: Adet | E21: 1 | AG21: =+E21 -> 1 | AH21: =+E21 -> 1 | AI21: =+E21 -> 1 | AJ21: =+E21 -> 1 | AK21: =+E21 -> 1 | AL21: =+E21 -> 1 | AM21: =+E21 -> 1 | AN21: =+E21 -> 1 | AO21: =+E21 -> 1 | AP21: =+E21 -> 1 | AQ21: =+E21 -> 1 | AR21: =+E21 -> 1 | AS21: =+E21 -> 1 | AT21: =+E21 -> 1 | AU21: =+E21 -> 1 | AV21: =+E21 -> 1 | AW21: =+E21 -> 1 | AX21: =+E21 -> 1 | AY21: =+E21 -> 1 | AZ21: =+E21 -> 1 | BA21: =+E21 -> 1 | BB21: =+E21 -> 1 | BC21: =+E21 -> 1 | BD21: =+E21 -> 1 | BE21: =+E21 -> 1 | BF21: =+E21 -> 1 | BG21: =+E21 -> 1 | BH21: =+E21 -> 1 | BI21: =+E21 -> 1 | BJ21: =+E21 -> 1 | BK21: =+E21 -> 1 | BL21: =+E21 -> 1 | BM21: =+E21 -> 1 | BN21: =+E21 -> 1 | BO21: =+E21 -> 1 | BP21: =+E21 -> 1 | BQ21: =+AK21 -> 1 | BR21: =+AK21 -> 1 | BS21: =+AK21 -> 1 | BT21: =+AK21 -> 1 | BU21: =+AO21 -> 1 | BV21: =+AO21 -> 1 | BW21: =+AO21 -> 1 | BX21: =+AO21 -> 1 | BY21: =+AS21 -> 1 | BZ21: =+AS21 -> 1 | CA21: =+AS21 -> 1 | CB21: =+AS21 -> 1 | CC21: =+AW21 -> 1 | CD21: =+AW21 -> 1 | CE21: =+AW21 -> 1 | CF21: =+AW21 -> 1 | CG21: =+BA21 -> 1 | CH21: =+BA21 -> 1 | CI21: =+BA21 -> 1 | CJ21: =+BA21 -> 1 | CK21: =+BE21 -> 1 | CL21: =+BE21 -> 1 | CM21: =+BE21 -> 1 | CN21: =+BE21 -> 1 | CO21: =+BI21 -> 1 | CP21: =+BI21 -> 1 | CQ21: =+BI21 -> 1 | CR21: =+BI21 -> 1 | CS21: =+BM21 -> 1 | CT21: =+BM21 -> 1 | CU21: =+BM21 -> 1 | CV21: =+BM21 -> 1 | CW21: =+BQ21 -> 1 | CX21: =+BQ21 -> 1 | CY21: =+BQ21 -> 1 | CZ21: =+BQ21 -> 1 | DA21: =+BU21 -> 1 | DB21: =+BU21 -> 1 | DC21: =+BU21 -> 1 | DD21: =+BU21 -> 1 | DE21: =+BY21 -> 1 | DF21: =+BY21 -> 1 | DG21: =+BY21 -> 1 | DH21: =+BY21 -> 1 | DI21: =+CC21 -> 1 | DJ21: =+CC21 -> 1 | DK21: =+CC21 -> 1 | DL21: =+CC21 -> 1 | DM21: =+CG21 -> 1 | DN21: =+CG21 -> 1 | DO21: =+CG21 -> 1 | DP21: =+CG21 -> 1 | DQ21: =+CK21 -> 1 | DR21: =+CK21 -> 1 | DS21: =+CK21 -> 1 | DT21: =+CK21 -> 1 | DU21: =+CO21 -> 1 | DV21: =+CO21 -> 1 | DW21: =+CO21 -> 1 | DX21: =+CO21 -> 1 | DY21: =+CS21 -> 1 | DZ21: =+CS21 -> 1 | EA21: =+CS21 -> 1 | EB21: =+CS21 -> 1 | EC21: =+CW21 -> 1 | ED21: =+CW21 -> 1 | EE21: =+CW21 -> 1 | EF21: =+CW21 -> 1 | EG21: =+DA21 -> 1 | EH21: =+DA21 -> 1 | EI21: =+DA21 -> 1 | EJ21: =+DA21 -> 1 | EK21: =+DE21 -> 1 | EL21: =+DE21 -> 1 | EM21: =+DE21 -> 1 | EN21: =+DE21 -> 1 | EO21: =+DI21 -> 1 | EP21: =+DI21 -> 1 | EQ21: =+DI21 -> 1 | ER21: =+DI21 -> 1 | ES21: =+DM21 -> 1 | ET21: =+DM21 -> 1 | EU21: =+DM21 -> 1 | EV21: =+DM21 -> 1 | EW21: =SUM(I21:EV21)/4 -> 30 | EX21: 16 | EY21: =24-EX21 -> 8 | EZ21: =+EW21*EX21*28 -> 13440 | FA21: =+EW21*EY21*30 -> 7200
C22: Hila | D22: Adet | E22: 1 | AG22: =+E22 -> 1 | AH22: =+E22 -> 1 | AI22: =+E22 -> 1 | AJ22: =+E22 -> 1 | AK22: =+E22 -> 1 | AL22: =+E22 -> 1 | AM22: =+E22 -> 1 | AN22: =+E22 -> 1 | AO22: =+E22 -> 1 | AP22: =+E22 -> 1 | AQ22: =+E22 -> 1 | AR22: =+E22 -> 1 | AS22: =+E22 -> 1 | AT22: =+E22 -> 1 | AU22: =+E22 -> 1 | AV22: =+E22 -> 1 | AW22: =+E22 -> 1 | AX22: =+E22 -> 1 | AY22: =+E22 -> 1 | AZ22: =+E22 -> 1 | BA22: =+E22 -> 1 | BB22: =+E22 -> 1 | BC22: =+E22 -> 1 | BD22: =+E22 -> 1 | BE22: =+E22 -> 1 | BF22: =+E22 -> 1 | BG22: =+E22 -> 1 | BH22: =+E22 -> 1 | BI22: =+E22 -> 1 | BJ22: =+E22 -> 1 | BK22: =+E22 -> 1 | BL22: =+E22 -> 1 | BM22: =+E22 -> 1 | BN22: =+E22 -> 1 | BO22: =+E22 -> 1 | BP22: =+E22 -> 1 | BQ22: =+AK22 -> 1 | BR22: =+AK22 -> 1 | BS22: =+AK22 -> 1 | BT22: =+AK22 -> 1 | BU22: =+AO22 -> 1 | BV22: =+AO22 -> 1 | BW22: =+AO22 -> 1 | BX22: =+AO22 -> 1 | BY22: =+AS22 -> 1 | BZ22: =+AS22 -> 1 | CA22: =+AS22 -> 1 | CB22: =+AS22 -> 1 | CC22: =+AW22 -> 1 | CD22: =+AW22 -> 1 | CE22: =+AW22 -> 1 | CF22: =+AW22 -> 1 | CG22: =+BA22 -> 1 | CH22: =+BA22 -> 1 | CI22: =+BA22 -> 1 | CJ22: =+BA22 -> 1 | CK22: =+BE22 -> 1 | CL22: =+BE22 -> 1 | CM22: =+BE22 -> 1 | CN22: =+BE22 -> 1 | CO22: =+BI22 -> 1 | CP22: =+BI22 -> 1 | CQ22: =+BI22 -> 1 | CR22: =+BI22 -> 1 | CS22: =+BM22 -> 1 | CT22: =+BM22 -> 1 | CU22: =+BM22 -> 1 | CV22: =+BM22 -> 1 | CW22: =+BQ22 -> 1 | CX22: =+BQ22 -> 1 | CY22: =+BQ22 -> 1 | CZ22: =+BQ22 -> 1 | DA22: =+BU22 -> 1 | DB22: =+BU22 -> 1 | DC22: =+BU22 -> 1 | DD22: =+BU22 -> 1 | DE22: =+BY22 -> 1 | DF22: =+BY22 -> 1 | DG22: =+BY22 -> 1 | DH22: =+BY22 -> 1 | DI22: =+CC22 -> 1 | DJ22: =+CC22 -> 1 | DK22: =+CC22 -> 1 | DL22: =+CC22 -> 1 | DM22: =+CG22 -> 1 | DN22: =+CG22 -> 1 | DO22: =+CG22 -> 1 | DP22: =+CG22 -> 1 | DQ22: =+CK22 -> 1 | DR22: =+CK22 -> 1 | DS22: =+CK22 -> 1 | DT22: =+CK22 -> 1 | DU22: =+CO22 -> 1 | DV22: =+CO22 -> 1 | DW22: =+CO22 -> 1 | DX22: =+CO22 -> 1 | DY22: =+CS22 -> 1 | DZ22: =+CS22 -> 1 | EA22: =+CS22 -> 1 | EB22: =+CS22 -> 1 | EC22: =+CW22 -> 1 | ED22: =+CW22 -> 1 | EE22: =+CW22 -> 1 | EF22: =+CW22 -> 1 | EG22: =+DA22 -> 1 | EH22: =+DA22 -> 1 | EI22: =+DA22 -> 1 | EJ22: =+DA22 -> 1 | EK22: =+DE22 -> 1 | EL22: =+DE22 -> 1 | EM22: =+DE22 -> 1 | EN22: =+DE22 -> 1 | EO22: =+DI22 -> 1 | EP22: =+DI22 -> 1 | EQ22: =+DI22 -> 1 | ER22: =+DI22 -> 1 | ES22: =+DM22 -> 1 | ET22: =+DM22 -> 1 | EU22: =+DM22 -> 1 | EV22: =+DM22 -> 1 | EW22: =SUM(I22:EV22)/4 -> 30 | EX22: 16 | EY22: =24-EX22 -> 8 | EZ22: =+EW22*EX22*28 -> 13440 | FA22: =+EW22*EY22*30 -> 7200
C23: Daria | D23: Adet | E23: 1 | AG23: =+E23 -> 1 | AH23: =+E23 -> 1 | AI23: =+E23 -> 1 | AJ23: =+E23 -> 1 | AK23: =+E23 -> 1 | AL23: =+E23 -> 1 | AM23: =+E23 -> 1 | AN23: =+E23 -> 1 | AO23: =+E23 -> 1 | AP23: =+E23 -> 1 | AQ23: =+E23 -> 1 | AR23: =+E23 -> 1 | AS23: =+E23 -> 1 | AT23: =+E23 -> 1 | AU23: =+E23 -> 1 | AV23: =+E23 -> 1 | AW23: =+E23 -> 1 | AX23: =+E23 -> 1 | AY23: =+E23 -> 1 | AZ23: =+E23 -> 1 | BA23: =+E23 -> 1 | BB23: =+E23 -> 1 | BC23: =+E23 -> 1 | BD23: =+E23 -> 1 | BE23: =+E23 -> 1 | BF23: =+E23 -> 1 | BG23: =+E23 -> 1 | BH23: =+E23 -> 1 | BI23: =+E23 -> 1 | BJ23: =+E23 -> 1 | BK23: =+E23 -> 1 | BL23: =+E23 -> 1 | BM23: =+E23 -> 1 | BN23: =+E23 -> 1 | BO23: =+E23 -> 1 | BP23: =+E23 -> 1 | BQ23: =+AK23 -> 1 | BR23: =+AK23 -> 1 | BS23: =+AK23 -> 1 | BT23: =+AK23 -> 1 | BU23: =+AO23 -> 1 | BV23: =+AO23 -> 1 | BW23: =+AO23 -> 1 | BX23: =+AO23 -> 1 | BY23: =+AS23 -> 1 | BZ23: =+AS23 -> 1 | CA23: =+AS23 -> 1 | CB23: =+AS23 -> 1 | CC23: =+AW23 -> 1 | CD23: =+AW23 -> 1 | CE23: =+AW23 -> 1 | CF23: =+AW23 -> 1 | CG23: =+BA23 -> 1 | CH23: =+BA23 -> 1 | CI23: =+BA23 -> 1 | CJ23: =+BA23 -> 1 | CK23: =+BE23 -> 1 | CL23: =+BE23 -> 1 | CM23: =+BE23 -> 1 | CN23: =+BE23 -> 1 | CO23: =+BI23 -> 1 | CP23: =+BI23 -> 1 | CQ23: =+BI23 -> 1 | CR23: =+BI23 -> 1 | CS23: =+BM23 -> 1 | CT23: =+BM23 -> 1 | CU23: =+BM23 -> 1 | CV23: =+BM23 -> 1 | CW23: =+BQ23 -> 1 | CX23: =+BQ23 -> 1 | CY23: =+BQ23 -> 1 | CZ23: =+BQ23 -> 1 | DA23: =+BU23 -> 1 | DB23: =+BU23 -> 1 | DC23: =+BU23 -> 1 | DD23: =+BU23 -> 1 | DE23: =+BY23 -> 1 | DF23: =+BY23 -> 1 | DG23: =+BY23 -> 1 | DH23: =+BY23 -> 1 | DI23: =+CC23 -> 1 | DJ23: =+CC23 -> 1 | DK23: =+CC23 -> 1 | DL23: =+CC23 -> 1 | DM23: =+CG23 -> 1 | DN23: =+CG23 -> 1 | DO23: =+CG23 -> 1 | DP23: =+CG23 -> 1 | DQ23: =+CK23 -> 1 | DR23: =+CK23 -> 1 | DS23: =+CK23 -> 1 | DT23: =+CK23 -> 1 | DU23: =+CO23 -> 1 | DV23: =+CO23 -> 1 | DW23: =+CO23 -> 1 | DX23: =+CO23 -> 1 | DY23: =+CS23 -> 1 | DZ23: =+CS23 -> 1 | EA23: =+CS23 -> 1 | EB23: =+CS23 -> 1 | EC23: =+CW23 -> 1 | ED23: =+CW23 -> 1 | EE23: =+CW23 -> 1 | EF23: =+CW23 -> 1 | EG23: =+DA23 -> 1 | EH23: =+DA23 -> 1 | EI23: =+DA23 -> 1 | EJ23: =+DA23 -> 1 | EK23: =+DE23 -> 1 | EL23: =+DE23 -> 1 | EM23: =+DE23 -> 1 | EN23: =+DE23 -> 1 | EO23: =+DI23 -> 1 | EP23: =+DI23 -> 1 | EQ23: =+DI23 -> 1 | ER23: =+DI23 -> 1 | ES23: =+DM23 -> 1 | ET23: =+DM23 -> 1 | EU23: =+DM23 -> 1 | EV23: =+DM23 -> 1 | EW23: =SUM(I23:EV23)/4 -> 30 | EX23: 16 | EY23: =24-EX23 -> 8 | EZ23: =+EW23*EX23*28 -> 13440 | FA23: =+EW23*EY23*30 -> 7200
C24: Hadar | D24: Adet | E24: 1 | AG24: =+E24 -> 1 | AH24: =+E24 -> 1 | AI24: =+E24 -> 1 | AJ24: =+E24 -> 1 | AK24: =+E24 -> 1 | AL24: =+E24 -> 1 | AM24: =+E24 -> 1 | AN24: =+E24 -> 1 | AO24: =+E24 -> 1 | AP24: =+E24 -> 1 | AQ24: =+E24 -> 1 | AR24: =+E24 -> 1 | AS24: =+E24 -> 1 | AT24: =+E24 -> 1 | AU24: =+E24 -> 1 | AV24: =+E24 -> 1 | AW24: =+E24 -> 1 | AX24: =+E24 -> 1 | AY24: =+E24 -> 1 | AZ24: =+E24 -> 1 | BA24: =+E24 -> 1 | BB24: =+E24 -> 1 | BC24: =+E24 -> 1 | BD24: =+E24 -> 1 | BE24: =+E24 -> 1 | BF24: =+E24 -> 1 | BG24: =+E24 -> 1 | BH24: =+E24 -> 1 | BI24: =+E24 -> 1 | BJ24: =+E24 -> 1 | BK24: =+E24 -> 1 | BL24: =+E24 -> 1 | BM24: =+E24 -> 1 | BN24: =+E24 -> 1 | BO24: =+E24 -> 1 | BP24: =+E24 -> 1 | BQ24: =+AK24 -> 1 | BR24: =+AK24 -> 1 | BS24: =+AK24 -> 1 | BT24: =+AK24 -> 1 | BU24: =+AO24 -> 1 | BV24: =+AO24 -> 1 | BW24: =+AO24 -> 1 | BX24: =+AO24 -> 1 | BY24: =+AS24 -> 1 | BZ24: =+AS24 -> 1 | CA24: =+AS24 -> 1 | CB24: =+AS24 -> 1 | CC24: =+AW24 -> 1 | CD24: =+AW24 -> 1 | CE24: =+AW24 -> 1 | CF24: =+AW24 -> 1 | CG24: =+BA24 -> 1 | CH24: =+BA24 -> 1 | CI24: =+BA24 -> 1 | CJ24: =+BA24 -> 1 | CK24: =+BE24 -> 1 | CL24: =+BE24 -> 1 | CM24: =+BE24 -> 1 | CN24: =+BE24 -> 1 | CO24: =+BI24 -> 1 | CP24: =+BI24 -> 1 | CQ24: =+BI24 -> 1 | CR24: =+BI24 -> 1 | CS24: =+BM24 -> 1 | CT24: =+BM24 -> 1 | CU24: =+BM24 -> 1 | CV24: =+BM24 -> 1 | CW24: =+BQ24 -> 1 | CX24: =+BQ24 -> 1 | CY24: =+BQ24 -> 1 | CZ24: =+BQ24 -> 1 | DA24: =+BU24 -> 1 | DB24: =+BU24 -> 1 | DC24: =+BU24 -> 1 | DD24: =+BU24 -> 1 | DE24: =+BY24 -> 1 | DF24: =+BY24 -> 1 | DG24: =+BY24 -> 1 | DH24: =+BY24 -> 1 | DI24: =+CC24 -> 1 | DJ24: =+CC24 -> 1 | DK24: =+CC24 -> 1 | DL24: =+CC24 -> 1 | DM24: =+CG24 -> 1 | DN24: =+CG24 -> 1 | DO24: =+CG24 -> 1 | DP24: =+CG24 -> 1 | DQ24: =+CK24 -> 1 | DR24: =+CK24 -> 1 | DS24: =+CK24 -> 1 | DT24: =+CK24 -> 1 | DU24: =+CO24 -> 1 | DV24: =+CO24 -> 1 | DW24: =+CO24 -> 1 | DX24: =+CO24 -> 1 | DY24: =+CS24 -> 1 | DZ24: =+CS24 -> 1 | EA24: =+CS24 -> 1 | EB24: =+CS24 -> 1 | EC24: =+CW24 -> 1 | ED24: =+CW24 -> 1 | EE24: =+CW24 -> 1 | EF24: =+CW24 -> 1 | EG24: =+DA24 -> 1 | EH24: =+DA24 -> 1 | EI24: =+DA24 -> 1 | EJ24: =+DA24 -> 1 | EK24: =+DE24 -> 1 | EL24: =+DE24 -> 1 | EM24: =+DE24 -> 1 | EN24: =+DE24 -> 1 | EO24: =+DI24 -> 1 | EP24: =+DI24 -> 1 | EQ24: =+DI24 -> 1 | ER24: =+DI24 -> 1 | ES24: =+DM24 -> 1 | ET24: =+DM24 -> 1 | EU24: =+DM24 -> 1 | EV24: =+DM24 -> 1 | EW24: =SUM(I24:EV24)/4 -> 30 | EX24: 16 | EY24: =24-EX24 -> 8 | EZ24: =+EW24*EX24*28 -> 13440 | FA24: =+EW24*EY24*30 -> 7200
C25: Split Barge (x5) | D25: Adet | E25: 5 | AG25: =+E25 -> 5 | AH25: =+E25 -> 5 | AI25: =+E25 -> 5 | AJ25: =+E25 -> 5 | AK25: =+E25 -> 5 | AL25: =+E25 -> 5 | AM25: =+E25 -> 5 | AN25: =+E25 -> 5 | AO25: =+E25 -> 5 | AP25: =+E25 -> 5 | AQ25: =+E25 -> 5 | AR25: =+E25 -> 5 | AS25: =+E25 -> 5 | AT25: =+E25 -> 5 | AU25: =+E25 -> 5 | AV25: =+E25 -> 5 | AW25: =+E25 -> 5 | AX25: =+E25 -> 5 | AY25: =+E25 -> 5 | AZ25: =+E25 -> 5 | BA25: =+E25 -> 5 | BB25: =+E25 -> 5 | BC25: =+E25 -> 5 | BD25: =+E25 -> 5 | BE25: =+E25 -> 5 | BF25: =+E25 -> 5 | BG25: =+E25 -> 5 | BH25: =+E25 -> 5 | BI25: =+E25 -> 5 | BJ25: =+E25 -> 5 | BK25: =+E25 -> 5 | BL25: =+E25 -> 5 | BM25: =+E25 -> 5 | BN25: =+E25 -> 5 | BO25: =+E25 -> 5 | BP25: =+E25 -> 5 | BQ25: =+AK25 -> 5 | BR25: =+AK25 -> 5 | BS25: =+AK25 -> 5 | BT25: =+AK25 -> 5 | BU25: =+AO25 -> 5 | BV25: =+AO25 -> 5 | BW25: =+AO25 -> 5 | BX25: =+AO25 -> 5 | BY25: =+AS25 -> 5 | BZ25: =+AS25 -> 5 | CA25: =+AS25 -> 5 | CB25: =+AS25 -> 5 | CC25: =+AW25 -> 5 | CD25: =+AW25 -> 5 | CE25: =+AW25 -> 5 | CF25: =+AW25 -> 5 | CG25: =+BA25 -> 5 | CH25: =+BA25 -> 5 | CI25: =+BA25 -> 5 | CJ25: =+BA25 -> 5 | CK25: =+BE25 -> 5 | CL25: =+BE25 -> 5 | CM25: =+BE25 -> 5 | CN25: =+BE25 -> 5 | CO25: =+BI25 -> 5 | CP25: =+BI25 -> 5 | CQ25: =+BI25 -> 5 | CR25: =+BI25 -> 5 | CS25: =+BM25 -> 5 | CT25: =+BM25 -> 5 | CU25: =+BM25 -> 5 | CV25: =+BM25 -> 5 | CW25: =+BQ25 -> 5 | CX25: =+BQ25 -> 5 | CY25: =+BQ25 -> 5 | CZ25: =+BQ25 -> 5 | DA25: =+BU25 -> 5 | DB25: =+BU25 -> 5 | DC25: =+BU25 -> 5 | DD25: =+BU25 -> 5 | DE25: =+BY25 -> 5 | DF25: =+BY25 -> 5 | DG25: =+BY25 -> 5 | DH25: =+BY25 -> 5 | DI25: =+CC25 -> 5 | DJ25: =+CC25 -> 5 | DK25: =+CC25 -> 5 | DL25: =+CC25 -> 5 | DM25: =+CG25 -> 5 | DN25: =+CG25 -> 5 | DO25: =+CG25 -> 5 | DP25: =+CG25 -> 5 | DQ25: =+CK25 -> 5 | DR25: =+CK25 -> 5 | DS25: =+CK25 -> 5 | DT25: =+CK25 -> 5 | DU25: =+CO25 -> 5 | DV25: =+CO25 -> 5 | DW25: =+CO25 -> 5 | DX25: =+CO25 -> 5 | DY25: =+CS25 -> 5 | DZ25: =+CS25 -> 5 | EA25: =+CS25 -> 5 | EB25: =+CS25 -> 5 | EC25: =+CW25 -> 5 | ED25: =+CW25 -> 5 | EE25: =+CW25 -> 5 | EF25: =+CW25 -> 5 | EG25: =+DA25 -> 5 | EH25: =+DA25 -> 5 | EI25: =+DA25 -> 5 | EJ25: =+DA25 -> 5 | EK25: =+DE25 -> 5 | EL25: =+DE25 -> 5 | EM25: =+DE25 -> 5 | EN25: =+DE25 -> 5 | EO25: =+DI25 -> 5 | EP25: =+DI25 -> 5 | EQ25: =+DI25 -> 5 | ER25: =+DI25 -> 5 | ES25: =+DM25 -> 5 | ET25: =+DM25 -> 5 | EU25: =+DM25 -> 5 | EV25: =+DM25 -> 5 | EW25: =SUM(I25:EV25)/4 -> 150 | EX25: 16 | EY25: =24-EX25 -> 8 | EZ25: =+EW25*EX25*28 -> 67200 | FA25: =+EW25*EY25*30 -> 36000
C26: Bozkurt | D26: Adet | E26: 1 | AG26: =+E26 -> 1 | AH26: =+E26 -> 1 | AI26: =+E26 -> 1 | AJ26: =+E26 -> 1 | AK26: =+E26 -> 1 | AL26: =+E26 -> 1 | AM26: =+E26 -> 1 | AN26: =+E26 -> 1 | AO26: =+E26 -> 1 | AP26: =+E26 -> 1 | AQ26: =+E26 -> 1 | AR26: =+E26 -> 1 | AS26: =+E26 -> 1 | AT26: =+E26 -> 1 | AU26: =+E26 -> 1 | AV26: =+E26 -> 1 | AW26: =+E26 -> 1 | AX26: =+E26 -> 1 | AY26: =+E26 -> 1 | AZ26: =+E26 -> 1 | BA26: =+E26 -> 1 | BB26: =+E26 -> 1 | BC26: =+E26 -> 1 | BD26: =+E26 -> 1 | BE26: =+E26 -> 1 | BF26: =+E26 -> 1 | BG26: =+E26 -> 1 | BH26: =+E26 -> 1 | BI26: =+E26 -> 1 | BJ26: =+E26 -> 1 | BK26: =+E26 -> 1 | BL26: =+E26 -> 1 | BM26: =+E26 -> 1 | BN26: =+E26 -> 1 | BO26: =+E26 -> 1 | BP26: =+E26 -> 1 | BQ26: =+AK26 -> 1 | BR26: =+AK26 -> 1 | BS26: =+AK26 -> 1 | BT26: =+AK26 -> 1 | BU26: =+AO26 -> 1 | BV26: =+AO26 -> 1 | BW26: =+AO26 -> 1 | BX26: =+AO26 -> 1 | BY26: =+AS26 -> 1 | BZ26: =+AS26 -> 1 | CA26: =+AS26 -> 1 | CB26: =+AS26 -> 1 | CC26: =+AW26 -> 1 | CD26: =+AW26 -> 1 | CE26: =+AW26 -> 1 | CF26: =+AW26 -> 1 | CG26: =+BA26 -> 1 | CH26: =+BA26 -> 1 | CI26: =+BA26 -> 1 | CJ26: =+BA26 -> 1 | CK26: =+BE26 -> 1 | CL26: =+BE26 -> 1 | CM26: =+BE26 -> 1 | CN26: =+BE26 -> 1 | CO26: =+BI26 -> 1 | CP26: =+BI26 -> 1 | CQ26: =+BI26 -> 1 | CR26: =+BI26 -> 1 | CS26: =+BM26 -> 1 | CT26: =+BM26 -> 1 | CU26: =+BM26 -> 1 | CV26: =+BM26 -> 1 | CW26: =+BQ26 -> 1 | CX26: =+BQ26 -> 1 | CY26: =+BQ26 -> 1 | CZ26: =+BQ26 -> 1 | DA26: =+BU26 -> 1 | DB26: =+BU26 -> 1 | DC26: =+BU26 -> 1 | DD26: =+BU26 -> 1 | DE26: =+BY26 -> 1 | DF26: =+BY26 -> 1 | DG26: =+BY26 -> 1 | DH26: =+BY26 -> 1 | DI26: =+CC26 -> 1 | DJ26: =+CC26 -> 1 | DK26: =+CC26 -> 1 | DL26: =+CC26 -> 1 | DM26: =+CG26 -> 1 | DN26: =+CG26 -> 1 | DO26: =+CG26 -> 1 | DP26: =+CG26 -> 1 | DQ26: =+CK26 -> 1 | DR26: =+CK26 -> 1 | DS26: =+CK26 -> 1 | DT26: =+CK26 -> 1 | DU26: =+CO26 -> 1 | DV26: =+CO26 -> 1 | DW26: =+CO26 -> 1 | DX26: =+CO26 -> 1 | DY26: =+CS26 -> 1 | DZ26: =+CS26 -> 1 | EA26: =+CS26 -> 1 | EB26: =+CS26 -> 1 | EC26: =+CW26 -> 1 | ED26: =+CW26 -> 1 | EE26: =+CW26 -> 1 | EF26: =+CW26 -> 1 | EG26: =+DA26 -> 1 | EH26: =+DA26 -> 1 | EI26: =+DA26 -> 1 | EJ26: =+DA26 -> 1 | EK26: =+DE26 -> 1 | EL26: =+DE26 -> 1 | EM26: =+DE26 -> 1 | EN26: =+DE26 -> 1 | EO26: =+DI26 -> 1 | EP26: =+DI26 -> 1 | EQ26: =+DI26 -> 1 | ER26: =+DI26 -> 1 | ES26: =+DM26 -> 1 | ET26: =+DM26 -> 1 | EU26: =+DM26 -> 1 | EV26: =+DM26 -> 1 | EW26: =SUM(I26:EV26)/4 -> 30 | EX26: 16 | EY26: =24-EX26 -> 8 | EZ26: =+EW26*EX26*28 -> 13440 | FA26: =+EW26*EY26*30 -> 7200
C27: Yozgat | D27: Adet | E27: 1 | AG27: =+E27 -> 1 | AH27: =+E27 -> 1 | AI27: =+E27 -> 1 | AJ27: =+E27 -> 1 | AK27: =+E27 -> 1 | AL27: =+E27 -> 1 | AM27: =+E27 -> 1 | AN27: =+E27 -> 1 | AO27: =+E27 -> 1 | AP27: =+E27 -> 1 | AQ27: =+E27 -> 1 | AR27: =+E27 -> 1 | AS27: =+E27 -> 1 | AT27: =+E27 -> 1 | AU27: =+E27 -> 1 | AV27: =+E27 -> 1 | AW27: =+E27 -> 1 | AX27: =+E27 -> 1 | AY27: =+E27 -> 1 | AZ27: =+E27 -> 1 | BA27: =+E27 -> 1 | BB27: =+E27 -> 1 | BC27: =+E27 -> 1 | BD27: =+E27 -> 1 | BE27: =+E27 -> 1 | BF27: =+E27 -> 1 | BG27: =+E27 -> 1 | BH27: =+E27 -> 1 | BI27: =+E27 -> 1 | BJ27: =+E27 -> 1 | BK27: =+E27 -> 1 | BL27: =+E27 -> 1 | BM27: =+E27 -> 1 | BN27: =+E27 -> 1 | BO27: =+E27 -> 1 | BP27: =+E27 -> 1 | BQ27: =+AK27 -> 1 | BR27: =+AK27 -> 1 | BS27: =+AK27 -> 1 | BT27: =+AK27 -> 1 | BU27: =+AO27 -> 1 | BV27: =+AO27 -> 1 | BW27: =+AO27 -> 1 | BX27: =+AO27 -> 1 | BY27: =+AS27 -> 1 | BZ27: =+AS27 -> 1 | CA27: =+AS27 -> 1 | CB27: =+AS27 -> 1 | CC27: =+AW27 -> 1 | CD27: =+AW27 -> 1 | CE27: =+AW27 -> 1 | CF27: =+AW27 -> 1 | CG27: =+BA27 -> 1 | CH27: =+BA27 -> 1 | CI27: =+BA27 -> 1 | CJ27: =+BA27 -> 1 | CK27: =+BE27 -> 1 | CL27: =+BE27 -> 1 | CM27: =+BE27 -> 1 | CN27: =+BE27 -> 1 | CO27: =+BI27 -> 1 | CP27: =+BI27 -> 1 | CQ27: =+BI27 -> 1 | CR27: =+BI27 -> 1 | CS27: =+BM27 -> 1 | CT27: =+BM27 -> 1 | CU27: =+BM27 -> 1 | CV27: =+BM27 -> 1 | CW27: =+BQ27 -> 1 | CX27: =+BQ27 -> 1 | CY27: =+BQ27 -> 1 | CZ27: =+BQ27 -> 1 | DA27: =+BU27 -> 1 | DB27: =+BU27 -> 1 | DC27: =+BU27 -> 1 | DD27: =+BU27 -> 1 | DE27: =+BY27 -> 1 | DF27: =+BY27 -> 1 | DG27: =+BY27 -> 1 | DH27: =+BY27 -> 1 | DI27: =+CC27 -> 1 | DJ27: =+CC27 -> 1 | DK27: =+CC27 -> 1 | DL27: =+CC27 -> 1 | DM27: =+CG27 -> 1 | DN27: =+CG27 -> 1 | DO27: =+CG27 -> 1 | DP27: =+CG27 -> 1 | DQ27: =+CK27 -> 1 | DR27: =+CK27 -> 1 | DS27: =+CK27 -> 1 | DT27: =+CK27 -> 1 | DU27: =+CO27 -> 1 | DV27: =+CO27 -> 1 | DW27: =+CO27 -> 1 | DX27: =+CO27 -> 1 | DY27: =+CS27 -> 1 | DZ27: =+CS27 -> 1 | EA27: =+CS27 -> 1 | EB27: =+CS27 -> 1 | EC27: =+CW27 -> 1 | ED27: =+CW27 -> 1 | EE27: =+CW27 -> 1 | EF27: =+CW27 -> 1 | EG27: =+DA27 -> 1 | EH27: =+DA27 -> 1 | EI27: =+DA27 -> 1 | EJ27: =+DA27 -> 1 | EK27: =+DE27 -> 1 | EL27: =+DE27 -> 1 | EM27: =+DE27 -> 1 | EN27: =+DE27 -> 1 | EO27: =+DI27 -> 1 | EP27: =+DI27 -> 1 | EQ27: =+DI27 -> 1 | ER27: =+DI27 -> 1 | ES27: =+DM27 -> 1 | ET27: =+DM27 -> 1 | EU27: =+DM27 -> 1 | EV27: =+DM27 -> 1 | EW27: =SUM(I27:EV27)/4 -> 30 | EX27: 16 | EY27: =24-EX27 -> 8 | EZ27: =+EW27*EX27*28 -> 13440 | FA27: =+EW27*EY27*30 -> 7200
C28: Dalgıç | D28: Adet | E28: 1 | AG28: =+E28 -> 1 | AH28: =+E28 -> 1 | AI28: =+E28 -> 1 | AJ28: =+E28 -> 1 | AK28: =+E28 -> 1 | AL28: =+E28 -> 1 | AM28: =+E28 -> 1 | AN28: =+E28 -> 1 | AO28: =+E28 -> 1 | AP28: =+E28 -> 1 | AQ28: =+E28 -> 1 | AR28: =+E28 -> 1 | AS28: =+E28 -> 1 | AT28: =+E28 -> 1 | AU28: =+E28 -> 1 | AV28: =+E28 -> 1 | AW28: =+E28 -> 1 | AX28: =+E28 -> 1 | AY28: =+E28 -> 1 | AZ28: =+E28 -> 1 | BA28: =+E28 -> 1 | BB28: =+E28 -> 1 | BC28: =+E28 -> 1 | BD28: =+E28 -> 1 | BE28: =+E28 -> 1 | BF28: =+E28 -> 1 | BG28: =+E28 -> 1 | BH28: =+E28 -> 1 | BI28: =+E28 -> 1 | BJ28: =+E28 -> 1 | BK28: =+E28 -> 1 | BL28: =+E28 -> 1 | BM28: =+E28 -> 1 | BN28: =+E28 -> 1 | BO28: =+E28 -> 1 | BP28: =+E28 -> 1 | BQ28: =+AK28 -> 1 | BR28: =+AK28 -> 1 | BS28: =+AK28 -> 1 | BT28: =+AK28 -> 1 | BU28: =+AO28 -> 1 | BV28: =+AO28 -> 1 | BW28: =+AO28 -> 1 | BX28: =+AO28 -> 1 | BY28: =+AS28 -> 1 | BZ28: =+AS28 -> 1 | CA28: =+AS28 -> 1 | CB28: =+AS28 -> 1 | CC28: =+AW28 -> 1 | CD28: =+AW28 -> 1 | CE28: =+AW28 -> 1 | CF28: =+AW28 -> 1 | CG28: =+BA28 -> 1 | CH28: =+BA28 -> 1 | CI28: =+BA28 -> 1 | CJ28: =+BA28 -> 1 | CK28: =+BE28 -> 1 | CL28: =+BE28 -> 1 | CM28: =+BE28 -> 1 | CN28: =+BE28 -> 1 | CO28: =+BI28 -> 1 | CP28: =+BI28 -> 1 | CQ28: =+BI28 -> 1 | CR28: =+BI28 -> 1 | CS28: =+BM28 -> 1 | CT28: =+BM28 -> 1 | CU28: =+BM28 -> 1 | CV28: =+BM28 -> 1 | CW28: =+BQ28 -> 1 | CX28: =+BQ28 -> 1 | CY28: =+BQ28 -> 1 | CZ28: =+BQ28 -> 1 | DA28: =+BU28 -> 1 | DB28: =+BU28 -> 1 | DC28: =+BU28 -> 1 | DD28: =+BU28 -> 1 | DE28: =+BY28 -> 1 | DF28: =+BY28 -> 1 | DG28: =+BY28 -> 1 | DH28: =+BY28 -> 1 | DI28: =+CC28 -> 1 | DJ28: =+CC28 -> 1 | DK28: =+CC28 -> 1 | DL28: =+CC28 -> 1 | DM28: =+CG28 -> 1 | DN28: =+CG28 -> 1 | DO28: =+CG28 -> 1 | DP28: =+CG28 -> 1 | DQ28: =+CK28 -> 1 | DR28: =+CK28 -> 1 | DS28: =+CK28 -> 1 | DT28: =+CK28 -> 1 | DU28: =+CO28 -> 1 | DV28: =+CO28 -> 1 | DW28: =+CO28 -> 1 | DX28: =+CO28 -> 1 | DY28: =+CS28 -> 1 | DZ28: =+CS28 -> 1 | EA28: =+CS28 -> 1 | EB28: =+CS28 -> 1 | EC28: =+CW28 -> 1 | ED28: =+CW28 -> 1 | EE28: =+CW28 -> 1 | EF28: =+CW28 -> 1 | EG28: =+DA28 -> 1 | EH28: =+DA28 -> 1 | EI28: =+DA28 -> 1 | EJ28: =+DA28 -> 1 | EK28: =+DE28 -> 1 | EL28: =+DE28 -> 1 | EM28: =+DE28 -> 1 | EN28: =+DE28 -> 1 | EO28: =+DI28 -> 1 | EP28: =+DI28 -> 1 | EQ28: =+DI28 -> 1 | ER28: =+DI28 -> 1 | ES28: =+DM28 -> 1 | ET28: =+DM28 -> 1 | EU28: =+DM28 -> 1 | EV28: =+DM28 -> 1 | EW28: =SUM(I28:EV28)/4 -> 30 | EX28: 16 | EY28: =24-EX28 -> 8 | EZ28: =+EW28*EX28*28 -> 13440 | FA28: =+EW28*EY28*30 -> 7200
... C36: Dump Truck (x20) | D36: Adet | E36: 20 | AG36: =+E36 -> 20 | AH36: =+E36 -> 20 | AI36: =+E36 -> 20 | AJ36: =+E36 -> 20 | AK36: =+E36 -> 20 | AL36: =+E36 -> 20 | AM36: =+E36 -> 20 | AN36: =+E36 -> 20 | AO36: =+E36 -> 20 | AP36: =+E36 -> 20 | AQ36: =+E36 -> 20 | AR36: =+E36 -> 20 | AS36: =+E36 -> 20 | AT36: =+E36 -> 20 | AU36: =+E36 -> 20 | AV36: =+E36 -> 20 | AW36: =+E36 -> 20 | AX36: =+E36 -> 20 | AY36: =+E36 -> 20 | AZ36: =+E36 -> 20 | BA36: =+E36 -> 20 | BB36: =+E36 -> 20 | BC36: =+E36 -> 20 | BD36: =+E36 -> 20 | BE36: =+E36 -> 20 | BF36: =+E36 -> 20 | BG36: =+E36 -> 20 | BH36: =+E36 -> 20 | BI36: =+E36 -> 20 | BJ36: =+E36 -> 20 | BK36: =+E36 -> 20 | BL36: =+E36 -> 20 | BM36: =+E36 -> 20 | BN36: =+E36 -> 20 | BO36: =+E36 -> 20 | BP36: =+E36 -> 20 | BQ36: =+AK36 -> 20 | BR36: =+AK36 -> 20 | BS36: =+AK36 -> 20 | BT36: =+AK36 -> 20 | BU36: =+AO36 -> 20 | BV36: =+AO36 -> 20 | BW36: =+AO36 -> 20 | BX36: =+AO36 -> 20 | BY36: =+AS36 -> 20 | BZ36: =+AS36 -> 20 | CA36: =+AS36 -> 20 | CB36: =+AS36 -> 20 | CC36: =+AW36 -> 20 | CD36: =+AW36 -> 20 | CE36: =+AW36 -> 20 | CF36: =+AW36 -> 20 | CG36: =+BA36 -> 20 | CH36: =+BA36 -> 20 | CI36: =+BA36 -> 20 | CJ36: =+BA36 -> 20 | CK36: =+BE36 -> 20 | CL36: =+BE36 -> 20 | CM36: =+BE36 -> 20 | CN36: =+BE36 -> 20 | CO36: =+BI36 -> 20 | CP36: =+BI36 -> 20 | CQ36: =+BI36 -> 20 | CR36: =+BI36 -> 20 | CS36: =+BM36 -> 20 | CT36: =+BM36 -> 20 | CU36: =+BM36 -> 20 | CV36: =+BM36 -> 20 | CW36: =+BQ36 -> 20 | CX36: =+BQ36 -> 20 | CY36: =+BQ36 -> 20 | CZ36: =+BQ36 -> 20 | DA36: =+BU36 -> 20 | DB36: =+BU36 -> 20 | DC36: =+BU36 -> 20 | DD36: =+BU36 -> 20 | DE36: =+BY36 -> 20 | DF36: =+BY36 -> 20 | DG36: =+BY36 -> 20 | DH36: =+BY36 -> 20 | DI36: =+CC36 -> 20 | DJ36: =+CC36 -> 20 | DK36: =+CC36 -> 20 | DL36: =+CC36 -> 20 | DM36: =+CG36 -> 20 | DN36: =+CG36 -> 20 | DO36: =+CG36 -> 20 | DP36: =+CG36 -> 20 | DQ36: =+CK36 -> 20 | DR36: =+CK36 -> 20 | DS36: =+CK36 -> 20 | DT36: =+CK36 -> 20 | DU36: =+CO36 -> 20 | DV36: =+CO36 -> 20 | DW36: =+CO36 -> 20 | DX36: =+CO36 -> 20 | DY36: =+CS36 -> 20 | DZ36: =+CS36 -> 20 | EA36: =+CS36 -> 20 | EB36: =+CS36 -> 20 | EC36: =+CW36 -> 20 | ED36: =+CW36 -> 20 | EE36: =+CW36 -> 20 | EF36: =+CW36 -> 20 | EG36: =+DA36 -> 20 | EH36: =+DA36 -> 20 | EI36: =+DA36 -> 20 | EJ36: =+DA36 -> 20 | EK36: =+DE36 -> 20 | EL36: =+DE36 -> 20 | EM36: =+DE36 -> 20 | EN36: =+DE36 -> 20 | EO36: =+DI36 -> 20 | EP36: =+DI36 -> 20 | EQ36: =+DI36 -> 20 | ER36: =+DI36 -> 20 | ES36: =+DM36 -> 20 | ET36: =+DM36 -> 20 | EU36: =+DM36 -> 20 | EV36: =+DM36 -> 20 | EW36: =SUM(I36:EV36)/4 -> 600 | EX36: 16 | EY36: =24-EX36 -> 8 | EZ36: =+EW36*EX36*28 -> 268800 | FA36: =+EW36*EY36*30 -> 144000
Z39: =+Y39 -> 0 | AA39: =+Z39 -> 0 | AB39: =+AA39 -> 0 | AC39: =+AB39 -> 0 | AD39: =+AC39 -> 0 | AE39: =+AD39 -> 0 | AF39: =+AE39 -> 0
C42: Personnel
C43: Formen | D43: Adet | E43: 6 | AG43: =+E43 -> 6 | AH43: =+E43 -> 6 | AI43: =+E43 -> 6 | AJ43: =+E43 -> 6 | AK43: =+E43 -> 6 | AL43: =+E43 -> 6 | AM43: =+E43 -> 6 | AN43: =+E43 -> 6 | AO43: =+E43 -> 6 | AP43: =+E43 -> 6 | AQ43: =+E43 -> 6 | AR43: =+E43 -> 6 | AS43: =+E43 -> 6 | AT43: =+E43 -> 6 | AU43: =+E43 -> 6 | AV43: =+E43 -> 6 | AW43: =+E43 -> 6 | AX43: =+E43 -> 6 | AY43: =+E43 -> 6 | AZ43: =+E43 -> 6 | BA43: =+E43 -> 6 | BB43: =+E43 -> 6 | BC43: =+E43 -> 6 | BD43: =+E43 -> 6 | BE43: =+E43 -> 6 | BF43: =+E43 -> 6 | BG43: =+E43 -> 6 | BH43: =+E43 -> 6 | BI43: =+E43 -> 6 | BJ43: =+E43 -> 6 | BK43: =+E43 -> 6 | BL43: =+E43 -> 6 | BM43: =+E43 -> 6 | BN43: =+E43 -> 6 | BO43: =+E43 -> 6 | BP43: =+E43 -> 6 | BQ43: =+AK43 -> 6 | BR43: =+AK43 -> 6 | BS43: =+AK43 -> 6 | BT43: =+AK43 -> 6 | BU43: =+AK43 -> 6 | BV43: =+AK43 -> 6 | BW43: =+AK43 -> 6 | BX43: =+AK43 -> 6 | BY43: =+AS43 -> 6 | BZ43: =+AS43 -> 6 | CA43: =+AS43 -> 6 | CB43: =+AS43 -> 6 | CC43: =+AS43 -> 6 | CD43: =+AS43 -> 6 | CE43: =+AS43 -> 6 | CF43: =+AS43 -> 6 | CG43: =+BA43 -> 6 | CH43: =+BA43 -> 6 | CI43: =+BA43 -> 6 | CJ43: =+BA43 -> 6 | CK43: =+BA43 -> 6 | CL43: =+BA43 -> 6 | CM43: =+BA43 -> 6 | CN43: =+BA43 -> 6 | CO43: =+BI43 -> 6 | CP43: =+BI43 -> 6 | CQ43: =+BI43 -> 6 | CR43: =+BI43 -> 6 | CS43: =+BI43 -> 6 | CT43: =+BI43 -> 6 | CU43: =+BI43 -> 6 | CV43: =+BI43 -> 6 | CW43: =+BQ43 -> 6 | CX43: =+BQ43 -> 6 | CY43: =+BQ43 -> 6 | CZ43: =+BQ43 -> 6 | DA43: =+BQ43 -> 6 | DB43: =+BQ43 -> 6 | DC43: =+BQ43 -> 6 | DD43: =+BQ43 -> 6 | DE43: =+BY43 -> 6 | DF43: =+BY43 -> 6 | DG43: =+BY43 -> 6 | DH43: =+BY43 -> 6 | DI43: =+BY43 -> 6 | DJ43: =+BY43 -> 6 | DK43: =+BY43 -> 6 | DL43: =+BY43 -> 6 | DM43: =+CG43 -> 6 | DN43: =+CG43 -> 6 | DO43: =+CG43 -> 6 | DP43: =+CG43 -> 6 | DQ43: =+CG43 -> 6 | DR43: =+CG43 -> 6 | DS43: =+CG43 -> 6 | DT43: =+CG43 -> 6 | DU43: =+CO43 -> 6 | DV43: =+CO43 -> 6 | DW43: =+CO43 -> 6 | DX43: =+CO43 -> 6 | DY43: =+CO43 -> 6 | DZ43: =+CO43 -> 6 | EA43: =+CO43 -> 6 | EB43: =+CO43 -> 6 | EC43: =+CW43 -> 6 | ED43: =+CW43 -> 6 | EE43: =+CW43 -> 6 | EF43: =+CW43 -> 6 | EG43: =+CW43 -> 6 | EH43: =+CW43 -> 6 | EI43: =+CW43 -> 6 | EJ43: =+CW43 -> 6 | EK43: =+DE43 -> 6 | EL43: =+DE43 -> 6 | EM43: =+DE43 -> 6 | EN43: =+DE43 -> 6 | EO43: =+DE43 -> 6 | EP43: =+DE43 -> 6 | EQ43: =+DE43 -> 6 | ER43: =+DE43 -> 6 | ES43: =+DM43 -> 6 | ET43: =+DM43 -> 6 | EU43: =+DM43 -> 6 | EV43: =+DM43 -> 6 | EW43: =SUM(I43:DD43)/4 -> 114
C44: Operator | D44: Adet | E44: 21 | AG44: =+E44 -> 21 | AH44: =+E44 -> 21 | AI44: =+E44 -> 21 | AJ44: =+E44 -> 21 | AK44: =+E44 -> 21 | AL44: =+E44 -> 21 | AM44: =+E44 -> 21 | AN44: =+E44 -> 21 | AO44: =+E44 -> 21 | AP44: =+E44 -> 21 | AQ44: =+E44 -> 21 | AR44: =+E44 -> 21 | AS44: =+E44 -> 21 | AT44: =+E44 -> 21 | AU44: =+E44 -> 21 | AV44: =+E44 -> 21 | AW44: =+E44 -> 21 | AX44: =+E44 -> 21 | AY44: =+E44 -> 21 | AZ44: =+E44 -> 21 | BA44: =+E44 -> 21 | BB44: =+E44 -> 21 | BC44: =+E44 -> 21 | BD44: =+E44 -> 21 | BE44: =+E44 -> 21 | BF44: =+E44 -> 21 | BG44: =+E44 -> 21 | BH44: =+E44 -> 21 | BI44: =+E44 -> 21 | BJ44: =+E44 -> 21 | BK44: =+E44 -> 21 | BL44: =+E44 -> 21 | BM44: =+E44 -> 21 | BN44: =+E44 -> 21 | BO44: =+E44 -> 21 | BP44: =+E44 -> 21 | BQ44: =+AK44 -> 21 | BR44: =+AK44 -> 21 | BS44: =+AK44 -> 21 | BT44: =+AK44 -> 21 | BU44: =+AK44 -> 21 | BV44: =+AK44 -> 21 | BW44: =+AK44 -> 21 | BX44: =+AK44 -> 21 | BY44: =+AS44 -> 21 | BZ44: =+AS44 -> 21 | CA44: =+AS44 -> 21 | CB44: =+AS44 -> 21 | CC44: =+AS44 -> 21 | CD44: =+AS44 -> 21 | CE44: =+AS44 -> 21 | CF44: =+AS44 -> 21 | CG44: =+BA44 -> 21 | CH44: =+BA44 -> 21 | CI44: =+BA44 -> 21 | CJ44: =+BA44 -> 21 | CK44: =+BA44 -> 21 | CL44: =+BA44 -> 21 | CM44: =+BA44 -> 21 | CN44: =+BA44 -> 21 | CO44: =+BI44 -> 21 | CP44: =+BI44 -> 21 | CQ44: =+BI44 -> 21 | CR44: =+BI44 -> 21 | CS44: =+BI44 -> 21 | CT44: =+BI44 -> 21 | CU44: =+BI44 -> 21 | CV44: =+BI44 -> 21 | CW44: =+BQ44 -> 21 | CX44: =+BQ44 -> 21 | CY44: =+BQ44 -> 21 | CZ44: =+BQ44 -> 21 | DA44: =+BQ44 -> 21 | DB44: =+BQ44 -> 21 | DC44: =+BQ44 -> 21 | DD44: =+BQ44 -> 21 | DE44: =+BY44 -> 21 | DF44: =+BY44 -> 21 | DG44: =+BY44 -> 21 | DH44: =+BY44 -> 21 | DI44: =+BY44 -> 21 | DJ44: =+BY44 -> 21 | DK44: =+BY44 -> 21 | DL44: =+BY44 -> 21 | DM44: =+CG44 -> 21 | DN44: =+CG44 -> 21 | DO44: =+CG44 -> 21 | DP44: =+CG44 -> 21 | DQ44: =+CG44 -> 21 | DR44: =+CG44 -> 21 | DS44: =+CG44 -> 21 | DT44: =+CG44 -> 21 | DU44: =+CO44 -> 21 | DV44: =+CO44 -> 21 | DW44: =+CO44 -> 21 | DX44: =+CO44 -> 21 | DY44: =+CO44 -> 21 | DZ44: =+CO44 -> 21 | EA44: =+CO44 -> 21 | EB44: =+CO44 -> 21 | EC44: =+CW44 -> 21 | ED44: =+CW44 -> 21 | EE44: =+CW44 -> 21 | EF44: =+CW44 -> 21 | EG44: =+CW44 -> 21 | EH44: =+CW44 -> 21 | EI44: =+CW44 -> 21 | EJ44: =+CW44 -> 21 | EK44: =+DE44 -> 21 | EL44: =+DE44 -> 21 | EM44: =+DE44 -> 21 | EN44: =+DE44 -> 21 | EO44: =+DE44 -> 21 | EP44: =+DE44 -> 21 | EQ44: =+DE44 -> 21 | ER44: =+DE44 -> 21 | ES44: =+DM44 -> 21 | ET44: =+DM44 -> 21 | EU44: =+DM44 -> 21 | EV44: =+DM44 -> 21 | EW44: =SUM(I44:DD44)/4 -> 399
C45: Kaptan | D45: Adet | E45: 15 | AG45: =+E45 -> 15 | AH45: =+E45 -> 15 | AI45: =+E45 -> 15 | AJ45: =+E45 -> 15 | AK45: =+E45 -> 15 | AL45: =+E45 -> 15 | AM45: =+E45 -> 15 | AN45: =+E45 -> 15 | AO45: =+E45 -> 15 | AP45: =+E45 -> 15 | AQ45: =+E45 -> 15 | AR45: =+E45 -> 15 | AS45: =+E45 -> 15 | AT45: =+E45 -> 15 | AU45: =+E45 -> 15 | AV45: =+E45 -> 15 | AW45: =+E45 -> 15 | AX45: =+E45 -> 15 | AY45: =+E45 -> 15 | AZ45: =+E45 -> 15 | BA45: =+E45 -> 15 | BB45: =+E45 -> 15 | BC45: =+E45 -> 15 | BD45: =+E45 -> 15 | BE45: =+E45 -> 15 | BF45: =+E45 -> 15 | BG45: =+E45 -> 15 | BH45: =+E45 -> 15 | BI45: =+E45 -> 15 | BJ45: =+E45 -> 15 | BK45: =+E45 -> 15 | BL45: =+E45 -> 15 | BM45: =+E45 -> 15 | BN45: =+E45 -> 15 | BO45: =+E45 -> 15 | BP45: =+E45 -> 15 | BQ45: =+AK45 -> 15 | BR45: =+AK45 -> 15 | BS45: =+AK45 -> 15 | BT45: =+AK45 -> 15 | BU45: =+AK45 -> 15 | BV45: =+AK45 -> 15 | BW45: =+AK45 -> 15 | BX45: =+AK45 -> 15 | BY45: =+AS45 -> 15 | BZ45: =+AS45 -> 15 | CA45: =+AS45 -> 15 | CB45: =+AS45 -> 15 | CC45: =+AS45 -> 15 | CD45: =+AS45 -> 15 | CE45: =+AS45 -> 15 | CF45: =+AS45 -> 15 | CG45: =+BA45 -> 15 | CH45: =+BA45 -> 15 | CI45: =+BA45 -> 15 | CJ45: =+BA45 -> 15 | CK45: =+BA45 -> 15 | CL45: =+BA45 -> 15 | CM45: =+BA45 -> 15 | CN45: =+BA45 -> 15 | CO45: =+BI45 -> 15 | CP45: =+BI45 -> 15 | CQ45: =+BI45 -> 15 | CR45: =+BI45 -> 15 | CS45: =+BI45 -> 15 | CT45: =+BI45 -> 15 | CU45: =+BI45 -> 15 | CV45: =+BI45 -> 15 | CW45: =+BQ45 -> 15 | CX45: =+BQ45 -> 15 | CY45: =+BQ45 -> 15 | CZ45: =+BQ45 -> 15 | DA45: =+BQ45 -> 15 | DB45: =+BQ45 -> 15 | DC45: =+BQ45 -> 15 | DD45: =+BQ45 -> 15 | DE45: =+BY45 -> 15 | DF45: =+BY45 -> 15 | DG45: =+BY45 -> 15 | DH45: =+BY45 -> 15 | DI45: =+BY45 -> 15 | DJ45: =+BY45 -> 15 | DK45: =+BY45 -> 15 | DL45: =+BY45 -> 15 | DM45: =+CG45 -> 15 | DN45: =+CG45 -> 15 | DO45: =+CG45 -> 15 | DP45: =+CG45 -> 15 | DQ45: =+CG45 -> 15 | DR45: =+CG45 -> 15 | DS45: =+CG45 -> 15 | DT45: =+CG45 -> 15 | DU45: =+CO45 -> 15 | DV45: =+CO45 -> 15 | DW45: =+CO45 -> 15 | DX45: =+CO45 -> 15 | DY45: =+CO45 -> 15 | DZ45: =+CO45 -> 15 | EA45: =+CO45 -> 15 | EB45: =+CO45 -> 15 | EC45: =+CW45 -> 15 | ED45: =+CW45 -> 15 | EE45: =+CW45 -> 15 | EF45: =+CW45 -> 15 | EG45: =+CW45 -> 15 | EH45: =+CW45 -> 15 | EI45: =+CW45 -> 15 | EJ45: =+CW45 -> 15 | EK45: =+DE45 -> 15 | EL45: =+DE45 -> 15 | EM45: =+DE45 -> 15 | EN45: =+DE45 -> 15 | EO45: =+DE45 -> 15 | EP45: =+DE45 -> 15 | EQ45: =+DE45 -> 15 | ER45: =+DE45 -> 15 | ES45: =+DM45 -> 15 | ET45: =+DM45 -> 15 | EU45: =+DM45 -> 15 | EV45: =+DM45 -> 15 | EW45: =SUM(I45:DD45)/4 -> 285
C46: Çarkçı | D46: Adet | E46: 10 | AG46: =+E46 -> 10 | AH46: =+E46 -> 10 | AI46: =+E46 -> 10 | AJ46: =+E46 -> 10 | AK46: =+E46 -> 10 | AL46: =+E46 -> 10 | AM46: =+E46 -> 10 | AN46: =+E46 -> 10 | AO46: =+E46 -> 10 | AP46: =+E46 -> 10 | AQ46: =+E46 -> 10 | AR46: =+E46 -> 10 | AS46: =+E46 -> 10 | AT46: =+E46 -> 10 | AU46: =+E46 -> 10 | AV46: =+E46 -> 10 | AW46: =+E46 -> 10 | AX46: =+E46 -> 10 | AY46: =+E46 -> 10 | AZ46: =+E46 -> 10 | BA46: =+E46 -> 10 | BB46: =+E46 -> 10 | BC46: =+E46 -> 10 | BD46: =+E46 -> 10 | BE46: =+E46 -> 10 | BF46: =+E46 -> 10 | BG46: =+E46 -> 10 | BH46: =+E46 -> 10 | BI46: =+E46 -> 10 | BJ46: =+E46 -> 10 | BK46: =+E46 -> 10 | BL46: =+E46 -> 10 | BM46: =+E46 -> 10 | BN46: =+E46 -> 10 | BO46: =+E46 -> 10 | BP46: =+E46 -> 10 | BQ46: =+AK46 -> 10 | BR46: =+AK46 -> 10 | BS46: =+AK46 -> 10 | BT46: =+AK46 -> 10 | BU46: =+AK46 -> 10 | BV46: =+AK46 -> 10 | BW46: =+AK46 -> 10 | BX46: =+AK46 -> 10 | BY46: =+AS46 -> 10 | BZ46: =+AS46 -> 10 | CA46: =+AS46 -> 10 | CB46: =+AS46 -> 10 | CC46: =+AS46 -> 10 | CD46: =+AS46 -> 10 | CE46: =+AS46 -> 10 | CF46: =+AS46 -> 10 | CG46: =+BA46 -> 10 | CH46: =+BA46 -> 10 | CI46: =+BA46 -> 10 | CJ46: =+BA46 -> 10 | CK46: =+BA46 -> 10 | CL46: =+BA46 -> 10 | CM46: =+BA46 -> 10 | CN46: =+BA46 -> 10 | CO46: =+BI46 -> 10 | CP46: =+BI46 -> 10 | CQ46: =+BI46 -> 10 | CR46: =+BI46 -> 10 | CS46: =+BI46 -> 10 | CT46: =+BI46 -> 10 | CU46: =+BI46 -> 10 | CV46: =+BI46 -> 10 | CW46: =+BQ46 -> 10 | CX46: =+BQ46 -> 10 | CY46: =+BQ46 -> 10 | CZ46: =+BQ46 -> 10 | DA46: =+BQ46 -> 10 | DB46: =+BQ46 -> 10 | DC46: =+BQ46 -> 10 | DD46: =+BQ46 -> 10 | DE46: =+BY46 -> 10 | DF46: =+BY46 -> 10 | DG46: =+BY46 -> 10 | DH46: =+BY46 -> 10 | DI46: =+BY46 -> 10 | DJ46: =+BY46 -> 10 | DK46: =+BY46 -> 10 | DL46: =+BY46 -> 10 | DM46: =+CG46 -> 10 | DN46: =+CG46 -> 10 | DO46: =+CG46 -> 10 | DP46: =+CG46 -> 10 | DQ46: =+CG46 -> 10 | DR46: =+CG46 -> 10 | DS46: =+CG46 -> 10 | DT46: =+CG46 -> 10 | DU46: =+CO46 -> 10 | DV46: =+CO46 -> 10 | DW46: =+CO46 -> 10 | DX46: =+CO46 -> 10 | DY46: =+CO46 -> 10 | DZ46: =+CO46 -> 10 | EA46: =+CO46 -> 10 | EB46: =+CO46 -> 10 | EC46: =+CW46 -> 10 | ED46: =+CW46 -> 10 | EE46: =+CW46 -> 10 | EF46: =+CW46 -> 10 | EG46: =+CW46 -> 10 | EH46: =+CW46 -> 10 | EI46: =+CW46 -> 10 | EJ46: =+CW46 -> 10 | EK46: =+DE46 -> 10 | EL46: =+DE46 -> 10 | EM46: =+DE46 -> 10 | EN46: =+DE46 -> 10 | EO46: =+DE46 -> 10 | EP46: =+DE46 -> 10 | EQ46: =+DE46 -> 10 | ER46: =+DE46 -> 10 | ES46: =+DM46 -> 10 | ET46: =+DM46 -> 10 | EU46: =+DM46 -> 10 | EV46: =+DM46 -> 10 | EW46: =SUM(I46:DD46)/4 -> 190
C47: Yağcı | D47: Adet | E47: 15 | AG47: =+E47 -> 15 | AH47: =+E47 -> 15 | AI47: =+E47 -> 15 | AJ47: =+E47 -> 15 | AK47: =+E47 -> 15 | AL47: =+E47 -> 15 | AM47: =+E47 -> 15 | AN47: =+E47 -> 15 | AO47: =+E47 -> 15 | AP47: =+E47 -> 15 | AQ47: =+E47 -> 15 | AR47: =+E47 -> 15 | AS47: =+E47 -> 15 | AT47: =+E47 -> 15 | AU47: =+E47 -> 15 | AV47: =+E47 -> 15 | AW47: =+E47 -> 15 | AX47: =+E47 -> 15 | AY47: =+E47 -> 15 | AZ47: =+E47 -> 15 | BA47: =+E47 -> 15 | BB47: =+E47 -> 15 | BC47: =+E47 -> 15 | BD47: =+E47 -> 15 | BE47: =+E47 -> 15 | BF47: =+E47 -> 15 | BG47: =+E47 -> 15 | BH47: =+E47 -> 15 | BI47: =+E47 -> 15 | BJ47: =+E47 -> 15 | BK47: =+E47 -> 15 | BL47: =+E47 -> 15 | BM47: =+E47 -> 15 | BN47: =+E47 -> 15 | BO47: =+E47 -> 15 | BP47: =+E47 -> 15 | BQ47: =+AK47 -> 15 | BR47: =+AK47 -> 15 | BS47: =+AK47 -> 15 | BT47: =+AK47 -> 15 | BU47: =+AK47 -> 15 | BV47: =+AK47 -> 15 | BW47: =+AK47 -> 15 | BX47: =+AK47 -> 15 | BY47: =+AS47 -> 15 | BZ47: =+AS47 -> 15 | CA47: =+AS47 -> 15 | CB47: =+AS47 -> 15 | CC47: =+AS47 -> 15 | CD47: =+AS47 -> 15 | CE47: =+AS47 -> 15 | CF47: =+AS47 -> 15 | CG47: =+BA47 -> 15 | CH47: =+BA47 -> 15 | CI47: =+BA47 -> 15 | CJ47: =+BA47 -> 15 | CK47: =+BA47 -> 15 | CL47: =+BA47 -> 15 | CM47: =+BA47 -> 15 | CN47: =+BA47 -> 15 | CO47: =+BI47 -> 15 | CP47: =+BI47 -> 15 | CQ47: =+BI47 -> 15 | CR47: =+BI47 -> 15 | CS47: =+BI47 -> 15 | CT47: =+BI47 -> 15 | CU47: =+BI47 -> 15 | CV47: =+BI47 -> 15 | CW47: =+BQ47 -> 15 | CX47: =+BQ47 -> 15 | CY47: =+BQ47 -> 15 | CZ47: =+BQ47 -> 15 | DA47: =+BQ47 -> 15 | DB47: =+BQ47 -> 15 | DC47: =+BQ47 -> 15 | DD47: =+BQ47 -> 15 | DE47: =+BY47 -> 15 | DF47: =+BY47 -> 15 | DG47: =+BY47 -> 15 | DH47: =+BY47 -> 15 | DI47: =+BY47 -> 15 | DJ47: =+BY47 -> 15 | DK47: =+BY47 -> 15 | DL47: =+BY47 -> 15 | DM47: =+CG47 -> 15 | DN47: =+CG47 -> 15 | DO47: =+CG47 -> 15 | DP47: =+CG47 -> 15 | DQ47: =+CG47 -> 15 | DR47: =+CG47 -> 15 | DS47: =+CG47 -> 15 | DT47: =+CG47 -> 15 | DU47: =+CO47 -> 15 | DV47: =+CO47 -> 15 | DW47: =+CO47 -> 15 | DX47: =+CO47 -> 15 | DY47: =+CO47 -> 15 | DZ47: =+CO47 -> 15 | EA47: =+CO47 -> 15 | EB47: =+CO47 -> 15 | EC47: =+CW47 -> 15 | ED47: =+CW47 -> 15 | EE47: =+CW47 -> 15 | EF47: =+CW47 -> 15 | EG47: =+CW47 -> 15 | EH47: =+CW47 -> 15 | EI47: =+CW47 -> 15 | EJ47: =+CW47 -> 15 | EK47: =+DE47 -> 15 | EL47: =+DE47 -> 15 | EM47: =+DE47 -> 15 | EN47: =+DE47 -> 15 | EO47: =+DE47 -> 15 | EP47: =+DE47 -> 15 | EQ47: =+DE47 -> 15 | ER47: =+DE47 -> 15 | ES47: =+DM47 -> 15 | ET47: =+DM47 -> 15 | EU47: =+DM47 -> 15 | EV47: =+DM47 -> 15 | EW47: =SUM(I47:DD47)/4 -> 285
C48: Gemici | D48: Adet | E48: 30 | AG48: =+E48 -> 30 | AH48: =+E48 -> 30 | AI48: =+E48 -> 30 | AJ48: =+E48 -> 30 | AK48: =+E48 -> 30 | AL48: =+E48 -> 30 | AM48: =+E48 -> 30 | AN48: =+E48 -> 30 | AO48: =+E48 -> 30 | AP48: =+E48 -> 30 | AQ48: =+E48 -> 30 | AR48: =+E48 -> 30 | AS48: =+E48 -> 30 | AT48: =+E48 -> 30 | AU48: =+E48 -> 30 | AV48: =+E48 -> 30 | AW48: =+E48 -> 30 | AX48: =+E48 -> 30 | AY48: =+E48 -> 30 | AZ48: =+E48 -> 30 | BA48: =+E48 -> 30 | BB48: =+E48 -> 30 | BC48: =+E48 -> 30 | BD48: =+E48 -> 30 | BE48: =+E48 -> 30 | BF48: =+E48 -> 30 | BG48: =+E48 -> 30 | BH48: =+E48 -> 30 | BI48: =+E48 -> 30 | BJ48: =+E48 -> 30 | BK48: =+E48 -> 30 | BL48: =+E48 -> 30 | BM48: =+E48 -> 30 | BN48: =+E48 -> 30 | BO48: =+E48 -> 30 | BP48: =+E48 -> 30 | BQ48: =+AK48 -> 30 | BR48: =+AK48 -> 30 | BS48: =+AK48 -> 30 | BT48: =+AK48 -> 30 | BU48: =+AK48 -> 30 | BV48: =+AK48 -> 30 | BW48: =+AK48 -> 30 | BX48: =+AK48 -> 30 | BY48: =+AS48 -> 30 | BZ48: =+AS48 -> 30 | CA48: =+AS48 -> 30 | CB48: =+AS48 -> 30 | CC48: =+AS48 -> 30 | CD48: =+AS48 -> 30 | CE48: =+AS48 -> 30 | CF48: =+AS48 -> 30 | CG48: =+BA48 -> 30 | CH48: =+BA48 -> 30 | CI48: =+BA48 -> 30 | CJ48: =+BA48 -> 30 | CK48: =+BA48 -> 30 | CL48: =+BA48 -> 30 | CM48: =+BA48 -> 30 | CN48: =+BA48 -> 30 | CO48: =+BI48 -> 30 | CP48: =+BI48 -> 30 | CQ48: =+BI48 -> 30 | CR48: =+BI48 -> 30 | CS48: =+BI48 -> 30 | CT48: =+BI48 -> 30 | CU48: =+BI48 -> 30 | CV48: =+BI48 -> 30 | CW48: =+BQ48 -> 30 | CX48: =+BQ48 -> 30 | CY48: =+BQ48 -> 30 | CZ48: =+BQ48 -> 30 | DA48: =+BQ48 -> 30 | DB48: =+BQ48 -> 30 | DC48: =+BQ48 -> 30 | DD48: =+BQ48 -> 30 | DE48: =+BY48 -> 30 | DF48: =+BY48 -> 30 | DG48: =+BY48 -> 30 | DH48: =+BY48 -> 30 | DI48: =+BY48 -> 30 | DJ48: =+BY48 -> 30 | DK48: =+BY48 -> 30 | DL48: =+BY48 -> 30 | DM48: =+CG48 -> 30 | DN48: =+CG48 -> 30 | DO48: =+CG48 -> 30 | DP48: =+CG48 -> 30 | DQ48: =+CG48 -> 30 | DR48: =+CG48 -> 30 | DS48: =+CG48 -> 30 | DT48: =+CG48 -> 30 | DU48: =+CO48 -> 30 | DV48: =+CO48 -> 30 | DW48: =+CO48 -> 30 | DX48: =+CO48 -> 30 | DY48: =+CO48 -> 30 | DZ48: =+CO48 -> 30 | EA48: =+CO48 -> 30 | EB48: =+CO48 -> 30 | EC48: =+CW48 -> 30 | ED48: =+CW48 -> 30 | EE48: =+CW48 -> 30 | EF48: =+CW48 -> 30 | EG48: =+CW48 -> 30 | EH48: =+CW48 -> 30 | EI48: =+CW48 -> 30 | EJ48: =+CW48 -> 30 | EK48: =+DE48 -> 30 | EL48: =+DE48 -> 30 | EM48: =+DE48 -> 30 | EN48: =+DE48 -> 30 | EO48: =+DE48 -> 30 | EP48: =+DE48 -> 30 | EQ48: =+DE48 -> 30 | ER48: =+DE48 -> 30 | ES48: =+DM48 -> 30 | ET48: =+DM48 -> 30 | EU48: =+DM48 -> 30 | EV48: =+DM48 -> 30 | EW48: =SUM(I48:DD48)/4 -> 570
C49: İşçi | D49: Adet | E49: 40 | AG49: =+E49 -> 40 | AH49: =+E49 -> 40 | AI49: =+E49 -> 40 | AJ49: =+E49 -> 40 | AK49: =+E49 -> 40 | AL49: =+E49 -> 40 | AM49: =+E49 -> 40 | AN49: =+E49 -> 40 | AO49: =+E49 -> 40 | AP49: =+E49 -> 40 | AQ49: =+E49 -> 40 | AR49: =+E49 -> 40 | AS49: =+E49 -> 40 | AT49: =+E49 -> 40 | AU49: =+E49 -> 40 | AV49: =+E49 -> 40 | AW49: =+E49 -> 40 | AX49: =+E49 -> 40 | AY49: =+E49 -> 40 | AZ49: =+E49 -> 40 | BA49: =+E49 -> 40 | BB49: =+E49 -> 40 | BC49: =+E49 -> 40 | BD49: =+E49 -> 40 | BE49: =+E49 -> 40 | BF49: =+E49 -> 40 | BG49: =+E49 -> 40 | BH49: =+E49 -> 40 | BI49: =+E49 -> 40 | BJ49: =+E49 -> 40 | BK49: =+E49 -> 40 | BL49: =+E49 -> 40 | BM49: =+E49 -> 40 | BN49: =+E49 -> 40 | BO49: =+E49 -> 40 | BP49: =+E49 -> 40 | BQ49: =+AK49 -> 40 | BR49: =+AK49 -> 40 | BS49: =+AK49 -> 40 | BT49: =+AK49 -> 40 | BU49: =+AK49 -> 40 | BV49: =+AK49 -> 40 | BW49: =+AK49 -> 40 | BX49: =+AK49 -> 40 | BY49: =+AS49 -> 40 | BZ49: =+AS49 -> 40 | CA49: =+AS49 -> 40 | CB49: =+AS49 -> 40 | CC49: =+AS49 -> 40 | CD49: =+AS49 -> 40 | CE49: =+AS49 -> 40 | CF49: =+AS49 -> 40 | CG49: =+BA49 -> 40 | CH49: =+BA49 -> 40 | CI49: =+BA49 -> 40 | CJ49: =+BA49 -> 40 | CK49: =+BA49 -> 40 | CL49: =+BA49 -> 40 | CM49: =+BA49 -> 40 | CN49: =+BA49 -> 40 | CO49: =+BI49 -> 40 | CP49: =+BI49 -> 40 | CQ49: =+BI49 -> 40 | CR49: =+BI49 -> 40 | CS49: =+BI49 -> 40 | CT49: =+BI49 -> 40 | CU49: =+BI49 -> 40 | CV49: =+BI49 -> 40 | CW49: =+BQ49 -> 40 | CX49: =+BQ49 -> 40 | CY49: =+BQ49 -> 40 | CZ49: =+BQ49 -> 40 | DA49: =+BQ49 -> 40 | DB49: =+BQ49 -> 40 | DC49: =+BQ49 -> 40 | DD49: =+BQ49 -> 40 | DE49: =+BY49 -> 40 | DF49: =+BY49 -> 40 | DG49: =+BY49 -> 40 | DH49: =+BY49 -> 40 | DI49: =+BY49 -> 40 | DJ49: =+BY49 -> 40 | DK49: =+BY49 -> 40 | DL49: =+BY49 -> 40 | DM49: =+CG49 -> 40 | DN49: =+CG49 -> 40 | DO49: =+CG49 -> 40 | DP49: =+CG49 -> 40 | DQ49: =+CG49 -> 40 | DR49: =+CG49 -> 40 | DS49: =+CG49 -> 40 | DT49: =+CG49 -> 40 | DU49: =+CO49 -> 40 | DV49: =+CO49 -> 40 | DW49: =+CO49 -> 40 | DX49: =+CO49 -> 40 | DY49: =+CO49 -> 40 | DZ49: =+CO49 -> 40 | EA49: =+CO49 -> 40 | EB49: =+CO49 -> 40 | EC49: =+CW49 -> 40 | ED49: =+CW49 -> 40 | EE49: =+CW49 -> 40 | EF49: =+CW49 -> 40 | EG49: =+CW49 -> 40 | EH49: =+CW49 -> 40 | EI49: =+CW49 -> 40 | EJ49: =+CW49 -> 40 | EK49: =+DE49 -> 40 | EL49: =+DE49 -> 40 | EM49: =+DE49 -> 40 | EN49: =+DE49 -> 40 | EO49: =+DE49 -> 40 | EP49: =+DE49 -> 40 | EQ49: =+DE49 -> 40 | ER49: =+DE49 -> 40 | ES49: =+DM49 -> 40 | ET49: =+DM49 -> 40 | EU49: =+DM49 -> 40 | EV49: =+DM49 -> 40 | EW49: =SUM(I49:DD49)/4 -> 760
E50: =SUM(E43:E49) -> 137
C52: Indirect
C54: Makine&Ekipman
C55: Car | D55: Adet | E55: 2 | AG55: =+E55 -> 2 | AH55: =+E55 -> 2 | AI55: =+E55 -> 2 | AJ55: =+E55 -> 2 | AK55: =+E55 -> 2 | AL55: =+E55 -> 2 | AM55: =+E55 -> 2 | AN55: =+E55 -> 2 | AO55: =+E55 -> 2 | AP55: =+E55 -> 2 | AQ55: =+E55 -> 2 | AR55: =+E55 -> 2 | AS55: =+E55 -> 2 | AT55: =+E55 -> 2 | AU55: =+E55 -> 2 | AV55: =+E55 -> 2 | AW55: =+E55 -> 2 | AX55: =+E55 -> 2 | AY55: =+E55 -> 2 | AZ55: =+E55 -> 2 | BA55: =+E55 -> 2 | BB55: =+E55 -> 2 | BC55: =+E55 -> 2 | BD55: =+E55 -> 2 | BE55: =+E55 -> 2 | BF55: =+E55 -> 2 | BG55: =+E55 -> 2 | BH55: =+E55 -> 2 | BI55: =+E55 -> 2 | BJ55: =+E55 -> 2 | BK55: =+E55 -> 2 | BL55: =+E55 -> 2 | BM55: =+E55 -> 2 | BN55: =+E55 -> 2 | BO55: =+E55 -> 2 | BP55: =+E55 -> 2 | BQ55: =+AK55 -> 2 | BR55: =+AK55 -> 2 | BS55: =+AK55 -> 2 | BT55: =+AK55 -> 2 | BU55: =+AO55 -> 2 | BV55: =+AO55 -> 2 | BW55: =+AO55 -> 2 | BX55: =+AO55 -> 2 | BY55: =+AS55 -> 2 | BZ55: =+AS55 -> 2 | CA55: =+AS55 -> 2 | CB55: =+AS55 -> 2 | CC55: =+AW55 -> 2 | CD55: =+AW55 -> 2 | CE55: =+AW55 -> 2 | CF55: =+AW55 -> 2 | CG55: =+BA55 -> 2 | CH55: =+BA55 -> 2 | CI55: =+BA55 -> 2 | CJ55: =+BA55 -> 2 | CK55: =+BE55 -> 2 | CL55: =+BE55 -> 2 | CM55: =+BE55 -> 2 | CN55: =+BE55 -> 2 | CO55: =+BI55 -> 2 | CP55: =+BI55 -> 2 | CQ55: =+BI55 -> 2 | CR55: =+BI55 -> 2 | CS55: =+BM55 -> 2 | CT55: =+BM55 -> 2 | CU55: =+BM55 -> 2 | CV55: =+BM55 -> 2 | CW55: =+BQ55 -> 2 | CX55: =+BQ55 -> 2 | CY55: =+BQ55 -> 2 | CZ55: =+BQ55 -> 2 | DA55: =+BU55 -> 2 | DB55: =+BU55 -> 2 | DC55: =+BU55 -> 2 | DD55: =+BU55 -> 2 | DE55: =+BY55 -> 2 | DF55: =+BY55 -> 2 | DG55: =+BY55 -> 2 | DH55: =+BY55 -> 2 | DI55: =+CC55 -> 2 | DJ55: =+CC55 -> 2 | DK55: =+CC55 -> 2 | DL55: =+CC55 -> 2 | DM55: =+CG55 -> 2 | DN55: =+CG55 -> 2 | DO55: =+CG55 -> 2 | DP55: =+CG55 -> 2 | DQ55: =+CK55 -> 2 | DR55: =+CK55 -> 2 | DS55: =+CK55 -> 2 | DT55: =+CK55 -> 2 | DU55: =+CO55 -> 2 | DV55: =+CO55 -> 2 | DW55: =+CO55 -> 2 | DX55: =+CO55 -> 2 | DY55: =+CS55 -> 2 | DZ55: =+CS55 -> 2 | EA55: =+CS55 -> 2 | EB55: =+CS55 -> 2 | EC55: =+CW55 -> 2 | ED55: =+CW55 -> 2 | EE55: =+CW55 -> 2 | EF55: =+CW55 -> 2 | EG55: =+DA55 -> 2 | EH55: =+DA55 -> 2 | EI55: =+DA55 -> 2 | EJ55: =+DA55 -> 2 | EK55: =+DE55 -> 2 | EL55: =+DE55 -> 2 | EM55: =+DE55 -> 2 | EN55: =+DE55 -> 2 | EO55: =+DI55 -> 2 | EP55: =+DI55 -> 2 | EQ55: =+DI55 -> 2 | ER55: =+DI55 -> 2 | ES55: =+DM55 -> 2 | ET55: =+DM55 -> 2 | EU55: =+DM55 -> 2 | EV55: =+DM55 -> 2 | EW55: =SUM(I55:DD55)/4 -> 38 | EX55: 16 | EY55: =24-EX55 -> 8 | EZ55: =+EW55*EX55*28 -> 17024 | FA55: =+EW55*EY55*30 -> 9120
C56: Pick-Up | D56: Adet | E56: 2 | AG56: =+E56 -> 2 | AH56: =+E56 -> 2 | AI56: =+E56 -> 2 | AJ56: =+E56 -> 2 | AK56: =+E56 -> 2 | AL56: =+E56 -> 2 | AM56: =+E56 -> 2 | AN56: =+E56 -> 2 | AO56: =+E56 -> 2 | AP56: =+E56 -> 2 | AQ56: =+E56 -> 2 | AR56: =+E56 -> 2 | AS56: =+E56 -> 2 | AT56: =+E56 -> 2 | AU56: =+E56 -> 2 | AV56: =+E56 -> 2 | AW56: =+E56 -> 2 | AX56: =+E56 -> 2 | AY56: =+E56 -> 2 | AZ56: =+E56 -> 2 | BA56: =+E56 -> 2 | BB56: =+E56 -> 2 | BC56: =+E56 -> 2 | BD56: =+E56 -> 2 | BE56: =+E56 -> 2 | BF56: =+E56 -> 2 | BG56: =+E56 -> 2 | BH56: =+E56 -> 2 | BI56: =+E56 -> 2 | BJ56: =+E56 -> 2 | BK56: =+E56 -> 2 | BL56: =+E56 -> 2 | BM56: =+E56 -> 2 | BN56: =+E56 -> 2 | BO56: =+E56 -> 2 | BP56: =+E56 -> 2 | BQ56: =+AK56 -> 2 | BR56: =+AK56 -> 2 | BS56: =+AK56 -> 2 | BT56: =+AK56 -> 2 | BU56: =+AO56 -> 2 | BV56: =+AO56 -> 2 | BW56: =+AO56 -> 2 | BX56: =+AO56 -> 2 | BY56: =+AS56 -> 2 | BZ56: =+AS56 -> 2 | CA56: =+AS56 -> 2 | CB56: =+AS56 -> 2 | CC56: =+AW56 -> 2 | CD56: =+AW56 -> 2 | CE56: =+AW56 -> 2 | CF56: =+AW56 -> 2 | CG56: =+BA56 -> 2 | CH56: =+BA56 -> 2 | CI56: =+BA56 -> 2 | CJ56: =+BA56 -> 2 | CK56: =+BE56 -> 2 | CL56: =+BE56 -> 2 | CM56: =+BE56 -> 2 | CN56: =+BE56 -> 2 | CO56: =+BI56 -> 2 | CP56: =+BI56 -> 2 | CQ56: =+BI56 -> 2 | CR56: =+BI56 -> 2 | CS56: =+BM56 -> 2 | CT56: =+BM56 -> 2 | CU56: =+BM56 -> 2 | CV56: =+BM56 -> 2 | CW56: =+BQ56 -> 2 | CX56: =+BQ56 -> 2 | CY56: =+BQ56 -> 2 | CZ56: =+BQ56 -> 2 | DA56: =+BU56 -> 2 | DB56: =+BU56 -> 2 | DC56: =+BU56 -> 2 | DD56: =+BU56 -> 2 | DE56: =+BY56 -> 2 | DF56: =+BY56 -> 2 | DG56: =+BY56 -> 2 | DH56: =+BY56 -> 2 | DI56: =+CC56 -> 2 | DJ56: =+CC56 -> 2 | DK56: =+CC56 -> 2 | DL56: =+CC56 -> 2 | DM56: =+CG56 -> 2 | DN56: =+CG56 -> 2 | DO56: =+CG56 -> 2 | DP56: =+CG56 -> 2 | DQ56: =+CK56 -> 2 | DR56: =+CK56 -> 2 | DS56: =+CK56 -> 2 | DT56: =+CK56 -> 2 | DU56: =+CO56 -> 2 | DV56: =+CO56 -> 2 | DW56: =+CO56 -> 2 | DX56: =+CO56 -> 2 | DY56: =+CS56 -> 2 | DZ56: =+CS56 -> 2 | EA56: =+CS56 -> 2 | EB56: =+CS56 -> 2 | EC56: =+CW56 -> 2 | ED56: =+CW56 -> 2 | EE56: =+CW56 -> 2 | EF56: =+CW56 -> 2 | EG56: =+DA56 -> 2 | EH56: =+DA56 -> 2 | EI56: =+DA56 -> 2 | EJ56: =+DA56 -> 2 | EK56: =+DE56 -> 2 | EL56: =+DE56 -> 2 | EM56: =+DE56 -> 2 | EN56: =+DE56 -> 2 | EO56: =+DI56 -> 2 | EP56: =+DI56 -> 2 | EQ56: =+DI56 -> 2 | ER56: =+DI56 -> 2 | ES56: =+DM56 -> 2 | ET56: =+DM56 -> 2 | EU56: =+DM56 -> 2 | EV56: =+DM56 -> 2 | EW56: =SUM(I56:DD56)/4 -> 38 | EX56: 16 | EY56: =24-EX56 -> 8 | EZ56: =+EW56*EX56*28 -> 17024 | FA56: =+EW56*EY56*30 -> 9120
C57: Mini-bus | D57: Adet | E57: 2 | AG57: =+E57 -> 2 | AH57: =+E57 -> 2 | AI57: =+E57 -> 2 | AJ57: =+E57 -> 2 | AK57: =+E57 -> 2 | AL57: =+E57 -> 2 | AM57: =+E57 -> 2 | AN57: =+E57 -> 2 | AO57: =+E57 -> 2 | AP57: =+E57 -> 2 | AQ57: =+E57 -> 2 | AR57: =+E57 -> 2 | AS57: =+E57 -> 2 | AT57: =+E57 -> 2 | AU57: =+E57 -> 2 | AV57: =+E57 -> 2 | AW57: =+E57 -> 2 | AX57: =+E57 -> 2 | AY57: =+E57 -> 2 | AZ57: =+E57 -> 2 | BA57: =+E57 -> 2 | BB57: =+E57 -> 2 | BC57: =+E57 -> 2 | BD57: =+E57 -> 2 | BE57: =+E57 -> 2 | BF57: =+E57 -> 2 | BG57: =+E57 -> 2 | BH57: =+E57 -> 2 | BI57: =+E57 -> 2 | BJ57: =+E57 -> 2 | BK57: =+E57 -> 2 | BL57: =+E57 -> 2 | BM57: =+E57 -> 2 | BN57: =+E57 -> 2 | BO57: =+E57 -> 2 | BP57: =+E57 -> 2 | BQ57: =+AK57 -> 2 | BR57: =+AK57 -> 2 | BS57: =+AK57 -> 2 | BT57: =+AK57 -> 2 | BU57: =+AO57 -> 2 | BV57: =+AO57 -> 2 | BW57: =+AO57 -> 2 | BX57: =+AO57 -> 2 | BY57: =+AS57 -> 2 | BZ57: =+AS57 -> 2 | CA57: =+AS57 -> 2 | CB57: =+AS57 -> 2 | CC57: =+AW57 -> 2 | CD57: =+AW57 -> 2 | CE57: =+AW57 -> 2 | CF57: =+AW57 -> 2 | CG57: =+BA57 -> 2 | CH57: =+BA57 -> 2 | CI57: =+BA57 -> 2 | CJ57: =+BA57 -> 2 | CK57: =+BE57 -> 2 | CL57: =+BE57 -> 2 | CM57: =+BE57 -> 2 | CN57: =+BE57 -> 2 | CO57: =+BI57 -> 2 | CP57: =+BI57 -> 2 | CQ57: =+BI57 -> 2 | CR57: =+BI57 -> 2 | CS57: =+BM57 -> 2 | CT57: =+BM57 -> 2 | CU57: =+BM57 -> 2 | CV57: =+BM57 -> 2 | CW57: =+BQ57 -> 2 | CX57: =+BQ57 -> 2 | CY57: =+BQ57 -> 2 | CZ57: =+BQ57 -> 2 | DA57: =+BU57 -> 2 | DB57: =+BU57 -> 2 | DC57: =+BU57 -> 2 | DD57: =+BU57 -> 2 | DE57: =+BY57 -> 2 | DF57: =+BY57 -> 2 | DG57: =+BY57 -> 2 | DH57: =+BY57 -> 2 | DI57: =+CC57 -> 2 | DJ57: =+CC57 -> 2 | DK57: =+CC57 -> 2 | DL57: =+CC57 -> 2 | DM57: =+CG57 -> 2 | DN57: =+CG57 -> 2 | DO57: =+CG57 -> 2 | DP57: =+CG57 -> 2 | DQ57: =+CK57 -> 2 | DR57: =+CK57 -> 2 | DS57: =+CK57 -> 2 | DT57: =+CK57 -> 2 | DU57: =+CO57 -> 2 | DV57: =+CO57 -> 2 | DW57: =+CO57 -> 2 | DX57: =+CO57 -> 2 | DY57: =+CS57 -> 2 | DZ57: =+CS57 -> 2 | EA57: =+CS57 -> 2 | EB57: =+CS57 -> 2 | EC57: =+CW57 -> 2 | ED57: =+CW57 -> 2 | EE57: =+CW57 -> 2 | EF57: =+CW57 -> 2 | EG57: =+DA57 -> 2 | EH57: =+DA57 -> 2 | EI57: =+DA57 -> 2 | EJ57: =+DA57 -> 2 | EK57: =+DE57 -> 2 | EL57: =+DE57 -> 2 | EM57: =+DE57 -> 2 | EN57: =+DE57 -> 2 | EO57: =+DI57 -> 2 | EP57: =+DI57 -> 2 | EQ57: =+DI57 -> 2 | ER57: =+DI57 -> 2 | ES57: =+DM57 -> 2 | ET57: =+DM57 -> 2 | EU57: =+DM57 -> 2 | EV57: =+DM57 -> 2 | EW57: =SUM(I57:DD57)/4 -> 38 | EX57: 16 | EY57: =24-EX57 -> 8 | EZ57: =+EW57*EX57*28 -> 17024 | FA57: =+EW57*EY57*30 -> 9120
C59: Personnel
C60: Project Manager | D60: Adet | E60: 1 | AG60: =+E60 -> 1 | AH60: =+E60 -> 1 | AI60: =+E60 -> 1 | AJ60: =+E60 -> 1 | AK60: =+E60 -> 1 | AL60: =+E60 -> 1 | AM60: =+E60 -> 1 | AN60: =+E60 -> 1 | AO60: =+E60 -> 1 | AP60: =+E60 -> 1 | AQ60: =+E60 -> 1 | AR60: =+E60 -> 1 | AS60: =+E60 -> 1 | AT60: =+E60 -> 1 | AU60: =+E60 -> 1 | AV60: =+E60 -> 1 | AW60: =+E60 -> 1 | AX60: =+E60 -> 1 | AY60: =+E60 -> 1 | AZ60: =+E60 -> 1 | BA60: =+E60 -> 1 | BB60: =+E60 -> 1 | BC60: =+E60 -> 1 | BD60: =+E60 -> 1 | BE60: =+E60 -> 1 | BF60: =+E60 -> 1 | BG60: =+E60 -> 1 | BH60: =+E60 -> 1 | BI60: =+E60 -> 1 | BJ60: =+E60 -> 1 | BK60: =+E60 -> 1 | BL60: =+E60 -> 1 | BM60: =+E60 -> 1 | BN60: =+E60 -> 1 | BO60: =+E60 -> 1 | BP60: =+E60 -> 1 | BQ60: =+AK60 -> 1 | BR60: =+AK60 -> 1 | BS60: =+AK60 -> 1 | BT60: =+AK60 -> 1 | BU60: =+AK60 -> 1 | BV60: =+AK60 -> 1 | BW60: =+AK60 -> 1 | BX60: =+AK60 -> 1 | BY60: =+AS60 -> 1 | BZ60: =+AS60 -> 1 | CA60: =+AS60 -> 1 | CB60: =+AS60 -> 1 | CC60: =+AS60 -> 1 | CD60: =+AS60 -> 1 | CE60: =+AS60 -> 1 | CF60: =+AS60 -> 1 | CG60: =+BA60 -> 1 | CH60: =+BA60 -> 1 | CI60: =+BA60 -> 1 | CJ60: =+BA60 -> 1 | CK60: =+BA60 -> 1 | CL60: =+BA60 -> 1 | CM60: =+BA60 -> 1 | CN60: =+BA60 -> 1 | CO60: =+BI60 -> 1 | CP60: =+BI60 -> 1 | CQ60: =+BI60 -> 1 | CR60: =+BI60 -> 1 | CS60: =+BI60 -> 1 | CT60: =+BI60 -> 1 | CU60: =+BI60 -> 1 | CV60: =+BI60 -> 1 | CW60: =+BQ60 -> 1 | CX60: =+BQ60 -> 1 | CY60: =+BQ60 -> 1 | CZ60: =+BQ60 -> 1 | DA60: =+BQ60 -> 1 | DB60: =+BQ60 -> 1 | DC60: =+BQ60 -> 1 | DD60: =+BQ60 -> 1 | DE60: =+BY60 -> 1 | DF60: =+BY60 -> 1 | DG60: =+BY60 -> 1 | DH60: =+BY60 -> 1 | DI60: =+BY60 -> 1 | DJ60: =+BY60 -> 1 | DK60: =+BY60 -> 1 | DL60: =+BY60 -> 1 | DM60: =+CG60 -> 1 | DN60: =+CG60 -> 1 | DO60: =+CG60 -> 1 | DP60: =+CG60 -> 1 | DQ60: =+CG60 -> 1 | DR60: =+CG60 -> 1 | DS60: =+CG60 -> 1 | DT60: =+CG60 -> 1 | DU60: =+CO60 -> 1 | DV60: =+CO60 -> 1 | DW60: =+CO60 -> 1 | DX60: =+CO60 -> 1 | DY60: =+CO60 -> 1 | DZ60: =+CO60 -> 1 | EA60: =+CO60 -> 1 | EB60: =+CO60 -> 1 | EC60: =+CW60 -> 1 | ED60: =+CW60 -> 1 | EE60: =+CW60 -> 1 | EF60: =+CW60 -> 1 | EG60: =+CW60 -> 1 | EH60: =+CW60 -> 1 | EI60: =+CW60 -> 1 | EJ60: =+CW60 -> 1 | EK60: =+DE60 -> 1 | EL60: =+DE60 -> 1 | EM60: =+DE60 -> 1 | EN60: =+DE60 -> 1 | EO60: =+DE60 -> 1 | EP60: =+DE60 -> 1 | EQ60: =+DE60 -> 1 | ER60: =+DE60 -> 1 | ES60: =+DM60 -> 1 | ET60: =+DM60 -> 1 | EU60: =+DM60 -> 1 | EV60: =+DM60 -> 1 | EW60: =SUM(I60:DD60)/4 -> 19
C61: Site Manager | D61: Adet | E61: 1 | AG61: =+E61 -> 1 | AH61: =+E61 -> 1 | AI61: =+E61 -> 1 | AJ61: =+E61 -> 1 | AK61: =+E61 -> 1 | AL61: =+E61 -> 1 | AM61: =+E61 -> 1 | AN61: =+E61 -> 1 | AO61: =+E61 -> 1 | AP61: =+E61 -> 1 | AQ61: =+E61 -> 1 | AR61: =+E61 -> 1 | AS61: =+E61 -> 1 | AT61: =+E61 -> 1 | AU61: =+E61 -> 1 | AV61: =+E61 -> 1 | AW61: =+E61 -> 1 | AX61: =+E61 -> 1 | AY61: =+E61 -> 1 | AZ61: =+E61 -> 1 | BA61: =+E61 -> 1 | BB61: =+E61 -> 1 | BC61: =+E61 -> 1 | BD61: =+E61 -> 1 | BE61: =+E61 -> 1 | BF61: =+E61 -> 1 | BG61: =+E61 -> 1 | BH61: =+E61 -> 1 | BI61: =+E61 -> 1 | BJ61: =+E61 -> 1 | BK61: =+E61 -> 1 | BL61: =+E61 -> 1 | BM61: =+E61 -> 1 | BN61: =+E61 -> 1 | BO61: =+E61 -> 1 | BP61: =+E61 -> 1 | BQ61: =+AK61 -> 1 | BR61: =+AK61 -> 1 | BS61: =+AK61 -> 1 | BT61: =+AK61 -> 1 | BU61: =+AK61 -> 1 | BV61: =+AK61 -> 1 | BW61: =+AK61 -> 1 | BX61: =+AK61 -> 1 | BY61: =+AS61 -> 1 | BZ61: =+AS61 -> 1 | CA61: =+AS61 -> 1 | CB61: =+AS61 -> 1 | CC61: =+AS61 -> 1 | CD61: =+AS61 -> 1 | CE61: =+AS61 -> 1 | CF61: =+AS61 -> 1 | CG61: =+BA61 -> 1 | CH61: =+BA61 -> 1 | CI61: =+BA61 -> 1 | CJ61: =+BA61 -> 1 | CK61: =+BA61 -> 1 | CL61: =+BA61 -> 1 | CM61: =+BA61 -> 1 | CN61: =+BA61 -> 1 | CO61: =+BI61 -> 1 | CP61: =+BI61 -> 1 | CQ61: =+BI61 -> 1 | CR61: =+BI61 -> 1 | CS61: =+BI61 -> 1 | CT61: =+BI61 -> 1 | CU61: =+BI61 -> 1 | CV61: =+BI61 -> 1 | CW61: =+BQ61 -> 1 | CX61: =+BQ61 -> 1 | CY61: =+BQ61 -> 1 | CZ61: =+BQ61 -> 1 | DA61: =+BQ61 -> 1 | DB61: =+BQ61 -> 1 | DC61: =+BQ61 -> 1 | DD61: =+BQ61 -> 1 | DE61: =+BY61 -> 1 | DF61: =+BY61 -> 1 | DG61: =+BY61 -> 1 | DH61: =+BY61 -> 1 | DI61: =+BY61 -> 1 | DJ61: =+BY61 -> 1 | DK61: =+BY61 -> 1 | DL61: =+BY61 -> 1 | DM61: =+CG61 -> 1 | DN61: =+CG61 -> 1 | DO61: =+CG61 -> 1 | DP61: =+CG61 -> 1 | DQ61: =+CG61 -> 1 | DR61: =+CG61 -> 1 | DS61: =+CG61 -> 1 | DT61: =+CG61 -> 1 | DU61: =+CO61 -> 1 | DV61: =+CO61 -> 1 | DW61: =+CO61 -> 1 | DX61: =+CO61 -> 1 | DY61: =+CO61 -> 1 | DZ61: =+CO61 -> 1 | EA61: =+CO61 -> 1 | EB61: =+CO61 -> 1 | EC61: =+CW61 -> 1 | ED61: =+CW61 -> 1 | EE61: =+CW61 -> 1 | EF61: =+CW61 -> 1 | EG61: =+CW61 -> 1 | EH61: =+CW61 -> 1 | EI61: =+CW61 -> 1 | EJ61: =+CW61 -> 1 | EK61: =+DE61 -> 1 | EL61: =+DE61 -> 1 | EM61: =+DE61 -> 1 | EN61: =+DE61 -> 1 | EO61: =+DE61 -> 1 | EP61: =+DE61 -> 1 | EQ61: =+DE61 -> 1 | ER61: =+DE61 -> 1 | ES61: =+DM61 -> 1 | ET61: =+DM61 -> 1 | EU61: =+DM61 -> 1 | EV61: =+DM61 -> 1 | EW61: =SUM(I61:DD61)/4 -> 19
C62: Survey Engineer | D62: Adet | E62: 1 | AG62: =+E62 -> 1 | AH62: =+E62 -> 1 | AI62: =+E62 -> 1 | AJ62: =+E62 -> 1 | AK62: =+E62 -> 1 | AL62: =+E62 -> 1 | AM62: =+E62 -> 1 | AN62: =+E62 -> 1 | AO62: =+E62 -> 1 | AP62: =+E62 -> 1 | AQ62: =+E62 -> 1 | AR62: =+E62 -> 1 | AS62: =+E62 -> 1 | AT62: =+E62 -> 1 | AU62: =+E62 -> 1 | AV62: =+E62 -> 1 | AW62: =+E62 -> 1 | AX62: =+E62 -> 1 | AY62: =+E62 -> 1 | AZ62: =+E62 -> 1 | BA62: =+E62 -> 1 | BB62: =+E62 -> 1 | BC62: =+E62 -> 1 | BD62: =+E62 -> 1 | BE62: =+E62 -> 1 | BF62: =+E62 -> 1 | BG62: =+E62 -> 1 | BH62: =+E62 -> 1 | BI62: =+E62 -> 1 | BJ62: =+E62 -> 1 | BK62: =+E62 -> 1 | BL62: =+E62 -> 1 | BM62: =+E62 -> 1 | BN62: =+E62 -> 1 | BO62: =+E62 -> 1 | BP62: =+E62 -> 1 | BQ62: =+AK62 -> 1 | BR62: =+AK62 -> 1 | BS62: =+AK62 -> 1 | BT62: =+AK62 -> 1 | BU62: =+AK62 -> 1 | BV62: =+AK62 -> 1 | BW62: =+AK62 -> 1 | BX62: =+AK62 -> 1 | BY62: =+AS62 -> 1 | BZ62: =+AS62 -> 1 | CA62: =+AS62 -> 1 | CB62: =+AS62 -> 1 | CC62: =+AS62 -> 1 | CD62: =+AS62 -> 1 | CE62: =+AS62 -> 1 | CF62: =+AS62 -> 1 | CG62: =+BA62 -> 1 | CH62: =+BA62 -> 1 | CI62: =+BA62 -> 1 | CJ62: =+BA62 -> 1 | CK62: =+BA62 -> 1 | CL62: =+BA62 -> 1 | CM62: =+BA62 -> 1 | CN62: =+BA62 -> 1 | CO62: =+BI62 -> 1 | CP62: =+BI62 -> 1 | CQ62: =+BI62 -> 1 | CR62: =+BI62 -> 1 | CS62: =+BI62 -> 1 | CT62: =+BI62 -> 1 | CU62: =+BI62 -> 1 | CV62: =+BI62 -> 1 | CW62: =+BQ62 -> 1 | CX62: =+BQ62 -> 1 | CY62: =+BQ62 -> 1 | CZ62: =+BQ62 -> 1 | DA62: =+BQ62 -> 1 | DB62: =+BQ62 -> 1 | DC62: =+BQ62 -> 1 | DD62: =+BQ62 -> 1 | DE62: =+BY62 -> 1 | DF62: =+BY62 -> 1 | DG62: =+BY62 -> 1 | DH62: =+BY62 -> 1 | DI62: =+BY62 -> 1 | DJ62: =+BY62 -> 1 | DK62: =+BY62 -> 1 | DL62: =+BY62 -> 1 | DM62: =+CG62 -> 1 | DN62: =+CG62 -> 1 | DO62: =+CG62 -> 1 | DP62: =+CG62 -> 1 | DQ62: =+CG62 -> 1 | DR62: =+CG62 -> 1 | DS62: =+CG62 -> 1 | DT62: =+CG62 -> 1 | DU62: =+CO62 -> 1 | DV62: =+CO62 -> 1 | DW62: =+CO62 -> 1 | DX62: =+CO62 -> 1 | DY62: =+CO62 -> 1 | DZ62: =+CO62 -> 1 | EA62: =+CO62 -> 1 | EB62: =+CO62 -> 1 | EC62: =+CW62 -> 1 | ED62: =+CW62 -> 1 | EE62: =+CW62 -> 1 | EF62: =+CW62 -> 1 | EG62: =+CW62 -> 1 | EH62: =+CW62 -> 1 | EI62: =+CW62 -> 1 | EJ62: =+CW62 -> 1 | EK62: =+DE62 -> 1 | EL62: =+DE62 -> 1 | EM62: =+DE62 -> 1 | EN62: =+DE62 -> 1 | EO62: =+DE62 -> 1 | EP62: =+DE62 -> 1 | EQ62: =+DE62 -> 1 | ER62: =+DE62 -> 1 | ES62: =+DM62 -> 1 | ET62: =+DM62 -> 1 | EU62: =+DM62 -> 1 | EV62: =+DM62 -> 1 | EW62: =SUM(I62:DD62)/4 -> 19
C63: Surveyor | D63: Adet | E63: 4 | AG63: =+E63 -> 4 | AH63: =+E63 -> 4 | AI63: =+E63 -> 4 | AJ63: =+E63 -> 4 | AK63: =+E63 -> 4 | AL63: =+E63 -> 4 | AM63: =+E63 -> 4 | AN63: =+E63 -> 4 | AO63: =+E63 -> 4 | AP63: =+E63 -> 4 | AQ63: =+E63 -> 4 | AR63: =+E63 -> 4 | AS63: =+E63 -> 4 | AT63: =+E63 -> 4 | AU63: =+E63 -> 4 | AV63: =+E63 -> 4 | AW63: =+E63 -> 4 | AX63: =+E63 -> 4 | AY63: =+E63 -> 4 | AZ63: =+E63 -> 4 | BA63: =+E63 -> 4 | BB63: =+E63 -> 4 | BC63: =+E63 -> 4 | BD63: =+E63 -> 4 | BE63: =+E63 -> 4 | BF63: =+E63 -> 4 | BG63: =+E63 -> 4 | BH63: =+E63 -> 4 | BI63: =+E63 -> 4 | BJ63: =+E63 -> 4 | BK63: =+E63 -> 4 | BL63: =+E63 -> 4 | BM63: =+E63 -> 4 | BN63: =+E63 -> 4 | BO63: =+E63 -> 4 | BP63: =+E63 -> 4 | BQ63: =+AK63 -> 4 | BR63: =+AK63 -> 4 | BS63: =+AK63 -> 4 | BT63: =+AK63 -> 4 | BU63: =+AK63 -> 4 | BV63: =+AK63 -> 4 | BW63: =+AK63 -> 4 | BX63: =+AK63 -> 4 | BY63: =+AS63 -> 4 | BZ63: =+AS63 -> 4 | CA63: =+AS63 -> 4 | CB63: =+AS63 -> 4 | CC63: =+AS63 -> 4 | CD63: =+AS63 -> 4 | CE63: =+AS63 -> 4 | CF63: =+AS63 -> 4 | CG63: =+BA63 -> 4 | CH63: =+BA63 -> 4 | CI63: =+BA63 -> 4 | CJ63: =+BA63 -> 4 | CK63: =+BA63 -> 4 | CL63: =+BA63 -> 4 | CM63: =+BA63 -> 4 | CN63: =+BA63 -> 4 | CO63: =+BI63 -> 4 | CP63: =+BI63 -> 4 | CQ63: =+BI63 -> 4 | CR63: =+BI63 -> 4 | CS63: =+BI63 -> 4 | CT63: =+BI63 -> 4 | CU63: =+BI63 -> 4 | CV63: =+BI63 -> 4 | CW63: =+BQ63 -> 4 | CX63: =+BQ63 -> 4 | CY63: =+BQ63 -> 4 | CZ63: =+BQ63 -> 4 | DA63: =+BQ63 -> 4 | DB63: =+BQ63 -> 4 | DC63: =+BQ63 -> 4 | DD63: =+BQ63 -> 4 | DE63: =+BY63 -> 4 | DF63: =+BY63 -> 4 | DG63: =+BY63 -> 4 | DH63: =+BY63 -> 4 | DI63: =+BY63 -> 4 | DJ63: =+BY63 -> 4 | DK63: =+BY63 -> 4 | DL63: =+BY63 -> 4 | DM63: =+CG63 -> 4 | DN63: =+CG63 -> 4 | DO63: =+CG63 -> 4 | DP63: =+CG63 -> 4 | DQ63: =+CG63 -> 4 | DR63: =+CG63 -> 4 | DS63: =+CG63 -> 4 | DT63: =+CG63 -> 4 | DU63: =+CO63 -> 4 | DV63: =+CO63 -> 4 | DW63: =+CO63 -> 4 | DX63: =+CO63 -> 4 | DY63: =+CO63 -> 4 | DZ63: =+CO63 -> 4 | EA63: =+CO63 -> 4 | EB63: =+CO63 -> 4 | EC63: =+CW63 -> 4 | ED63: =+CW63 -> 4 | EE63: =+CW63 -> 4 | EF63: =+CW63 -> 4 | EG63: =+CW63 -> 4 | EH63: =+CW63 -> 4 | EI63: =+CW63 -> 4 | EJ63: =+CW63 -> 4 | EK63: =+DE63 -> 4 | EL63: =+DE63 -> 4 | EM63: =+DE63 -> 4 | EN63: =+DE63 -> 4 | EO63: =+DE63 -> 4 | EP63: =+DE63 -> 4 | EQ63: =+DE63 -> 4 | ER63: =+DE63 -> 4 | ES63: =+DM63 -> 4 | ET63: =+DM63 -> 4 | EU63: =+DM63 -> 4 | EV63: =+DM63 -> 4 | EW63: =SUM(I63:DD63)/4 -> 76
C64: Site Engineer | D64: Adet | E64: 2 | AG64: =+E64 -> 2 | AH64: =+E64 -> 2 | AI64: =+E64 -> 2 | AJ64: =+E64 -> 2 | AK64: =+E64 -> 2 | AL64: =+E64 -> 2 | AM64: =+E64 -> 2 | AN64: =+E64 -> 2 | AO64: =+E64 -> 2 | AP64: =+E64 -> 2 | AQ64: =+E64 -> 2 | AR64: =+E64 -> 2 | AS64: =+E64 -> 2 | AT64: =+E64 -> 2 | AU64: =+E64 -> 2 | AV64: =+E64 -> 2 | AW64: =+E64 -> 2 | AX64: =+E64 -> 2 | AY64: =+E64 -> 2 | AZ64: =+E64 -> 2 | BA64: =+E64 -> 2 | BB64: =+E64 -> 2 | BC64: =+E64 -> 2 | BD64: =+E64 -> 2 | BE64: =+E64 -> 2 | BF64: =+E64 -> 2 | BG64: =+E64 -> 2 | BH64: =+E64 -> 2 | BI64: =+E64 -> 2 | BJ64: =+E64 -> 2 | BK64: =+E64 -> 2 | BL64: =+E64 -> 2 | BM64: =+E64 -> 2 | BN64: =+E64 -> 2 | BO64: =+E64 -> 2 | BP64: =+E64 -> 2 | BQ64: =+AK64 -> 2 | BR64: =+AK64 -> 2 | BS64: =+AK64 -> 2 | BT64: =+AK64 -> 2 | BU64: =+AK64 -> 2 | BV64: =+AK64 -> 2 | BW64: =+AK64 -> 2 | BX64: =+AK64 -> 2 | BY64: =+AS64 -> 2 | BZ64: =+AS64 -> 2 | CA64: =+AS64 -> 2 | CB64: =+AS64 -> 2 | CC64: =+AS64 -> 2 | CD64: =+AS64 -> 2 | CE64: =+AS64 -> 2 | CF64: =+AS64 -> 2 | CG64: =+BA64 -> 2 | CH64: =+BA64 -> 2 | CI64: =+BA64 -> 2 | CJ64: =+BA64 -> 2 | CK64: =+BA64 -> 2 | CL64: =+BA64 -> 2 | CM64: =+BA64 -> 2 | CN64: =+BA64 -> 2 | CO64: =+BI64 -> 2 | CP64: =+BI64 -> 2 | CQ64: =+BI64 -> 2 | CR64: =+BI64 -> 2 | CS64: =+BI64 -> 2 | CT64: =+BI64 -> 2 | CU64: =+BI64 -> 2 | CV64: =+BI64 -> 2 | CW64: =+BQ64 -> 2 | CX64: =+BQ64 -> 2 | CY64: =+BQ64 -> 2 | CZ64: =+BQ64 -> 2 | DA64: =+BQ64 -> 2 | DB64: =+BQ64 -> 2 | DC64: =+BQ64 -> 2 | DD64: =+BQ64 -> 2 | DE64: =+BY64 -> 2 | DF64: =+BY64 -> 2 | DG64: =+BY64 -> 2 | DH64: =+BY64 -> 2 | DI64: =+BY64 -> 2 | DJ64: =+BY64 -> 2 | DK64: =+BY64 -> 2 | DL64: =+BY64 -> 2 | DM64: =+CG64 -> 2 | DN64: =+CG64 -> 2 | DO64: =+CG64 -> 2 | DP64: =+CG64 -> 2 | DQ64: =+CG64 -> 2 | DR64: =+CG64 -> 2 | DS64: =+CG64 -> 2 | DT64: =+CG64 -> 2 | DU64: =+CO64 -> 2 | DV64: =+CO64 -> 2 | DW64: =+CO64 -> 2 | DX64: =+CO64 -> 2 | DY64: =+CO64 -> 2 | DZ64: =+CO64 -> 2 | EA64: =+CO64 -> 2 | EB64: =+CO64 -> 2 | EC64: =+CW64 -> 2 | ED64: =+CW64 -> 2 | EE64: =+CW64 -> 2 | EF64: =+CW64 -> 2 | EG64: =+CW64 -> 2 | EH64: =+CW64 -> 2 | EI64: =+CW64 -> 2 | EJ64: =+CW64 -> 2 | EK64: =+DE64 -> 2 | EL64: =+DE64 -> 2 | EM64: =+DE64 -> 2 | EN64: =+DE64 -> 2 | EO64: =+DE64 -> 2 | EP64: =+DE64 -> 2 | EQ64: =+DE64 -> 2 | ER64: =+DE64 -> 2 | ES64: =+DM64 -> 2 | ET64: =+DM64 -> 2 | EU64: =+DM64 -> 2 | EV64: =+DM64 -> 2 | EW64: =SUM(I64:DD64)/4 -> 38
C65: Technical Office Chief | D65: Adet | E65: 1 | AG65: =+E65 -> 1 | AH65: =+E65 -> 1 | AI65: =+E65 -> 1 | AJ65: =+E65 -> 1 | AK65: =+E65 -> 1 | AL65: =+E65 -> 1 | AM65: =+E65 -> 1 | AN65: =+E65 -> 1 | AO65: =+E65 -> 1 | AP65: =+E65 -> 1 | AQ65: =+E65 -> 1 | AR65: =+E65 -> 1 | AS65: =+E65 -> 1 | AT65: =+E65 -> 1 | AU65: =+E65 -> 1 | AV65: =+E65 -> 1 | AW65: =+E65 -> 1 | AX65: =+E65 -> 1 | AY65: =+E65 -> 1 | AZ65: =+E65 -> 1 | BA65: =+E65 -> 1 | BB65: =+E65 -> 1 | BC65: =+E65 -> 1 | BD65: =+E65 -> 1 | BE65: =+E65 -> 1 | BF65: =+E65 -> 1 | BG65: =+E65 -> 1 | BH65: =+E65 -> 1 | BI65: =+E65 -> 1 | BJ65: =+E65 -> 1 | BK65: =+E65 -> 1 | BL65: =+E65 -> 1 | BM65: =+E65 -> 1 | BN65: =+E65 -> 1 | BO65: =+E65 -> 1 | BP65: =+E65 -> 1 | BQ65: =+AK65 -> 1 | BR65: =+AK65 -> 1 | BS65: =+AK65 -> 1 | BT65: =+AK65 -> 1 | BU65: =+AK65 -> 1 | BV65: =+AK65 -> 1 | BW65: =+AK65 -> 1 | BX65: =+AK65 -> 1 | BY65: =+AS65 -> 1 | BZ65: =+AS65 -> 1 | CA65: =+AS65 -> 1 | CB65: =+AS65 -> 1 | CC65: =+AS65 -> 1 | CD65: =+AS65 -> 1 | CE65: =+AS65 -> 1 | CF65: =+AS65 -> 1 | CG65: =+BA65 -> 1 | CH65: =+BA65 -> 1 | CI65: =+BA65 -> 1 | CJ65: =+BA65 -> 1 | CK65: =+BA65 -> 1 | CL65: =+BA65 -> 1 | CM65: =+BA65 -> 1 | CN65: =+BA65 -> 1 | CO65: =+BI65 -> 1 | CP65: =+BI65 -> 1 | CQ65: =+BI65 -> 1 | CR65: =+BI65 -> 1 | CS65: =+BI65 -> 1 | CT65: =+BI65 -> 1 | CU65: =+BI65 -> 1 | CV65: =+BI65 -> 1 | CW65: =+BQ65 -> 1 | CX65: =+BQ65 -> 1 | CY65: =+BQ65 -> 1 | CZ65: =+BQ65 -> 1 | DA65: =+BQ65 -> 1 | DB65: =+BQ65 -> 1 | DC65: =+BQ65 -> 1 | DD65: =+BQ65 -> 1 | DE65: =+BY65 -> 1 | DF65: =+BY65 -> 1 | DG65: =+BY65 -> 1 | DH65: =+BY65 -> 1 | DI65: =+BY65 -> 1 | DJ65: =+BY65 -> 1 | DK65: =+BY65 -> 1 | DL65: =+BY65 -> 1 | DM65: =+CG65 -> 1 | DN65: =+CG65 -> 1 | DO65: =+CG65 -> 1 | DP65: =+CG65 -> 1 | DQ65: =+CG65 -> 1 | DR65: =+CG65 -> 1 | DS65: =+CG65 -> 1 | DT65: =+CG65 -> 1 | DU65: =+CO65 -> 1 | DV65: =+CO65 -> 1 | DW65: =+CO65 -> 1 | DX65: =+CO65 -> 1 | DY65: =+CO65 -> 1 | DZ65: =+CO65 -> 1 | EA65: =+CO65 -> 1 | EB65: =+CO65 -> 1 | EC65: =+CW65 -> 1 | ED65: =+CW65 -> 1 | EE65: =+CW65 -> 1 | EF65: =+CW65 -> 1 | EG65: =+CW65 -> 1 | EH65: =+CW65 -> 1 | EI65: =+CW65 -> 1 | EJ65: =+CW65 -> 1 | EK65: =+DE65 -> 1 | EL65: =+DE65 -> 1 | EM65: =+DE65 -> 1 | EN65: =+DE65 -> 1 | EO65: =+DE65 -> 1 | EP65: =+DE65 -> 1 | EQ65: =+DE65 -> 1 | ER65: =+DE65 -> 1 | ES65: =+DM65 -> 1 | ET65: =+DM65 -> 1 | EU65: =+DM65 -> 1 | EV65: =+DM65 -> 1 | EW65: =SUM(I65:DD65)/4 -> 19
C66: Finance & Admin. Chief | D66: Adet | E66: 1 | AG66: =+E66 -> 1 | AH66: =+E66 -> 1 | AI66: =+E66 -> 1 | AJ66: =+E66 -> 1 | AK66: =+E66 -> 1 | AL66: =+E66 -> 1 | AM66: =+E66 -> 1 | AN66: =+E66 -> 1 | AO66: =+E66 -> 1 | AP66: =+E66 -> 1 | AQ66: =+E66 -> 1 | AR66: =+E66 -> 1 | AS66: =+E66 -> 1 | AT66: =+E66 -> 1 | AU66: =+E66 -> 1 | AV66: =+E66 -> 1 | AW66: =+E66 -> 1 | AX66: =+E66 -> 1 | AY66: =+E66 -> 1 | AZ66: =+E66 -> 1 | BA66: =+E66 -> 1 | BB66: =+E66 -> 1 | BC66: =+E66 -> 1 | BD66: =+E66 -> 1 | BE66: =+E66 -> 1 | BF66: =+E66 -> 1 | BG66: =+E66 -> 1 | BH66: =+E66 -> 1 | BI66: =+E66 -> 1 | BJ66: =+E66 -> 1 | BK66: =+E66 -> 1 | BL66: =+E66 -> 1 | BM66: =+E66 -> 1 | BN66: =+E66 -> 1 | BO66: =+E66 -> 1 | BP66: =+E66 -> 1 | BQ66: =+AK66 -> 1 | BR66: =+AK66 -> 1 | BS66: =+AK66 -> 1 | BT66: =+AK66 -> 1 | BU66: =+AK66 -> 1 | BV66: =+AK66 -> 1 | BW66: =+AK66 -> 1 | BX66: =+AK66 -> 1 | BY66: =+AS66 -> 1 | BZ66: =+AS66 -> 1 | CA66: =+AS66 -> 1 | CB66: =+AS66 -> 1 | CC66: =+AS66 -> 1 | CD66: =+AS66 -> 1 | CE66: =+AS66 -> 1 | CF66: =+AS66 -> 1 | CG66: =+BA66 -> 1 | CH66: =+BA66 -> 1 | CI66: =+BA66 -> 1 | CJ66: =+BA66 -> 1 | CK66: =+BA66 -> 1 | CL66: =+BA66 -> 1 | CM66: =+BA66 -> 1 | CN66: =+BA66 -> 1 | CO66: =+BI66 -> 1 | CP66: =+BI66 -> 1 | CQ66: =+BI66 -> 1 | CR66: =+BI66 -> 1 | CS66: =+BI66 -> 1 | CT66: =+BI66 -> 1 | CU66: =+BI66 -> 1 | CV66: =+BI66 -> 1 | CW66: =+BQ66 -> 1 | CX66: =+BQ66 -> 1 | CY66: =+BQ66 -> 1 | CZ66: =+BQ66 -> 1 | DA66: =+BQ66 -> 1 | DB66: =+BQ66 -> 1 | DC66: =+BQ66 -> 1 | DD66: =+BQ66 -> 1 | DE66: =+BY66 -> 1 | DF66: =+BY66 -> 1 | DG66: =+BY66 -> 1 | DH66: =+BY66 -> 1 | DI66: =+BY66 -> 1 | DJ66: =+BY66 -> 1 | DK66: =+BY66 -> 1 | DL66: =+BY66 -> 1 | DM66: =+CG66 -> 1 | DN66: =+CG66 -> 1 | DO66: =+CG66 -> 1 | DP66: =+CG66 -> 1 | DQ66: =+CG66 -> 1 | DR66: =+CG66 -> 1 | DS66: =+CG66 -> 1 | DT66: =+CG66 -> 1 | DU66: =+CO66 -> 1 | DV66: =+CO66 -> 1 | DW66: =+CO66 -> 1 | DX66: =+CO66 -> 1 | DY66: =+CO66 -> 1 | DZ66: =+CO66 -> 1 | EA66: =+CO66 -> 1 | EB66: =+CO66 -> 1 | EC66: =+CW66 -> 1 | ED66: =+CW66 -> 1 | EE66: =+CW66 -> 1 | EF66: =+CW66 -> 1 | EG66: =+CW66 -> 1 | EH66: =+CW66 -> 1 | EI66: =+CW66 -> 1 | EJ66: =+CW66 -> 1 | EK66: =+DE66 -> 1 | EL66: =+DE66 -> 1 | EM66: =+DE66 -> 1 | EN66: =+DE66 -> 1 | EO66: =+DE66 -> 1 | EP66: =+DE66 -> 1 | EQ66: =+DE66 -> 1 | ER66: =+DE66 -> 1 | ES66: =+DM66 -> 1 | ET66: =+DM66 -> 1 | EU66: =+DM66 -> 1 | EV66: =+DM66 -> 1 | EW66: =SUM(I66:DD66)/4 -> 19
C67: Procurement | D67: Adet | E67: 1 | AG67: =+E67 -> 1 | AH67: =+E67 -> 1 | AI67: =+E67 -> 1 | AJ67: =+E67 -> 1 | AK67: =+E67 -> 1 | AL67: =+E67 -> 1 | AM67: =+E67 -> 1 | AN67: =+E67 -> 1 | AO67: =+E67 -> 1 | AP67: =+E67 -> 1 | AQ67: =+E67 -> 1 | AR67: =+E67 -> 1 | AS67: =+E67 -> 1 | AT67: =+E67 -> 1 | AU67: =+E67 -> 1 | AV67: =+E67 -> 1 | AW67: =+E67 -> 1 | AX67: =+E67 -> 1 | AY67: =+E67 -> 1 | AZ67: =+E67 -> 1 | BA67: =+E67 -> 1 | BB67: =+E67 -> 1 | BC67: =+E67 -> 1 | BD67: =+E67 -> 1 | BE67: =+E67 -> 1 | BF67: =+E67 -> 1 | BG67: =+E67 -> 1 | BH67: =+E67 -> 1 | BI67: =+E67 -> 1 | BJ67: =+E67 -> 1 | BK67: =+E67 -> 1 | BL67: =+E67 -> 1 | BM67: =+E67 -> 1 | BN67: =+E67 -> 1 | BO67: =+E67 -> 1 | BP67: =+E67 -> 1 | BQ67: =+AK67 -> 1 | BR67: =+AK67 -> 1 | BS67: =+AK67 -> 1 | BT67: =+AK67 -> 1 | BU67: =+AK67 -> 1 | BV67: =+AK67 -> 1 | BW67: =+AK67 -> 1 | BX67: =+AK67 -> 1 | BY67: =+AS67 -> 1 | BZ67: =+AS67 -> 1 | CA67: =+AS67 -> 1 | CB67: =+AS67 -> 1 | CC67: =+AS67 -> 1 | CD67: =+AS67 -> 1 | CE67: =+AS67 -> 1 | CF67: =+AS67 -> 1 | CG67: =+BA67 -> 1 | CH67: =+BA67 -> 1 | CI67: =+BA67 -> 1 | CJ67: =+BA67 -> 1 | CK67: =+BA67 -> 1 | CL67: =+BA67 -> 1 | CM67: =+BA67 -> 1 | CN67: =+BA67 -> 1 | CO67: =+BI67 -> 1 | CP67: =+BI67 -> 1 | CQ67: =+BI67 -> 1 | CR67: =+BI67 -> 1 | CS67: =+BI67 -> 1 | CT67: =+BI67 -> 1 | CU67: =+BI67 -> 1 | CV67: =+BI67 -> 1 | CW67: =+BQ67 -> 1 | CX67: =+BQ67 -> 1 | CY67: =+BQ67 -> 1 | CZ67: =+BQ67 -> 1 | DA67: =+BQ67 -> 1 | DB67: =+BQ67 -> 1 | DC67: =+BQ67 -> 1 | DD67: =+BQ67 -> 1 | DE67: =+BY67 -> 1 | DF67: =+BY67 -> 1 | DG67: =+BY67 -> 1 | DH67: =+BY67 -> 1 | DI67: =+BY67 -> 1 | DJ67: =+BY67 -> 1 | DK67: =+BY67 -> 1 | DL67: =+BY67 -> 1 | DM67: =+CG67 -> 1 | DN67: =+CG67 -> 1 | DO67: =+CG67 -> 1 | DP67: =+CG67 -> 1 | DQ67: =+CG67 -> 1 | DR67: =+CG67 -> 1 | DS67: =+CG67 -> 1 | DT67: =+CG67 -> 1 | DU67: =+CO67 -> 1 | DV67: =+CO67 -> 1 | DW67: =+CO67 -> 1 | DX67: =+CO67 -> 1 | DY67: =+CO67 -> 1 | DZ67: =+CO67 -> 1 | EA67: =+CO67 -> 1 | EB67: =+CO67 -> 1 | EC67: =+CW67 -> 1 | ED67: =+CW67 -> 1 | EE67: =+CW67 -> 1 | EF67: =+CW67 -> 1 | EG67: =+CW67 -> 1 | EH67: =+CW67 -> 1 | EI67: =+CW67 -> 1 | EJ67: =+CW67 -> 1 | EK67: =+DE67 -> 1 | EL67: =+DE67 -> 1 | EM67: =+DE67 -> 1 | EN67: =+DE67 -> 1 | EO67: =+DE67 -> 1 | EP67: =+DE67 -> 1 | EQ67: =+DE67 -> 1 | ER67: =+DE67 -> 1 | ES67: =+DM67 -> 1 | ET67: =+DM67 -> 1 | EU67: =+DM67 -> 1 | EV67: =+DM67 -> 1 | EW67: =SUM(I67:DD67)/4 -> 19
C68: QHSE Manager | D68: Adet | E68: 1 | AG68: =+E68 -> 1 | AH68: =+E68 -> 1 | AI68: =+E68 -> 1 | AJ68: =+E68 -> 1 | AK68: =+E68 -> 1 | AL68: =+E68 -> 1 | AM68: =+E68 -> 1 | AN68: =+E68 -> 1 | AO68: =+E68 -> 1 | AP68: =+E68 -> 1 | AQ68: =+E68 -> 1 | AR68: =+E68 -> 1 | AS68: =+E68 -> 1 | AT68: =+E68 -> 1 | AU68: =+E68 -> 1 | AV68: =+E68 -> 1 | AW68: =+E68 -> 1 | AX68: =+E68 -> 1 | AY68: =+E68 -> 1 | AZ68: =+E68 -> 1 | BA68: =+E68 -> 1 | BB68: =+E68 -> 1 | BC68: =+E68 -> 1 | BD68: =+E68 -> 1 | BE68: =+E68 -> 1 | BF68: =+E68 -> 1 | BG68: =+E68 -> 1 | BH68: =+E68 -> 1 | BI68: =+E68 -> 1 | BJ68: =+E68 -> 1 | BK68: =+E68 -> 1 | BL68: =+E68 -> 1 | BM68: =+E68 -> 1 | BN68: =+E68 -> 1 | BO68: =+E68 -> 1 | BP68: =+E68 -> 1 | BQ68: =+AK68 -> 1 | BR68: =+AK68 -> 1 | BS68: =+AK68 -> 1 | BT68: =+AK68 -> 1 | BU68: =+AK68 -> 1 | BV68: =+AK68 -> 1 | BW68: =+AK68 -> 1 | BX68: =+AK68 -> 1 | BY68: =+AS68 -> 1 | BZ68: =+AS68 -> 1 | CA68: =+AS68 -> 1 | CB68: =+AS68 -> 1 | CC68: =+AS68 -> 1 | CD68: =+AS68 -> 1 | CE68: =+AS68 -> 1 | CF68: =+AS68 -> 1 | CG68: =+BA68 -> 1 | CH68: =+BA68 -> 1 | CI68: =+BA68 -> 1 | CJ68: =+BA68 -> 1 | CK68: =+BA68 -> 1 | CL68: =+BA68 -> 1 | CM68: =+BA68 -> 1 | CN68: =+BA68 -> 1 | CO68: =+BI68 -> 1 | CP68: =+BI68 -> 1 | CQ68: =+BI68 -> 1 | CR68: =+BI68 -> 1 | CS68: =+BI68 -> 1 | CT68: =+BI68 -> 1 | CU68: =+BI68 -> 1 | CV68: =+BI68 -> 1 | CW68: =+BQ68 -> 1 | CX68: =+BQ68 -> 1 | CY68: =+BQ68 -> 1 | CZ68: =+BQ68 -> 1 | DA68: =+BQ68 -> 1 | DB68: =+BQ68 -> 1 | DC68: =+BQ68 -> 1 | DD68: =+BQ68 -> 1 | DE68: =+BY68 -> 1 | DF68: =+BY68 -> 1 | DG68: =+BY68 -> 1 | DH68: =+BY68 -> 1 | DI68: =+BY68 -> 1 | DJ68: =+BY68 -> 1 | DK68: =+BY68 -> 1 | DL68: =+BY68 -> 1 | DM68: =+CG68 -> 1 | DN68: =+CG68 -> 1 | DO68: =+CG68 -> 1 | DP68: =+CG68 -> 1 | DQ68: =+CG68 -> 1 | DR68: =+CG68 -> 1 | DS68: =+CG68 -> 1 | DT68: =+CG68 -> 1 | DU68: =+CO68 -> 1 | DV68: =+CO68 -> 1 | DW68: =+CO68 -> 1 | DX68: =+CO68 -> 1 | DY68: =+CO68 -> 1 | DZ68: =+CO68 -> 1 | EA68: =+CO68 -> 1 | EB68: =+CO68 -> 1 | EC68: =+CW68 -> 1 | ED68: =+CW68 -> 1 | EE68: =+CW68 -> 1 | EF68: =+CW68 -> 1 | EG68: =+CW68 -> 1 | EH68: =+CW68 -> 1 | EI68: =+CW68 -> 1 | EJ68: =+CW68 -> 1 | EK68: =+DE68 -> 1 | EL68: =+DE68 -> 1 | EM68: =+DE68 -> 1 | EN68: =+DE68 -> 1 | EO68: =+DE68 -> 1 | EP68: =+DE68 -> 1 | EQ68: =+DE68 -> 1 | ER68: =+DE68 -> 1 | ES68: =+DM68 -> 1 | ET68: =+DM68 -> 1 | EU68: =+DM68 -> 1 | EV68: =+DM68 -> 1 | EW68: =SUM(I68:DD68)/4 -> 19
C69: Driver | D69: Adet | E69: 6 | AG69: =+E69 -> 6 | AH69: =+E69 -> 6 | AI69: =+E69 -> 6 | AJ69: =+E69 -> 6 | AK69: =+E69 -> 6 | AL69: =+E69 -> 6 | AM69: =+E69 -> 6 | AN69: =+E69 -> 6 | AO69: =+E69 -> 6 | AP69: =+E69 -> 6 | AQ69: =+E69 -> 6 | AR69: =+E69 -> 6 | AS69: =+E69 -> 6 | AT69: =+E69 -> 6 | AU69: =+E69 -> 6 | AV69: =+E69 -> 6 | AW69: =+E69 -> 6 | AX69: =+E69 -> 6 | AY69: =+E69 -> 6 | AZ69: =+E69 -> 6 | BA69: =+E69 -> 6 | BB69: =+E69 -> 6 | BC69: =+E69 -> 6 | BD69: =+E69 -> 6 | BE69: =+E69 -> 6 | BF69: =+E69 -> 6 | BG69: =+E69 -> 6 | BH69: =+E69 -> 6 | BI69: =+E69 -> 6 | BJ69: =+E69 -> 6 | BK69: =+E69 -> 6 | BL69: =+E69 -> 6 | BM69: =+E69 -> 6 | BN69: =+E69 -> 6 | BO69: =+E69 -> 6 | BP69: =+E69 -> 6 | BQ69: =+AK69 -> 6 | BR69: =+AK69 -> 6 | BS69: =+AK69 -> 6 | BT69: =+AK69 -> 6 | BU69: =+AK69 -> 6 | BV69: =+AK69 -> 6 | BW69: =+AK69 -> 6 | BX69: =+AK69 -> 6 | BY69: =+AS69 -> 6 | BZ69: =+AS69 -> 6 | CA69: =+AS69 -> 6 | CB69: =+AS69 -> 6 | CC69: =+AS69 -> 6 | CD69: =+AS69 -> 6 | CE69: =+AS69 -> 6 | CF69: =+AS69 -> 6 | CG69: =+BA69 -> 6 | CH69: =+BA69 -> 6 | CI69: =+BA69 -> 6 | CJ69: =+BA69 -> 6 | CK69: =+BA69 -> 6 | CL69: =+BA69 -> 6 | CM69: =+BA69 -> 6 | CN69: =+BA69 -> 6 | CO69: =+BI69 -> 6 | CP69: =+BI69 -> 6 | CQ69: =+BI69 -> 6 | CR69: =+BI69 -> 6 | CS69: =+BI69 -> 6 | CT69: =+BI69 -> 6 | CU69: =+BI69 -> 6 | CV69: =+BI69 -> 6 | CW69: =+BQ69 -> 6 | CX69: =+BQ69 -> 6 | CY69: =+BQ69 -> 6 | CZ69: =+BQ69 -> 6 | DA69: =+BQ69 -> 6 | DB69: =+BQ69 -> 6 | DC69: =+BQ69 -> 6 | DD69: =+BQ69 -> 6 | DE69: =+BY69 -> 6 | DF69: =+BY69 -> 6 | DG69: =+BY69 -> 6 | DH69: =+BY69 -> 6 | DI69: =+BY69 -> 6 | DJ69: =+BY69 -> 6 | DK69: =+BY69 -> 6 | DL69: =+BY69 -> 6 | DM69: =+CG69 -> 6 | DN69: =+CG69 -> 6 | DO69: =+CG69 -> 6 | DP69: =+CG69 -> 6 | DQ69: =+CG69 -> 6 | DR69: =+CG69 -> 6 | DS69: =+CG69 -> 6 | DT69: =+CG69 -> 6 | DU69: =+CO69 -> 6 | DV69: =+CO69 -> 6 | DW69: =+CO69 -> 6 | DX69: =+CO69 -> 6 | DY69: =+CO69 -> 6 | DZ69: =+CO69 -> 6 | EA69: =+CO69 -> 6 | EB69: =+CO69 -> 6 | EC69: =+CW69 -> 6 | ED69: =+CW69 -> 6 | EE69: =+CW69 -> 6 | EF69: =+CW69 -> 6 | EG69: =+CW69 -> 6 | EH69: =+CW69 -> 6 | EI69: =+CW69 -> 6 | EJ69: =+CW69 -> 6 | EK69: =+DE69 -> 6 | EL69: =+DE69 -> 6 | EM69: =+DE69 -> 6 | EN69: =+DE69 -> 6 | EO69: =+DE69 -> 6 | EP69: =+DE69 -> 6 | EQ69: =+DE69 -> 6 | ER69: =+DE69 -> 6 | ES69: =+DM69 -> 6 | ET69: =+DM69 -> 6 | EU69: =+DM69 -> 6 | EV69: =+DM69 -> 6 | EW69: =SUM(I69:DD69)/4 -> 114
C70: Unskilled Labor (Office Boy, cleaner, tea-man etc.) | D70: Adet | E70: 2 | AG70: =+E70 -> 2 | AH70: =+E70 -> 2 | AI70: =+E70 -> 2 | AJ70: =+E70 -> 2 | AK70: =+E70 -> 2 | AL70: =+E70 -> 2 | AM70: =+E70 -> 2 | AN70: =+E70 -> 2 | AO70: =+E70 -> 2 | AP70: =+E70 -> 2 | AQ70: =+E70 -> 2 | AR70: =+E70 -> 2 | AS70: =+E70 -> 2 | AT70: =+E70 -> 2 | AU70: =+E70 -> 2 | AV70: =+E70 -> 2 | AW70: =+E70 -> 2 | AX70: =+E70 -> 2 | AY70: =+E70 -> 2 | AZ70: =+E70 -> 2 | BA70: =+E70 -> 2 | BB70: =+E70 -> 2 | BC70: =+E70 -> 2 | BD70: =+E70 -> 2 | BE70: =+E70 -> 2 | BF70: =+E70 -> 2 | BG70: =+E70 -> 2 | BH70: =+E70 -> 2 | BI70: =+E70 -> 2 | BJ70: =+E70 -> 2 | BK70: =+E70 -> 2 | BL70: =+E70 -> 2 | BM70: =+E70 -> 2 | BN70: =+E70 -> 2 | BO70: =+E70 -> 2 | BP70: =+E70 -> 2 | BQ70: =+AK70 -> 2 | BR70: =+AK70 -> 2 | BS70: =+AK70 -> 2 | BT70: =+AK70 -> 2 | BU70: =+AK70 -> 2 | BV70: =+AK70 -> 2 | BW70: =+AK70 -> 2 | BX70: =+AK70 -> 2 | BY70: =+AS70 -> 2 | BZ70: =+AS70 -> 2 | CA70: =+AS70 -> 2 | CB70: =+AS70 -> 2 | CC70: =+AS70 -> 2 | CD70: =+AS70 -> 2 | CE70: =+AS70 -> 2 | CF70: =+AS70 -> 2 | CG70: =+BA70 -> 2 | CH70: =+BA70 -> 2 | CI70: =+BA70 -> 2 | CJ70: =+BA70 -> 2 | CK70: =+BA70 -> 2 | CL70: =+BA70 -> 2 | CM70: =+BA70 -> 2 | CN70: =+BA70 -> 2 | CO70: =+BI70 -> 2 | CP70: =+BI70 -> 2 | CQ70: =+BI70 -> 2 | CR70: =+BI70 -> 2 | CS70: =+BI70 -> 2 | CT70: =+BI70 -> 2 | CU70: =+BI70 -> 2 | CV70: =+BI70 -> 2 | CW70: =+BQ70 -> 2 | CX70: =+BQ70 -> 2 | CY70: =+BQ70 -> 2 | CZ70: =+BQ70 -> 2 | DA70: =+BQ70 -> 2 | DB70: =+BQ70 -> 2 | DC70: =+BQ70 -> 2 | DD70: =+BQ70 -> 2 | DE70: =+BY70 -> 2 | DF70: =+BY70 -> 2 | DG70: =+BY70 -> 2 | DH70: =+BY70 -> 2 | DI70: =+BY70 -> 2 | DJ70: =+BY70 -> 2 | DK70: =+BY70 -> 2 | DL70: =+BY70 -> 2 | DM70: =+CG70 -> 2 | DN70: =+CG70 -> 2 | DO70: =+CG70 -> 2 | DP70: =+CG70 -> 2 | DQ70: =+CG70 -> 2 | DR70: =+CG70 -> 2 | DS70: =+CG70 -> 2 | DT70: =+CG70 -> 2 | DU70: =+CO70 -> 2 | DV70: =+CO70 -> 2 | DW70: =+CO70 -> 2 | DX70: =+CO70 -> 2 | DY70: =+CO70 -> 2 | DZ70: =+CO70 -> 2 | EA70: =+CO70 -> 2 | EB70: =+CO70 -> 2 | EC70: =+CW70 -> 2 | ED70: =+CW70 -> 2 | EE70: =+CW70 -> 2 | EF70: =+CW70 -> 2 | EG70: =+CW70 -> 2 | EH70: =+CW70 -> 2 | EI70: =+CW70 -> 2 | EJ70: =+CW70 -> 2 | EK70: =+DE70 -> 2 | EL70: =+DE70 -> 2 | EM70: =+DE70 -> 2 | EN70: =+DE70 -> 2 | EO70: =+DE70 -> 2 | EP70: =+DE70 -> 2 | EQ70: =+DE70 -> 2 | ER70: =+DE70 -> 2 | ES70: =+DM70 -> 2 | ET70: =+DM70 -> 2 | EU70: =+DM70 -> 2 | EV70: =+DM70 -> 2 | EW70: =SUM(I70:DD70)/4 -> 38
C71: Workshop Staff | D71: Adet | E71: 4 | AG71: =+E71 -> 4 | AH71: =+E71 -> 4 | AI71: =+E71 -> 4 | AJ71: =+E71 -> 4 | AK71: =+E71 -> 4 | AL71: =+E71 -> 4 | AM71: =+E71 -> 4 | AN71: =+E71 -> 4 | AO71: =+E71 -> 4 | AP71: =+E71 -> 4 | AQ71: =+E71 -> 4 | AR71: =+E71 -> 4 | AS71: =+E71 -> 4 | AT71: =+E71 -> 4 | AU71: =+E71 -> 4 | AV71: =+E71 -> 4 | AW71: =+E71 -> 4 | AX71: =+E71 -> 4 | AY71: =+E71 -> 4 | AZ71: =+E71 -> 4 | BA71: =+E71 -> 4 | BB71: =+E71 -> 4 | BC71: =+E71 -> 4 | BD71: =+E71 -> 4 | BE71: =+E71 -> 4 | BF71: =+E71 -> 4 | BG71: =+E71 -> 4 | BH71: =+E71 -> 4 | BI71: =+E71 -> 4 | BJ71: =+E71 -> 4 | BK71: =+E71 -> 4 | BL71: =+E71 -> 4 | BM71: =+E71 -> 4 | BN71: =+E71 -> 4 | BO71: =+E71 -> 4 | BP71: =+E71 -> 4 | BQ71: =+AK71 -> 4 | BR71: =+AK71 -> 4 | BS71: =+AK71 -> 4 | BT71: =+AK71 -> 4 | BU71: =+AK71 -> 4 | BV71: =+AK71 -> 4 | BW71: =+AK71 -> 4 | BX71: =+AK71 -> 4 | BY71: =+AS71 -> 4 | BZ71: =+AS71 -> 4 | CA71: =+AS71 -> 4 | CB71: =+AS71 -> 4 | CC71: =+AS71 -> 4 | CD71: =+AS71 -> 4 | CE71: =+AS71 -> 4 | CF71: =+AS71 -> 4 | CG71: =+BA71 -> 4 | CH71: =+BA71 -> 4 | CI71: =+BA71 -> 4 | CJ71: =+BA71 -> 4 | CK71: =+BA71 -> 4 | CL71: =+BA71 -> 4 | CM71: =+BA71 -> 4 | CN71: =+BA71 -> 4 | CO71: =+BI71 -> 4 | CP71: =+BI71 -> 4 | CQ71: =+BI71 -> 4 | CR71: =+BI71 -> 4 | CS71: =+BI71 -> 4 | CT71: =+BI71 -> 4 | CU71: =+BI71 -> 4 | CV71: =+BI71 -> 4 | CW71: =+BQ71 -> 4 | CX71: =+BQ71 -> 4 | CY71: =+BQ71 -> 4 | CZ71: =+BQ71 -> 4 | DA71: =+BQ71 -> 4 | DB71: =+BQ71 -> 4 | DC71: =+BQ71 -> 4 | DD71: =+BQ71 -> 4 | DE71: =+BY71 -> 4 | DF71: =+BY71 -> 4 | DG71: =+BY71 -> 4 | DH71: =+BY71 -> 4 | DI71: =+BY71 -> 4 | DJ71: =+BY71 -> 4 | DK71: =+BY71 -> 4 | DL71: =+BY71 -> 4 | DM71: =+CG71 -> 4 | DN71: =+CG71 -> 4 | DO71: =+CG71 -> 4 | DP71: =+CG71 -> 4 | DQ71: =+CG71 -> 4 | DR71: =+CG71 -> 4 | DS71: =+CG71 -> 4 | DT71: =+CG71 -> 4 | DU71: =+CO71 -> 4 | DV71: =+CO71 -> 4 | DW71: =+CO71 -> 4 | DX71: =+CO71 -> 4 | DY71: =+CO71 -> 4 | DZ71: =+CO71 -> 4 | EA71: =+CO71 -> 4 | EB71: =+CO71 -> 4 | EC71: =+CW71 -> 4 | ED71: =+CW71 -> 4 | EE71: =+CW71 -> 4 | EF71: =+CW71 -> 4 | EG71: =+CW71 -> 4 | EH71: =+CW71 -> 4 | EI71: =+CW71 -> 4 | EJ71: =+CW71 -> 4 | EK71: =+DE71 -> 4 | EL71: =+DE71 -> 4 | EM71: =+DE71 -> 4 | EN71: =+DE71 -> 4 | EO71: =+DE71 -> 4 | EP71: =+DE71 -> 4 | EQ71: =+DE71 -> 4 | ER71: =+DE71 -> 4 | ES71: =+DM71 -> 4 | ET71: =+DM71 -> 4 | EU71: =+DM71 -> 4 | EV71: =+DM71 -> 4 | EW71: =SUM(I71:DD71)/4 -> 76
... C73: Vardiya Amiri | D73: Adet | E73: 2 | AG73: =+E73 -> 2 | AH73: =+E73 -> 2 | AI73: =+E73 -> 2 | AJ73: =+E73 -> 2 | AK73: =+E73 -> 2 | AL73: =+E73 -> 2 | AM73: =+E73 -> 2 | AN73: =+E73 -> 2 | AO73: =+E73 -> 2 | AP73: =+E73 -> 2 | AQ73: =+E73 -> 2 | AR73: =+E73 -> 2 | AS73: =+E73 -> 2 | AT73: =+E73 -> 2 | AU73: =+E73 -> 2 | AV73: =+E73 -> 2 | AW73: =+E73 -> 2 | AX73: =+E73 -> 2 | AY73: =+E73 -> 2 | AZ73: =+E73 -> 2 | BA73: =+E73 -> 2 | BB73: =+E73 -> 2 | BC73: =+E73 -> 2 | BD73: =+E73 -> 2 | BE73: =+E73 -> 2 | BF73: =+E73 -> 2 | BG73: =+E73 -> 2 | BH73: =+E73 -> 2 | BI73: =+E73 -> 2 | BJ73: =+E73 -> 2 | BK73: =+E73 -> 2 | BL73: =+E73 -> 2 | BM73: =+E73 -> 2 | BN73: =+E73 -> 2 | BO73: =+E73 -> 2 | BP73: =+E73 -> 2 | BQ73: =+AK73 -> 2 | BR73: =+AK73 -> 2 | BS73: =+AK73 -> 2 | BT73: =+AK73 -> 2 | BU73: =+AK73 -> 2 | BV73: =+AK73 -> 2 | BW73: =+AK73 -> 2 | BX73: =+AK73 -> 2 | BY73: =+AS73 -> 2 | BZ73: =+AS73 -> 2 | CA73: =+AS73 -> 2 | CB73: =+AS73 -> 2 | CC73: =+AS73 -> 2 | CD73: =+AS73 -> 2 | CE73: =+AS73 -> 2 | CF73: =+AS73 -> 2 | CG73: =+BA73 -> 2 | CH73: =+BA73 -> 2 | CI73: =+BA73 -> 2 | CJ73: =+BA73 -> 2 | CK73: =+BA73 -> 2 | CL73: =+BA73 -> 2 | CM73: =+BA73 -> 2 | CN73: =+BA73 -> 2 | CO73: =+BI73 -> 2 | CP73: =+BI73 -> 2 | CQ73: =+BI73 -> 2 | CR73: =+BI73 -> 2 | CS73: =+BI73 -> 2 | CT73: =+BI73 -> 2 | CU73: =+BI73 -> 2 | CV73: =+BI73 -> 2 | CW73: =+BQ73 -> 2 | CX73: =+BQ73 -> 2 | CY73: =+BQ73 -> 2 | CZ73: =+BQ73 -> 2 | DA73: =+BQ73 -> 2 | DB73: =+BQ73 -> 2 | DC73: =+BQ73 -> 2 | DD73: =+BQ73 -> 2 | DE73: =+BY73 -> 2 | DF73: =+BY73 -> 2 | DG73: =+BY73 -> 2 | DH73: =+BY73 -> 2 | DI73: =+BY73 -> 2 | DJ73: =+BY73 -> 2 | DK73: =+BY73 -> 2 | DL73: =+BY73 -> 2 | DM73: =+CG73 -> 2 | DN73: =+CG73 -> 2 | DO73: =+CG73 -> 2 | DP73: =+CG73 -> 2 | DQ73: =+CG73 -> 2 | DR73: =+CG73 -> 2 | DS73: =+CG73 -> 2 | DT73: =+CG73 -> 2 | DU73: =+CO73 -> 2 | DV73: =+CO73 -> 2 | DW73: =+CO73 -> 2 | DX73: =+CO73 -> 2 | DY73: =+CO73 -> 2 | DZ73: =+CO73 -> 2 | EA73: =+CO73 -> 2 | EB73: =+CO73 -> 2 | EC73: =+CW73 -> 2 | ED73: =+CW73 -> 2 | EE73: =+CW73 -> 2 | EF73: =+CW73 -> 2 | EG73: =+CW73 -> 2 | EH73: =+CW73 -> 2 | EI73: =+CW73 -> 2 | EJ73: =+CW73 -> 2 | EK73: =+DE73 -> 2 | EL73: =+DE73 -> 2 | EM73: =+DE73 -> 2 | EN73: =+DE73 -> 2 | EO73: =+DE73 -> 2 | EP73: =+DE73 -> 2 | EQ73: =+DE73 -> 2 | ER73: =+DE73 -> 2 | ES73: =+DM73 -> 2 | ET73: =+DM73 -> 2 | EU73: =+DM73 -> 2 | EV73: =+DM73 -> 2 | EW73: =SUM(I73:DD73)/4 -> 38
C79: TOTAL PERSONNEL:
EW81: =SUM(EW6:EW79)*0.5 -> 2509.5

Sheet Machinery Deployment Chart
C1: WORK SCHEDULE VERSUS RESOURCE CHART
C2: PROJECT NAME: | D2: =+schedule_ARAS!D2 -> FİLYOS LİMANI TAHKİMAT İŞİ
C3: PROJECT DURATION: | D3: =+schedule_ARAS!D3 -> 36 | E3: Months
B5: S.NO. | C5: WORK DESCRIPTION | D5: UNIT | E5: QTY. | F5: Month-1 | J5: Month-2 | N5: Month-3 | R5: Month-4 | V5: Month-5 | Z5: Month-6 | AD5: Month-7 | AH5: Month-8 | AL5: Month-9 | AP5: Month-10 | AT5: Month-11 | AX5: Month-12 | BB5: Month-13 | BF5: Month-14 | BJ5: Month-15 | BN5: Month-16 | BR5: Month-17 | BV5: Month-18 | BZ5: Month-19 | CD5: Month-20 | CH5: Month-21 | CL5: Month-22 | CP5: Month-23 | CT5: Month-24 | CX5: Month-25 | DB5: Month-26 | DF5: Month-27 | DJ5: Month-28 | DN5: Month-29 | DR5: Month-30 | DV5: Month-31 | DZ5: Month-32 | ED5: Month-33 | EH5: Month-34 | EL5: Month-35 | EP5: Month-36 | ET5: Total Deployment | EU5: Total Working Duration (Hr.) | EV5: Total Stand-by Duration (Hr.)
C6: DIRECT MACHINERY
C8: =+schedule_ARAS!C12 -> Kurtuluş Kara | D8: Ad | E8: =+schedule_ARAS!E12 -> 1 | N8: =+M8 -> 0 | O8: =+M8 -> 0 | P8: =+M8 -> 0 | Q8: =+M8 -> 0 | R8: =+Q8 -> 0 | S8: =+Q8 -> 0 | T8: =+Q8 -> 0 | U8: =+Q8 -> 0 | V8: =+U8 -> 0 | W8: =+U8 -> 0 | X8: =+U8 -> 0 | Y8: =+U8 -> 0 | Z8: =+Y8 -> 0 | AA8: =+Y8 -> 0 | AB8: =+Y8 -> 0 | AC8: =+Y8 -> 0 | AD8: =+E8 -> 1 | AE8: =+E8 -> 1 | AF8: =+E8 -> 1 | AG8: =+E8 -> 1 | AH8: =+AG8 -> 1 | AI8: =+AG8 -> 1 | AJ8: =+AG8 -> 1 | AK8: =+AG8 -> 1 | AL8: =+AK8 -> 1 | AM8: =+AK8 -> 1 | AN8: =+AK8 -> 1 | AO8: =+AK8 -> 1 | AP8: =+AO8 -> 1 | AQ8: =+AO8 -> 1 | AR8: =+AO8 -> 1 | AS8: =+AO8 -> 1 | AT8: =+AS8 -> 1 | AU8: =+AS8 -> 1 | AV8: =+AS8 -> 1 | AW8: =+AS8 -> 1 | AX8: =+AW8 -> 1 | AY8: =+AW8 -> 1 | AZ8: =+AW8 -> 1 | BA8: =+AW8 -> 1 | BB8: =+BA8 -> 1 | BC8: =+BA8 -> 1 | BD8: =+BA8 -> 1 | BE8: =+BA8 -> 1 | BF8: =+BE8 -> 1 | BG8: =+BE8 -> 1 | BH8: =+BE8 -> 1 | BI8: =+BE8 -> 1 | BJ8: =+BI8 -> 1 | BK8: =+BI8 -> 1 | BL8: =+BI8 -> 1 | BM8: =+BI8 -> 1 | BN8: =+BM8 -> 1 | BO8: =+BM8 -> 1 | BP8: =+BM8 -> 1 | BQ8: =+BM8 -> 1 | BR8: =+BQ8 -> 1 | BS8: =+BQ8 -> 1 | BT8: =+BQ8 -> 1 | BU8: =+BQ8 -> 1 | BV8: =+BU8 -> 1 | BW8: =+BU8 -> 1 | BX8: =+BU8 -> 1 | BY8: =+BU8 -> 1 | BZ8: =+BY8 -> 1 | CA8: =+BY8 -> 1 | CB8: =+BY8 -> 1 | CC8: =+BY8 -> 1 | CD8: =+CC8 -> 1 | CE8: =+CC8 -> 1 | CF8: =+CC8 -> 1 | CG8: =+CC8 -> 1 | CH8: =+CG8 -> 1 | CI8: =+CG8 -> 1 | CJ8: =+CG8 -> 1 | CK8: =+CG8 -> 1 | CL8: =+CK8 -> 1 | CM8: =+CK8 -> 1 | CN8: =+CK8 -> 1 | CO8: =+CK8 -> 1 | CP8: =+CO8 -> 1 | CQ8: =+CO8 -> 1 | CR8: =+CO8 -> 1 | CS8: =+CO8 -> 1 | CT8: =+CS8 -> 1 | CU8: =+CS8 -> 1 | CV8: =+CS8 -> 1 | CW8: =+CS8 -> 1 | CX8: =+CW8 -> 1 | CY8: =+CW8 -> 1 | CZ8: =+CW8 -> 1 | DA8: =+CW8 -> 1 | DB8: =+DA8 -> 1 | DC8: =+DA8 -> 1 | DD8: =+DA8 -> 1 | DE8: =+DA8 -> 1 | DF8: =+DE8 -> 1 | DG8: =+DE8 -> 1 | DH8: =+DE8 -> 1 | DI8: =+DE8 -> 1 | DJ8: =+DI8 -> 1 | DK8: =+DI8 -> 1 | DL8: =+DI8 -> 1 | DM8: =+DI8 -> 1 | DN8: =+DM8 -> 1 | DO8: =+DM8 -> 1 | DP8: =+DM8 -> 1 | DQ8: =+DM8 -> 1 | DR8: =+DQ8 -> 1 | DS8: =+DQ8 -> 1 | DT8: =+DQ8 -> 1 | DU8: =+DQ8 -> 1 | DV8: =+DU8 -> 1 | DW8: =+DU8 -> 1 | DX8: =+DU8 -> 1 | DY8: =+DU8 -> 1 | DZ8: =+DY8 -> 1 | EA8: =+DY8 -> 1 | EB8: =+DY8 -> 1 | EC8: =+DY8 -> 1 | ED8: =+EC8 -> 1 | EE8: =+EC8 -> 1 | EF8: =+EC8 -> 1 | EG8: =+EC8 -> 1 | EH8: =+EG8 -> 1 | EI8: =+EG8 -> 1 | EJ8: =+EG8 -> 1 | EK8: =+EG8 -> 1 | EL8: =+EK8 -> 1 | EM8: =+EK8 -> 1 | EN8: =+EK8 -> 1 | EO8: =+EK8 -> 1 | EP8: =+EO8 -> 1 | EQ8: =+EO8 -> 1 | ER8: =+EO8 -> 1 | ES8: =+EO8 -> 1 | ET8: =+schedule_ARAS!EW12 -> 30 | EU8: =+schedule_ARAS!EZ12 -> 13440 | EV8: =+schedule_ARAS!FA12 -> 7200
C9: =+schedule_ARAS!C13 -> Koparan | D9: Ad | E9: =+schedule_ARAS!E13 -> 1 | N9: =+M9 -> 0 | O9: =+M9 -> 0 | P9: =+M9 -> 0 | Q9: =+M9 -> 0 | R9: =+Q9 -> 0 | S9: =+Q9 -> 0 | T9: =+Q9 -> 0 | U9: =+Q9 -> 0 | V9: =+U9 -> 0 | W9: =+U9 -> 0 | X9: =+U9 -> 0 | Y9: =+U9 -> 0 | Z9: =+Y9 -> 0 | AA9: =+Y9 -> 0 | AB9: =+Y9 -> 0 | AC9: =+Y9 -> 0 | AD9: =+E9 -> 1 | AE9: =+E9 -> 1 | AF9: =+E9 -> 1 | AG9: =+E9 -> 1 | AH9: =+AG9 -> 1 | AI9: =+AG9 -> 1 | AJ9: =+AG9 -> 1 | AK9: =+AG9 -> 1 | AL9: =+AK9 -> 1 | AM9: =+AK9 -> 1 | AN9: =+AK9 -> 1 | AO9: =+AK9 -> 1 | AP9: =+AO9 -> 1 | AQ9: =+AO9 -> 1 | AR9: =+AO9 -> 1 | AS9: =+AO9 -> 1 | AT9: =+AS9 -> 1 | AU9: =+AS9 -> 1 | AV9: =+AS9 -> 1 | AW9: =+AS9 -> 1 | AX9: =+AW9 -> 1 | AY9: =+AW9 -> 1 | AZ9: =+AW9 -> 1 | BA9: =+AW9 -> 1 | BB9: =+BA9 -> 1 | BC9: =+BA9 -> 1 | BD9: =+BA9 -> 1 | BE9: =+BA9 -> 1 | BF9: =+BE9 -> 1 | BG9: =+BE9 -> 1 | BH9: =+BE9 -> 1 | BI9: =+BE9 -> 1 | BJ9: =+BI9 -> 1 | BK9: =+BI9 -> 1 | BL9: =+BI9 -> 1 | BM9: =+BI9 -> 1 | BN9: =+BM9 -> 1 | BO9: =+BM9 -> 1 | BP9: =+BM9 -> 1 | BQ9: =+BM9 -> 1 | BR9: =+BQ9 -> 1 | BS9: =+BQ9 -> 1 | BT9: =+BQ9 -> 1 | BU9: =+BQ9 -> 1 | BV9: =+BU9 -> 1 | BW9: =+BU9 -> 1 | BX9: =+BU9 -> 1 | BY9: =+BU9 -> 1 | BZ9: =+BY9 -> 1 | CA9: =+BY9 -> 1 | CB9: =+BY9 -> 1 | CC9: =+BY9 -> 1 | CD9: =+CC9 -> 1 | CE9: =+CC9 -> 1 | CF9: =+CC9 -> 1 | CG9: =+CC9 -> 1 | CH9: =+CG9 -> 1 | CI9: =+CG9 -> 1 | CJ9: =+CG9 -> 1 | CK9: =+CG9 -> 1 | CL9: =+CK9 -> 1 | CM9: =+CK9 -> 1 | CN9: =+CK9 -> 1 | CO9: =+CK9 -> 1 | CP9: =+CO9 -> 1 | CQ9: =+CO9 -> 1 | CR9: =+CO9 -> 1 | CS9: =+CO9 -> 1 | CT9: =+CS9 -> 1 | CU9: =+CS9 -> 1 | CV9: =+CS9 -> 1 | CW9: =+CS9 -> 1 | CX9: =+CW9 -> 1 | CY9: =+CW9 -> 1 | CZ9: =+CW9 -> 1 | DA9: =+CW9 -> 1 | DB9: =+DA9 -> 1 | DC9: =+DA9 -> 1 | DD9: =+DA9 -> 1 | DE9: =+DA9 -> 1 | DF9: =+DE9 -> 1 | DG9: =+DE9 -> 1 | DH9: =+DE9 -> 1 | DI9: =+DE9 -> 1 | DJ9: =+DI9 -> 1 | DK9: =+DI9 -> 1 | DL9: =+DI9 -> 1 | DM9: =+DI9 -> 1 | DN9: =+DM9 -> 1 | DO9: =+DM9 -> 1 | DP9: =+DM9 -> 1 | DQ9: =+DM9 -> 1 | DR9: =+DQ9 -> 1 | DS9: =+DQ9 -> 1 | DT9: =+DQ9 -> 1 | DU9: =+DQ9 -> 1 | DV9: =+DU9 -> 1 | DW9: =+DU9 -> 1 | DX9: =+DU9 -> 1 | DY9: =+DU9 -> 1 | DZ9: =+DY9 -> 1 | EA9: =+DY9 -> 1 | EB9: =+DY9 -> 1 | EC9: =+DY9 -> 1 | ED9: =+EC9 -> 1 | EE9: =+EC9 -> 1 | EF9: =+EC9 -> 1 | EG9: =+EC9 -> 1 | EH9: =+EG9 -> 1 | EI9: =+EG9 -> 1 | EJ9: =+EG9 -> 1 | EK9: =+EG9 -> 1 | EL9: =+EK9 -> 1 | EM9: =+EK9 -> 1 | EN9: =+EK9 -> 1 | EO9: =+EK9 -> 1 | EP9: =+EO9 -> 1 | EQ9: =+EO9 -> 1 | ER9: =+EO9 -> 1 | ES9: =+EO9 -> 1 | ET9: =+schedule_ARAS!EW13 -> 30 | EU9: =+schedule_ARAS!EZ13 -> 13440 | EV9: =+schedule_ARAS!FA13 -> 7200
C10: =+schedule_ARAS!C14 -> Necem D-18 | D10: Ad | E10: =+schedule_ARAS!E14 -> 1 | N10: =+M10 -> 0 | O10: =+M10 -> 0 | P10: =+M10 -> 0 | Q10: =+M10 -> 0 | R10: =+Q10 -> 0 | S10: =+Q10 -> 0 | T10: =+Q10 -> 0 | U10: =+Q10 -> 0 | V10: =+U10 -> 0 | W10: =+U10 -> 0 | X10: =+U10 -> 0 | Y10: =+U10 -> 0 | Z10: =+Y10 -> 0 | AA10: =+Y10 -> 0 | AB10: =+Y10 -> 0 | AC10: =+Y10 -> 0 | AD10: =+E10 -> 1 | AE10: =+E10 -> 1 | AF10: =+E10 -> 1 | AG10: =+E10 -> 1 | AH10: =+AG10 -> 1 | AI10: =+AG10 -> 1 | AJ10: =+AG10 -> 1 | AK10: =+AG10 -> 1 | AL10: =+AK10 -> 1 | AM10: =+AK10 -> 1 | AN10: =+AK10 -> 1 | AO10: =+AK10 -> 1 | AP10: =+AO10 -> 1 | AQ10: =+AO10 -> 1 | AR10: =+AO10 -> 1 | AS10: =+AO10 -> 1 | AT10: =+AS10 -> 1 | AU10: =+AS10 -> 1 | AV10: =+AS10 -> 1 | AW10: =+AS10 -> 1 | AX10: =+AW10 -> 1 | AY10: =+AW10 -> 1 | AZ10: =+AW10 -> 1 | BA10: =+AW10 -> 1 | BB10: =+BA10 -> 1 | BC10: =+BA10 -> 1 | BD10: =+BA10 -> 1 | BE10: =+BA10 -> 1 | BF10: =+BE10 -> 1 | BG10: =+BE10 -> 1 | BH10: =+BE10 -> 1 | BI10: =+BE10 -> 1 | BJ10: =+BI10 -> 1 | BK10: =+BI10 -> 1 | BL10: =+BI10 -> 1 | BM10: =+BI10 -> 1 | BN10: =+BM10 -> 1 | BO10: =+BM10 -> 1 | BP10: =+BM10 -> 1 | BQ10: =+BM10 -> 1 | BR10: =+BQ10 -> 1 | BS10: =+BQ10 -> 1 | BT10: =+BQ10 -> 1 | BU10: =+BQ10 -> 1 | BV10: =+BU10 -> 1 | BW10: =+BU10 -> 1 | BX10: =+BU10 -> 1 | BY10: =+BU10 -> 1 | BZ10: =+BY10 -> 1 | CA10: =+BY10 -> 1 | CB10: =+BY10 -> 1 | CC10: =+BY10 -> 1 | CD10: =+CC10 -> 1 | CE10: =+CC10 -> 1 | CF10: =+CC10 -> 1 | CG10: =+CC10 -> 1 | CH10: =+CG10 -> 1 | CI10: =+CG10 -> 1 | CJ10: =+CG10 -> 1 | CK10: =+CG10 -> 1 | CL10: =+CK10 -> 1 | CM10: =+CK10 -> 1 | CN10: =+CK10 -> 1 | CO10: =+CK10 -> 1 | CP10: =+CO10 -> 1 | CQ10: =+CO10 -> 1 | CR10: =+CO10 -> 1 | CS10: =+CO10 -> 1 | CT10: =+CS10 -> 1 | CU10: =+CS10 -> 1 | CV10: =+CS10 -> 1 | CW10: =+CS10 -> 1 | CX10: =+CW10 -> 1 | CY10: =+CW10 -> 1 | CZ10: =+CW10 -> 1 | DA10: =+CW10 -> 1 | DB10: =+DA10 -> 1 | DC10: =+DA10 -> 1 | DD10: =+DA10 -> 1 | DE10: =+DA10 -> 1 | DF10: =+DE10 -> 1 | DG10: =+DE10 -> 1 | DH10: =+DE10 -> 1 | DI10: =+DE10 -> 1 | DJ10: =+DI10 -> 1 | DK10: =+DI10 -> 1 | DL10: =+DI10 -> 1 | DM10: =+DI10 -> 1 | DN10: =+DM10 -> 1 | DO10: =+DM10 -> 1 | DP10: =+DM10 -> 1 | DQ10: =+DM10 -> 1 | DR10: =+DQ10 -> 1 | DS10: =+DQ10 -> 1 | DT10: =+DQ10 -> 1 | DU10: =+DQ10 -> 1 | DV10: =+DU10 -> 1 | DW10: =+DU10 -> 1 | DX10: =+DU10 -> 1 | DY10: =+DU10 -> 1 | DZ10: =+DY10 -> 1 | EA10: =+DY10 -> 1 | EB10: =+DY10 -> 1 | EC10: =+DY10 -> 1 | ED10: =+EC10 -> 1 | EE10: =+EC10 -> 1 | EF10: =+EC10 -> 1 | EG10: =+EC10 -> 1 | EH10: =+EG10 -> 1 | EI10: =+EG10 -> 1 | EJ10: =+EG10 -> 1 | EK10: =+EG10 -> 1 | EL10: =+EK10 -> 1 | EM10: =+EK10 -> 1 | EN10: =+EK10 -> 1 | EO10: =+EK10 -> 1 | EP10: =+EO10 -> 1 | EQ10: =+EO10 -> 1 | ER10: =+EO10 -> 1 | ES10: =+EO10 -> 1 | ET10: =+schedule_ARAS!EW14 -> 30 | EU10: =+schedule_ARAS!EZ14 -> 13440 | EV10: =+schedule_ARAS!FA14 -> 7200
C11: =+schedule_ARAS!C15 -> Alpaslan - II | D11: Ad | E11: =+schedule_ARAS!E15 -> 1 | N11: =+M11 -> 0 | O11: =+M11 -> 0 | P11: =+M11 -> 0 | Q11: =+M11 -> 0 | R11: =+Q11 -> 0 | S11: =+Q11 -> 0 | T11: =+Q11 -> 0 | U11: =+Q11 -> 0 | V11: =+U11 -> 0 | W11: =+U11 -> 0 | X11: =+U11 -> 0 | Y11: =+U11 -> 0 | Z11: =+Y11 -> 0 | AA11: =+Y11 -> 0 | AB11: =+Y11 -> 0 | AC11: =+Y11 -> 0 | AD11: =+E11 -> 1 | AE11: =+E11 -> 1 | AF11: =+E11 -> 1 | AG11: =+E11 -> 1 | AH11: =+AG11 -> 1 | AI11: =+AG11 -> 1 | AJ11: =+AG11 -> 1 | AK11: =+AG11 -> 1 | AL11: =+AK11 -> 1 | AM11: =+AK11 -> 1 | AN11: =+AK11 -> 1 | AO11: =+AK11 -> 1 | AP11: =+AO11 -> 1 | AQ11: =+AO11 -> 1 | AR11: =+AO11 -> 1 | AS11: =+AO11 -> 1 | AT11: =+AS11 -> 1 | AU11: =+AS11 -> 1 | AV11: =+AS11 -> 1 | AW11: =+AS11 -> 1 | AX11: =+AW11 -> 1 | AY11: =+AW11 -> 1 | AZ11: =+AW11 -> 1 | BA11: =+AW11 -> 1 | BB11: =+BA11 -> 1 | BC11: =+BA11 -> 1 | BD11: =+BA11 -> 1 | BE11: =+BA11 -> 1 | BF11: =+BE11 -> 1 | BG11: =+BE11 -> 1 | BH11: =+BE11 -> 1 | BI11: =+BE11 -> 1 | BJ11: =+BI11 -> 1 | BK11: =+BI11 -> 1 | BL11: =+BI11 -> 1 | BM11: =+BI11 -> 1 | BN11: =+BM11 -> 1 | BO11: =+BM11 -> 1 | BP11: =+BM11 -> 1 | BQ11: =+BM11 -> 1 | BR11: =+BQ11 -> 1 | BS11: =+BQ11 -> 1 | BT11: =+BQ11 -> 1 | BU11: =+BQ11 -> 1 | BV11: =+BU11 -> 1 | BW11: =+BU11 -> 1 | BX11: =+BU11 -> 1 | BY11: =+BU11 -> 1 | BZ11: =+BY11 -> 1 | CA11: =+BY11 -> 1 | CB11: =+BY11 -> 1 | CC11: =+BY11 -> 1 | CD11: =+CC11 -> 1 | CE11: =+CC11 -> 1 | CF11: =+CC11 -> 1 | CG11: =+CC11 -> 1 | CH11: =+CG11 -> 1 | CI11: =+CG11 -> 1 | CJ11: =+CG11 -> 1 | CK11: =+CG11 -> 1 | CL11: =+CK11 -> 1 | CM11: =+CK11 -> 1 | CN11: =+CK11 -> 1 | CO11: =+CK11 -> 1 | CP11: =+CO11 -> 1 | CQ11: =+CO11 -> 1 | CR11: =+CO11 -> 1 | CS11: =+CO11 -> 1 | CT11: =+CS11 -> 1 | CU11: =+CS11 -> 1 | CV11: =+CS11 -> 1 | CW11: =+CS11 -> 1 | CX11: =+CW11 -> 1 | CY11: =+CW11 -> 1 | CZ11: =+CW11 -> 1 | DA11: =+CW11 -> 1 | DB11: =+DA11 -> 1 | DC11: =+DA11 -> 1 | DD11: =+DA11 -> 1 | DE11: =+DA11 -> 1 | DF11: =+DE11 -> 1 | DG11: =+DE11 -> 1 | DH11: =+DE11 -> 1 | DI11: =+DE11 -> 1 | DJ11: =+DI11 -> 1 | DK11: =+DI11 -> 1 | DL11: =+DI11 -> 1 | DM11: =+DI11 -> 1 | DN11: =+DM11 -> 1 | DO11: =+DM11 -> 1 | DP11: =+DM11 -> 1 | DQ11: =+DM11 -> 1 | DR11: =+DQ11 -> 1 | DS11: =+DQ11 -> 1 | DT11: =+DQ11 -> 1 | DU11: =+DQ11 -> 1 | DV11: =+DU11 -> 1 | DW11: =+DU11 -> 1 | DX11: =+DU11 -> 1 | DY11: =+DU11 -> 1 | DZ11: =+DY11 -> 1 | EA11: =+DY11 -> 1 | EB11: =+DY11 -> 1 | EC11: =+DY11 -> 1 | ED11: =+EC11 -> 1 | EE11: =+EC11 -> 1 | EF11: =+EC11 -> 1 | EG11: =+EC11 -> 1 | EH11: =+EG11 -> 1 | EI11: =+EG11 -> 1 | EJ11: =+EG11 -> 1 | EK11: =+EG11 -> 1 | EL11: =+EK11 -> 1 | EM11: =+EK11 -> 1 | EN11: =+EK11 -> 1 | EO11: =+EK11 -> 1 | EP11: =+EO11 -> 1 | EQ11: =+EO11 -> 1 | ER11: =+EO11 -> 1 | ES11: =+EO11 -> 1 | ET11: =+schedule_ARAS!EW15 -> 30 | EU11: =+schedule_ARAS!EZ15 -> 13440 | EV11: =+schedule_ARAS!FA15 -> 7200
C12: =+schedule_ARAS!C16 -> Koca Seyit | D12: Ad | E12: =+schedule_ARAS!E16 -> 1 | N12: =+M12 -> 0 | O12: =+M12 -> 0 | P12: =+M12 -> 0 | Q12: =+M12 -> 0 | R12: =+Q12 -> 0 | S12: =+Q12 -> 0 | T12: =+Q12 -> 0 | U12: =+Q12 -> 0 | V12: =+U12 -> 0 | W12: =+U12 -> 0 | X12: =+U12 -> 0 | Y12: =+U12 -> 0 | Z12: =+Y12 -> 0 | AA12: =+Y12 -> 0 | AB12: =+Y12 -> 0 | AC12: =+Y12 -> 0 | AD12: =+E12 -> 1 | AE12: =+E12 -> 1 | AF12: =+E12 -> 1 | AG12: =+E12 -> 1 | AH12: =+AG12 -> 1 | AI12: =+AG12 -> 1 | AJ12: =+AG12 -> 1 | AK12: =+AG12 -> 1 | AL12: =+AK12 -> 1 | AM12: =+AK12 -> 1 | AN12: =+AK12 -> 1 | AO12: =+AK12 -> 1 | AP12: =+AO12 -> 1 | AQ12: =+AO12 -> 1 | AR12: =+AO12 -> 1 | AS12: =+AO12 -> 1 | AT12: =+AS12 -> 1 | AU12: =+AS12 -> 1 | AV12: =+AS12 -> 1 | AW12: =+AS12 -> 1 | AX12: =+AW12 -> 1 | AY12: =+AW12 -> 1 | AZ12: =+AW12 -> 1 | BA12: =+AW12 -> 1 | BB12: =+BA12 -> 1 | BC12: =+BA12 -> 1 | BD12: =+BA12 -> 1 | BE12: =+BA12 -> 1 | BF12: =+BE12 -> 1 | BG12: =+BE12 -> 1 | BH12: =+BE12 -> 1 | BI12: =+BE12 -> 1 | BJ12: =+BI12 -> 1 | BK12: =+BI12 -> 1 | BL12: =+BI12 -> 1 | BM12: =+BI12 -> 1 | BN12: =+BM12 -> 1 | BO12: =+BM12 -> 1 | BP12: =+BM12 -> 1 | BQ12: =+BM12 -> 1 | BR12: =+BQ12 -> 1 | BS12: =+BQ12 -> 1 | BT12: =+BQ12 -> 1 | BU12: =+BQ12 -> 1 | BV12: =+BU12 -> 1 | BW12: =+BU12 -> 1 | BX12: =+BU12 -> 1 | BY12: =+BU12 -> 1 | BZ12: =+BY12 -> 1 | CA12: =+BY12 -> 1 | CB12: =+BY12 -> 1 | CC12: =+BY12 -> 1 | CD12: =+CC12 -> 1 | CE12: =+CC12 -> 1 | CF12: =+CC12 -> 1 | CG12: =+CC12 -> 1 | CH12: =+CG12 -> 1 | CI12: =+CG12 -> 1 | CJ12: =+CG12 -> 1 | CK12: =+CG12 -> 1 | CL12: =+CK12 -> 1 | CM12: =+CK12 -> 1 | CN12: =+CK12 -> 1 | CO12: =+CK12 -> 1 | CP12: =+CO12 -> 1 | CQ12: =+CO12 -> 1 | CR12: =+CO12 -> 1 | CS12: =+CO12 -> 1 | CT12: =+CS12 -> 1 | CU12: =+CS12 -> 1 | CV12: =+CS12 -> 1 | CW12: =+CS12 -> 1 | CX12: =+CW12 -> 1 | CY12: =+CW12 -> 1 | CZ12: =+CW12 -> 1 | DA12: =+CW12 -> 1 | DB12: =+DA12 -> 1 | DC12: =+DA12 -> 1 | DD12: =+DA12 -> 1 | DE12: =+DA12 -> 1 | DF12: =+DE12 -> 1 | DG12: =+DE12 -> 1 | DH12: =+DE12 -> 1 | DI12: =+DE12 -> 1 | DJ12: =+DI12 -> 1 | DK12: =+DI12 -> 1 | DL12: =+DI12 -> 1 | DM12: =+DI12 -> 1 | DN12: =+DM12 -> 1 | DO12: =+DM12 -> 1 | DP12: =+DM12 -> 1 | DQ12: =+DM12 -> 1 | DR12: =+DQ12 -> 1 | DS12: =+DQ12 -> 1 | DT12: =+DQ12 -> 1 | DU12: =+DQ12 -> 1 | DV12: =+DU12 -> 1 | DW12: =+DU12 -> 1 | DX12: =+DU12 -> 1 | DY12: =+DU12 -> 1 | DZ12: =+DY12 -> 1 | EA12: =+DY12 -> 1 | EB12: =+DY12 -> 1 | EC12: =+DY12 -> 1 | ED12: =+EC12 -> 1 | EE12: =+EC12 -> 1 | EF12: =+EC12 -> 1 | EG12: =+EC12 -> 1 | EH12: =+EG12 -> 1 | EI12: =+EG12 -> 1 | EJ12: =+EG12 -> 1 | EK12: =+EG12 -> 1 | EL12: =+EK12 -> 1 | EM12: =+EK12 -> 1 | EN12: =+EK12 -> 1 | EO12: =+EK12 -> 1 | EP12: =+EO12 -> 1 | EQ12: =+EO12 -> 1 | ER12: =+EO12 -> 1 | ES12: =+EO12 -> 1 | ET12: =+schedule_ARAS!EW16 -> 30 | EU12: =+schedule_ARAS!EZ16 -> 13440 | EV12: =+schedule_ARAS!FA16 -> 7200
C13: =+schedule_ARAS!C17 -> Floating Crane 3 | D13: Ad | E13: =+schedule_ARAS!E17 -> 1 | N13: =+M13 -> 0 | O13: =+M13 -> 0 | P13: =+M13 -> 0 | Q13: =+M13 -> 0 | R13: =+Q13 -> 0 | S13: =+Q13 -> 0 | T13: =+Q13 -> 0 | U13: =+Q13 -> 0 | V13: =+U13 -> 0 | W13: =+U13 -> 0 | X13: =+U13 -> 0 | Y13: =+U13 -> 0 | Z13: =+Y13 -> 0 | AA13: =+Y13 -> 0 | AB13: =+Y13 -> 0 | AC13: =+Y13 -> 0 | AD13: =+E13 -> 1 | AE13: =+E13 -> 1 | AF13: =+E13 -> 1 | AG13: =+E13 -> 1 | AH13: =+AG13 -> 1 | AI13: =+AG13 -> 1 | AJ13: =+AG13 -> 1 | AK13: =+AG13 -> 1 | AL13: =+AK13 -> 1 | AM13: =+AK13 -> 1 | AN13: =+AK13 -> 1 | AO13: =+AK13 -> 1 | AP13: =+AO13 -> 1 | AQ13: =+AO13 -> 1 | AR13: =+AO13 -> 1 | AS13: =+AO13 -> 1 | AT13: =+AS13 -> 1 | AU13: =+AS13 -> 1 | AV13: =+AS13 -> 1 | AW13: =+AS13 -> 1 | AX13: =+AW13 -> 1 | AY13: =+AW13 -> 1 | AZ13: =+AW13 -> 1 | BA13: =+AW13 -> 1 | BB13: =+BA13 -> 1 | BC13: =+BA13 -> 1 | BD13: =+BA13 -> 1 | BE13: =+BA13 -> 1 | BF13: =+BE13 -> 1 | BG13: =+BE13 -> 1 | BH13: =+BE13 -> 1 | BI13: =+BE13 -> 1 | BJ13: =+BI13 -> 1 | BK13: =+BI13 -> 1 | BL13: =+BI13 -> 1 | BM13: =+BI13 -> 1 | BN13: =+BM13 -> 1 | BO13: =+BM13 -> 1 | BP13: =+BM13 -> 1 | BQ13: =+BM13 -> 1 | BR13: =+BQ13 -> 1 | BS13: =+BQ13 -> 1 | BT13: =+BQ13 -> 1 | BU13: =+BQ13 -> 1 | BV13: =+BU13 -> 1 | BW13: =+BU13 -> 1 | BX13: =+BU13 -> 1 | BY13: =+BU13 -> 1 | BZ13: =+BY13 -> 1 | CA13: =+BY13 -> 1 | CB13: =+BY13 -> 1 | CC13: =+BY13 -> 1 | CD13: =+CC13 -> 1 | CE13: =+CC13 -> 1 | CF13: =+CC13 -> 1 | CG13: =+CC13 -> 1 | CH13: =+CG13 -> 1 | CI13: =+CG13 -> 1 | CJ13: =+CG13 -> 1 | CK13: =+CG13 -> 1 | CL13: =+CK13 -> 1 | CM13: =+CK13 -> 1 | CN13: =+CK13 -> 1 | CO13: =+CK13 -> 1 | CP13: =+CO13 -> 1 | CQ13: =+CO13 -> 1 | CR13: =+CO13 -> 1 | CS13: =+CO13 -> 1 | CT13: =+CS13 -> 1 | CU13: =+CS13 -> 1 | CV13: =+CS13 -> 1 | CW13: =+CS13 -> 1 | CX13: =+CW13 -> 1 | CY13: =+CW13 -> 1 | CZ13: =+CW13 -> 1 | DA13: =+CW13 -> 1 | DB13: =+DA13 -> 1 | DC13: =+DA13 -> 1 | DD13: =+DA13 -> 1 | DE13: =+DA13 -> 1 | DF13: =+DE13 -> 1 | DG13: =+DE13 -> 1 | DH13: =+DE13 -> 1 | DI13: =+DE13 -> 1 | DJ13: =+DI13 -> 1 | DK13: =+DI13 -> 1 | DL13: =+DI13 -> 1 | DM13: =+DI13 -> 1 | DN13: =+DM13 -> 1 | DO13: =+DM13 -> 1 | DP13: =+DM13 -> 1 | DQ13: =+DM13 -> 1 | DR13: =+DQ13 -> 1 | DS13: =+DQ13 -> 1 | DT13: =+DQ13 -> 1 | DU13: =+DQ13 -> 1 | DV13: =+DU13 -> 1 | DW13: =+DU13 -> 1 | DX13: =+DU13 -> 1 | DY13: =+DU13 -> 1 | DZ13: =+DY13 -> 1 | EA13: =+DY13 -> 1 | EB13: =+DY13 -> 1 | EC13: =+DY13 -> 1 | ED13: =+EC13 -> 1 | EE13: =+EC13 -> 1 | EF13: =+EC13 -> 1 | EG13: =+EC13 -> 1 | EH13: =+EG13 -> 1 | EI13: =+EG13 -> 1 | EJ13: =+EG13 -> 1 | EK13: =+EG13 -> 1 | EL13: =+EK13 -> 1 | EM13: =+EK13 -> 1 | EN13: =+EK13 -> 1 | EO13: =+EK13 -> 1 | EP13: =+EO13 -> 1 | EQ13: =+EO13 -> 1 | ER13: =+EO13 -> 1 | ES13: =+EO13 -> 1 | ET13: =+schedule_ARAS!EW17 -> 30 | EU13: =+schedule_ARAS!EZ17 -> 13440 | EV13: =+schedule_ARAS!FA17 -> 7200
C14: =+schedule_ARAS!C18 -> Midia 5 | D14: Ad | E14: =+schedule_ARAS!E18 -> 1 | N14: =+M14 -> 0 | O14: =+M14 -> 0 | P14: =+M14 -> 0 | Q14: =+M14 -> 0 | R14: =+Q14 -> 0 | S14: =+Q14 -> 0 | T14: =+Q14 -> 0 | U14: =+Q14 -> 0 | V14: =+U14 -> 0 | W14: =+U14 -> 0 | X14: =+U14 -> 0 | Y14: =+U14 -> 0 | Z14: =+Y14 -> 0 | AA14: =+Y14 -> 0 | AB14: =+Y14 -> 0 | AC14: =+Y14 -> 0 | AD14: =+E14 -> 1 | AE14: =+E14 -> 1 | AF14: =+E14 -> 1 | AG14: =+E14 -> 1 | AH14: =+AG14 -> 1 | AI14: =+AG14 -> 1 | AJ14: =+AG14 -> 1 | AK14: =+AG14 -> 1 | AL14: =+AK14 -> 1 | AM14: =+AK14 -> 1 | AN14: =+AK14 -> 1 | AO14: =+AK14 -> 1 | AP14: =+AO14 -> 1 | AQ14: =+AO14 -> 1 | AR14: =+AO14 -> 1 | AS14: =+AO14 -> 1 | AT14: =+AS14 -> 1 | AU14: =+AS14 -> 1 | AV14: =+AS14 -> 1 | AW14: =+AS14 -> 1 | AX14: =+AW14 -> 1 | AY14: =+AW14 -> 1 | AZ14: =+AW14 -> 1 | BA14: =+AW14 -> 1 | BB14: =+BA14 -> 1 | BC14: =+BA14 -> 1 | BD14: =+BA14 -> 1 | BE14: =+BA14 -> 1 | BF14: =+BE14 -> 1 | BG14: =+BE14 -> 1 | BH14: =+BE14 -> 1 | BI14: =+BE14 -> 1 | BJ14: =+BI14 -> 1 | BK14: =+BI14 -> 1 | BL14: =+BI14 -> 1 | BM14: =+BI14 -> 1 | BN14: =+BM14 -> 1 | BO14: =+BM14 -> 1 | BP14: =+BM14 -> 1 | BQ14: =+BM14 -> 1 | BR14: =+BQ14 -> 1 | BS14: =+BQ14 -> 1 | BT14: =+BQ14 -> 1 | BU14: =+BQ14 -> 1 | BV14: =+BU14 -> 1 | BW14: =+BU14 -> 1 | BX14: =+BU14 -> 1 | BY14: =+BU14 -> 1 | BZ14: =+BY14 -> 1 | CA14: =+BY14 -> 1 | CB14: =+BY14 -> 1 | CC14: =+BY14 -> 1 | CD14: =+CC14 -> 1 | CE14: =+CC14 -> 1 | CF14: =+CC14 -> 1 | CG14: =+CC14 -> 1 | CH14: =+CG14 -> 1 | CI14: =+CG14 -> 1 | CJ14: =+CG14 -> 1 | CK14: =+CG14 -> 1 | CL14: =+CK14 -> 1 | CM14: =+CK14 -> 1 | CN14: =+CK14 -> 1 | CO14: =+CK14 -> 1 | CP14: =+CO14 -> 1 | CQ14: =+CO14 -> 1 | CR14: =+CO14 -> 1 | CS14: =+CO14 -> 1 | CT14: =+CS14 -> 1 | CU14: =+CS14 -> 1 | CV14: =+CS14 -> 1 | CW14: =+CS14 -> 1 | CX14: =+CW14 -> 1 | CY14: =+CW14 -> 1 | CZ14: =+CW14 -> 1 | DA14: =+CW14 -> 1 | DB14: =+DA14 -> 1 | DC14: =+DA14 -> 1 | DD14: =+DA14 -> 1 | DE14: =+DA14 -> 1 | DF14: =+DE14 -> 1 | DG14: =+DE14 -> 1 | DH14: =+DE14 -> 1 | DI14: =+DE14 -> 1 | DJ14: =+DI14 -> 1 | DK14: =+DI14 -> 1 | DL14: =+DI14 -> 1 | DM14: =+DI14 -> 1 | DN14: =+DM14 -> 1 | DO14: =+DM14 -> 1 | DP14: =+DM14 -> 1 | DQ14: =+DM14 -> 1 | DR14: =+DQ14 -> 1 | DS14: =+DQ14 -> 1 | DT14: =+DQ14 -> 1 | DU14: =+DQ14 -> 1 | DV14: =+DU14 -> 1 | DW14: =+DU14 -> 1 | DX14: =+DU14 -> 1 | DY14: =+DU14 -> 1 | DZ14: =+DY14 -> 1 | EA14: =+DY14 -> 1 | EB14: =+DY14 -> 1 | EC14: =+DY14 -> 1 | ED14: =+EC14 -> 1 | EE14: =+EC14 -> 1 | EF14: =+EC14 -> 1 | EG14: =+EC14 -> 1 | EH14: =+EG14 -> 1 | EI14: =+EG14 -> 1 | EJ14: =+EG14 -> 1 | EK14: =+EG14 -> 1 | EL14: =+EK14 -> 1 | EM14: =+EK14 -> 1 | EN14: =+EK14 -> 1 | EO14: =+EK14 -> 1 | EP14: =+EO14 -> 1 | EQ14: =+EO14 -> 1 | ER14: =+EO14 -> 1 | ES14: =+EO14 -> 1 | ET14: =+schedule_ARAS!EW18 -> 30 | EU14: =+schedule_ARAS!EZ18 -> 13440 | EV14: =+schedule_ARAS!FA18 -> 7200
C15: =+schedule_ARAS!C19 -> Midia 8 | D15: Ad | E15: =+schedule_ARAS!E19 -> 1 | N15: =+M15 -> 0 | O15: =+M15 -> 0 | P15: =+M15 -> 0 | Q15: =+M15 -> 0 | R15: =+Q15 -> 0 | S15: =+Q15 -> 0 | T15: =+Q15 -> 0 | U15: =+Q15 -> 0 | V15: =+U15 -> 0 | W15: =+U15 -> 0 | X15: =+U15 -> 0 | Y15: =+U15 -> 0 | Z15: =+Y15 -> 0 | AA15: =+Y15 -> 0 | AB15: =+Y15 -> 0 | AC15: =+Y15 -> 0 | AD15: =+E15 -> 1 | AE15: =+E15 -> 1 | AF15: =+E15 -> 1 | AG15: =+E15 -> 1 | AH15: =+AG15 -> 1 | AI15: =+AG15 -> 1 | AJ15: =+AG15 -> 1 | AK15: =+AG15 -> 1 | AL15: =+AK15 -> 1 | AM15: =+AK15 -> 1 | AN15: =+AK15 -> 1 | AO15: =+AK15 -> 1 | AP15: =+AO15 -> 1 | AQ15: =+AO15 -> 1 | AR15: =+AO15 -> 1 | AS15: =+AO15 -> 1 | AT15: =+AS15 -> 1 | AU15: =+AS15 -> 1 | AV15: =+AS15 -> 1 | AW15: =+AS15 -> 1 | AX15: =+AW15 -> 1 | AY15: =+AW15 -> 1 | AZ15: =+AW15 -> 1 | BA15: =+AW15 -> 1 | BB15: =+BA15 -> 1 | BC15: =+BA15 -> 1 | BD15: =+BA15 -> 1 | BE15: =+BA15 -> 1 | BF15: =+BE15 -> 1 | BG15: =+BE15 -> 1 | BH15: =+BE15 -> 1 | BI15: =+BE15 -> 1 | BJ15: =+BI15 -> 1 | BK15: =+BI15 -> 1 | BL15: =+BI15 -> 1 | BM15: =+BI15 -> 1 | BN15: =+BM15 -> 1 | BO15: =+BM15 -> 1 | BP15: =+BM15 -> 1 | BQ15: =+BM15 -> 1 | BR15: =+BQ15 -> 1 | BS15: =+BQ15 -> 1 | BT15: =+BQ15 -> 1 | BU15: =+BQ15 -> 1 | BV15: =+BU15 -> 1 | BW15: =+BU15 -> 1 | BX15: =+BU15 -> 1 | BY15: =+BU15 -> 1 | BZ15: =+BY15 -> 1 | CA15: =+BY15 -> 1 | CB15: =+BY15 -> 1 | CC15: =+BY15 -> 1 | CD15: =+CC15 -> 1 | CE15: =+CC15 -> 1 | CF15: =+CC15 -> 1 | CG15: =+CC15 -> 1 | CH15: =+CG15 -> 1 | CI15: =+CG15 -> 1 | CJ15: =+CG15 -> 1 | CK15: =+CG15 -> 1 | CL15: =+CK15 -> 1 | CM15: =+CK15 -> 1 | CN15: =+CK15 -> 1 | CO15: =+CK15 -> 1 | CP15: =+CO15 -> 1 | CQ15: =+CO15 -> 1 | CR15: =+CO15 -> 1 | CS15: =+CO15 -> 1 | CT15: =+CS15 -> 1 | CU15: =+CS15 -> 1 | CV15: =+CS15 -> 1 | CW15: =+CS15 -> 1 | CX15: =+CW15 -> 1 | CY15: =+CW15 -> 1 | CZ15: =+CW15 -> 1 | DA15: =+CW15 -> 1 | DB15: =+DA15 -> 1 | DC15: =+DA15 -> 1 | DD15: =+DA15 -> 1 | DE15: =+DA15 -> 1 | DF15: =+DE15 -> 1 | DG15: =+DE15 -> 1 | DH15: =+DE15 -> 1 | DI15: =+DE15 -> 1 | DJ15: =+DI15 -> 1 | DK15: =+DI15 -> 1 | DL15: =+DI15 -> 1 | DM15: =+DI15 -> 1 | DN15: =+DM15 -> 1 | DO15: =+DM15 -> 1 | DP15: =+DM15 -> 1 | DQ15: =+DM15 -> 1 | DR15: =+DQ15 -> 1 | DS15: =+DQ15 -> 1 | DT15: =+DQ15 -> 1 | DU15: =+DQ15 -> 1 | DV15: =+DU15 -> 1 | DW15: =+DU15 -> 1 | DX15: =+DU15 -> 1 | DY15: =+DU15 -> 1 | DZ15: =+DY15 -> 1 | EA15: =+DY15 -> 1 | EB15: =+DY15 -> 1 | EC15: =+DY15 -> 1 | ED15: =+EC15 -> 1 | EE15: =+EC15 -> 1 | EF15: =+EC15 -> 1 | EG15: =+EC15 -> 1 | EH15: =+EG15 -> 1 | EI15: =+EG15 -> 1 | EJ15: =+EG15 -> 1 | EK15: =+EG15 -> 1 | EL15: =+EK15 -> 1 | EM15: =+EK15 -> 1 | EN15: =+EK15 -> 1 | EO15: =+EK15 -> 1 | EP15: =+EO15 -> 1 | EQ15: =+EO15 -> 1 | ER15: =+EO15 -> 1 | ES15: =+EO15 -> 1 | ET15: =+schedule_ARAS!EW19 -> 30 | EU15: =+schedule_ARAS!EZ19 -> 13440 | EV15: =+schedule_ARAS!FA19 -> 7200
C16: =+schedule_ARAS!C20 -> Midia 13 | D16: Ad | E16: =+schedule_ARAS!E20 -> 1 | N16: =+M16 -> 0 | O16: =+M16 -> 0 | P16: =+M16 -> 0 | Q16: =+M16 -> 0 | R16: =+Q16 -> 0 | S16: =+Q16 -> 0 | T16: =+Q16 -> 0 | U16: =+Q16 -> 0 | V16: =+U16 -> 0 | W16: =+U16 -> 0 | X16: =+U16 -> 0 | Y16: =+U16 -> 0 | Z16: =+Y16 -> 0 | AA16: =+Y16 -> 0 | AB16: =+Y16 -> 0 | AC16: =+Y16 -> 0 | AD16: =+E16 -> 1 | AE16: =+E16 -> 1 | AF16: =+E16 -> 1 | AG16: =+E16 -> 1 | AH16: =+AG16 -> 1 | AI16: =+AG16 -> 1 | AJ16: =+AG16 -> 1 | AK16: =+AG16 -> 1 | AL16: =+AK16 -> 1 | AM16: =+AK16 -> 1 | AN16: =+AK16 -> 1 | AO16: =+AK16 -> 1 | AP16: =+AO16 -> 1 | AQ16: =+AO16 -> 1 | AR16: =+AO16 -> 1 | AS16: =+AO16 -> 1 | AT16: =+AS16 -> 1 | AU16: =+AS16 -> 1 | AV16: =+AS16 -> 1 | AW16: =+AS16 -> 1 | AX16: =+AW16 -> 1 | AY16: =+AW16 -> 1 | AZ16: =+AW16 -> 1 | BA16: =+AW16 -> 1 | BB16: =+BA16 -> 1 | BC16: =+BA16 -> 1 | BD16: =+BA16 -> 1 | BE16: =+BA16 -> 1 | BF16: =+BE16 -> 1 | BG16: =+BE16 -> 1 | BH16: =+BE16 -> 1 | BI16: =+BE16 -> 1 | BJ16: =+BI16 -> 1 | BK16: =+BI16 -> 1 | BL16: =+BI16 -> 1 | BM16: =+BI16 -> 1 | BN16: =+BM16 -> 1 | BO16: =+BM16 -> 1 | BP16: =+BM16 -> 1 | BQ16: =+BM16 -> 1 | BR16: =+BQ16 -> 1 | BS16: =+BQ16 -> 1 | BT16: =+BQ16 -> 1 | BU16: =+BQ16 -> 1 | BV16: =+BU16 -> 1 | BW16: =+BU16 -> 1 | BX16: =+BU16 -> 1 | BY16: =+BU16 -> 1 | BZ16: =+BY16 -> 1 | CA16: =+BY16 -> 1 | CB16: =+BY16 -> 1 | CC16: =+BY16 -> 1 | CD16: =+CC16 -> 1 | CE16: =+CC16 -> 1 | CF16: =+CC16 -> 1 | CG16: =+CC16 -> 1 | CH16: =+CG16 -> 1 | CI16: =+CG16 -> 1 | CJ16: =+CG16 -> 1 | CK16: =+CG16 -> 1 | CL16: =+CK16 -> 1 | CM16: =+CK16 -> 1 | CN16: =+CK16 -> 1 | CO16: =+CK16 -> 1 | CP16: =+CO16 -> 1 | CQ16: =+CO16 -> 1 | CR16: =+CO16 -> 1 | CS16: =+CO16 -> 1 | CT16: =+CS16 -> 1 | CU16: =+CS16 -> 1 | CV16: =+CS16 -> 1 | CW16: =+CS16 -> 1 | CX16: =+CW16 -> 1 | CY16: =+CW16 -> 1 | CZ16: =+CW16 -> 1 | DA16: =+CW16 -> 1 | DB16: =+DA16 -> 1 | DC16: =+DA16 -> 1 | DD16: =+DA16 -> 1 | DE16: =+DA16 -> 1 | DF16: =+DE16 -> 1 | DG16: =+DE16 -> 1 | DH16: =+DE16 -> 1 | DI16: =+DE16 -> 1 | DJ16: =+DI16 -> 1 | DK16: =+DI16 -> 1 | DL16: =+DI16 -> 1 | DM16: =+DI16 -> 1 | DN16: =+DM16 -> 1 | DO16: =+DM16 -> 1 | DP16: =+DM16 -> 1 | DQ16: =+DM16 -> 1 | DR16: =+DQ16 -> 1 | DS16: =+DQ16 -> 1 | DT16: =+DQ16 -> 1 | DU16: =+DQ16 -> 1 | DV16: =+DU16 -> 1 | DW16: =+DU16 -> 1 | DX16: =+DU16 -> 1 | DY16: =+DU16 -> 1 | DZ16: =+DY16 -> 1 | EA16: =+DY16 -> 1 | EB16: =+DY16 -> 1 | EC16: =+DY16 -> 1 | ED16: =+EC16 -> 1 | EE16: =+EC16 -> 1 | EF16: =+EC16 -> 1 | EG16: =+EC16 -> 1 | EH16: =+EG16 -> 1 | EI16: =+EG16 -> 1 | EJ16: =+EG16 -> 1 | EK16: =+EG16 -> 1 | EL16: =+EK16 -> 1 | EM16: =+EK16 -> 1 | EN16: =+EK16 -> 1 | EO16: =+EK16 -> 1 | EP16: =+EO16 -> 1 | EQ16: =+EO16 -> 1 | ER16: =+EO16 -> 1 | ES16: =+EO16 -> 1 | ET16: =+schedule_ARAS!EW20 -> 30 | EU16: =+schedule_ARAS!EZ20 -> 13440 | EV16: =+schedule_ARAS!FA20 -> 7200
C17: =+schedule_ARAS!C21 -> Paşa | D17: Ad | E17: =+schedule_ARAS!E21 -> 1 | N17: =+M17 -> 0 | O17: =+M17 -> 0 | P17: =+M17 -> 0 | Q17: =+M17 -> 0 | R17: =+Q17 -> 0 | S17: =+Q17 -> 0 | T17: =+Q17 -> 0 | U17: =+Q17 -> 0 | V17: =+U17 -> 0 | W17: =+U17 -> 0 | X17: =+U17 -> 0 | Y17: =+U17 -> 0 | Z17: =+Y17 -> 0 | AA17: =+Y17 -> 0 | AB17: =+Y17 -> 0 | AC17: =+Y17 -> 0 | AD17: =+E17 -> 1 | AE17: =+E17 -> 1 | AF17: =+E17 -> 1 | AG17: =+E17 -> 1 | AH17: =+AG17 -> 1 | AI17: =+AG17 -> 1 | AJ17: =+AG17 -> 1 | AK17: =+AG17 -> 1 | AL17: =+AK17 -> 1 | AM17: =+AK17 -> 1 | AN17: =+AK17 -> 1 | AO17: =+AK17 -> 1 | AP17: =+AO17 -> 1 | AQ17: =+AO17 -> 1 | AR17: =+AO17 -> 1 | AS17: =+AO17 -> 1 | AT17: =+AS17 -> 1 | AU17: =+AS17 -> 1 | AV17: =+AS17 -> 1 | AW17: =+AS17 -> 1 | AX17: =+AW17 -> 1 | AY17: =+AW17 -> 1 | AZ17: =+AW17 -> 1 | BA17: =+AW17 -> 1 | BB17: =+BA17 -> 1 | BC17: =+BA17 -> 1 | BD17: =+BA17 -> 1 | BE17: =+BA17 -> 1 | BF17: =+BE17 -> 1 | BG17: =+BE17 -> 1 | BH17: =+BE17 -> 1 | BI17: =+BE17 -> 1 | BJ17: =+BI17 -> 1 | BK17: =+BI17 -> 1 | BL17: =+BI17 -> 1 | BM17: =+BI17 -> 1 | BN17: =+BM17 -> 1 | BO17: =+BM17 -> 1 | BP17: =+BM17 -> 1 | BQ17: =+BM17 -> 1 | BR17: =+BQ17 -> 1 | BS17: =+BQ17 -> 1 | BT17: =+BQ17 -> 1 | BU17: =+BQ17 -> 1 | BV17: =+BU17 -> 1 | BW17: =+BU17 -> 1 | BX17: =+BU17 -> 1 | BY17: =+BU17 -> 1 | BZ17: =+BY17 -> 1 | CA17: =+BY17 -> 1 | CB17: =+BY17 -> 1 | CC17: =+BY17 -> 1 | CD17: =+CC17 -> 1 | CE17: =+CC17 -> 1 | CF17: =+CC17 -> 1 | CG17: =+CC17 -> 1 | CH17: =+CG17 -> 1 | CI17: =+CG17 -> 1 | CJ17: =+CG17 -> 1 | CK17: =+CG17 -> 1 | CL17: =+CK17 -> 1 | CM17: =+CK17 -> 1 | CN17: =+CK17 -> 1 | CO17: =+CK17 -> 1 | CP17: =+CO17 -> 1 | CQ17: =+CO17 -> 1 | CR17: =+CO17 -> 1 | CS17: =+CO17 -> 1 | CT17: =+CS17 -> 1 | CU17: =+CS17 -> 1 | CV17: =+CS17 -> 1 | CW17: =+CS17 -> 1 | CX17: =+CW17 -> 1 | CY17: =+CW17 -> 1 | CZ17: =+CW17 -> 1 | DA17: =+CW17 -> 1 | DB17: =+DA17 -> 1 | DC17: =+DA17 -> 1 | DD17: =+DA17 -> 1 | DE17: =+DA17 -> 1 | DF17: =+DE17 -> 1 | DG17: =+DE17 -> 1 | DH17: =+DE17 -> 1 | DI17: =+DE17 -> 1 | DJ17: =+DI17 -> 1 | DK17: =+DI17 -> 1 | DL17: =+DI17 -> 1 | DM17: =+DI17 -> 1 | DN17: =+DM17 -> 1 | DO17: =+DM17 -> 1 | DP17: =+DM17 -> 1 | DQ17: =+DM17 -> 1 | DR17: =+DQ17 -> 1 | DS17: =+DQ17 -> 1 | DT17: =+DQ17 -> 1 | DU17: =+DQ17 -> 1 | DV17: =+DU17 -> 1 | DW17: =+DU17 -> 1 | DX17: =+DU17 -> 1 | DY17: =+DU17 -> 1 | DZ17: =+DY17 -> 1 | EA17: =+DY17 -> 1 | EB17: =+DY17 -> 1 | EC17: =+DY17 -> 1 | ED17: =+EC17 -> 1 | EE17: =+EC17 -> 1 | EF17: =+EC17 -> 1 | EG17: =+EC17 -> 1 | EH17: =+EG17 -> 1 | EI17: =+EG17 -> 1 | EJ17: =+EG17 -> 1 | EK17: =+EG17 -> 1 | EL17: =+EK17 -> 1 | EM17: =+EK17 -> 1 | EN17: =+EK17 -> 1 | EO17: =+EK17 -> 1 | EP17: =+EO17 -> 1 | EQ17: =+EO17 -> 1 | ER17: =+EO17 -> 1 | ES17: =+EO17 -> 1 | ET17: =+schedule_ARAS!EW21 -> 30 | EU17: =+schedule_ARAS!EZ21 -> 13440 | EV17: =+schedule_ARAS!FA21 -> 7200
C18: =+schedule_ARAS!C22 -> Hila | D18: Ad | E18: =+schedule_ARAS!E22 -> 1 | N18: =+M18 -> 0 | O18: =+M18 -> 0 | P18: =+M18 -> 0 | Q18: =+M18 -> 0 | R18: =+Q18 -> 0 | S18: =+Q18 -> 0 | T18: =+Q18 -> 0 | U18: =+Q18 -> 0 | V18: =+U18 -> 0 | W18: =+U18 -> 0 | X18: =+U18 -> 0 | Y18: =+U18 -> 0 | Z18: =+Y18 -> 0 | AA18: =+Y18 -> 0 | AB18: =+Y18 -> 0 | AC18: =+Y18 -> 0 | AD18: =+E18 -> 1 | AE18: =+E18 -> 1 | AF18: =+E18 -> 1 | AG18: =+E18 -> 1 | AH18: =+AG18 -> 1 | AI18: =+AG18 -> 1 | AJ18: =+AG18 -> 1 | AK18: =+AG18 -> 1 | AL18: =+AK18 -> 1 | AM18: =+AK18 -> 1 | AN18: =+AK18 -> 1 | AO18: =+AK18 -> 1 | AP18: =+AO18 -> 1 | AQ18: =+AO18 -> 1 | AR18: =+AO18 -> 1 | AS18: =+AO18 -> 1 | AT18: =+AS18 -> 1 | AU18: =+AS18 -> 1 | AV18: =+AS18 -> 1 | AW18: =+AS18 -> 1 | AX18: =+AW18 -> 1 | AY18: =+AW18 -> 1 | AZ18: =+AW18 -> 1 | BA18: =+AW18 -> 1 | BB18: =+BA18 -> 1 | BC18: =+BA18 -> 1 | BD18: =+BA18 -> 1 | BE18: =+BA18 -> 1 | BF18: =+BE18 -> 1 | BG18: =+BE18 -> 1 | BH18: =+BE18 -> 1 | BI18: =+BE18 -> 1 | BJ18: =+BI18 -> 1 | BK18: =+BI18 -> 1 | BL18: =+BI18 -> 1 | BM18: =+BI18 -> 1 | BN18: =+BM18 -> 1 | BO18: =+BM18 -> 1 | BP18: =+BM18 -> 1 | BQ18: =+BM18 -> 1 | BR18: =+BQ18 -> 1 | BS18: =+BQ18 -> 1 | BT18: =+BQ18 -> 1 | BU18: =+BQ18 -> 1 | BV18: =+BU18 -> 1 | BW18: =+BU18 -> 1 | BX18: =+BU18 -> 1 | BY18: =+BU18 -> 1 | BZ18: =+BY18 -> 1 | CA18: =+BY18 -> 1 | CB18: =+BY18 -> 1 | CC18: =+BY18 -> 1 | CD18: =+CC18 -> 1 | CE18: =+CC18 -> 1 | CF18: =+CC18 -> 1 | CG18: =+CC18 -> 1 | CH18: =+CG18 -> 1 | CI18: =+CG18 -> 1 | CJ18: =+CG18 -> 1 | CK18: =+CG18 -> 1 | CL18: =+CK18 -> 1 | CM18: =+CK18 -> 1 | CN18: =+CK18 -> 1 | CO18: =+CK18 -> 1 | CP18: =+CO18 -> 1 | CQ18: =+CO18 -> 1 | CR18: =+CO18 -> 1 | CS18: =+CO18 -> 1 | CT18: =+CS18 -> 1 | CU18: =+CS18 -> 1 | CV18: =+CS18 -> 1 | CW18: =+CS18 -> 1 | CX18: =+CW18 -> 1 | CY18: =+CW18 -> 1 | CZ18: =+CW18 -> 1 | DA18: =+CW18 -> 1 | DB18: =+DA18 -> 1 | DC18: =+DA18 -> 1 | DD18: =+DA18 -> 1 | DE18: =+DA18 -> 1 | DF18: =+DE18 -> 1 | DG18: =+DE18 -> 1 | DH18: =+DE18 -> 1 | DI18: =+DE18 -> 1 | DJ18: =+DI18 -> 1 | DK18: =+DI18 -> 1 | DL18: =+DI18 -> 1 | DM18: =+DI18 -> 1 | DN18: =+DM18 -> 1 | DO18: =+DM18 -> 1 | DP18: =+DM18 -> 1 | DQ18: =+DM18 -> 1 | DR18: =+DQ18 -> 1 | DS18: =+DQ18 -> 1 | DT18: =+DQ18 -> 1 | DU18: =+DQ18 -> 1 | DV18: =+DU18 -> 1 | DW18: =+DU18 -> 1 | DX18: =+DU18 -> 1 | DY18: =+DU18 -> 1 | DZ18: =+DY18 -> 1 | EA18: =+DY18 -> 1 | EB18: =+DY18 -> 1 | EC18: =+DY18 -> 1 | ED18: =+EC18 -> 1 | EE18: =+EC18 -> 1 | EF18: =+EC18 -> 1 | EG18: =+EC18 -> 1 | EH18: =+EG18 -> 1 | EI18: =+EG18 -> 1 | EJ18: =+EG18 -> 1 | EK18: =+EG18 -> 1 | EL18: =+EK18 -> 1 | EM18: =+EK18 -> 1 | EN18: =+EK18 -> 1 | EO18: =+EK18 -> 1 | EP18: =+EO18 -> 1 | EQ18: =+EO18 -> 1 | ER18: =+EO18 -> 1 | ES18: =+EO18 -> 1 | ET18: =+schedule_ARAS!EW22 -> 30 | EU18: =+schedule_ARAS!EZ22 -> 13440 | EV18: =+schedule_ARAS!FA22 -> 7200
C19: =+schedule_ARAS!C23 -> Daria | D19: Ad | E19: =+schedule_ARAS!E23 -> 1 | N19: =+M19 -> 0 | O19: =+M19 -> 0 | P19: =+M19 -> 0 | Q19: =+M19 -> 0 | R19: =+Q19 -> 0 | S19: =+Q19 -> 0 | T19: =+Q19 -> 0 | U19: =+Q19 -> 0 | V19: =+U19 -> 0 | W19: =+U19 -> 0 | X19: =+U19 -> 0 | Y19: =+U19 -> 0 | Z19: =+Y19 -> 0 | AA19: =+Y19 -> 0 | AB19: =+Y19 -> 0 | AC19: =+Y19 -> 0 | AD19: =+E19 -> 1 | AE19: =+E19 -> 1 | AF19: =+E19 -> 1 | AG19: =+E19 -> 1 | AH19: =+AG19 -> 1 | AI19: =+AG19 -> 1 | AJ19: =+AG19 -> 1 | AK19: =+AG19 -> 1 | AL19: =+AK19 -> 1 | AM19: =+AK19 -> 1 | AN19: =+AK19 -> 1 | AO19: =+AK19 -> 1 | AP19: =+AO19 -> 1 | AQ19: =+AO19 -> 1 | AR19: =+AO19 -> 1 | AS19: =+AO19 -> 1 | AT19: =+AS19 -> 1 | AU19: =+AS19 -> 1 | AV19: =+AS19 -> 1 | AW19: =+AS19 -> 1 | AX19: =+AW19 -> 1 | AY19: =+AW19 -> 1 | AZ19: =+AW19 -> 1 | BA19: =+AW19 -> 1 | BB19: =+BA19 -> 1 | BC19: =+BA19 -> 1 | BD19: =+BA19 -> 1 | BE19: =+BA19 -> 1 | BF19: =+BE19 -> 1 | BG19: =+BE19 -> 1 | BH19: =+BE19 -> 1 | BI19: =+BE19 -> 1 | BJ19: =+BI19 -> 1 | BK19: =+BI19 -> 1 | BL19: =+BI19 -> 1 | BM19: =+BI19 -> 1 | BN19: =+BM19 -> 1 | BO19: =+BM19 -> 1 | BP19: =+BM19 -> 1 | BQ19: =+BM19 -> 1 | BR19: =+BQ19 -> 1 | BS19: =+BQ19 -> 1 | BT19: =+BQ19 -> 1 | BU19: =+BQ19 -> 1 | BV19: =+BU19 -> 1 | BW19: =+BU19 -> 1 | BX19: =+BU19 -> 1 | BY19: =+BU19 -> 1 | BZ19: =+BY19 -> 1 | CA19: =+BY19 -> 1 | CB19: =+BY19 -> 1 | CC19: =+BY19 -> 1 | CD19: =+CC19 -> 1 | CE19: =+CC19 -> 1 | CF19: =+CC19 -> 1 | CG19: =+CC19 -> 1 | CH19: =+CG19 -> 1 | CI19: =+CG19 -> 1 | CJ19: =+CG19 -> 1 | CK19: =+CG19 -> 1 | CL19: =+CK19 -> 1 | CM19: =+CK19 -> 1 | CN19: =+CK19 -> 1 | CO19: =+CK19 -> 1 | CP19: =+CO19 -> 1 | CQ19: =+CO19 -> 1 | CR19: =+CO19 -> 1 | CS19: =+CO19 -> 1 | CT19: =+CS19 -> 1 | CU19: =+CS19 -> 1 | CV19: =+CS19 -> 1 | CW19: =+CS19 -> 1 | CX19: =+CW19 -> 1 | CY19: =+CW19 -> 1 | CZ19: =+CW19 -> 1 | DA19: =+CW19 -> 1 | DB19: =+DA19 -> 1 | DC19: =+DA19 -> 1 | DD19: =+DA19 -> 1 | DE19: =+DA19 -> 1 | DF19: =+DE19 -> 1 | DG19: =+DE19 -> 1 | DH19: =+DE19 -> 1 | DI19: =+DE19 -> 1 | DJ19: =+DI19 -> 1 | DK19: =+DI19 -> 1 | DL19: =+DI19 -> 1 | DM19: =+DI19 -> 1 | DN19: =+DM19 -> 1 | DO19: =+DM19 -> 1 | DP19: =+DM19 -> 1 | DQ19: =+DM19 -> 1 | DR19: =+DQ19 -> 1 | DS19: =+DQ19 -> 1 | DT19: =+DQ19 -> 1 | DU19: =+DQ19 -> 1 | DV19: =+DU19 -> 1 | DW19: =+DU19 -> 1 | DX19: =+DU19 -> 1 | DY19: =+DU19 -> 1 | DZ19: =+DY19 -> 1 | EA19: =+DY19 -> 1 | EB19: =+DY19 -> 1 | EC19: =+DY19 -> 1 | ED19: =+EC19 -> 1 | EE19: =+EC19 -> 1 | EF19: =+EC19 -> 1 | EG19: =+EC19 -> 1 | EH19: =+EG19 -> 1 | EI19: =+EG19 -> 1 | EJ19: =+EG19 -> 1 | EK19: =+EG19 -> 1 | EL19: =+EK19 -> 1 | EM19: =+EK19 -> 1 | EN19: =+EK19 -> 1 | EO19: =+EK19 -> 1 | EP19: =+EO19 -> 1 | EQ19: =+EO19 -> 1 | ER19: =+EO19 -> 1 | ES19: =+EO19 -> 1 | ET19: =+schedule_ARAS!EW23 -> 30 | EU19: =+schedule_ARAS!EZ23 -> 13440 | EV19: =+schedule_ARAS!FA23 -> 7200
... C25: =+schedule_ARAS!C29 -> Yunus - 6 | D25: Ad | E25: =+schedule_ARAS!E29 -> 1 | N25: =+M25 -> 0 | O25: =+M25 -> 0 | P25: =+M25 -> 0 | Q25: =+M25 -> 0 | R25: =+Q25 -> 0 | S25: =+Q25 -> 0 | T25: =+Q25 -> 0 | U25: =+Q25 -> 0 | V25: =+U25 -> 0 | W25: =+U25 -> 0 | X25: =+U25 -> 0 | Y25: =+U25 -> 0 | Z25: =+Y25 -> 0 | AA25: =+Y25 -> 0 | AB25: =+Y25 -> 0 | AC25: =+Y25 -> 0 | AD25: =+E25 -> 1 | AE25: =+E25 -> 1 | AF25: =+E25 -> 1 | AG25: =+E25 -> 1 | AH25: =+AG25 -> 1 | AI25: =+AG25 -> 1 | AJ25: =+AG25 -> 1 | AK25: =+AG25 -> 1 | AL25: =+AK25 -> 1 | AM25: =+AK25 -> 1 | AN25: =+AK25 -> 1 | AO25: =+AK25 -> 1 | AP25: =+AO25 -> 1 | AQ25: =+AO25 -> 1 | AR25: =+AO25 -> 1 | AS25: =+AO25 -> 1 | AT25: =+AS25 -> 1 | AU25: =+AS25 -> 1 | AV25: =+AS25 -> 1 | AW25: =+AS25 -> 1 | AX25: =+AW25 -> 1 | AY25: =+AW25 -> 1 | AZ25: =+AW25 -> 1 | BA25: =+AW25 -> 1 | BB25: =+BA25 -> 1 | BC25: =+BA25 -> 1 | BD25: =+BA25 -> 1 | BE25: =+BA25 -> 1 | BF25: =+BE25 -> 1 | BG25: =+BE25 -> 1 | BH25: =+BE25 -> 1 | BI25: =+BE25 -> 1 | BJ25: =+BI25 -> 1 | BK25: =+BI25 -> 1 | BL25: =+BI25 -> 1 | BM25: =+BI25 -> 1 | BN25: =+BM25 -> 1 | BO25: =+BM25 -> 1 | BP25: =+BM25 -> 1 | BQ25: =+BM25 -> 1 | BR25: =+BQ25 -> 1 | BS25: =+BQ25 -> 1 | BT25: =+BQ25 -> 1 | BU25: =+BQ25 -> 1 | BV25: =+BU25 -> 1 | BW25: =+BU25 -> 1 | BX25: =+BU25 -> 1 | BY25: =+BU25 -> 1 | BZ25: =+BY25 -> 1 | CA25: =+BY25 -> 1 | CB25: =+BY25 -> 1 | CC25: =+BY25 -> 1 | CD25: =+CC25 -> 1 | CE25: =+CC25 -> 1 | CF25: =+CC25 -> 1 | CG25: =+CC25 -> 1 | CH25: =+CG25 -> 1 | CI25: =+CG25 -> 1 | CJ25: =+CG25 -> 1 | CK25: =+CG25 -> 1 | CL25: =+CK25 -> 1 | CM25: =+CK25 -> 1 | CN25: =+CK25 -> 1 | CO25: =+CK25 -> 1 | CP25: =+CO25 -> 1 | CQ25: =+CO25 -> 1 | CR25: =+CO25 -> 1 | CS25: =+CO25 -> 1 | CT25: =+CS25 -> 1 | CU25: =+CS25 -> 1 | CV25: =+CS25 -> 1 | CW25: =+CS25 -> 1 | CX25: =+CW25 -> 1 | CY25: =+CW25 -> 1 | CZ25: =+CW25 -> 1 | DA25: =+CW25 -> 1 | DB25: =+DA25 -> 1 | DC25: =+DA25 -> 1 | DD25: =+DA25 -> 1 | DE25: =+DA25 -> 1 | DF25: =+DE25 -> 1 | DG25: =+DE25 -> 1 | DH25: =+DE25 -> 1 | DI25: =+DE25 -> 1 | DJ25: =+DI25 -> 1 | DK25: =+DI25 -> 1 | DL25: =+DI25 -> 1 | DM25: =+DI25 -> 1 | DN25: =+DM25 -> 1 | DO25: =+DM25 -> 1 | DP25: =+DM25 -> 1 | DQ25: =+DM25 -> 1 | DR25: =+DQ25 -> 1 | DS25: =+DQ25 -> 1 | DT25: =+DQ25 -> 1 | DU25: =+DQ25 -> 1 | DV25: =+DU25 -> 1 | DW25: =+DU25 -> 1 | DX25: =+DU25 -> 1 | DY25: =+DU25 -> 1 | DZ25: =+DY25 -> 1 | EA25: =+DY25 -> 1 | EB25: =+DY25 -> 1 | EC25: =+DY25 -> 1 | ED25: =+EC25 -> 1 | EE25: =+EC25 -> 1 | EF25: =+EC25 -> 1 | EG25: =+EC25 -> 1 | EH25: =+EG25 -> 1 | EI25: =+EG25 -> 1 | EJ25: =+EG25 -> 1 | EK25: =+EG25 -> 1 | EL25: =+EK25 -> 1 | EM25: =+EK25 -> 1 | EN25: =+EK25 -> 1 | EO25: =+EK25 -> 1 | EP25: =+EO25 -> 1 | EQ25: =+EO25 -> 1 | ER25: =+EO25 -> 1 | ES25: =+EO25 -> 1 | ET25: =+schedule_ARAS!EW29 -> 30 | EU25: =+schedule_ARAS!EZ29 -> 13440 | EV25: =+schedule_ARAS!FA29 -> 7200
C26: =+schedule_ARAS!C30 -> Atmaca | D26: Ad | E26: =+schedule_ARAS!E30 -> 1 | AD26: =+E26 -> 1 | AE26: =+E26 -> 1 | AF26: =+E26 -> 1 | AG26: =+E26 -> 1 | AH26: =+AG26 -> 1 | AI26: =+AG26 -> 1 | AJ26: =+AG26 -> 1 | AK26: =+AG26 -> 1 | AL26: =+AK26 -> 1 | AM26: =+AK26 -> 1 | AN26: =+AK26 -> 1 | AO26: =+AK26 -> 1 | AP26: =+AO26 -> 1 | AQ26: =+AO26 -> 1 | AR26: =+AO26 -> 1 | AS26: =+AO26 -> 1 | AT26: =+AS26 -> 1 | AU26: =+AS26 -> 1 | AV26: =+AS26 -> 1 | AW26: =+AS26 -> 1 | AX26: =+AW26 -> 1 | AY26: =+AW26 -> 1 | AZ26: =+AW26 -> 1 | BA26: =+AW26 -> 1 | BB26: =+BA26 -> 1 | BC26: =+BA26 -> 1 | BD26: =+BA26 -> 1 | BE26: =+BA26 -> 1 | BF26: =+BE26 -> 1 | BG26: =+BE26 -> 1 | BH26: =+BE26 -> 1 | BI26: =+BE26 -> 1 | BJ26: =+BI26 -> 1 | BK26: =+BI26 -> 1 | BL26: =+BI26 -> 1 | BM26: =+BI26 -> 1 | BN26: =+BM26 -> 1 | BO26: =+BM26 -> 1 | BP26: =+BM26 -> 1 | BQ26: =+BM26 -> 1 | BR26: =+BQ26 -> 1 | BS26: =+BQ26 -> 1 | BT26: =+BQ26 -> 1 | BU26: =+BQ26 -> 1 | BV26: =+BU26 -> 1 | BW26: =+BU26 -> 1 | BX26: =+BU26 -> 1 | BY26: =+BU26 -> 1 | BZ26: =+BY26 -> 1 | CA26: =+BY26 -> 1 | CB26: =+BY26 -> 1 | CC26: =+BY26 -> 1 | CD26: =+CC26 -> 1 | CE26: =+CC26 -> 1 | CF26: =+CC26 -> 1 | CG26: =+CC26 -> 1 | CH26: =+CG26 -> 1 | CI26: =+CG26 -> 1 | CJ26: =+CG26 -> 1 | CK26: =+CG26 -> 1 | CL26: =+CK26 -> 1 | CM26: =+CK26 -> 1 | CN26: =+CK26 -> 1 | CO26: =+CK26 -> 1 | CP26: =+CO26 -> 1 | CQ26: =+CO26 -> 1 | CR26: =+CO26 -> 1 | CS26: =+CO26 -> 1 | CT26: =+CS26 -> 1 | CU26: =+CS26 -> 1 | CV26: =+CS26 -> 1 | CW26: =+CS26 -> 1 | CX26: =+CW26 -> 1 | CY26: =+CW26 -> 1 | CZ26: =+CW26 -> 1 | DA26: =+CW26 -> 1 | DB26: =+DA26 -> 1 | DC26: =+DA26 -> 1 | DD26: =+DA26 -> 1 | DE26: =+DA26 -> 1 | DF26: =+DE26 -> 1 | DG26: =+DE26 -> 1 | DH26: =+DE26 -> 1 | DI26: =+DE26 -> 1 | DJ26: =+DI26 -> 1 | DK26: =+DI26 -> 1 | DL26: =+DI26 -> 1 | DM26: =+DI26 -> 1 | DN26: =+DM26 -> 1 | DO26: =+DM26 -> 1 | DP26: =+DM26 -> 1 | DQ26: =+DM26 -> 1 | DR26: =+DQ26 -> 1 | DS26: =+DQ26 -> 1 | DT26: =+DQ26 -> 1 | DU26: =+DQ26 -> 1 | DV26: =+DU26 -> 1 | DW26: =+DU26 -> 1 | DX26: =+DU26 -> 1 | DY26: =+DU26 -> 1 | DZ26: =+DY26 -> 1 | EA26: =+DY26 -> 1 | EB26: =+DY26 -> 1 | EC26: =+DY26 -> 1 | ED26: =+EC26 -> 1 | EE26: =+EC26 -> 1 | EF26: =+EC26 -> 1 | EG26: =+EC26 -> 1 | EH26: =+EG26 -> 1 | EI26: =+EG26 -> 1 | EJ26: =+EG26 -> 1 | EK26: =+EG26 -> 1 | EL26: =+EK26 -> 1 | EM26: =+EK26 -> 1 | EN26: =+EK26 -> 1 | EO26: =+EK26 -> 1 | EP26: =+EO26 -> 1 | EQ26: =+EO26 -> 1 | ER26: =+EO26 -> 1 | ES26: =+EO26 -> 1 | ET26: =+schedule_ARAS!EW30 -> 30 | EU26: =+schedule_ARAS!EZ30 -> 13440 | EV26: =+schedule_ARAS!FA30 -> 7200
C27: =+schedule_ARAS!C31 -> Tayfun | D27: Ad | E27: =+schedule_ARAS!E31 -> 1 | AD27: =+E27 -> 1 | AE27: =+E27 -> 1 | AF27: =+E27 -> 1 | AG27: =+E27 -> 1 | AH27: =+AG27 -> 1 | AI27: =+AG27 -> 1 | AJ27: =+AG27 -> 1 | AK27: =+AG27 -> 1 | AL27: =+AK27 -> 1 | AM27: =+AK27 -> 1 | AN27: =+AK27 -> 1 | AO27: =+AK27 -> 1 | AP27: =+AO27 -> 1 | AQ27: =+AO27 -> 1 | AR27: =+AO27 -> 1 | AS27: =+AO27 -> 1 | AT27: =+AS27 -> 1 | AU27: =+AS27 -> 1 | AV27: =+AS27 -> 1 | AW27: =+AS27 -> 1 | AX27: =+AW27 -> 1 | AY27: =+AW27 -> 1 | AZ27: =+AW27 -> 1 | BA27: =+AW27 -> 1 | BB27: =+BA27 -> 1 | BC27: =+BA27 -> 1 | BD27: =+BA27 -> 1 | BE27: =+BA27 -> 1 | BF27: =+BE27 -> 1 | BG27: =+BE27 -> 1 | BH27: =+BE27 -> 1 | BI27: =+BE27 -> 1 | BJ27: =+BI27 -> 1 | BK27: =+BI27 -> 1 | BL27: =+BI27 -> 1 | BM27: =+BI27 -> 1 | BN27: =+BM27 -> 1 | BO27: =+BM27 -> 1 | BP27: =+BM27 -> 1 | BQ27: =+BM27 -> 1 | BR27: =+BQ27 -> 1 | BS27: =+BQ27 -> 1 | BT27: =+BQ27 -> 1 | BU27: =+BQ27 -> 1 | BV27: =+BU27 -> 1 | BW27: =+BU27 -> 1 | BX27: =+BU27 -> 1 | BY27: =+BU27 -> 1 | BZ27: =+BY27 -> 1 | CA27: =+BY27 -> 1 | CB27: =+BY27 -> 1 | CC27: =+BY27 -> 1 | CD27: =+CC27 -> 1 | CE27: =+CC27 -> 1 | CF27: =+CC27 -> 1 | CG27: =+CC27 -> 1 | CH27: =+CG27 -> 1 | CI27: =+CG27 -> 1 | CJ27: =+CG27 -> 1 | CK27: =+CG27 -> 1 | CL27: =+CK27 -> 1 | CM27: =+CK27 -> 1 | CN27: =+CK27 -> 1 | CO27: =+CK27 -> 1 | CP27: =+CO27 -> 1 | CQ27: =+CO27 -> 1 | CR27: =+CO27 -> 1 | CS27: =+CO27 -> 1 | CT27: =+CS27 -> 1 | CU27: =+CS27 -> 1 | CV27: =+CS27 -> 1 | CW27: =+CS27 -> 1 | CX27: =+CW27 -> 1 | CY27: =+CW27 -> 1 | CZ27: =+CW27 -> 1 | DA27: =+CW27 -> 1 | DB27: =+DA27 -> 1 | DC27: =+DA27 -> 1 | DD27: =+DA27 -> 1 | DE27: =+DA27 -> 1 | DF27: =+DE27 -> 1 | DG27: =+DE27 -> 1 | DH27: =+DE27 -> 1 | DI27: =+DE27 -> 1 | DJ27: =+DI27 -> 1 | DK27: =+DI27 -> 1 | DL27: =+DI27 -> 1 | DM27: =+DI27 -> 1 | DN27: =+DM27 -> 1 | DO27: =+DM27 -> 1 | DP27: =+DM27 -> 1 | DQ27: =+DM27 -> 1 | DR27: =+DQ27 -> 1 | DS27: =+DQ27 -> 1 | DT27: =+DQ27 -> 1 | DU27: =+DQ27 -> 1 | DV27: =+DU27 -> 1 | DW27: =+DU27 -> 1 | DX27: =+DU27 -> 1 | DY27: =+DU27 -> 1 | DZ27: =+DY27 -> 1 | EA27: =+DY27 -> 1 | EB27: =+DY27 -> 1 | EC27: =+DY27 -> 1 | ED27: =+EC27 -> 1 | EE27: =+EC27 -> 1 | EF27: =+EC27 -> 1 | EG27: =+EC27 -> 1 | EH27: =+EG27 -> 1 | EI27: =+EG27 -> 1 | EJ27: =+EG27 -> 1 | EK27: =+EG27 -> 1 | EL27: =+EK27 -> 1 | EM27: =+EK27 -> 1 | EN27: =+EK27 -> 1 | EO27: =+EK27 -> 1 | EP27: =+EO27 -> 1 | EQ27: =+EO27 -> 1 | ER27: =+EO27 -> 1 | ES27: =+EO27 -> 1 | ET27: =+schedule_ARAS!EW31 -> 30 | EU27: =+schedule_ARAS!EZ31 -> 13440 | EV27: =+schedule_ARAS!FA31 -> 7200
C28: =+schedule_ARAS!C32 -> Crawler Crane (x5) | D28: Ad | E28: =+schedule_ARAS!E32 -> 5 | N28: =+M28 -> 0 | O28: =+M28 -> 0 | P28: =+M28 -> 0 | Q28: =+M28 -> 0 | R28: =+Q28 -> 0 | S28: =+Q28 -> 0 | T28: =+Q28 -> 0 | U28: =+Q28 -> 0 | V28: =+U28 -> 0 | W28: =+U28 -> 0 | X28: =+U28 -> 0 | Y28: =+U28 -> 0 | Z28: =+Y28 -> 0 | AA28: =+Y28 -> 0 | AB28: =+Y28 -> 0 | AC28: =+Y28 -> 0 | AD28: =+E28 -> 5 | AE28: =+E28 -> 5 | AF28: =+E28 -> 5 | AG28: =+E28 -> 5 | AH28: =+AG28 -> 5 | AI28: =+AG28 -> 5 | AJ28: =+AG28 -> 5 | AK28: =+AG28 -> 5 | AL28: =+AK28 -> 5 | AM28: =+AK28 -> 5 | AN28: =+AK28 -> 5 | AO28: =+AK28 -> 5 | AP28: =+AO28 -> 5 | AQ28: =+AO28 -> 5 | AR28: =+AO28 -> 5 | AS28: =+AO28 -> 5 | AT28: =+AS28 -> 5 | AU28: =+AS28 -> 5 | AV28: =+AS28 -> 5 | AW28: =+AS28 -> 5 | AX28: =+AW28 -> 5 | AY28: =+AW28 -> 5 | AZ28: =+AW28 -> 5 | BA28: =+AW28 -> 5 | BB28: =+BA28 -> 5 | BC28: =+BA28 -> 5 | BD28: =+BA28 -> 5 | BE28: =+BA28 -> 5 | BF28: =+BE28 -> 5 | BG28: =+BE28 -> 5 | BH28: =+BE28 -> 5 | BI28: =+BE28 -> 5 | BJ28: =+BI28 -> 5 | BK28: =+BI28 -> 5 | BL28: =+BI28 -> 5 | BM28: =+BI28 -> 5 | BN28: =+BM28 -> 5 | BO28: =+BM28 -> 5 | BP28: =+BM28 -> 5 | BQ28: =+BM28 -> 5 | BR28: =+BQ28 -> 5 | BS28: =+BQ28 -> 5 | BT28: =+BQ28 -> 5 | BU28: =+BQ28 -> 5 | BV28: =+BU28 -> 5 | BW28: =+BU28 -> 5 | BX28: =+BU28 -> 5 | BY28: =+BU28 -> 5 | BZ28: =+BY28 -> 5 | CA28: =+BY28 -> 5 | CB28: =+BY28 -> 5 | CC28: =+BY28 -> 5 | CD28: =+CC28 -> 5 | CE28: =+CC28 -> 5 | CF28: =+CC28 -> 5 | CG28: =+CC28 -> 5 | CH28: =+CG28 -> 5 | CI28: =+CG28 -> 5 | CJ28: =+CG28 -> 5 | CK28: =+CG28 -> 5 | CL28: =+CK28 -> 5 | CM28: =+CK28 -> 5 | CN28: =+CK28 -> 5 | CO28: =+CK28 -> 5 | CP28: =+CO28 -> 5 | CQ28: =+CO28 -> 5 | CR28: =+CO28 -> 5 | CS28: =+CO28 -> 5 | CT28: =+CS28 -> 5 | CU28: =+CS28 -> 5 | CV28: =+CS28 -> 5 | CW28: =+CS28 -> 5 | CX28: =+CW28 -> 5 | CY28: =+CW28 -> 5 | CZ28: =+CW28 -> 5 | DA28: =+CW28 -> 5 | DB28: =+DA28 -> 5 | DC28: =+DA28 -> 5 | DD28: =+DA28 -> 5 | DE28: =+DA28 -> 5 | DF28: =+DE28 -> 5 | DG28: =+DE28 -> 5 | DH28: =+DE28 -> 5 | DI28: =+DE28 -> 5 | DJ28: =+DI28 -> 5 | DK28: =+DI28 -> 5 | DL28: =+DI28 -> 5 | DM28: =+DI28 -> 5 | DN28: =+DM28 -> 5 | DO28: =+DM28 -> 5 | DP28: =+DM28 -> 5 | DQ28: =+DM28 -> 5 | DR28: =+DQ28 -> 5 | DS28: =+DQ28 -> 5 | DT28: =+DQ28 -> 5 | DU28: =+DQ28 -> 5 | DV28: =+DU28 -> 5 | DW28: =+DU28 -> 5 | DX28: =+DU28 -> 5 | DY28: =+DU28 -> 5 | DZ28: =+DY28 -> 5 | EA28: =+DY28 -> 5 | EB28: =+DY28 -> 5 | EC28: =+DY28 -> 5 | ED28: =+EC28 -> 5 | EE28: =+EC28 -> 5 | EF28: =+EC28 -> 5 | EG28: =+EC28 -> 5 | EH28: =+EG28 -> 5 | EI28: =+EG28 -> 5 | EJ28: =+EG28 -> 5 | EK28: =+EG28 -> 5 | EL28: =+EK28 -> 5 | EM28: =+EK28 -> 5 | EN28: =+EK28 -> 5 | EO28: =+EK28 -> 5 | EP28: =+EO28 -> 5 | EQ28: =+EO28 -> 5 | ER28: =+EO28 -> 5 | ES28: =+EO28 -> 5 | ET28: =+schedule_ARAS!EW32 -> 150 | EU28: =+schedule_ARAS!EZ32 -> 67200 | EV28: =+schedule_ARAS!FA32 -> 36000
C29: =+schedule_ARAS!C33 -> Excavator (x5) | D29: Ad | E29: =+schedule_ARAS!E33 -> 5 | N29: =+M29 -> 0 | O29: =+M29 -> 0 | P29: =+M29 -> 0 | Q29: =+M29 -> 0 | R29: =+Q29 -> 0 | S29: =+Q29 -> 0 | T29: =+Q29 -> 0 | U29: =+Q29 -> 0 | V29: =+U29 -> 0 | W29: =+U29 -> 0 | X29: =+U29 -> 0 | Y29: =+U29 -> 0 | Z29: =+Y29 -> 0 | AA29: =+Y29 -> 0 | AB29: =+Y29 -> 0 | AC29: =+Y29 -> 0 | AD29: =+E29 -> 5 | AE29: =+E29 -> 5 | AF29: =+E29 -> 5 | AG29: =+E29 -> 5 | AH29: =+AG29 -> 5 | AI29: =+AG29 -> 5 | AJ29: =+AG29 -> 5 | AK29: =+AG29 -> 5 | AL29: =+AK29 -> 5 | AM29: =+AK29 -> 5 | AN29: =+AK29 -> 5 | AO29: =+AK29 -> 5 | AP29: =+AO29 -> 5 | AQ29: =+AO29 -> 5 | AR29: =+AO29 -> 5 | AS29: =+AO29 -> 5 | AT29: =+AS29 -> 5 | AU29: =+AS29 -> 5 | AV29: =+AS29 -> 5 | AW29: =+AS29 -> 5 | AX29: =+AW29 -> 5 | AY29: =+AW29 -> 5 | AZ29: =+AW29 -> 5 | BA29: =+AW29 -> 5 | BB29: =+BA29 -> 5 | BC29: =+BA29 -> 5 | BD29: =+BA29 -> 5 | BE29: =+BA29 -> 5 | BF29: =+BE29 -> 5 | BG29: =+BE29 -> 5 | BH29: =+BE29 -> 5 | BI29: =+BE29 -> 5 | BJ29: =+BI29 -> 5 | BK29: =+BI29 -> 5 | BL29: =+BI29 -> 5 | BM29: =+BI29 -> 5 | BN29: =+BM29 -> 5 | BO29: =+BM29 -> 5 | BP29: =+BM29 -> 5 | BQ29: =+BM29 -> 5 | BR29: =+BQ29 -> 5 | BS29: =+BQ29 -> 5 | BT29: =+BQ29 -> 5 | BU29: =+BQ29 -> 5 | BV29: =+BU29 -> 5 | BW29: =+BU29 -> 5 | BX29: =+BU29 -> 5 | BY29: =+BU29 -> 5 | BZ29: =+BY29 -> 5 | CA29: =+BY29 -> 5 | CB29: =+BY29 -> 5 | CC29: =+BY29 -> 5 | CD29: =+CC29 -> 5 | CE29: =+CC29 -> 5 | CF29: =+CC29 -> 5 | CG29: =+CC29 -> 5 | CH29: =+CG29 -> 5 | CI29: =+CG29 -> 5 | CJ29: =+CG29 -> 5 | CK29: =+CG29 -> 5 | CL29: =+CK29 -> 5 | CM29: =+CK29 -> 5 | CN29: =+CK29 -> 5 | CO29: =+CK29 -> 5 | CP29: =+CO29 -> 5 | CQ29: =+CO29 -> 5 | CR29: =+CO29 -> 5 | CS29: =+CO29 -> 5 | CT29: =+CS29 -> 5 | CU29: =+CS29 -> 5 | CV29: =+CS29 -> 5 | CW29: =+CS29 -> 5 | CX29: =+CW29 -> 5 | CY29: =+CW29 -> 5 | CZ29: =+CW29 -> 5 | DA29: =+CW29 -> 5 | DB29: =+DA29 -> 5 | DC29: =+DA29 -> 5 | DD29: =+DA29 -> 5 | DE29: =+DA29 -> 5 | DF29: =+DE29 -> 5 | DG29: =+DE29 -> 5 | DH29: =+DE29 -> 5 | DI29: =+DE29 -> 5 | DJ29: =+DI29 -> 5 | DK29: =+DI29 -> 5 | DL29: =+DI29 -> 5 | DM29: =+DI29 -> 5 | DN29: =+DM29 -> 5 | DO29: =+DM29 -> 5 | DP29: =+DM29 -> 5 | DQ29: =+DM29 -> 5 | DR29: =+DQ29 -> 5 | DS29: =+DQ29 -> 5 | DT29: =+DQ29 -> 5 | DU29: =+DQ29 -> 5 | DV29: =+DU29 -> 5 | DW29: =+DU29 -> 5 | DX29: =+DU29 -> 5 | DY29: =+DU29 -> 5 | DZ29: =+DY29 -> 5 | EA29: =+DY29 -> 5 | EB29: =+DY29 -> 5 | EC29: =+DY29 -> 5 | ED29: =+EC29 -> 5 | EE29: =+EC29 -> 5 | EF29: =+EC29 -> 5 | EG29: =+EC29 -> 5 | EH29: =+EG29 -> 5 | EI29: =+EG29 -> 5 | EJ29: =+EG29 -> 5 | EK29: =+EG29 -> 5 | EL29: =+EK29 -> 5 | EM29: =+EK29 -> 5 | EN29: =+EK29 -> 5 | EO29: =+EK29 -> 5 | EP29: =+EO29 -> 5 | EQ29: =+EO29 -> 5 | ER29: =+EO29 -> 5 | ES29: =+EO29 -> 5 | ET29: =+schedule_ARAS!EW33 -> 150 | EU29: =+schedule_ARAS!EZ33 -> 67200 | EV29: =+schedule_ARAS!FA33 -> 36000
C30: =+schedule_ARAS!C34 -> Loader (x3) | D30: Ad | E30: =+schedule_ARAS!E34 -> 3 | N30: =+M30 -> 0 | O30: =+M30 -> 0 | P30: =+M30 -> 0 | Q30: =+M30 -> 0 | R30: =+Q30 -> 0 | S30: =+Q30 -> 0 | T30: =+Q30 -> 0 | U30: =+Q30 -> 0 | V30: =+U30 -> 0 | W30: =+U30 -> 0 | X30: =+U30 -> 0 | Y30: =+U30 -> 0 | Z30: =+Y30 -> 0 | AA30: =+Y30 -> 0 | AB30: =+Y30 -> 0 | AC30: =+Y30 -> 0 | AD30: =+E30 -> 3 | AE30: =+E30 -> 3 | AF30: =+E30 -> 3 | AG30: =+E30 -> 3 | AH30: =+AG30 -> 3 | AI30: =+AG30 -> 3 | AJ30: =+AG30 -> 3 | AK30: =+AG30 -> 3 | AL30: =+AK30 -> 3 | AM30: =+AK30 -> 3 | AN30: =+AK30 -> 3 | AO30: =+AK30 -> 3 | AP30: =+AO30 -> 3 | AQ30: =+AO30 -> 3 | AR30: =+AO30 -> 3 | AS30: =+AO30 -> 3 | AT30: =+AS30 -> 3 | AU30: =+AS30 -> 3 | AV30: =+AS30 -> 3 | AW30: =+AS30 -> 3 | AX30: =+AW30 -> 3 | AY30: =+AW30 -> 3 | AZ30: =+AW30 -> 3 | BA30: =+AW30 -> 3 | BB30: =+BA30 -> 3 | BC30: =+BA30 -> 3 | BD30: =+BA30 -> 3 | BE30: =+BA30 -> 3 | BF30: =+BE30 -> 3 | BG30: =+BE30 -> 3 | BH30: =+BE30 -> 3 | BI30: =+BE30 -> 3 | BJ30: =+BI30 -> 3 | BK30: =+BI30 -> 3 | BL30: =+BI30 -> 3 | BM30: =+BI30 -> 3 | BN30: =+BM30 -> 3 | BO30: =+BM30 -> 3 | BP30: =+BM30 -> 3 | BQ30: =+BM30 -> 3 | BR30: =+BQ30 -> 3 | BS30: =+BQ30 -> 3 | BT30: =+BQ30 -> 3 | BU30: =+BQ30 -> 3 | BV30: =+BU30 -> 3 | BW30: =+BU30 -> 3 | BX30: =+BU30 -> 3 | BY30: =+BU30 -> 3 | BZ30: =+BY30 -> 3 | CA30: =+BY30 -> 3 | CB30: =+BY30 -> 3 | CC30: =+BY30 -> 3 | CD30: =+CC30 -> 3 | CE30: =+CC30 -> 3 | CF30: =+CC30 -> 3 | CG30: =+CC30 -> 3 | CH30: =+CG30 -> 3 | CI30: =+CG30 -> 3 | CJ30: =+CG30 -> 3 | CK30: =+CG30 -> 3 | CL30: =+CK30 -> 3 | CM30: =+CK30 -> 3 | CN30: =+CK30 -> 3 | CO30: =+CK30 -> 3 | CP30: =+CO30 -> 3 | CQ30: =+CO30 -> 3 | CR30: =+CO30 -> 3 | CS30: =+CO30 -> 3 | CT30: =+CS30 -> 3 | CU30: =+CS30 -> 3 | CV30: =+CS30 -> 3 | CW30: =+CS30 -> 3 | CX30: =+CW30 -> 3 | CY30: =+CW30 -> 3 | CZ30: =+CW30 -> 3 | DA30: =+CW30 -> 3 | DB30: =+DA30 -> 3 | DC30: =+DA30 -> 3 | DD30: =+DA30 -> 3 | DE30: =+DA30 -> 3 | DF30: =+DE30 -> 3 | DG30: =+DE30 -> 3 | DH30: =+DE30 -> 3 | DI30: =+DE30 -> 3 | DJ30: =+DI30 -> 3 | DK30: =+DI30 -> 3 | DL30: =+DI30 -> 3 | DM30: =+DI30 -> 3 | DN30: =+DM30 -> 3 | DO30: =+DM30 -> 3 | DP30: =+DM30 -> 3 | DQ30: =+DM30 -> 3 | DR30: =+DQ30 -> 3 | DS30: =+DQ30 -> 3 | DT30: =+DQ30 -> 3 | DU30: =+DQ30 -> 3 | DV30: =+DU30 -> 3 | DW30: =+DU30 -> 3 | DX30: =+DU30 -> 3 | DY30: =+DU30 -> 3 | DZ30: =+DY30 -> 3 | EA30: =+DY30 -> 3 | EB30: =+DY30 -> 3 | EC30: =+DY30 -> 3 | ED30: =+EC30 -> 3 | EE30: =+EC30 -> 3 | EF30: =+EC30 -> 3 | EG30: =+EC30 -> 3 | EH30: =+EG30 -> 3 | EI30: =+EG30 -> 3 | EJ30: =+EG30 -> 3 | EK30: =+EG30 -> 3 | EL30: =+EK30 -> 3 | EM30: =+EK30 -> 3 | EN30: =+EK30 -> 3 | EO30: =+EK30 -> 3 | EP30: =+EO30 -> 3 | EQ30: =+EO30 -> 3 | ER30: =+EO30 -> 3 | ES30: =+EO30 -> 3 | ET30: =+schedule_ARAS!EW34 -> 90 | EU30: =+schedule_ARAS!EZ34 -> 40320 | EV30: =+schedule_ARAS!FA34 -> 21600
C31: =+schedule_ARAS!C35 -> Cylinder (x2) | D31: Ad | E31: =+schedule_ARAS!E35 -> 2 | N31: =+M31 -> 0 | O31: =+M31 -> 0 | P31: =+M31 -> 0 | Q31: =+M31 -> 0 | R31: =+Q31 -> 0 | S31: =+Q31 -> 0 | T31: =+Q31 -> 0 | U31: =+Q31 -> 0 | V31: =+U31 -> 0 | W31: =+U31 -> 0 | X31: =+U31 -> 0 | Y31: =+U31 -> 0 | Z31: =+Y31 -> 0 | AA31: =+Y31 -> 0 | AB31: =+Y31 -> 0 | AC31: =+Y31 -> 0 | AD31: =+E31 -> 2 | AE31: =+E31 -> 2 | AF31: =+E31 -> 2 | AG31: =+E31 -> 2 | AH31: =+AG31 -> 2 | AI31: =+AG31 -> 2 | AJ31: =+AG31 -> 2 | AK31: =+AG31 -> 2 | AL31: =+AK31 -> 2 | AM31: =+AK31 -> 2 | AN31: =+AK31 -> 2 | AO31: =+AK31 -> 2 | AP31: =+AO31 -> 2 | AQ31: =+AO31 -> 2 | AR31: =+AO31 -> 2 | AS31: =+AO31 -> 2 | AT31: =+AS31 -> 2 | AU31: =+AS31 -> 2 | AV31: =+AS31 -> 2 | AW31: =+AS31 -> 2 | AX31: =+AW31 -> 2 | AY31: =+AW31 -> 2 | AZ31: =+AW31 -> 2 | BA31: =+AW31 -> 2 | BB31: =+BA31 -> 2 | BC31: =+BA31 -> 2 | BD31: =+BA31 -> 2 | BE31: =+BA31 -> 2 | BF31: =+BE31 -> 2 | BG31: =+BE31 -> 2 | BH31: =+BE31 -> 2 | BI31: =+BE31 -> 2 | BJ31: =+BI31 -> 2 | BK31: =+BI31 -> 2 | BL31: =+BI31 -> 2 | BM31: =+BI31 -> 2 | BN31: =+BM31 -> 2 | BO31: =+BM31 -> 2 | BP31: =+BM31 -> 2 | BQ31: =+BM31 -> 2 | BR31: =+BQ31 -> 2 | BS31: =+BQ31 -> 2 | BT31: =+BQ31 -> 2 | BU31: =+BQ31 -> 2 | BV31: =+BU31 -> 2 | BW31: =+BU31 -> 2 | BX31: =+BU31 -> 2 | BY31: =+BU31 -> 2 | BZ31: =+BY31 -> 2 | CA31: =+BY31 -> 2 | CB31: =+BY31 -> 2 | CC31: =+BY31 -> 2 | CD31: =+CC31 -> 2 | CE31: =+CC31 -> 2 | CF31: =+CC31 -> 2 | CG31: =+CC31 -> 2 | CH31: =+CG31 -> 2 | CI31: =+CG31 -> 2 | CJ31: =+CG31 -> 2 | CK31: =+CG31 -> 2 | CL31: =+CK31 -> 2 | CM31: =+CK31 -> 2 | CN31: =+CK31 -> 2 | CO31: =+CK31 -> 2 | CP31: =+CO31 -> 2 | CQ31: =+CO31 -> 2 | CR31: =+CO31 -> 2 | CS31: =+CO31 -> 2 | CT31: =+CS31 -> 2 | CU31: =+CS31 -> 2 | CV31: =+CS31 -> 2 | CW31: =+CS31 -> 2 | CX31: =+CW31 -> 2 | CY31: =+CW31 -> 2 | CZ31: =+CW31 -> 2 | DA31: =+CW31 -> 2 | DB31: =+DA31 -> 2 | DC31: =+DA31 -> 2 | DD31: =+DA31 -> 2 | DE31: =+DA31 -> 2 | DF31: =+DE31 -> 2 | DG31: =+DE31 -> 2 | DH31: =+DE31 -> 2 | DI31: =+DE31 -> 2 | DJ31: =+DI31 -> 2 | DK31: =+DI31 -> 2 | DL31: =+DI31 -> 2 | DM31: =+DI31 -> 2 | DN31: =+DM31 -> 2 | DO31: =+DM31 -> 2 | DP31: =+DM31 -> 2 | DQ31: =+DM31 -> 2 | DR31: =+DQ31 -> 2 | DS31: =+DQ31 -> 2 | DT31: =+DQ31 -> 2 | DU31: =+DQ31 -> 2 | DV31: =+DU31 -> 2 | DW31: =+DU31 -> 2 | DX31: =+DU31 -> 2 | DY31: =+DU31 -> 2 | DZ31: =+DY31 -> 2 | EA31: =+DY31 -> 2 | EB31: =+DY31 -> 2 | EC31: =+DY31 -> 2 | ED31: =+EC31 -> 2 | EE31: =+EC31 -> 2 | EF31: =+EC31 -> 2 | EG31: =+EC31 -> 2 | EH31: =+EG31 -> 2 | EI31: =+EG31 -> 2 | EJ31: =+EG31 -> 2 | EK31: =+EG31 -> 2 | EL31: =+EK31 -> 2 | EM31: =+EK31 -> 2 | EN31: =+EK31 -> 2 | EO31: =+EK31 -> 2 | EP31: =+EO31 -> 2 | EQ31: =+EO31 -> 2 | ER31: =+EO31 -> 2 | ES31: =+EO31 -> 2 | ET31: =+schedule_ARAS!EW35 -> 60 | EU31: =+schedule_ARAS!EZ35 -> 26880 | EV31: =+schedule_ARAS!FA35 -> 14400
C32: =+schedule_ARAS!C36 -> Dump Truck (x20) | D32: Ad | E32: =+schedule_ARAS!E36 -> 20 | N32: =+M32 -> 0 | O32: =+M32 -> 0 | P32: =+M32 -> 0 | Q32: =+M32 -> 0 | R32: =+Q32 -> 0 | S32: =+Q32 -> 0 | T32: =+Q32 -> 0 | U32: =+Q32 -> 0 | V32: =+U32 -> 0 | W32: =+U32 -> 0 | X32: =+U32 -> 0 | Y32: =+U32 -> 0 | Z32: =+Y32 -> 0 | AA32: =+Y32 -> 0 | AB32: =+Y32 -> 0 | AC32: =+Y32 -> 0 | AD32: =+E32 -> 20 | AE32: =+E32 -> 20 | AF32: =+E32 -> 20 | AG32: =+E32 -> 20 | AH32: =+AG32 -> 20 | AI32: =+AG32 -> 20 | AJ32: =+AG32 -> 20 | AK32: =+AG32 -> 20 | AL32: =+AK32 -> 20 | AM32: =+AK32 -> 20 | AN32: =+AK32 -> 20 | AO32: =+AK32 -> 20 | AP32: =+AO32 -> 20 | AQ32: =+AO32 -> 20 | AR32: =+AO32 -> 20 | AS32: =+AO32 -> 20 | AT32: =+AS32 -> 20 | AU32: =+AS32 -> 20 | AV32: =+AS32 -> 20 | AW32: =+AS32 -> 20 | AX32: =+AW32 -> 20 | AY32: =+AW32 -> 20 | AZ32: =+AW32 -> 20 | BA32: =+AW32 -> 20 | BB32: =+BA32 -> 20 | BC32: =+BA32 -> 20 | BD32: =+BA32 -> 20 | BE32: =+BA32 -> 20 | BF32: =+BE32 -> 20 | BG32: =+BE32 -> 20 | BH32: =+BE32 -> 20 | BI32: =+BE32 -> 20 | BJ32: =+BI32 -> 20 | BK32: =+BI32 -> 20 | BL32: =+BI32 -> 20 | BM32: =+BI32 -> 20 | BN32: =+BM32 -> 20 | BO32: =+BM32 -> 20 | BP32: =+BM32 -> 20 | BQ32: =+BM32 -> 20 | BR32: =+BQ32 -> 20 | BS32: =+BQ32 -> 20 | BT32: =+BQ32 -> 20 | BU32: =+BQ32 -> 20 | BV32: =+BU32 -> 20 | BW32: =+BU32 -> 20 | BX32: =+BU32 -> 20 | BY32: =+BU32 -> 20 | BZ32: =+BY32 -> 20 | CA32: =+BY32 -> 20 | CB32: =+BY32 -> 20 | CC32: =+BY32 -> 20 | CD32: =+CC32 -> 20 | CE32: =+CC32 -> 20 | CF32: =+CC32 -> 20 | CG32: =+CC32 -> 20 | CH32: =+CG32 -> 20 | CI32: =+CG32 -> 20 | CJ32: =+CG32 -> 20 | CK32: =+CG32 -> 20 | CL32: =+CK32 -> 20 | CM32: =+CK32 -> 20 | CN32: =+CK32 -> 20 | CO32: =+CK32 -> 20 | CP32: =+CO32 -> 20 | CQ32: =+CO32 -> 20 | CR32: =+CO32 -> 20 | CS32: =+CO32 -> 20 | CT32: =+CS32 -> 20 | CU32: =+CS32 -> 20 | CV32: =+CS32 -> 20 | CW32: =+CS32 -> 20 | CX32: =+CW32 -> 20 | CY32: =+CW32 -> 20 | CZ32: =+CW32 -> 20 | DA32: =+CW32 -> 20 | DB32: =+DA32 -> 20 | DC32: =+DA32 -> 20 | DD32: =+DA32 -> 20 | DE32: =+DA32 -> 20 | DF32: =+DE32 -> 20 | DG32: =+DE32 -> 20 | DH32: =+DE32 -> 20 | DI32: =+DE32 -> 20 | DJ32: =+DI32 -> 20 | DK32: =+DI32 -> 20 | DL32: =+DI32 -> 20 | DM32: =+DI32 -> 20 | DN32: =+DM32 -> 20 | DO32: =+DM32 -> 20 | DP32: =+DM32 -> 20 | DQ32: =+DM32 -> 20 | DR32: =+DQ32 -> 20 | DS32: =+DQ32 -> 20 | DT32: =+DQ32 -> 20 | DU32: =+DQ32 -> 20 | DV32: =+DU32 -> 20 | DW32: =+DU32 -> 20 | DX32: =+DU32 -> 20 | DY32: =+DU32 -> 20 | DZ32: =+DY32 -> 20 | EA32: =+DY32 -> 20 | EB32: =+DY32 -> 20 | EC32: =+DY32 -> 20 | ED32: =+EC32 -> 20 | EE32: =+EC32 -> 20 | EF32: =+EC32 -> 20 | EG32: =+EC32 -> 20 | EH32: =+EG32 -> 20 | EI32: =+EG32 -> 20 | EJ32: =+EG32 -> 20 | EK32: =+EG32 -> 20 | EL32: =+EK32 -> 20 | EM32: =+EK32 -> 20 | EN32: =+EK32 -> 20 | EO32: =+EK32 -> 20 | EP32: =+EO32 -> 20 | EQ32: =+EO32 -> 20 | ER32: =+EO32 -> 20 | ES32: =+EO32 -> 20 | ET32: =+schedule_ARAS!EW36 -> 600 | EU32: =+schedule_ARAS!EZ36 -> 268800 | EV32: =+schedule_ARAS!FA36 -> 144000
C39: TOTAL DIRECT MACHINERY: | ET39: =SUM(ET19:ET38) -> 1440 | EU39: =SUM(EU19:EU38) -> 645120 | EV39: =SUM(EV19:EV20) -> 14400
C40: INDIRECT MACHINERY
C41: =+schedule_ARAS!C55 -> Car | D41: Ad | E41: =+schedule_ARAS!E55 -> 2 | AD41: =+E41 -> 2 | AE41: =+E41 -> 2 | AF41: =+E41 -> 2 | AG41: =+E41 -> 2 | AH41: =+E41 -> 2 | AI41: =+E41 -> 2 | AJ41: =+E41 -> 2 | AK41: =+E41 -> 2 | AL41: =+E41 -> 2 | AM41: =+E41 -> 2 | AN41: =+E41 -> 2 | AO41: =+E41 -> 2 | AP41: =+E41 -> 2 | AQ41: =+E41 -> 2 | AR41: =+E41 -> 2 | AS41: =+E41 -> 2 | AT41: =+E41 -> 2 | AU41: =+E41 -> 2 | AV41: =+E41 -> 2 | AW41: =+E41 -> 2 | AX41: =+AG41 -> 2 | AY41: =+AG41 -> 2 | AZ41: =+AG41 -> 2 | BA41: =+AG41 -> 2 | BB41: =+AK41 -> 2 | BC41: =+AK41 -> 2 | BD41: =+AK41 -> 2 | BE41: =+AK41 -> 2 | BF41: =+AO41 -> 2 | BG41: =+AO41 -> 2 | BH41: =+AO41 -> 2 | BI41: =+AO41 -> 2 | BJ41: =+AS41 -> 2 | BK41: =+AS41 -> 2 | BL41: =+AS41 -> 2 | BM41: =+AS41 -> 2 | BN41: =+AW41 -> 2 | BO41: =+AW41 -> 2 | BP41: =+AW41 -> 2 | BQ41: =+AW41 -> 2 | BR41: =+BA41 -> 2 | BS41: =+BA41 -> 2 | BT41: =+BA41 -> 2 | BU41: =+BA41 -> 2 | BV41: =+BE41 -> 2 | BW41: =+BE41 -> 2 | BX41: =+BE41 -> 2 | BY41: =+BE41 -> 2 | BZ41: =+BI41 -> 2 | CA41: =+BI41 -> 2 | CB41: =+BI41 -> 2 | CC41: =+BI41 -> 2 | CD41: =+BM41 -> 2 | CE41: =+BM41 -> 2 | CF41: =+BM41 -> 2 | CG41: =+BM41 -> 2 | CH41: =+BQ41 -> 2 | CI41: =+BQ41 -> 2 | CJ41: =+BQ41 -> 2 | CK41: =+BQ41 -> 2 | CL41: =+BU41 -> 2 | CM41: =+BU41 -> 2 | CN41: =+BU41 -> 2 | CO41: =+BU41 -> 2 | CP41: =+BY41 -> 2 | CQ41: =+BY41 -> 2 | CR41: =+BY41 -> 2 | CS41: =+BY41 -> 2 | CT41: =+CC41 -> 2 | CU41: =+CC41 -> 2 | CV41: =+CC41 -> 2 | CW41: =+CC41 -> 2 | ET41: =+schedule_ARAS!EW55 -> 38 | EU41: =+schedule_ARAS!EZ55 -> 17024 | EV41: =+schedule_ARAS!FA55 -> 9120
C42: =+schedule_ARAS!C56 -> Pick-Up | D42: Ad | E42: =+schedule_ARAS!E56 -> 2 | AD42: =+E42 -> 2 | AE42: =+E42 -> 2 | AF42: =+E42 -> 2 | AG42: =+E42 -> 2 | AH42: =+E42 -> 2 | AI42: =+E42 -> 2 | AJ42: =+E42 -> 2 | AK42: =+E42 -> 2 | AL42: =+E42 -> 2 | AM42: =+E42 -> 2 | AN42: =+E42 -> 2 | AO42: =+E42 -> 2 | AP42: =+E42 -> 2 | AQ42: =+E42 -> 2 | AR42: =+E42 -> 2 | AS42: =+E42 -> 2 | AT42: =+E42 -> 2 | AU42: =+E42 -> 2 | AV42: =+E42 -> 2 | AW42: =+E42 -> 2 | AX42: =+AG42 -> 2 | AY42: =+AG42 -> 2 | AZ42: =+AG42 -> 2 | BA42: =+AG42 -> 2 | BB42: =+AK42 -> 2 | BC42: =+AK42 -> 2 | BD42: =+AK42 -> 2 | BE42: =+AK42 -> 2 | BF42: =+AO42 -> 2 | BG42: =+AO42 -> 2 | BH42: =+AO42 -> 2 | BI42: =+AO42 -> 2 | BJ42: =+AS42 -> 2 | BK42: =+AS42 -> 2 | BL42: =+AS42 -> 2 | BM42: =+AS42 -> 2 | BN42: =+AW42 -> 2 | BO42: =+AW42 -> 2 | BP42: =+AW42 -> 2 | BQ42: =+AW42 -> 2 | BR42: =+BA42 -> 2 | BS42: =+BA42 -> 2 | BT42: =+BA42 -> 2 | BU42: =+BA42 -> 2 | BV42: =+BE42 -> 2 | BW42: =+BE42 -> 2 | BX42: =+BE42 -> 2 | BY42: =+BE42 -> 2 | BZ42: =+BI42 -> 2 | CA42: =+BI42 -> 2 | CB42: =+BI42 -> 2 | CC42: =+BI42 -> 2 | CD42: =+BM42 -> 2 | CE42: =+BM42 -> 2 | CF42: =+BM42 -> 2 | CG42: =+BM42 -> 2 | CH42: =+BQ42 -> 2 | CI42: =+BQ42 -> 2 | CJ42: =+BQ42 -> 2 | CK42: =+BQ42 -> 2 | CL42: =+BU42 -> 2 | CM42: =+BU42 -> 2 | CN42: =+BU42 -> 2 | CO42: =+BU42 -> 2 | CP42: =+BY42 -> 2 | CQ42: =+BY42 -> 2 | CR42: =+BY42 -> 2 | CS42: =+BY42 -> 2 | CT42: =+CC42 -> 2 | CU42: =+CC42 -> 2 | CV42: =+CC42 -> 2 | CW42: =+CC42 -> 2 | ET42: =+schedule_ARAS!EW56 -> 38 | EU42: =+schedule_ARAS!EZ56 -> 17024 | EV42: =+schedule_ARAS!FA56 -> 9120
C43: =+schedule_ARAS!C57 -> Mini-bus | D43: Ad | E43: =+schedule_ARAS!E57 -> 2 | AD43: =+E43 -> 2 | AE43: =+E43 -> 2 | AF43: =+E43 -> 2 | AG43: =+E43 -> 2 | AH43: =+E43 -> 2 | AI43: =+E43 -> 2 | AJ43: =+E43 -> 2 | AK43: =+E43 -> 2 | AL43: =+E43 -> 2 | AM43: =+E43 -> 2 | AN43: =+E43 -> 2 | AO43: =+E43 -> 2 | AP43: =+E43 -> 2 | AQ43: =+E43 -> 2 | AR43: =+E43 -> 2 | AS43: =+E43 -> 2 | AT43: =+E43 -> 2 | AU43: =+E43 -> 2 | AV43: =+E43 -> 2 | AW43: =+E43 -> 2 | AX43: =+AG43 -> 2 | AY43: =+AG43 -> 2 | AZ43: =+AG43 -> 2 | BA43: =+AG43 -> 2 | BB43: =+AK43 -> 2 | BC43: =+AK43 -> 2 | BD43: =+AK43 -> 2 | BE43: =+AK43 -> 2 | BF43: =+AO43 -> 2 | BG43: =+AO43 -> 2 | BH43: =+AO43 -> 2 | BI43: =+AO43 -> 2 | BJ43: =+AS43 -> 2 | BK43: =+AS43 -> 2 | BL43: =+AS43 -> 2 | BM43: =+AS43 -> 2 | BN43: =+AW43 -> 2 | BO43: =+AW43 -> 2 | BP43: =+AW43 -> 2 | BQ43: =+AW43 -> 2 | BR43: =+BA43 -> 2 | BS43: =+BA43 -> 2 | BT43: =+BA43 -> 2 | BU43: =+BA43 -> 2 | BV43: =+BE43 -> 2 | BW43: =+BE43 -> 2 | BX43: =+BE43 -> 2 | BY43: =+BE43 -> 2 | BZ43: =+BI43 -> 2 | CA43: =+BI43 -> 2 | CB43: =+BI43 -> 2 | CC43: =+BI43 -> 2 | CD43: =+BM43 -> 2 | CE43: =+BM43 -> 2 | CF43: =+BM43 -> 2 | CG43: =+BM43 -> 2 | CH43: =+BQ43 -> 2 | CI43: =+BQ43 -> 2 | CJ43: =+BQ43 -> 2 | CK43: =+BQ43 -> 2 | CL43: =+BU43 -> 2 | CM43: =+BU43 -> 2 | CN43: =+BU43 -> 2 | CO43: =+BU43 -> 2 | CP43: =+BY43 -> 2 | CQ43: =+BY43 -> 2 | CR43: =+BY43 -> 2 | CS43: =+BY43 -> 2 | CT43: =+CC43 -> 2 | CU43: =+CC43 -> 2 | CV43: =+CC43 -> 2 | CW43: =+CC43 -> 2 | ET43: =+schedule_ARAS!EW57 -> 38 | EU43: =+schedule_ARAS!EZ57 -> 17024 | EV43: =+schedule_ARAS!FA57 -> 9120
ET44: =SUM(F44:DA44)/4 -> 0
ET45: =SUM(F45:DA45)/4 -> 0
ET46: =SUM(F46:DA46)/4 -> 0
C47: =+schedule_ARAS!C58 -> 0 | D47: =+schedule_ARAS!D58 -> 0 | ET47: =SUM(F47:DA47)/4 -> 0 | EU47: =+schedule_ARAS!EZ58 -> 0 | EV47: =+schedule_ARAS!FA58 -> 0
ET51: =SUM(F51:DA51)/4 -> 0
ET52: =SUM(F52:DA52)/4 -> 0
ET53: =SUM(F53:DA53)/4 -> 0
ET54: =SUM(F54:DA54)/4 -> 0
ET55: =SUM(F55:DA55)/4 -> 0
ET56: =SUM(F56:DA56)/4 -> 0
C62: TOTAL INDIRECT MACHINERY: | ET62: =SUM(ET41:ET46) -> 114 | EU62: =SUM(EU41:EU46) -> 51072 | EV62: =SUM(EV40:EV46) -> 27360
C63: TOTAL MACHINERY: | ET63: =+ET62+ET39 -> 1554 | EU63: =+EU62+EU39 -> 696192 | EV63: =+EV62+EV39 -> 41760

Sheet Manpower Histogram
C1: WORK SCHEDULE VERSUS RESOURCE CHART
C2: PROJECT NAME: | D2: =+schedule_ARAS!D2 -> FİLYOS LİMANI TAHKİMAT İŞİ
C3: PROJECT DURATION: | D3: =+schedule_ARAS!D3 -> 36 | E3: Months
B5: S.NO. | C5: WORK DESCRIPTION | D5: UNIT | E5: QTY. | F5: Capacity (per day) | G5: Duration (Machine/Man.Month) | H5: Month-1 | L5: Month-2 | P5: Month-3 | T5: Month-4 | X5: Month-5 | AB5: Month-6 | AF5: Month-7 | AJ5: Month-8 | AN5: Month-9 | AR5: Month-10 | AV5: Month-11 | AZ5: Month-12 | BD5: Month-13 | BH5: Month-14 | BL5: Month-15 | BP5: Month-16 | BT5: Month-17 | BX5: Month-18 | CB5: Month-19 | CF5: Month-20 | CJ5: Month-21 | CN5: Month-22 | CR5: Month-23 | CV5: Month-24 | CZ5: Month-25 | DD5: Month-26 | DH5: Month-27 | DL5: Month-28 | DP5: Month-29 | DT5: Month-30 | DX5: Month-31 | EB5: Month-32 | EF5: Month-33 | EJ5: Month-34 | EN5: Month-35 | ER5: Month-36
C6: DIRECT PERSONNEL
C7: =+schedule_ARAS!C43 -> Formen | D7: Ad | E7: =+schedule_ARAS!E43 -> 6 | AF7: =+E7 -> 6 | AG7: =+E7 -> 6 | AH7: =+E7 -> 6 | AI7: =+E7 -> 6 | AJ7: =+E7 -> 6 | AK7: =+E7 -> 6 | AL7: =+E7 -> 6 | AM7: =+E7 -> 6 | AN7: =+E7 -> 6 | AO7: =+E7 -> 6 | AP7: =+E7 -> 6 | AQ7: =+E7 -> 6 | AR7: =+E7 -> 6 | AS7: =+E7 -> 6 | AT7: =+E7 -> 6 | AU7: =+E7 -> 6 | AV7: =+E7 -> 6 | AW7: =+E7 -> 6 | AX7: =+E7 -> 6 | AY7: =+E7 -> 6 | AZ7: =+AG7 -> 6 | BA7: =+AG7 -> 6 | BB7: =+AG7 -> 6 | BC7: =+AG7 -> 6 | BD7: =+AK7 -> 6 | BE7: =+AK7 -> 6 | BF7: =+AK7 -> 6 | BG7: =+AK7 -> 6 | BH7: =+AO7 -> 6 | BI7: =+AO7 -> 6 | BJ7: =+AO7 -> 6 | BK7: =+AO7 -> 6 | BL7: =+AS7 -> 6 | BM7: =+AS7 -> 6 | BN7: =+AS7 -> 6 | BO7: =+AS7 -> 6 | BP7: =+AW7 -> 6 | BQ7: =+AW7 -> 6 | BR7: =+AW7 -> 6 | BS7: =+AW7 -> 6 | BT7: =+BA7 -> 6 | BU7: =+BA7 -> 6 | BV7: =+BA7 -> 6 | BW7: =+BA7 -> 6 | BX7: =+BE7 -> 6 | BY7: =+BE7 -> 6 | BZ7: =+BE7 -> 6 | CA7: =+BE7 -> 6 | CB7: =+BI7 -> 6 | CC7: =+BI7 -> 6 | CD7: =+BI7 -> 6 | CE7: =+BI7 -> 6 | CF7: =+BM7 -> 6 | CG7: =+BM7 -> 6 | CH7: =+BM7 -> 6 | CI7: =+BM7 -> 6 | CJ7: =+BQ7 -> 6 | CK7: =+BQ7 -> 6 | CL7: =+BQ7 -> 6 | CM7: =+BQ7 -> 6 | CN7: =+BU7 -> 6 | CO7: =+BU7 -> 6 | CP7: =+BU7 -> 6 | CQ7: =+BU7 -> 6 | CR7: =+BY7 -> 6 | CS7: =+BY7 -> 6 | CT7: =+BY7 -> 6 | CU7: =+BY7 -> 6 | CV7: =+CC7 -> 6 | CW7: =+CC7 -> 6 | CX7: =+CC7 -> 6 | CY7: =+CC7 -> 6 | CZ7: =+BY7 -> 6 | DA7: =+BY7 -> 6 | DB7: =+BY7 -> 6 | DC7: =+BY7 -> 6 | DD7: =+BY7 -> 6 | DE7: =+BY7 -> 6 | DF7: =+BY7 -> 6 | DG7: =+BY7 -> 6 | DH7: =+CC7 -> 6 | DI7: =+CC7 -> 6 | DJ7: =+CC7 -> 6 | DK7: =+CC7 -> 6 | DL7: =+CG7 -> 6 | DM7: =+CG7 -> 6 | DN7: =+CG7 -> 6 | DO7: =+CG7 -> 6 | DP7: =+CK7 -> 6 | DQ7: =+CK7 -> 6 | DR7: =+CK7 -> 6 | DS7: =+CK7 -> 6 | DT7: =+CO7 -> 6 | DU7: =+CO7 -> 6 | DV7: =+CO7 -> 6 | DW7: =+CO7 -> 6 | DX7: =+CS7 -> 6 | DY7: =+CS7 -> 6 | DZ7: =+CS7 -> 6 | EA7: =+CS7 -> 6 | EB7: =+CW7 -> 6 | EC7: =+CW7 -> 6 | ED7: =+CW7 -> 6 | EE7: =+CW7 -> 6 | EF7: =+DA7 -> 6 | EG7: =+DA7 -> 6 | EH7: =+DA7 -> 6 | EI7: =+DA7 -> 6 | EJ7: =+DE7 -> 6 | EK7: =+DE7 -> 6 | EL7: =+DE7 -> 6 | EM7: =+DE7 -> 6 | EN7: =+DI7 -> 6 | EO7: =+DI7 -> 6 | EP7: =+DI7 -> 6 | EQ7: =+DI7 -> 6 | ER7: =+DM7 -> 6 | ES7: =+DM7 -> 6 | ET7: =+DM7 -> 6 | EU7: =+DM7 -> 6 | EV7: =SUM(H7:DC7)/4 -> 114
C8: =+schedule_ARAS!C44 -> Operator | D8: Ad | E8: =+schedule_ARAS!E44 -> 21 | AF8: =+E8 -> 21 | AG8: =+E8 -> 21 | AH8: =+E8 -> 21 | AI8: =+E8 -> 21 | AJ8: =+E8 -> 21 | AK8: =+E8 -> 21 | AL8: =+E8 -> 21 | AM8: =+E8 -> 21 | AN8: =+E8 -> 21 | AO8: =+E8 -> 21 | AP8: =+E8 -> 21 | AQ8: =+E8 -> 21 | AR8: =+E8 -> 21 | AS8: =+E8 -> 21 | AT8: =+E8 -> 21 | AU8: =+E8 -> 21 | AV8: =+E8 -> 21 | AW8: =+E8 -> 21 | AX8: =+E8 -> 21 | AY8: =+E8 -> 21 | AZ8: =+AG8 -> 21 | BA8: =+AG8 -> 21 | BB8: =+AG8 -> 21 | BC8: =+AG8 -> 21 | BD8: =+AK8 -> 21 | BE8: =+AK8 -> 21 | BF8: =+AK8 -> 21 | BG8: =+AK8 -> 21 | BH8: =+AO8 -> 21 | BI8: =+AO8 -> 21 | BJ8: =+AO8 -> 21 | BK8: =+AO8 -> 21 | BL8: =+AS8 -> 21 | BM8: =+AS8 -> 21 | BN8: =+AS8 -> 21 | BO8: =+AS8 -> 21 | BP8: =+AW8 -> 21 | BQ8: =+AW8 -> 21 | BR8: =+AW8 -> 21 | BS8: =+AW8 -> 21 | BT8: =+BA8 -> 21 | BU8: =+BA8 -> 21 | BV8: =+BA8 -> 21 | BW8: =+BA8 -> 21 | BX8: =+BE8 -> 21 | BY8: =+BE8 -> 21 | BZ8: =+BE8 -> 21 | CA8: =+BE8 -> 21 | CB8: =+BI8 -> 21 | CC8: =+BI8 -> 21 | CD8: =+BI8 -> 21 | CE8: =+BI8 -> 21 | CF8: =+BM8 -> 21 | CG8: =+BM8 -> 21 | CH8: =+BM8 -> 21 | CI8: =+BM8 -> 21 | CJ8: =+BQ8 -> 21 | CK8: =+BQ8 -> 21 | CL8: =+BQ8 -> 21 | CM8: =+BQ8 -> 21 | CN8: =+BU8 -> 21 | CO8: =+BU8 -> 21 | CP8: =+BU8 -> 21 | CQ8: =+BU8 -> 21 | CR8: =+BY8 -> 21 | CS8: =+BY8 -> 21 | CT8: =+BY8 -> 21 | CU8: =+BY8 -> 21 | CV8: =+CC8 -> 21 | CW8: =+CC8 -> 21 | CX8: =+CC8 -> 21 | CY8: =+CC8 -> 21 | CZ8: =+BY8 -> 21 | DA8: =+BY8 -> 21 | DB8: =+BY8 -> 21 | DC8: =+BY8 -> 21 | DD8: =+BY8 -> 21 | DE8: =+BY8 -> 21 | DF8: =+BY8 -> 21 | DG8: =+BY8 -> 21 | DH8: =+CC8 -> 21 | DI8: =+CC8 -> 21 | DJ8: =+CC8 -> 21 | DK8: =+CC8 -> 21 | DL8: =+CG8 -> 21 | DM8: =+CG8 -> 21 | DN8: =+CG8 -> 21 | DO8: =+CG8 -> 21 | DP8: =+CK8 -> 21 | DQ8: =+CK8 -> 21 | DR8: =+CK8 -> 21 | DS8: =+CK8 -> 21 | DT8: =+CO8 -> 21 | DU8: =+CO8 -> 21 | DV8: =+CO8 -> 21 | DW8: =+CO8 -> 21 | DX8: =+CS8 -> 21 | DY8: =+CS8 -> 21 | DZ8: =+CS8 -> 21 | EA8: =+CS8 -> 21 | EB8: =+CW8 -> 21 | EC8: =+CW8 -> 21 | ED8: =+CW8 -> 21 | EE8: =+CW8 -> 21 | EF8: =+DA8 -> 21 | EG8: =+DA8 -> 21 | EH8: =+DA8 -> 21 | EI8: =+DA8 -> 21 | EJ8: =+DE8 -> 21 | EK8: =+DE8 -> 21 | EL8: =+DE8 -> 21 | EM8: =+DE8 -> 21 | EN8: =+DI8 -> 21 | EO8: =+DI8 -> 21 | EP8: =+DI8 -> 21 | EQ8: =+DI8 -> 21 | ER8: =+DM8 -> 21 | ES8: =+DM8 -> 21 | ET8: =+DM8 -> 21 | EU8: =+DM8 -> 21 | EV8: =SUM(H8:DC8)/4 -> 399
C9: =+schedule_ARAS!C45 -> Kaptan | D9: Ad | E9: =+schedule_ARAS!E45 -> 15 | AF9: =+E9 -> 15 | AG9: =+E9 -> 15 | AH9: =+E9 -> 15 | AI9: =+E9 -> 15 | AJ9: =+E9 -> 15 | AK9: =+E9 -> 15 | AL9: =+E9 -> 15 | AM9: =+E9 -> 15 | AN9: =+E9 -> 15 | AO9: =+E9 -> 15 | AP9: =+E9 -> 15 | AQ9: =+E9 -> 15 | AR9: =+E9 -> 15 | AS9: =+E9 -> 15 | AT9: =+E9 -> 15 | AU9: =+E9 -> 15 | AV9: =+E9 -> 15 | AW9: =+E9 -> 15 | AX9: =+E9 -> 15 | AY9: =+E9 -> 15 | AZ9: =+AG9 -> 15 | BA9: =+AG9 -> 15 | BB9: =+AG9 -> 15 | BC9: =+AG9 -> 15 | BD9: =+AK9 -> 15 | BE9: =+AK9 -> 15 | BF9: =+AK9 -> 15 | BG9: =+AK9 -> 15 | BH9: =+AO9 -> 15 | BI9: =+AO9 -> 15 | BJ9: =+AO9 -> 15 | BK9: =+AO9 -> 15 | BL9: =+AS9 -> 15 | BM9: =+AS9 -> 15 | BN9: =+AS9 -> 15 | BO9: =+AS9 -> 15 | BP9: =+AW9 -> 15 | BQ9: =+AW9 -> 15 | BR9: =+AW9 -> 15 | BS9: =+AW9 -> 15 | BT9: =+BA9 -> 15 | BU9: =+BA9 -> 15 | BV9: =+BA9 -> 15 | BW9: =+BA9 -> 15 | BX9: =+BE9 -> 15 | BY9: =+BE9 -> 15 | BZ9: =+BE9 -> 15 | CA9: =+BE9 -> 15 | CB9: =+BI9 -> 15 | CC9: =+BI9 -> 15 | CD9: =+BI9 -> 15 | CE9: =+BI9 -> 15 | CF9: =+BM9 -> 15 | CG9: =+BM9 -> 15 | CH9: =+BM9 -> 15 | CI9: =+BM9 -> 15 | CJ9: =+BQ9 -> 15 | CK9: =+BQ9 -> 15 | CL9: =+BQ9 -> 15 | CM9: =+BQ9 -> 15 | CN9: =+BU9 -> 15 | CO9: =+BU9 -> 15 | CP9: =+BU9 -> 15 | CQ9: =+BU9 -> 15 | CR9: =+BY9 -> 15 | CS9: =+BY9 -> 15 | CT9: =+BY9 -> 15 | CU9: =+BY9 -> 15 | CV9: =+CC9 -> 15 | CW9: =+CC9 -> 15 | CX9: =+CC9 -> 15 | CY9: =+CC9 -> 15 | CZ9: =+BY9 -> 15 | DA9: =+BY9 -> 15 | DB9: =+BY9 -> 15 | DC9: =+BY9 -> 15 | DD9: =+BY9 -> 15 | DE9: =+BY9 -> 15 | DF9: =+BY9 -> 15 | DG9: =+BY9 -> 15 | DH9: =+CC9 -> 15 | DI9: =+CC9 -> 15 | DJ9: =+CC9 -> 15 | DK9: =+CC9 -> 15 | DL9: =+CG9 -> 15 | DM9: =+CG9 -> 15 | DN9: =+CG9 -> 15 | DO9: =+CG9 -> 15 | DP9: =+CK9 -> 15 | DQ9: =+CK9 -> 15 | DR9: =+CK9 -> 15 | DS9: =+CK9 -> 15 | DT9: =+CO9 -> 15 | DU9: =+CO9 -> 15 | DV9: =+CO9 -> 15 | DW9: =+CO9 -> 15 | DX9: =+CS9 -> 15 | DY9: =+CS9 -> 15 | DZ9: =+CS9 -> 15 | EA9: =+CS9 -> 15 | EB9: =+CW9 -> 15 | EC9: =+CW9 -> 15 | ED9: =+CW9 -> 15 | EE9: =+CW9 -> 15 | EF9: =+DA9 -> 15 | EG9: =+DA9 -> 15 | EH9: =+DA9 -> 15 | EI9: =+DA9 -> 15 | EJ9: =+DE9 -> 15 | EK9: =+DE9 -> 15 | EL9: =+DE9 -> 15 | EM9: =+DE9 -> 15 | EN9: =+DI9 -> 15 | EO9: =+DI9 -> 15 | EP9: =+DI9 -> 15 | EQ9: =+DI9 -> 15 | ER9: =+DM9 -> 15 | ES9: =+DM9 -> 15 | ET9: =+DM9 -> 15 | EU9: =+DM9 -> 15 | EV9: =SUM(H9:DC9)/4 -> 285
C10: =+schedule_ARAS!C46 -> Çarkçı | D10: Ad | E10: =+schedule_ARAS!E46 -> 10 | AF10: =+E10 -> 10 | AG10: =+E10 -> 10 | AH10: =+E10 -> 10 | AI10: =+E10 -> 10 | AJ10: =+E10 -> 10 | AK10: =+E10 -> 10 | AL10: =+E10 -> 10 | AM10: =+E10 -> 10 | AN10: =+E10 -> 10 | AO10: =+E10 -> 10 | AP10: =+E10 -> 10 | AQ10: =+E10 -> 10 | AR10: =+E10 -> 10 | AS10: =+E10 -> 10 | AT10: =+E10 -> 10 | AU10: =+E10 -> 10 | AV10: =+E10 -> 10 | AW10: =+E10 -> 10 | AX10: =+E10 -> 10 | AY10: =+E10 -> 10 | AZ10: =+AG10 -> 10 | BA10: =+AG10 -> 10 | BB10: =+AG10 -> 10 | BC10: =+AG10 -> 10 | BD10: =+AK10 -> 10 | BE10: =+AK10 -> 10 | BF10: =+AK10 -> 10 | BG10: =+AK10 -> 10 | BH10: =+AO10 -> 10 | BI10: =+AO10 -> 10 | BJ10: =+AO10 -> 10 | BK10: =+AO10 -> 10 | BL10: =+AS10 -> 10 | BM10: =+AS10 -> 10 | BN10: =+AS10 -> 10 | BO10: =+AS10 -> 10 | BP10: =+AW10 -> 10 | BQ10: =+AW10 -> 10 | BR10: =+AW10 -> 10 | BS10: =+AW10 -> 10 | BT10: =+BA10 -> 10 | BU10: =+BA10 -> 10 | BV10: =+BA10 -> 10 | BW10: =+BA10 -> 10 | BX10: =+BE10 -> 10 | BY10: =+BE10 -> 10 | BZ10: =+BE10 -> 10 | CA10: =+BE10 -> 10 | CB10: =+BI10 -> 10 | CC10: =+BI10 -> 10 | CD10: =+BI10 -> 10 | CE10: =+BI10 -> 10 | CF10: =+BM10 -> 10 | CG10: =+BM10 -> 10 | CH10: =+BM10 -> 10 | CI10: =+BM10 -> 10 | CJ10: =+BQ10 -> 10 | CK10: =+BQ10 -> 10 | CL10: =+BQ10 -> 10 | CM10: =+BQ10 -> 10 | CN10: =+BU10 -> 10 | CO10: =+BU10 -> 10 | CP10: =+BU10 -> 10 | CQ10: =+BU10 -> 10 | CR10: =+BY10 -> 10 | CS10: =+BY10 -> 10 | CT10: =+BY10 -> 10 | CU10: =+BY10 -> 10 | CV10: =+CC10 -> 10 | CW10: =+CC10 -> 10 | CX10: =+CC10 -> 10 | CY10: =+CC10 -> 10 | CZ10: =+BY10 -> 10 | DA10: =+BY10 -> 10 | DB10: =+BY10 -> 10 | DC10: =+BY10 -> 10 | DD10: =+BY10 -> 10 | DE10: =+BY10 -> 10 | DF10: =+BY10 -> 10 | DG10: =+BY10 -> 10 | DH10: =+CC10 -> 10 | DI10: =+CC10 -> 10 | DJ10: =+CC10 -> 10 | DK10: =+CC10 -> 10 | DL10: =+CG10 -> 10 | DM10: =+CG10 -> 10 | DN10: =+CG10 -> 10 | DO10: =+CG10 -> 10 | DP10: =+CK10 -> 10 | DQ10: =+CK10 -> 10 | DR10: =+CK10 -> 10 | DS10: =+CK10 -> 10 | DT10: =+CO10 -> 10 | DU10: =+CO10 -> 10 | DV10: =+CO10 -> 10 | DW10: =+CO10 -> 10 | DX10: =+CS10 -> 10 | DY10: =+CS10 -> 10 | DZ10: =+CS10 -> 10 | EA10: =+CS10 -> 10 | EB10: =+CW10 -> 10 | EC10: =+CW10 -> 10 | ED10: =+CW10 -> 10 | EE10: =+CW10 -> 10 | EF10: =+DA10 -> 10 | EG10: =+DA10 -> 10 | EH10: =+DA10 -> 10 | EI10: =+DA10 -> 10 | EJ10: =+DE10 -> 10 | EK10: =+DE10 -> 10 | EL10: =+DE10 -> 10 | EM10: =+DE10 -> 10 | EN10: =+DI10 -> 10 | EO10: =+DI10 -> 10 | EP10: =+DI10 -> 10 | EQ10: =+DI10 -> 10 | ER10: =+DM10 -> 10 | ES10: =+DM10 -> 10 | ET10: =+DM10 -> 10 | EU10: =+DM10 -> 10 | EV10: =SUM(H10:DC10)/4 -> 190
C11: =+schedule_ARAS!C47 -> Yağcı | D11: Ad | E11: =+schedule_ARAS!E47 -> 15 | AF11: =+E11 -> 15 | AG11: =+E11 -> 15 | AH11: =+E11 -> 15 | AI11: =+E11 -> 15 | AJ11: =+E11 -> 15 | AK11: =+E11 -> 15 | AL11: =+E11 -> 15 | AM11: =+E11 -> 15 | AN11: =+E11 -> 15 | AO11: =+E11 -> 15 | AP11: =+E11 -> 15 | AQ11: =+E11 -> 15 | AR11: =+E11 -> 15 | AS11: =+E11 -> 15 | AT11: =+E11 -> 15 | AU11: =+E11 -> 15 | AV11: =+E11 -> 15 | AW11: =+E11 -> 15 | AX11: =+E11 -> 15 | AY11: =+E11 -> 15 | AZ11: =+AG11 -> 15 | BA11: =+AG11 -> 15 | BB11: =+AG11 -> 15 | BC11: =+AG11 -> 15 | BD11: =+AK11 -> 15 | BE11: =+AK11 -> 15 | BF11: =+AK11 -> 15 | BG11: =+AK11 -> 15 | BH11: =+AO11 -> 15 | BI11: =+AO11 -> 15 | BJ11: =+AO11 -> 15 | BK11: =+AO11 -> 15 | BL11: =+AS11 -> 15 | BM11: =+AS11 -> 15 | BN11: =+AS11 -> 15 | BO11: =+AS11 -> 15 | BP11: =+AW11 -> 15 | BQ11: =+AW11 -> 15 | BR11: =+AW11 -> 15 | BS11: =+AW11 -> 15 | BT11: =+BA11 -> 15 | BU11: =+BA11 -> 15 | BV11: =+BA11 -> 15 | BW11: =+BA11 -> 15 | BX11: =+BE11 -> 15 | BY11: =+BE11 -> 15 | BZ11: =+BE11 -> 15 | CA11: =+BE11 -> 15 | CB11: =+BI11 -> 15 | CC11: =+BI11 -> 15 | CD11: =+BI11 -> 15 | CE11: =+BI11 -> 15 | CF11: =+BM11 -> 15 | CG11: =+BM11 -> 15 | CH11: =+BM11 -> 15 | CI11: =+BM11 -> 15 | CJ11: =+BQ11 -> 15 | CK11: =+BQ11 -> 15 | CL11: =+BQ11 -> 15 | CM11: =+BQ11 -> 15 | CN11: =+BU11 -> 15 | CO11: =+BU11 -> 15 | CP11: =+BU11 -> 15 | CQ11: =+BU11 -> 15 | CR11: =+BY11 -> 15 | CS11: =+BY11 -> 15 | CT11: =+BY11 -> 15 | CU11: =+BY11 -> 15 | CV11: =+CC11 -> 15 | CW11: =+CC11 -> 15 | CX11: =+CC11 -> 15 | CY11: =+CC11 -> 15 | CZ11: =+BY11 -> 15 | DA11: =+BY11 -> 15 | DB11: =+BY11 -> 15 | DC11: =+BY11 -> 15 | DD11: =+BY11 -> 15 | DE11: =+BY11 -> 15 | DF11: =+BY11 -> 15 | DG11: =+BY11 -> 15 | DH11: =+CC11 -> 15 | DI11: =+CC11 -> 15 | DJ11: =+CC11 -> 15 | DK11: =+CC11 -> 15 | DL11: =+CG11 -> 15 | DM11: =+CG11 -> 15 | DN11: =+CG11 -> 15 | DO11: =+CG11 -> 15 | DP11: =+CK11 -> 15 | DQ11: =+CK11 -> 15 | DR11: =+CK11 -> 15 | DS11: =+CK11 -> 15 | DT11: =+CO11 -> 15 | DU11: =+CO11 -> 15 | DV11: =+CO11 -> 15 | DW11: =+CO11 -> 15 | DX11: =+CS11 -> 15 | DY11: =+CS11 -> 15 | DZ11: =+CS11 -> 15 | EA11: =+CS11 -> 15 | EB11: =+CW11 -> 15 | EC11: =+CW11 -> 15 | ED11: =+CW11 -> 15 | EE11: =+CW11 -> 15 | EF11: =+DA11 -> 15 | EG11: =+DA11 -> 15 | EH11: =+DA11 -> 15 | EI11: =+DA11 -> 15 | EJ11: =+DE11 -> 15 | EK11: =+DE11 -> 15 | EL11: =+DE11 -> 15 | EM11: =+DE11 -> 15 | EN11: =+DI11 -> 15 | EO11: =+DI11 -> 15 | EP11: =+DI11 -> 15 | EQ11: =+DI11 -> 15 | ER11: =+DM11 -> 15 | ES11: =+DM11 -> 15 | ET11: =+DM11 -> 15 | EU11: =+DM11 -> 15 | EV11: =SUM(H11:DC11)/4 -> 285
C12: =+schedule_ARAS!C48 -> Gemici | D12: Ad | E12: =+schedule_ARAS!E48 -> 30 | AF12: =+E12 -> 30 | AG12: =+E12 -> 30 | AH12: =+E12 -> 30 | AI12: =+E12 -> 30 | AJ12: =+E12 -> 30 | AK12: =+E12 -> 30 | AL12: =+E12 -> 30 | AM12: =+E12 -> 30 | AN12: =+E12 -> 30 | AO12: =+E12 -> 30 | AP12: =+E12 -> 30 | AQ12: =+E12 -> 30 | AR12: =+E12 -> 30 | AS12: =+E12 -> 30 | AT12: =+E12 -> 30 | AU12: =+E12 -> 30 | AV12: =+E12 -> 30 | AW12: =+E12 -> 30 | AX12: =+E12 -> 30 | AY12: =+E12 -> 30 | AZ12: =+AG12 -> 30 | BA12: =+AG12 -> 30 | BB12: =+AG12 -> 30 | BC12: =+AG12 -> 30 | BD12: =+AK12 -> 30 | BE12: =+AK12 -> 30 | BF12: =+AK12 -> 30 | BG12: =+AK12 -> 30 | BH12: =+AO12 -> 30 | BI12: =+AO12 -> 30 | BJ12: =+AO12 -> 30 | BK12: =+AO12 -> 30 | BL12: =+AS12 -> 30 | BM12: =+AS12 -> 30 | BN12: =+AS12 -> 30 | BO12: =+AS12 -> 30 | BP12: =+AW12 -> 30 | BQ12: =+AW12 -> 30 | BR12: =+AW12 -> 30 | BS12: =+AW12 -> 30 | BT12: =+BA12 -> 30 | BU12: =+BA12 -> 30 | BV12: =+BA12 -> 30 | BW12: =+BA12 -> 30 | BX12: =+BE12 -> 30 | BY12: =+BE12 -> 30 | BZ12: =+BE12 -> 30 | CA12: =+BE12 -> 30 | CB12: =+BI12 -> 30 | CC12: =+BI12 -> 30 | CD12: =+BI12 -> 30 | CE12: =+BI12 -> 30 | CF12: =+BM12 -> 30 | CG12: =+BM12 -> 30 | CH12: =+BM12 -> 30 | CI12: =+BM12 -> 30 | CJ12: =+BQ12 -> 30 | CK12: =+BQ12 -> 30 | CL12: =+BQ12 -> 30 | CM12: =+BQ12 -> 30 | CN12: =+BU12 -> 30 | CO12: =+BU12 -> 30 | CP12: =+BU12 -> 30 | CQ12: =+BU12 -> 30 | CR12: =+BY12 -> 30 | CS12: =+BY12 -> 30 | CT12: =+BY12 -> 30 | CU12: =+BY12 -> 30 | CV12: =+CC12 -> 30 | CW12: =+CC12 -> 30 | CX12: =+CC12 -> 30 | CY12: =+CC12 -> 30 | CZ12: =+BY12 -> 30 | DA12: =+BY12 -> 30 | DB12: =+BY12 -> 30 | DC12: =+BY12 -> 30 | DD12: =+BY12 -> 30 | DE12: =+BY12 -> 30 | DF12: =+BY12 -> 30 | DG12: =+BY12 -> 30 | DH12: =+CC12 -> 30 | DI12: =+CC12 -> 30 | DJ12: =+CC12 -> 30 | DK12: =+CC12 -> 30 | DL12: =+CG12 -> 30 | DM12: =+CG12 -> 30 | DN12: =+CG12 -> 30 | DO12: =+CG12 -> 30 | DP12: =+CK12 -> 30 | DQ12: =+CK12 -> 30 | DR12: =+CK12 -> 30 | DS12: =+CK12 -> 30 | DT12: =+CO12 -> 30 | DU12: =+CO12 -> 30 | DV12: =+CO12 -> 30 | DW12: =+CO12 -> 30 | DX12: =+CS12 -> 30 | DY12: =+CS12 -> 30 | DZ12: =+CS12 -> 30 | EA12: =+CS12 -> 30 | EB12: =+CW12 -> 30 | EC12: =+CW12 -> 30 | ED12: =+CW12 -> 30 | EE12: =+CW12 -> 30 | EF12: =+DA12 -> 30 | EG12: =+DA12 -> 30 | EH12: =+DA12 -> 30 | EI12: =+DA12 -> 30 | EJ12: =+DE12 -> 30 | EK12: =+DE12 -> 30 | EL12: =+DE12 -> 30 | EM12: =+DE12 -> 30 | EN12: =+DI12 -> 30 | EO12: =+DI12 -> 30 | EP12: =+DI12 -> 30 | EQ12: =+DI12 -> 30 | ER12: =+DM12 -> 30 | ES12: =+DM12 -> 30 | ET12: =+DM12 -> 30 | EU12: =+DM12 -> 30 | EV12: =SUM(H12:DC12)/4 -> 570
C13: =+schedule_ARAS!C49 -> İşçi | D13: Ad | E13: =+schedule_ARAS!E49 -> 40 | AF13: =+E13 -> 40 | AG13: =+E13 -> 40 | AH13: =+E13 -> 40 | AI13: =+E13 -> 40 | AJ13: =+E13 -> 40 | AK13: =+E13 -> 40 | AL13: =+E13 -> 40 | AM13: =+E13 -> 40 | AN13: =+E13 -> 40 | AO13: =+E13 -> 40 | AP13: =+E13 -> 40 | AQ13: =+E13 -> 40 | AR13: =+E13 -> 40 | AS13: =+E13 -> 40 | AT13: =+E13 -> 40 | AU13: =+E13 -> 40 | AV13: =+E13 -> 40 | AW13: =+E13 -> 40 | AX13: =+E13 -> 40 | AY13: =+E13 -> 40 | AZ13: =+AG13 -> 40 | BA13: =+AG13 -> 40 | BB13: =+AG13 -> 40 | BC13: =+AG13 -> 40 | BD13: =+AK13 -> 40 | BE13: =+AK13 -> 40 | BF13: =+AK13 -> 40 | BG13: =+AK13 -> 40 | BH13: =+AO13 -> 40 | BI13: =+AO13 -> 40 | BJ13: =+AO13 -> 40 | BK13: =+AO13 -> 40 | BL13: =+AS13 -> 40 | BM13: =+AS13 -> 40 | BN13: =+AS13 -> 40 | BO13: =+AS13 -> 40 | BP13: =+AW13 -> 40 | BQ13: =+AW13 -> 40 | BR13: =+AW13 -> 40 | BS13: =+AW13 -> 40 | BT13: =+BA13 -> 40 | BU13: =+BA13 -> 40 | BV13: =+BA13 -> 40 | BW13: =+BA13 -> 40 | BX13: =+BE13 -> 40 | BY13: =+BE13 -> 40 | BZ13: =+BE13 -> 40 | CA13: =+BE13 -> 40 | CB13: =+BI13 -> 40 | CC13: =+BI13 -> 40 | CD13: =+BI13 -> 40 | CE13: =+BI13 -> 40 | CF13: =+BM13 -> 40 | CG13: =+BM13 -> 40 | CH13: =+BM13 -> 40 | CI13: =+BM13 -> 40 | CJ13: =+BQ13 -> 40 | CK13: =+BQ13 -> 40 | CL13: =+BQ13 -> 40 | CM13: =+BQ13 -> 40 | CN13: =+BU13 -> 40 | CO13: =+BU13 -> 40 | CP13: =+BU13 -> 40 | CQ13: =+BU13 -> 40 | CR13: =+BY13 -> 40 | CS13: =+BY13 -> 40 | CT13: =+BY13 -> 40 | CU13: =+BY13 -> 40 | CV13: =+CC13 -> 40 | CW13: =+CC13 -> 40 | CX13: =+CC13 -> 40 | CY13: =+CC13 -> 40 | CZ13: =+BY13 -> 40 | DA13: =+BY13 -> 40 | DB13: =+BY13 -> 40 | DC13: =+BY13 -> 40 | DD13: =+BY13 -> 40 | DE13: =+BY13 -> 40 | DF13: =+BY13 -> 40 | DG13: =+BY13 -> 40 | DH13: =+CC13 -> 40 | DI13: =+CC13 -> 40 | DJ13: =+CC13 -> 40 | DK13: =+CC13 -> 40 | DL13: =+CG13 -> 40 | DM13: =+CG13 -> 40 | DN13: =+CG13 -> 40 | DO13: =+CG13 -> 40 | DP13: =+CK13 -> 40 | DQ13: =+CK13 -> 40 | DR13: =+CK13 -> 40 | DS13: =+CK13 -> 40 | DT13: =+CO13 -> 40 | DU13: =+CO13 -> 40 | DV13: =+CO13 -> 40 | DW13: =+CO13 -> 40 | DX13: =+CS13 -> 40 | DY13: =+CS13 -> 40 | DZ13: =+CS13 -> 40 | EA13: =+CS13 -> 40 | EB13: =+CW13 -> 40 | EC13: =+CW13 -> 40 | ED13: =+CW13 -> 40 | EE13: =+CW13 -> 40 | EF13: =+DA13 -> 40 | EG13: =+DA13 -> 40 | EH13: =+DA13 -> 40 | EI13: =+DA13 -> 40 | EJ13: =+DE13 -> 40 | EK13: =+DE13 -> 40 | EL13: =+DE13 -> 40 | EM13: =+DE13 -> 40 | EN13: =+DI13 -> 40 | EO13: =+DI13 -> 40 | EP13: =+DI13 -> 40 | EQ13: =+DI13 -> 40 | ER13: =+DM13 -> 40 | ES13: =+DM13 -> 40 | ET13: =+DM13 -> 40 | EU13: =+DM13 -> 40 | EV13: =SUM(H13:DC13)/4 -> 760
AF14: =+E14 -> 0 | AG14: =+E14 -> 0 | AH14: =+E14 -> 0 | AI14: =+E14 -> 0 | AJ14: =+E14 -> 0 | AK14: =+E14 -> 0 | AL14: =+E14 -> 0 | AM14: =+E14 -> 0 | AN14: =+E14 -> 0 | AO14: =+E14 -> 0 | AP14: =+E14 -> 0 | AQ14: =+E14 -> 0 | AR14: =+E14 -> 0 | AS14: =+E14 -> 0 | AT14: =+E14 -> 0 | AU14: =+E14 -> 0 | AV14: =+E14 -> 0 | AW14: =+E14 -> 0 | AX14: =+E14 -> 0 | AY14: =+E14 -> 0 | AZ14: =+AG14 -> 0 | BA14: =+AG14 -> 0 | BB14: =+AG14 -> 0 | BC14: =+AG14 -> 0 | BD14: =+AK14 -> 0 | BE14: =+AK14 -> 0 | BF14: =+AK14 -> 0 | BG14: =+AK14 -> 0 | BH14: =+AO14 -> 0 | BI14: =+AO14 -> 0 | BJ14: =+AO14 -> 0 | BK14: =+AO14 -> 0 | BL14: =+AS14 -> 0 | BM14: =+AS14 -> 0 | BN14: =+AS14 -> 0 | BO14: =+AS14 -> 0 | BP14: =+AW14 -> 0 | BQ14: =+AW14 -> 0 | BR14: =+AW14 -> 0 | BS14: =+AW14 -> 0 | BT14: =+BA14 -> 0 | BU14: =+BA14 -> 0 | BV14: =+BA14 -> 0 | BW14: =+BA14 -> 0 | BX14: =+BE14 -> 0 | BY14: =+BE14 -> 0 | BZ14: =+BE14 -> 0 | CA14: =+BE14 -> 0 | CB14: =+BI14 -> 0 | CC14: =+BI14 -> 0 | CD14: =+BI14 -> 0 | CE14: =+BI14 -> 0 | CF14: =+BM14 -> 0 | CG14: =+BM14 -> 0 | CH14: =+BM14 -> 0 | CI14: =+BM14 -> 0 | CJ14: =+BQ14 -> 0 | CK14: =+BQ14 -> 0 | CL14: =+BQ14 -> 0 | CM14: =+BQ14 -> 0 | CN14: =+BU14 -> 0 | CO14: =+BU14 -> 0 | CP14: =+BU14 -> 0 | CQ14: =+BU14 -> 0 | CR14: =+BY14 -> 0 | CS14: =+BY14 -> 0 | CT14: =+BY14 -> 0 | CU14: =+BY14 -> 0 | CV14: =+CC14 -> 0 | CW14: =+CC14 -> 0 | CX14: =+CC14 -> 0 | CY14: =+CC14 -> 0 | CZ14: =+BY14 -> 0 | DA14: =+BY14 -> 0 | DB14: =+BY14 -> 0 | DC14: =+BY14 -> 0 | DD14: =+BY14 -> 0 | DE14: =+BY14 -> 0 | DF14: =+BY14 -> 0 | DG14: =+BY14 -> 0 | DH14: =+CC14 -> 0 | DI14: =+CC14 -> 0 | DJ14: =+CC14 -> 0 | DK14: =+CC14 -> 0 | DL14: =+CG14 -> 0 | DM14: =+CG14 -> 0 | DN14: =+CG14 -> 0 | DO14: =+CG14 -> 0 | DP14: =+CK14 -> 0 | DQ14: =+CK14 -> 0 | DR14: =+CK14 -> 0 | DS14: =+CK14 -> 0 | DT14: =+CO14 -> 0 | DU14: =+CO14 -> 0 | DV14: =+CO14 -> 0 | DW14: =+CO14 -> 0 | DX14: =+CS14 -> 0 | DY14: =+CS14 -> 0 | DZ14: =+CS14 -> 0 | EA14: =+CS14 -> 0 | EB14: =+CW14 -> 0 | EC14: =+CW14 -> 0 | ED14: =+CW14 -> 0 | EE14: =+CW14 -> 0 | EF14: =+DA14 -> 0 | EG14: =+DA14 -> 0 | EH14: =+DA14 -> 0 | EI14: =+DA14 -> 0 | EJ14: =+DE14 -> 0 | EK14: =+DE14 -> 0 | EL14: =+DE14 -> 0 | EM14: =+DE14 -> 0 | EN14: =+DI14 -> 0 | EO14: =+DI14 -> 0 | EP14: =+DI14 -> 0 | EQ14: =+DI14 -> 0 | ER14: =+DM14 -> 0 | ES14: =+DM14 -> 0 | ET14: =+DM14 -> 0 | EU14: =+DM14 -> 0 | EV14: =SUM(H14:DC14)/4 -> 0
AF15: =+E15 -> 0 | AG15: =+E15 -> 0 | AH15: =+E15 -> 0 | AI15: =+E15 -> 0 | AJ15: =+E15 -> 0 | AK15: =+E15 -> 0 | AL15: =+E15 -> 0 | AM15: =+E15 -> 0 | AN15: =+E15 -> 0 | AO15: =+E15 -> 0 | AP15: =+E15 -> 0 | AQ15: =+E15 -> 0 | AR15: =+E15 -> 0 | AS15: =+E15 -> 0 | AT15: =+E15 -> 0 | AU15: =+E15 -> 0 | AV15: =+E15 -> 0 | AW15: =+E15 -> 0 | AX15: =+E15 -> 0 | AY15: =+E15 -> 0 | AZ15: =+AG15 -> 0 | BA15: =+AG15 -> 0 | BB15: =+AG15 -> 0 | BC15: =+AG15 -> 0 | BD15: =+AK15 -> 0 | BE15: =+AK15 -> 0 | BF15: =+AK15 -> 0 | BG15: =+AK15 -> 0 | BH15: =+AO15 -> 0 | BI15: =+AO15 -> 0 | BJ15: =+AO15 -> 0 | BK15: =+AO15 -> 0 | BL15: =+AS15 -> 0 | BM15: =+AS15 -> 0 | BN15: =+AS15 -> 0 | BO15: =+AS15 -> 0 | BP15: =+AW15 -> 0 | BQ15: =+AW15 -> 0 | BR15: =+AW15 -> 0 | BS15: =+AW15 -> 0 | BT15: =+BA15 -> 0 | BU15: =+BA15 -> 0 | BV15: =+BA15 -> 0 | BW15: =+BA15 -> 0 | BX15: =+BE15 -> 0 | BY15: =+BE15 -> 0 | BZ15: =+BE15 -> 0 | CA15: =+BE15 -> 0 | CB15: =+BI15 -> 0 | CC15: =+BI15 -> 0 | CD15: =+BI15 -> 0 | CE15: =+BI15 -> 0 | CF15: =+BM15 -> 0 | CG15: =+BM15 -> 0 | CH15: =+BM15 -> 0 | CI15: =+BM15 -> 0 | CJ15: =+BQ15 -> 0 | CK15: =+BQ15 -> 0 | CL15: =+BQ15 -> 0 | CM15: =+BQ15 -> 0 | CN15: =+BU15 -> 0 | CO15: =+BU15 -> 0 | CP15: =+BU15 -> 0 | CQ15: =+BU15 -> 0 | CR15: =+BY15 -> 0 | CS15: =+BY15 -> 0 | CT15: =+BY15 -> 0 | CU15: =+BY15 -> 0 | CV15: =+CC15 -> 0 | CW15: =+CC15 -> 0 | CX15: =+CC15 -> 0 | CY15: =+CC15 -> 0 | CZ15: =+BY15 -> 0 | DA15: =+BY15 -> 0 | DB15: =+BY15 -> 0 | DC15: =+BY15 -> 0 | DD15: =+BY15 -> 0 | DE15: =+BY15 -> 0 | DF15: =+BY15 -> 0 | DG15: =+BY15 -> 0 | DH15: =+CC15 -> 0 | DI15: =+CC15 -> 0 | DJ15: =+CC15 -> 0 | DK15: =+CC15 -> 0 | DL15: =+CG15 -> 0 | DM15: =+CG15 -> 0 | DN15: =+CG15 -> 0 | DO15: =+CG15 -> 0 | DP15: =+CK15 -> 0 | DQ15: =+CK15 -> 0 | DR15: =+CK15 -> 0 | DS15: =+CK15 -> 0 | DT15: =+CO15 -> 0 | DU15: =+CO15 -> 0 | DV15: =+CO15 -> 0 | DW15: =+CO15 -> 0 | DX15: =+CS15 -> 0 | DY15: =+CS15 -> 0 | DZ15: =+CS15 -> 0 | EA15: =+CS15 -> 0 | EB15: =+CW15 -> 0 | EC15: =+CW15 -> 0 | ED15: =+CW15 -> 0 | EE15: =+CW15 -> 0 | EF15: =+DA15 -> 0 | EG15: =+DA15 -> 0 | EH15: =+DA15 -> 0 | EI15: =+DA15 -> 0 | EJ15: =+DE15 -> 0 | EK15: =+DE15 -> 0 | EL15: =+DE15 -> 0 | EM15: =+DE15 -> 0 | EN15: =+DI15 -> 0 | EO15: =+DI15 -> 0 | EP15: =+DI15 -> 0 | EQ15: =+DI15 -> 0 | ER15: =+DM15 -> 0 | ES15: =+DM15 -> 0 | ET15: =+DM15 -> 0 | EU15: =+DM15 -> 0
D16: TOTAL DIRECT PERSONNEL: | H16: =SUM(H7:H13) -> 0 | I16: =SUM(I7:I13) -> 0 | J16: =SUM(J7:J13) -> 0 | K16: =SUM(K7:K13) -> 0 | L16: =SUM(L7:L13) -> 0 | M16: =SUM(M7:M13) -> 0 | N16: =SUM(N7:N13) -> 0 | O16: =SUM(O7:O13) -> 0 | ... EV16: =SUM(EV7:EV13) -> 2603
C17: INDIRECT PERSONNEL
C18: =+schedule_ARAS!C60 -> Project Manager | D18: =+schedule_ARAS!D60 -> Adet | E18: =+schedule_ARAS!E60 -> 1 | AF18: =+E18 -> 1 | AG18: =+E18 -> 1 | AH18: =+E18 -> 1 | AI18: =+E18 -> 1 | AJ18: =+E18 -> 1 | AK18: =+E18 -> 1 | AL18: =+E18 -> 1 | AM18: =+E18 -> 1 | AN18: =+E18 -> 1 | AO18: =+E18 -> 1 | AP18: =+E18 -> 1 | AQ18: =+E18 -> 1 | AR18: =+E18 -> 1 | AS18: =+E18 -> 1 | AT18: =+E18 -> 1 | AU18: =+E18 -> 1 | AV18: =+E18 -> 1 | AW18: =+E18 -> 1 | AX18: =+E18 -> 1 | AY18: =+E18 -> 1 | AZ18: =+AG18 -> 1 | BA18: =+AG18 -> 1 | BB18: =+AG18 -> 1 | BC18: =+AG18 -> 1 | BD18: =+AK18 -> 1 | BE18: =+AK18 -> 1 | BF18: =+AK18 -> 1 | BG18: =+AK18 -> 1 | BH18: =+AO18 -> 1 | BI18: =+AO18 -> 1 | BJ18: =+AO18 -> 1 | BK18: =+AO18 -> 1 | BL18: =+AS18 -> 1 | BM18: =+AS18 -> 1 | BN18: =+AS18 -> 1 | BO18: =+AS18 -> 1 | BP18: =+AW18 -> 1 | BQ18: =+AW18 -> 1 | BR18: =+AW18 -> 1 | BS18: =+AW18 -> 1 | BT18: =+BA18 -> 1 | BU18: =+BA18 -> 1 | BV18: =+BA18 -> 1 | BW18: =+BA18 -> 1 | BX18: =+BE18 -> 1 | BY18: =+BE18 -> 1 | BZ18: =+BE18 -> 1 | CA18: =+BE18 -> 1 | CB18: =+BI18 -> 1 | CC18: =+BI18 -> 1 | CD18: =+BI18 -> 1 | CE18: =+BI18 -> 1 | CF18: =+BM18 -> 1 | CG18: =+BM18 -> 1 | CH18: =+BM18 -> 1 | CI18: =+BM18 -> 1 | CJ18: =+BQ18 -> 1 | CK18: =+BQ18 -> 1 | CL18: =+BQ18 -> 1 | CM18: =+BQ18 -> 1 | CN18: =+BU18 -> 1 | CO18: =+BU18 -> 1 | CP18: =+BU18 -> 1 | CQ18: =+BU18 -> 1 | CR18: =+BY18 -> 1 | CS18: =+BY18 -> 1 | CT18: =+BY18 -> 1 | CU18: =+BY18 -> 1 | CV18: =+CC18 -> 1 | CW18: =+CC18 -> 1 | CX18: =+CC18 -> 1 | CY18: =+CC18 -> 1 | CZ18: =+BY18 -> 1 | DA18: =+BY18 -> 1 | DB18: =+BY18 -> 1 | DC18: =+BY18 -> 1 | DD18: =+BY18 -> 1 | DE18: =+BY18 -> 1 | DF18: =+BY18 -> 1 | DG18: =+BY18 -> 1 | DH18: =+BY18 -> 1 | DI18: =+BY18 -> 1 | DJ18: =+BY18 -> 1 | DK18: =+BY18 -> 1 | DL18: =+BY18 -> 1 | DM18: =+BY18 -> 1 | DN18: =+BY18 -> 1 | DO18: =+BY18 -> 1 | DP18: =+BY18 -> 1 | DQ18: =+BY18 -> 1 | DR18: =+BY18 -> 1 | DS18: =+BY18 -> 1 | DT18: =+DA18 -> 1 | DU18: =+DA18 -> 1 | DV18: =+DA18 -> 1 | DW18: =+DA18 -> 1 | DX18: =+DE18 -> 1 | DY18: =+DE18 -> 1 | DZ18: =+DE18 -> 1 | EA18: =+DE18 -> 1 | EB18: =+DI18 -> 1 | EC18: =+DI18 -> 1 | ED18: =+DI18 -> 1 | EE18: =+DI18 -> 1 | EF18: =+DM18 -> 1 | EG18: =+DM18 -> 1 | EH18: =+DM18 -> 1 | EI18: =+DM18 -> 1 | EJ18: =+DQ18 -> 1 | EK18: =+DQ18 -> 1 | EL18: =+DQ18 -> 1 | EM18: =+DQ18 -> 1 | EN18: =+DU18 -> 1 | EO18: =+DU18 -> 1 | EP18: =+DU18 -> 1 | EQ18: =+DU18 -> 1 | ER18: =+DY18 -> 1 | ES18: =+DY18 -> 1 | ET18: =+DY18 -> 1 | EU18: =+DY18 -> 1 | EV18: =SUM(H18:DC18)/4 -> 19
C19: =+schedule_ARAS!C61 -> Site Manager | D19: =+schedule_ARAS!D61 -> Adet | E19: =+schedule_ARAS!E61 -> 1 | AF19: =+E19 -> 1 | AG19: =+E19 -> 1 | AH19: =+E19 -> 1 | AI19: =+E19 -> 1 | AJ19: =+E19 -> 1 | AK19: =+E19 -> 1 | AL19: =+E19 -> 1 | AM19: =+E19 -> 1 | AN19: =+E19 -> 1 | AO19: =+E19 -> 1 | AP19: =+E19 -> 1 | AQ19: =+E19 -> 1 | AR19: =+E19 -> 1 | AS19: =+E19 -> 1 | AT19: =+E19 -> 1 | AU19: =+E19 -> 1 | AV19: =+E19 -> 1 | AW19: =+E19 -> 1 | AX19: =+E19 -> 1 | AY19: =+E19 -> 1 | AZ19: =+AG19 -> 1 | BA19: =+AG19 -> 1 | BB19: =+AG19 -> 1 | BC19: =+AG19 -> 1 | BD19: =+AK19 -> 1 | BE19: =+AK19 -> 1 | BF19: =+AK19 -> 1 | BG19: =+AK19 -> 1 | BH19: =+AO19 -> 1 | BI19: =+AO19 -> 1 | BJ19: =+AO19 -> 1 | BK19: =+AO19 -> 1 | BL19: =+AS19 -> 1 | BM19: =+AS19 -> 1 | BN19: =+AS19 -> 1 | BO19: =+AS19 -> 1 | BP19: =+AW19 -> 1 | BQ19: =+AW19 -> 1 | BR19: =+AW19 -> 1 | BS19: =+AW19 -> 1 | BT19: =+BA19 -> 1 | BU19: =+BA19 -> 1 | BV19: =+BA19 -> 1 | BW19: =+BA19 -> 1 | BX19: =+BE19 -> 1 | BY19: =+BE19 -> 1 | BZ19: =+BE19 -> 1 | CA19: =+BE19 -> 1 | CB19: =+BI19 -> 1 | CC19: =+BI19 -> 1 | CD19: =+BI19 -> 1 | CE19: =+BI19 -> 1 | CF19: =+BM19 -> 1 | CG19: =+BM19 -> 1 | CH19: =+BM19 -> 1 | CI19: =+BM19 -> 1 | CJ19: =+BQ19 -> 1 | CK19: =+BQ19 -> 1 | CL19: =+BQ19 -> 1 | CM19: =+BQ19 -> 1 | CN19: =+BU19 -> 1 | CO19: =+BU19 -> 1 | CP19: =+BU19 -> 1 | CQ19: =+BU19 -> 1 | CR19: =+BY19 -> 1 | CS19: =+BY19 -> 1 | CT19: =+BY19 -> 1 | CU19: =+BY19 -> 1 | CV19: =+CC19 -> 1 | CW19: =+CC19 -> 1 | CX19: =+CC19 -> 1 | CY19: =+CC19 -> 1 | CZ19: =+BY19 -> 1 | DA19: =+BY19 -> 1 | DB19: =+BY19 -> 1 | DC19: =+BY19 -> 1 | DD19: =+BY19 -> 1 | DE19: =+BY19 -> 1 | DF19: =+BY19 -> 1 | DG19: =+BY19 -> 1 | DH19: =+BY19 -> 1 | DI19: =+BY19 -> 1 | DJ19: =+BY19 -> 1 | DK19: =+BY19 -> 1 | DL19: =+BY19 -> 1 | DM19: =+BY19 -> 1 | DN19: =+BY19 -> 1 | DO19: =+BY19 -> 1 | DP19: =+BY19 -> 1 | DQ19: =+BY19 -> 1 | DR19: =+BY19 -> 1 | DS19: =+BY19 -> 1 | DT19: =+DA19 -> 1 | DU19: =+DA19 -> 1 | DV19: =+DA19 -> 1 | DW19: =+DA19 -> 1 | DX19: =+DE19 -> 1 | DY19: =+DE19 -> 1 | DZ19: =+DE19 -> 1 | EA19: =+DE19 -> 1 | EB19: =+DI19 -> 1 | EC19: =+DI19 -> 1 | ED19: =+DI19 -> 1 | EE19: =+DI19 -> 1 | EF19: =+DM19 -> 1 | EG19: =+DM19 -> 1 | EH19: =+DM19 -> 1 | EI19: =+DM19 -> 1 | EJ19: =+DQ19 -> 1 | EK19: =+DQ19 -> 1 | EL19: =+DQ19 -> 1 | EM19: =+DQ19 -> 1 | EN19: =+DU19 -> 1 | EO19: =+DU19 -> 1 | EP19: =+DU19 -> 1 | EQ19: =+DU19 -> 1 | ER19: =+DY19 -> 1 | ES19: =+DY19 -> 1 | ET19: =+DY19 -> 1 | EU19: =+DY19 -> 1 | EV19: =SUM(H19:DC19)/4 -> 19
C20: =+schedule_ARAS!C62 -> Survey Engineer | D20: =+schedule_ARAS!D62 -> Adet | E20: =+schedule_ARAS!E62 -> 1 | AF20: =+E20 -> 1 | AG20: =+E20 -> 1 | AH20: =+E20 -> 1 | AI20: =+E20 -> 1 | AJ20: =+E20 -> 1 | AK20: =+E20 -> 1 | AL20: =+E20 -> 1 | AM20: =+E20 -> 1 | AN20: =+E20 -> 1 | AO20: =+E20 -> 1 | AP20: =+E20 -> 1 | AQ20: =+E20 -> 1 | AR20: =+E20 -> 1 | AS20: =+E20 -> 1 | AT20: =+E20 -> 1 | AU20: =+E20 -> 1 | AV20: =+E20 -> 1 | AW20: =+E20 -> 1 | AX20: =+E20 -> 1 | AY20: =+E20 -> 1 | AZ20: =+AG20 -> 1 | BA20: =+AG20 -> 1 | BB20: =+AG20 -> 1 | BC20: =+AG20 -> 1 | BD20: =+AK20 -> 1 | BE20: =+AK20 -> 1 | BF20: =+AK20 -> 1 | BG20: =+AK20 -> 1 | BH20: =+AO20 -> 1 | BI20: =+AO20 -> 1 | BJ20: =+AO20 -> 1 | BK20: =+AO20 -> 1 | BL20: =+AS20 -> 1 | BM20: =+AS20 -> 1 | BN20: =+AS20 -> 1 | BO20: =+AS20 -> 1 | BP20: =+AW20 -> 1 | BQ20: =+AW20 -> 1 | BR20: =+AW20 -> 1 | BS20: =+AW20 -> 1 | BT20: =+BA20 -> 1 | BU20: =+BA20 -> 1 | BV20: =+BA20 -> 1 | BW20: =+BA20 -> 1 | BX20: =+BE20 -> 1 | BY20: =+BE20 -> 1 | BZ20: =+BE20 -> 1 | CA20: =+BE20 -> 1 | CB20: =+BI20 -> 1 | CC20: =+BI20 -> 1 | CD20: =+BI20 -> 1 | CE20: =+BI20 -> 1 | CF20: =+BM20 -> 1 | CG20: =+BM20 -> 1 | CH20: =+BM20 -> 1 | CI20: =+BM20 -> 1 | CJ20: =+BQ20 -> 1 | CK20: =+BQ20 -> 1 | CL20: =+BQ20 -> 1 | CM20: =+BQ20 -> 1 | CN20: =+BU20 -> 1 | CO20: =+BU20 -> 1 | CP20: =+BU20 -> 1 | CQ20: =+BU20 -> 1 | CR20: =+BY20 -> 1 | CS20: =+BY20 -> 1 | CT20: =+BY20 -> 1 | CU20: =+BY20 -> 1 | CV20: =+CC20 -> 1 | CW20: =+CC20 -> 1 | CX20: =+CC20 -> 1 | CY20: =+CC20 -> 1 | CZ20: =+BY20 -> 1 | DA20: =+BY20 -> 1 | DB20: =+BY20 -> 1 | DC20: =+BY20 -> 1 | DD20: =+BY20 -> 1 | DE20: =+BY20 -> 1 | DF20: =+BY20 -> 1 | DG20: =+BY20 -> 1 | DH20: =+BY20 -> 1 | DI20: =+BY20 -> 1 | DJ20: =+BY20 -> 1 | DK20: =+BY20 -> 1 | DL20: =+BY20 -> 1 | DM20: =+BY20 -> 1 | DN20: =+BY20 -> 1 | DO20: =+BY20 -> 1 | DP20: =+BY20 -> 1 | DQ20: =+BY20 -> 1 | DR20: =+BY20 -> 1 | DS20: =+BY20 -> 1 | DT20: =+DA20 -> 1 | DU20: =+DA20 -> 1 | DV20: =+DA20 -> 1 | DW20: =+DA20 -> 1 | DX20: =+DE20 -> 1 | DY20: =+DE20 -> 1 | DZ20: =+DE20 -> 1 | EA20: =+DE20 -> 1 | EB20: =+DI20 -> 1 | EC20: =+DI20 -> 1 | ED20: =+DI20 -> 1 | EE20: =+DI20 -> 1 | EF20: =+DM20 -> 1 | EG20: =+DM20 -> 1 | EH20: =+DM20 -> 1 | EI20: =+DM20 -> 1 | EJ20: =+DQ20 -> 1 | EK20: =+DQ20 -> 1 | EL20: =+DQ20 -> 1 | EM20: =+DQ20 -> 1 | EN20: =+DU20 -> 1 | EO20: =+DU20 -> 1 | EP20: =+DU20 -> 1 | EQ20: =+DU20 -> 1 | ER20: =+DY20 -> 1 | ES20: =+DY20 -> 1 | ET20: =+DY20 -> 1 | EU20: =+DY20 -> 1 | EV20: =SUM(H20:DC20)/4 -> 19
