Workbook

Sheet 2.Subcontract Price Summary O1
B1: Doc. No: FR.SAT.07-A Date of Issue : 30.03.2018 Rev. Date : .. Rev. No : 02
B3: Price Summary
B4: ■ Project : | E4: [Currency :EURO]
B5: Item No. | C5: Description | D5: Amount | E5: Remarks
B6: 0. | C6: Mobilisation
B7: '0 | C7: Mobilisation | D7: ='6.Mob-Demob'!G15/3*2 -> 268666.67 | E7: =D7*I26 -> 147766.67 | G7: Section 9*(2/3)
B8: 1. | C8: Direct | G8: Running Cost
B9: 1.1 | C9: Direct Material | D9: ='8.Material'!E23 -> 0 | E9: =D9*J26 -> 0 | G9: Construction Materials
B10: 1.2 | C10: Direct Equipment | D10: ='4.Equipment'!AK12 -> 669375 | E10: =D10*I26 -> 368156.25 | G10: Construction Equipment | H10: Mark Up | I10: ARAS | J10: TAŞARON | K10: YAKIT | L10: MALZEME
B11: 1.3 | C11: Direct Labor | D11: ='5.Manpower'!AI24 -> 357812.5 | E11: =D11*I26 -> 196796.88 | G11: Rate*1,35 | H11: Genel Gider ve Merkez Payı | I11: 0.03 | J11: 0 | K11: 0.02 | L11: 0.02
B12: 1.4 | C12: Direct Consumables | D12: ='7.MGO+Lub+Insurance'!I11 -> 310800 | E12: =D12*K26 -> 44133.6 | G12: Diesel, Lube and water | H12: Teminatlar | I12: 0.002 | J12: 0.002 | K12: 0.002 | L12: 0.002
H13: Finasman | I13: 0.005 | J13: 0.005 | K13: 0.01 | L13: 0.005
B14: 2. | C14: Indirect | G14: Running Cost | H14: Enflasyon | I14: 0 | J14: 0 | K14: 0.01 | L14: 0.01
B15: 2.1 | C15: Site Management&Staff | D15: ='9.Indirect'!E23 -> 594274.38 | E15: =D15*I26 -> 326850.91 | G15: Engineer ect*1,35 | H15: QHSE Cost | I15: 0.01
B16: 2.2 | C16: Temporary Facilities | G16: Site Office, Accomodation ect | H16: SSK | I16: 0 | J16: 0 | K16: 0 | L16: 0
B17: 2.3 | C17: Indirect Consumables | G17: Car rent ect… | H17: Risk/Fire | I17: 0.05 | J17: 0.02 | K17: 0 | L17: 0.01
H18: Kar/Zarar | I18: 0.15 | J18: 0.08 | K18: 0.06 | L18: 0.06
B19: 3. | C19: Environmental Monitoring | H19: Gelir Vergisi | I19: 0.05 | J19: 0.01 | K19: 0.01 | L19: 0.01
B20: 4. | C20: Permit process | H20: Sigorta | I20: 0.01 | J20: 0 | K20: 0 | L20: 0
B21: 4.1 | C21: Consulting for permission | H21: Damga Vergisi ve Noter | I21: 0.012 | J21: =I21 -> 0.012 | K21: =J21 -> 0.012 | L21: =K21 -> 0.012
B22: 4.2 | C22: Any extra charge for permit | H22: Stopaj | I22: 0.036
H23: TOPLAM | I23: =SUM(I11:I22) -> 0.355 | J23: =SUM(J11:J22) -> 0.129 | K23: =SUM(K11:K22) -> 0.124 | L23: =SUM(L11:L22) -> 0.129
B24: 5. | C24: Demobilisation
B25: 5 | C25: Demobilisation | D25: ='6.Mob-Demob'!G15/3 -> 134333.33 | E25: =D25*I26 -> 73883.333 | G25: Section 9*(1/3) | H25: Markup-Çarpanı | I25: =ROUND(1/(1-I23),3) -> 1.55 | J25: =ROUND(1/(1-J23),3) -> 1.148 | K25: =ROUND(1/(1-K23),3) -> 1.142 | L25: =ROUND(1/(1-L23),3) -> 1.148
B26: 6 | C26: Overheads and Profits | I26: =I25-1 -> 0.55 | J26: =J25-1 -> 0.148 | K26: =K25-1 -> 0.142 | L26: =L25-1 -> 0.148
B27: 6.1 | C27: Overheads and Profits | D27: =SUM(E7:E25) -> 1157587.6 | G27: Approximately*1,15
C29: TOTAL | D29: =SUM(D7:D28) -> 3492849.5
B30: ■ Terms and Conditions

Sheet 3.Schedule
A2: Table 1: Work Schedule
A3: Item | B3: Description | C3: Unit | D3: Tot. Qua. | E3: Daily Production | F3: Duration | G3: Duration | AN3: REMARKS
H4: 1 | L4: 2 | P4: 3 | T4: 4 | X4: 5 | AB4: 6 | AF4: 7 | AJ4: 8
A5: 1 | B5: Mobilisation of Marine Vessel | C5: LS | D5: 1 | E5: =1/30 -> 0.033333333 | F5: =ROUNDUP(D5/E5,0) -> 30 | G5: =SUM(H5:AI5) -> 1 | H5: 0.25 | I5: 0.25 | J5: 0.25 | K5: 0.25
A6: 2 | B6: Dredging of Pipeline Trench | C6: m3 | D6: 24080.5 | E6: 400 | F6: =ROUNDUP(D6/E6,0) -> 61 | G6: =SUM(H6:AI6) -> 2 | L6: 0.25 | M6: 0.25 | N6: 0.25 | O6: 0.25 | P6: 0.25 | Q6: 0.25 | R6: 0.25 | S6: 0.25
A7: 3 | B7: Sinking Pipeline | C7: m | D7: 500 | E7: =D7/7 -> 71.428571 | F7: =ROUNDUP(D7/E7,0) -> 7 | G7: =SUM(H7:AI7) -> 0.25 | U7: 0.25
A8: 4 | B8: Backfilling of Pipeline | F8: =SUM(F9:F13) -> 53 | G8: =SUM(H8:AI8) -> 0
A9: 4.1 | B9: Pipe Bedding | C9: m3 | D9: 377.52 | E9: 100 | F9: =ROUNDUP(D9/E9,0) -> 4 | G9: =SUM(H9:AI9) -> 0.25 | T9: 0.25
A10: 4.2 | B10: Native Soil | C10: m3 | D10: 2153.72 | E10: 350 | F10: =ROUNDUP(D10/E10,0) -> 7 | G10: =SUM(H10:AI10) -> 0.25 | V10: 0.25
A11: 4.3 | B11: 30-80 mm Crushed Stone | C11: m3 | D11: 4228.36 | E11: 700 | F11: =ROUNDUP(D11/E11,0) -> 7 | G11: =SUM(H11:AI11) -> 0.25 | W11: 0.25
A12: 4.4 | B12: 60-300 kg ROCK | C12: m3 | D12: 6902.44 | E12: 500 | F12: =ROUNDUP(D12/E12,0) -> 14 | G12: =SUM(H12:AI12) -> 0.5 | X12: 0.25 | Y12: 0.25
A13: 4.5 | B13: Backfill | C13: m3 | D13: 10418.48 | E13: 500 | F13: =ROUNDUP(D13/E13,0) -> 21 | G13: =SUM(H13:AI13) -> 0.75 | Z13: 0.25 | AA13: 0.25 | AB13: 0.25
A14: 3 | B14: Demobilisation | C14: no's | D14: 1 | E14: =1/30 -> 0.033333333 | F14: =ROUNDUP(D14/E14,0) -> 30 | G14: =SUM(H14:AI14) -> 1 | AC14: 0.25 | AD14: 0.25 | AE14: 0.25 | AF14: 0.25

Sheet 4.Equipment
B2: Table 2: Equipment Schedule
A3: Item | B3: Equipment | AI3: Total Month | AJ3: Monthly Price | AK3: Total Price | AL3: REMARKS
C4: 1 | G4: 2 | K4: 3 | O4: 4 | S4: 5 | W4: 6 | AA4: 7 | AE4: 8
A5: 1 | B5: Tugboat | G5: 0.25 | H5: 0.25 | I5: 0.25 | J5: 0.25 | K5: 0.25 | L5: 0.25 | M5: 0.25 | N5: 0.25 | O5: 0.25 | P5: 0.25 | Q5: 0.25 | R5: 0.25 | S5: 0.25 | T5: 0.25 | U5: 0.25 | V5: 0.25 | W5: 0.25 | AI5: =SUM(C5:AH5) -> 4.25 | AJ5: 75000 | AK5: =AI5*AJ5 -> 318750 | AL5: Own
A6: 1 | B6: Backhoe Dredger | G6: 0.25 | H6: 0.25 | I6: 0.25 | J6: 0.25 | K6: 0.25 | L6: 0.25 | M6: 0.25 | N6: 0.25 | O6: 0.25 | P6: 0.25 | Q6: 0.25 | R6: 0.25 | S6: 0.25 | T6: 0.25 | U6: 0.25 | V6: 0.25 | W6: 0.25 | AI6: =SUM(C6:AH6) -> 4.25 | AJ6: 100000 | AK6: =AI6*AJ6 -> 425000 | AL6: Own
A7: 2 | B7: Split Barge-1 | G7: 0.25 | H7: 0.25 | I7: 0.25 | J7: 0.25 | K7: 0.25 | L7: 0.25 | M7: 0.25 | N7: 0.25 | O7: 0.25 | P7: 0.25 | Q7: 0.25 | R7: 0.25 | S7: 0.25 | T7: 0.25 | U7: 0.25 | V7: 0.25 | W7: 0.25 | AI7: =SUM(C7:AH7) -> 4.25 | AJ7: 20000 | AK7: =AI7*AJ7 -> 85000 | AL7: Own
A8: 3 | B8: Split Barge-2 | G8: 0.25 | H8: 0.25 | I8: 0.25 | J8: 0.25 | K8: 0.25 | L8: 0.25 | M8: 0.25 | N8: 0.25 | O8: 0.25 | P8: 0.25 | Q8: 0.25 | R8: 0.25 | S8: 0.25 | T8: 0.25 | U8: 0.25 | V8: 0.25 | W8: 0.25 | AI8: =SUM(C8:AH8) -> 4.25 | AJ8: 20000 | AK8: =AI8*AJ8 -> 85000 | AL8: Own
A9: 4 | B9: Survey Boat | G9: 0.25 | H9: 0.25 | I9: 0.25 | J9: 0.25 | K9: 0.25 | L9: 0.25 | M9: 0.25 | N9: 0.25 | O9: 0.25 | P9: 0.25 | Q9: 0.25 | R9: 0.25 | S9: 0.25 | T9: 0.25 | U9: 0.25 | V9: 0.25 | W9: 0.25 | AI9: =SUM(C9:AH9) -> 4.25 | AJ9: 10000 | AK9: =AI9*AJ9 -> 42500 | AL9: Own
A10: 5 | B10: Service Boat | G10: 0.25 | H10: 0.25 | I10: 0.25 | J10: 0.25 | K10: 0.25 | L10: 0.25 | M10: 0.25 | N10: 0.25 | O10: 0.25 | P10: 0.25 | Q10: 0.25 | R10: 0.25 | S10: 0.25 | T10: 0.25 | U10: 0.25 | V10: 0.25 | W10: 0.25 | AI10: =SUM(C10:AH10) -> 4.25 | AJ10: 7500 | AK10: =AI10*AJ10 -> 31875 | AL10: Own
AK12: =SUM(AK6:AK11) -> 669375

Sheet 5.Manpower
B2: Table 3: Manpower Schedule
A3: Item | B3: Equipment | AJ3: REMARKS
C4: 1 | G4: 2 | K4: 3 | O4: 4 | S4: 5 | W4: 6 | AA4: 7 | AE4: Total Month | AF4: Staff No | AG4: Avr.Staff Salary | AH4: Monthly Total | AI4: Total Price
A5: Staff
A6: 1 | B6: Project Manager | C6: 0.25 | D6: 0.25 | E6: 0.25 | F6: 0.25 | G6: 0.25 | H6: 0.25 | I6: 0.25 | J6: 0.25 | K6: 0.25 | L6: 0.25 | M6: 0.25 | N6: 0.25 | O6: 0.25 | P6: 0.25 | Q6: 0.25 | R6: 0.25 | S6: 0.25 | T6: 0.25 | U6: 0.25 | V6: 0.25 | W6: 0.25 | X6: 0.25 | Y6: 0.25 | Z6: 0.25 | AA6: 0.25 | AE6: =SUM(C6:AD6) -> 6.25 | AF6: 1 | AG6: 2250 | AH6: =AG6*AF6 -> 2250 | AI6: =AH6*AE6 -> 14062.5
A7: 2 | B7: Construction Manager | C7: 0.25 | D7: 0.25 | E7: 0.25 | F7: 0.25 | G7: 0.25 | H7: 0.25 | I7: 0.25 | J7: 0.25 | K7: 0.25 | L7: 0.25 | M7: 0.25 | N7: 0.25 | O7: 0.25 | P7: 0.25 | Q7: 0.25 | R7: 0.25 | S7: 0.25 | T7: 0.25 | U7: 0.25 | V7: 0.25 | W7: 0.25 | X7: 0.25 | Y7: 0.25 | Z7: 0.25 | AA7: 0.25 | AE7: =SUM(C7:AD7) -> 6.25 | AF7: 1 | AG7: 1750 | AH7: =AG7*AF7 -> 1750 | AI7: =AH7*AE7 -> 10937.5
A8: 6 | B8: Survey Chief | C8: 0.25 | D8: 0.25 | E8: 0.25 | F8: 0.25 | G8: 0.25 | H8: 0.25 | I8: 0.25 | J8: 0.25 | K8: 0.25 | L8: 0.25 | M8: 0.25 | N8: 0.25 | O8: 0.25 | P8: 0.25 | Q8: 0.25 | R8: 0.25 | S8: 0.25 | T8: 0.25 | U8: 0.25 | V8: 0.25 | W8: 0.25 | X8: 0.25 | Y8: 0.25 | Z8: 0.25 | AA8: 0.25 | AE8: =SUM(C8:AD8) -> 6.25 | AF8: 1 | AG8: 1750 | AH8: =AG8*AF8 -> 1750 | AI8: =AH8*AE8 -> 10937.5
A9: 7 | B9: Site Engineer | C9: 0.25 | D9: 0.25 | E9: 0.25 | F9: 0.25 | G9: 0.25 | H9: 0.25 | I9: 0.25 | J9: 0.25 | K9: 0.25 | L9: 0.25 | M9: 0.25 | N9: 0.25 | O9: 0.25 | P9: 0.25 | Q9: 0.25 | R9: 0.25 | S9: 0.25 | T9: 0.25 | U9: 0.25 | V9: 0.25 | W9: 0.25 | X9: 0.25 | Y9: 0.25 | Z9: 0.25 | AA9: 0.25 | AE9: =SUM(C9:AD9) -> 6.25 | AF9: 2 | AG9: 1250 | AH9: =AG9*AF9 -> 2500 | AI9: =AH9*AE9 -> 15625
A10: 8 | B10: Surveyor | C10: 0.25 | D10: 0.25 | E10: 0.25 | F10: 0.25 | G10: 0.25 | H10: 0.25 | I10: 0.25 | J10: 0.25 | K10: 0.25 | L10: 0.25 | M10: 0.25 | N10: 0.25 | O10: 0.25 | P10: 0.25 | Q10: 0.25 | R10: 0.25 | S10: 0.25 | T10: 0.25 | U10: 0.25 | V10: 0.25 | W10: 0.25 | X10: 0.25 | Y10: 0.25 | Z10: 0.25 | AA10: 0.25 | AE10: =SUM(C10:AD10) -> 6.25 | AF10: 2 | AG10: 1000 | AH10: =AG10*AF10 -> 2000 | AI10: =AH10*AE10 -> 12500
A11: 10 | B11: Admin Personnel | C11: 0.25 | D11: 0.25 | E11: 0.25 | F11: 0.25 | G11: 0.25 | H11: 0.25 | I11: 0.25 | J11: 0.25 | K11: 0.25 | L11: 0.25 | M11: 0.25 | N11: 0.25 | O11: 0.25 | P11: 0.25 | Q11: 0.25 | R11: 0.25 | S11: 0.25 | T11: 0.25 | U11: 0.25 | V11: 0.25 | W11: 0.25 | X11: 0.25 | Y11: 0.25 | Z11: 0.25 | AA11: 0.25 | AE11: =SUM(C11:AD11) -> 6.25 | AF11: 2 | AG11: 1000 | AH11: =AG11*AF11 -> 2000 | AI11: =AH11*AE11 -> 12500
A12: Labour
A13: 1 | B13: Tugboat | C13: 0.25 | D13: 0.25 | E13: 0.25 | F13: 0.25 | G13: 0.25 | H13: 0.25 | I13: 0.25 | J13: 0.25 | K13: 0.25 | L13: 0.25 | M13: 0.25 | N13: 0.25 | O13: 0.25 | P13: 0.25 | Q13: 0.25 | R13: 0.25 | S13: 0.25 | T13: 0.25 | U13: 0.25 | V13: 0.25 | W13: 0.25 | X13: 0.25 | Y13: 0.25 | Z13: 0.25 | AA13: 0.25 | AE13: =SUM(C13:AD13) -> 6.25 | AF13: 8 | AG13: 1250 | AH13: =AG13*AF13 -> 10000 | AI13: =AE13*AH13 -> 62500
A14: 2 | B14: Backhoe Dredger | C14: 0.25 | D14: 0.25 | E14: 0.25 | F14: 0.25 | G14: 0.25 | H14: 0.25 | I14: 0.25 | J14: 0.25 | K14: 0.25 | L14: 0.25 | M14: 0.25 | N14: 0.25 | O14: 0.25 | P14: 0.25 | Q14: 0.25 | R14: 0.25 | S14: 0.25 | T14: 0.25 | U14: 0.25 | V14: 0.25 | W14: 0.25 | X14: 0.25 | Y14: 0.25 | Z14: 0.25 | AA14: 0.25 | AE14: =SUM(C14:AD14) -> 6.25 | AF14: 6 | AG14: 2000 | AH14: =AG14*AF14 -> 12000 | AI14: =AE14*AH14 -> 75000
A15: 3 | B15: Split Barge-1 | C15: 0.25 | D15: 0.25 | E15: 0.25 | F15: 0.25 | G15: 0.25 | H15: 0.25 | I15: 0.25 | J15: 0.25 | K15: 0.25 | L15: 0.25 | M15: 0.25 | N15: 0.25 | O15: 0.25 | P15: 0.25 | Q15: 0.25 | R15: 0.25 | S15: 0.25 | T15: 0.25 | U15: 0.25 | V15: 0.25 | W15: 0.25 | X15: 0.25 | Y15: 0.25 | Z15: 0.25 | AA15: 0.25 | AE15: =SUM(C15:AD15) -> 6.25 | AF15: 5 | AG15: 1000 | AH15: =AG15*AF15 -> 5000 | AI15: =AE15*AH15 -> 31250
A16: 4 | B16: Split Barge-2 | C16: 0.25 | D16: 0.25 | E16: 0.25 | F16: 0.25 | G16: 0.25 | H16: 0.25 | I16: 0.25 | J16: 0.25 | K16: 0.25 | L16: 0.25 | M16: 0.25 | N16: 0.25 | O16: 0.25 | P16: 0.25 | Q16: 0.25 | R16: 0.25 | S16: 0.25 | T16: 0.25 | U16: 0.25 | V16: 0.25 | W16: 0.25 | X16: 0.25 | Y16: 0.25 | Z16: 0.25 | AA16: 0.25 | AE16: =SUM(C16:AD16) -> 6.25 | AF16: 5 | AG16: 1000 | AH16: =AG16*AF16 -> 5000 | AI16: =AE16*AH16 -> 31250
A17: 5 | B17: Survey Boat | C17: 0.25 | D17: 0.25 | E17: 0.25 | F17: 0.25 | G17: 0.25 | H17: 0.25 | I17: 0.25 | J17: 0.25 | K17: 0.25 | L17: 0.25 | M17: 0.25 | N17: 0.25 | O17: 0.25 | P17: 0.25 | Q17: 0.25 | R17: 0.25 | S17: 0.25 | T17: 0.25 | U17: 0.25 | V17: 0.25 | W17: 0.25 | X17: 0.25 | Y17: 0.25 | Z17: 0.25 | AA17: 0.25 | AE17: =SUM(C17:AD17) -> 6.25 | AF17: 2 | AG17: 1000 | AH17: =AG17*AF17 -> 2000 | AI17: =AE17*AH17 -> 12500
A18: 6 | B18: Service Boat | C18: 0.25 | D18: 0.25 | E18: 0.25 | F18: 0.25 | G18: 0.25 | H18: 0.25 | I18: 0.25 | J18: 0.25 | K18: 0.25 | L18: 0.25 | M18: 0.25 | N18: 0.25 | O18: 0.25 | P18: 0.25 | Q18: 0.25 | R18: 0.25 | S18: 0.25 | T18: 0.25 | U18: 0.25 | V18: 0.25 | W18: 0.25 | X18: 0.25 | Y18: 0.25 | Z18: 0.25 | AA18: 0.25 | AE18: =SUM(C18:AD18) -> 6.25 | AF18: 2 | AG18: 1000 | AH18: =AG18*AF18 -> 2000 | AI18: =AE18*AH18 -> 12500
A19: 7 | B19: Divers | C19: 0.25 | D19: 0.25 | E19: 0.25 | F19: 0.25 | G19: 0.25 | H19: 0.25 | I19: 0.25 | J19: 0.25 | K19: 0.25 | L19: 0.25 | M19: 0.25 | N19: 0.25 | O19: 0.25 | P19: 0.25 | Q19: 0.25 | R19: 0.25 | S19: 0.25 | T19: 0.25 | U19: 0.25 | V19: 0.25 | W19: 0.25 | X19: 0.25 | Y19: 0.25 | Z19: 0.25 | AA19: 0.25 | AE19: =SUM(C19:AD19) -> 6.25 | AF19: 2 | AG19: 2000 | AH19: =AG19*AF19 -> 4000 | AI19: =AE19*AH19 -> 25000
A20: 8 | B20: Excavator | C20: 0.25 | D20: 0.25 | E20: 0.25 | F20: 0.25 | G20: 0.25 | H20: 0.25 | I20: 0.25 | J20: 0.25 | K20: 0.25 | L20: 0.25 | M20: 0.25 | N20: 0.25 | O20: 0.25 | P20: 0.25 | Q20: 0.25 | R20: 0.25 | S20: 0.25 | T20: 0.25 | U20: 0.25 | V20: 0.25 | W20: 0.25 | X20: 0.25 | Y20: 0.25 | Z20: 0.25 | AA20: 0.25 | AE20: =SUM(C20:AD20) -> 6.25 | AF20: 6 | AG20: 2500 | AH20: =AG20*AF20 -> 15000 | AI20: =AE20*AH20 -> 93750
A21: 9 | B21: Roller | C21: 0.25 | D21: 0.25 | E21: 0.25 | F21: 0.25 | G21: 0.25 | H21: 0.25 | I21: 0.25 | J21: 0.25 | K21: 0.25 | L21: 0.25 | M21: 0.25 | N21: 0.25 | O21: 0.25 | P21: 0.25 | Q21: 0.25 | R21: 0.25 | S21: 0.25 | T21: 0.25 | U21: 0.25 | V21: 0.25 | W21: 0.25 | X21: 0.25 | Y21: 0.25 | Z21: 0.25 | AA21: 0.25 | AE21: =SUM(C21:AA21) -> 6.25 | AF21: 7 | AG21: 2500 | AH21: =AG21*AF21 -> 17500 | AI21: =AE21*AH21 -> 109375
AF22: =SUM(AF6:AF11) -> 9 | AG22: Total Price for Staff | AI22: =SUM(AI6:AI11) -> 76562.5
AF23: =SUM(AF13:AF21) -> 43 | AG23: Total Price for Labour | AI23: =SUM(AI14:AI20) -> 281250
AF24: =SUM(AF22:AF23) -> 52 | AG24: Total Workmanship | AI24: =SUM(AI22:AI23) -> 357812.5

Sheet 6.Mob-Demob
B2: Mob+Demob Duration | C2: 2
A3: Item | B3: Equipment | C3: Equipment Rate | E3: Manpower | F3: MGO (ton/month) | G3: MGO (USD)
A4: 0 | B4: Tugboat | C4: 75000 | D4: =C4*$C$2 -> 150000 | E4: =8*3000*C2 -> 48000 | F4: =5.5*30 -> 165 | G4: =F4*800 -> 132000
A5: 1 | B5: Backhoe Dredger | C5: ='4.Equipment'!AJ6 -> 100000 | D5: =C5*$C$2 -> 200000 | E5: ='5.Manpower'!AH14*'6.Mob-Demob'!$C$2 -> 24000 | G5: =F5*800 -> 0
A6: 2 | B6: Split Barge-1 | C6: ='4.Equipment'!AJ7 -> 20000 | D6: =C6*$C$2 -> 40000 | E6: ='5.Manpower'!AH15*'6.Mob-Demob'!$C$2 -> 10000 | F6: =0.75*30 -> 22.5 | G6: =F6*800 -> 18000
A7: 3 | B7: Split Barge-2 | C7: ='4.Equipment'!AJ8 -> 20000 | D7: =C7*$C$2 -> 40000 | E7: ='5.Manpower'!AH16*'6.Mob-Demob'!$C$2 -> 10000 | F7: =0.75*30 -> 22.5 | G7: =F7*800 -> 18000
A8: 4 | B8: Survey Boat | C8: ='4.Equipment'!AJ9 -> 10000 | D8: =C8*$C$2 -> 20000 | E8: ='5.Manpower'!AH17*'6.Mob-Demob'!$C$2 -> 4000 | G8: =F8*800 -> 0
A9: 5 | B9: Service Boat | C9: ='4.Equipment'!AJ10 -> 7500 | D9: =C9*$C$2 -> 15000 | E9: ='5.Manpower'!AH18*'6.Mob-Demob'!$C$2 -> 4000 | G9: =F9*800 -> 0
G10: =F10*800 -> 0
G11: =F11*800 -> 0
G12: =F12*800 -> 0
D13: =SUM(D5:D12) -> 315000 | E13: =SUM(E5:E12) -> 52000 | G13: =SUM(G5:G12) -> 36000
F15: Mob Total | G15: =SUM(D13:G13) -> 403000

Sheet 7.MGO+Lub+Insurance
B2: Table 2: Marine construction works
A3: Item | B3: Equipment | J3: REMARKS
C4: Total Month | D4: Daily MGO | E4: Monthly MGO | F4: MGO USD | G4: Lub USD | H4: Insurance | I4: Total Price
A5: 1 | B5: Tugboat | C5: ='4.Equipment'!AI5 -> 4.25 | D5: 4 | E5: =D5*30 -> 120 | F5: =E5*800*C5 -> 408000 | G5: 12000 | H5: 6000 | I5: =H5+G5+F5 -> 426000
A6: 1 | B6: Backhoe Dredger | C6: ='4.Equipment'!AI6 -> 4.25 | D6: 1 | E6: =D6*30 -> 30 | F6: =E6*800*C6 -> 102000 | G6: 12000 | H6: 6000 | I6: =H6+G6+F6 -> 120000
A7: 2 | B7: Split Barge-1 | C7: ='4.Equipment'!AI7 -> 4.25 | D7: 0.5 | E7: =D7*30 -> 15 | F7: =E7*800*C7 -> 51000 | G7: 12000 | H7: 6000 | I7: =H7+G7+F7 -> 69000 | J7: Own
A8: 3 | B8: Split Barge-2 | C8: ='4.Equipment'!AI8 -> 4.25 | D8: 0.5 | E8: =D8*30 -> 15 | F8: =E8*800*C8 -> 51000 | G8: 12000 | H8: 6000 | I8: =H8+G8+F8 -> 69000
A9: 4 | B9: Survey Boat | C9: ='4.Equipment'!AI9 -> 4.25 | D9: 0.2 | E9: =D9*30 -> 6 | F9: =E9*800*C9 -> 20400 | G9: 4000 | H9: 2000 | I9: =H9+G9+F9 -> 26400
A10: 5 | B10: Service Boat | C10: ='4.Equipment'!AI10 -> 4.25 | D10: 0.2 | E10: =D10*30 -> 6 | F10: =E10*800*C10 -> 20400 | G10: 4000 | H10: 2000 | I10: =H10+G10+F10 -> 26400
G11: =SUM(G6:G10) -> 44000 | H11: =SUM(H6:H10) -> 22000 | I11: =SUM(I6:I10) -> 310800

Sheet 8.Material
B2: Table 2: Material List
A3: Item | B3: Equipment | F3: REMARKS
C4: Total Amount | D4: Unit Price | E4: Total Price
E23: =SUM(E5:E22) -> 0

Sheet 9.Indirect
B2: Table 2: Marine construction works
A3: Item | B3: Equipment | F3: REMARKS
C4: Total Amount | D4: Unit Price | E4: Total Price
A5: 1 | B5: Taxes (%6) | C5: 1 | D5: ='5.Manpower'!$AI$24*0.06 -> 21468.75 | E5: =C5*D5 -> 21468.75
A6: 2 | B6: Social Security Costs (%29) | C6: 1 | D6: ='5.Manpower'!$AI$24*0.29 -> 103765.62 | E6: =C6*D6 -> 103765.62
A7: 3 | B7: Accomandation | C7: ='5.Manpower'!$AF$24 -> 52 | D7: =450*6 -> 2700 | E7: =C7*D7 -> 140400
A8: 4 | B8: Work Permit Cost | C8: ='5.Manpower'!$AF$24 -> 52 | D8: 2000 | E8: =C8*D8 -> 104000
A9: 5 | B9: Provision | C9: ='5.Manpower'!$AF$24 -> 52 | D9: =24*30*6 -> 4320 | E9: =C9*D9 -> 224640
E23: =SUM(E5:E22) -> 594274.38
